Workbook
Name \a: #REF!
Name \b: #REF!
Name \c: #REF!
Name \g: #REF!
Name \N: #REF!
Name \o: #REF!
Name \P: #REF!
Name \P: #REF!
Name \P: #REF!
Name \P: #REF!
Name \r: #N/A
Name \s: #N/A
Name \x: #REF!
Name \y: #REF!
Name \z: #REF!
Name ___________________an1: [0]!is1b,[0]!is1c,[0]!STATS2,[0]!STATS3
Name ___________________an1: [0]!is1b,[0]!is1c,[0]!STATS2,[0]!STATS3
Name ___________________an1: [0]!is1b,[0]!is1c,[0]!STATS2,[0]!STATS3
Name __________________an1: [0]!is1b,[0]!is1c,[0]!STATS2,[0]!STATS3
Name __________________an1: [0]!is1b,[0]!is1c,[0]!STATS2,[0]!STATS3
Name __________________an1: [0]!is1b,[0]!is1c,[0]!STATS2,[0]!STATS3
Name __________________df1: {#N/A,#N/A,FALSE,"Calc";#N/A,#N/A,FALSE,"Sensitivity";#N/A,#N/A,FALSE,"LT Earn.Dil.";#N/A,#N/A,FALSE,"Dil. AVP"}
Name __________________df1: {#N/A,#N/A,FALSE,"Calc";#N/A,#N/A,FALSE,"Sensitivity";#N/A,#N/A,FALSE,"LT Earn.Dil.";#N/A,#N/A,FALSE,"Dil. AVP"}
Name __________________df1: {#N/A,#N/A,FALSE,"Calc";#N/A,#N/A,FALSE,"Sensitivity";#N/A,#N/A,FALSE,"LT Earn.Dil.";#N/A,#N/A,FALSE,"Dil. AVP"}
Name __________________df2: {#N/A,#N/A,FALSE,"Calc";#N/A,#N/A,FALSE,"Sensitivity";#N/A,#N/A,FALSE,"LT Earn.Dil.";#N/A,#N/A,FALSE,"Dil. AVP"}
Name __________________df2: {#N/A,#N/A,FALSE,"Calc";#N/A,#N/A,FALSE,"Sensitivity";#N/A,#N/A,FALSE,"LT Earn.Dil.";#N/A,#N/A,FALSE,"Dil. AVP"}
Name __________________df2: {#N/A,#N/A,FALSE,"Calc";#N/A,#N/A,FALSE,"Sensitivity";#N/A,#N/A,FALSE,"LT Earn.Dil.";#N/A,#N/A,FALSE,"Dil. AVP"}
Name __________________hd1: {#N/A,#N/A,FALSE,"Calc";#N/A,#N/A,FALSE,"Sensitivity";#N/A,#N/A,FALSE,"LT Earn.Dil.";#N/A,#N/A,FALSE,"Dil. AVP"}
Name __________________hd1: {#N/A,#N/A,FALSE,"Calc";#N/A,#N/A,FALSE,"Sensitivity";#N/A,#N/A,FALSE,"LT Earn.Dil.";#N/A,#N/A,FALSE,"Dil. AVP"}
Name __________________hd1: {#N/A,#N/A,FALSE,"Calc";#N/A,#N/A,FALSE,"Sensitivity";#N/A,#N/A,FALSE,"LT Earn.Dil.";#N/A,#N/A,FALSE,"Dil. AVP"}
Name __________________hd2: {#N/A,#N/A,FALSE,"Calc";#N/A,#N/A,FALSE,"Sensitivity";#N/A,#N/A,FALSE,"LT Earn.Dil.";#N/A,#N/A,FALSE,"Dil. AVP"}
Name __________________hd2: {#N/A,#N/A,FALSE,"Calc";#N/A,#N/A,FALSE,"Sensitivity";#N/A,#N/A,FALSE,"LT Earn.Dil.";#N/A,#N/A,FALSE,"Dil. AVP"}
Name __________________hd2: {#N/A,#N/A,FALSE,"Calc";#N/A,#N/A,FALSE,"Sensitivity";#N/A,#N/A,FALSE,"LT Earn.Dil.";#N/A,#N/A,FALSE,"Dil. AVP"}
Name __________________P1: [0]!_________________P1
Name __________________P1: [0]!_________________P1
Name __________________P1: [0]!_________________P1
Name _________________an1: [0]!is1b,[0]!is1c,[0]!STATS2,[0]!STATS3
Name _________________an1: [0]!is1b,[0]!is1c,[0]!STATS2,[0]!STATS3
Name _________________an1: [0]!is1b,[0]!is1c,[0]!STATS2,[0]!STATS3
Name _________________df1: {#N/A,#N/A,FALSE,"Calc";#N/A,#N/A,FALSE,"Sensitivity";#N/A,#N/A,FALSE,"LT Earn.Dil.";#N/A,#N/A,FALSE,"Dil. AVP"}
Name _________________df1: {#N/A,#N/A,FALSE,"Calc";#N/A,#N/A,FALSE,"Sensitivity";#N/A,#N/A,FALSE,"LT Earn.Dil.";#N/A,#N/A,FALSE,"Dil. AVP"}
Name _________________df1: {#N/A,#N/A,FALSE,"Calc";#N/A,#N/A,FALSE,"Sensitivity";#N/A,#N/A,FALSE,"LT Earn.Dil.";#N/A,#N/A,FALSE,"Dil. AVP"}
Name _________________df2: {#N/A,#N/A,FALSE,"Calc";#N/A,#N/A,FALSE,"Sensitivity";#N/A,#N/A,FALSE,"LT Earn.Dil.";#N/A,#N/A,FALSE,"Dil. AVP"}
Name _________________df2: {#N/A,#N/A,FALSE,"Calc";#N/A,#N/A,FALSE,"Sensitivity";#N/A,#N/A,FALSE,"LT Earn.Dil.";#N/A,#N/A,FALSE,"Dil. AVP"}
Name _________________df2: {#N/A,#N/A,FALSE,"Calc";#N/A,#N/A,FALSE,"Sensitivity";#N/A,#N/A,FALSE,"LT Earn.Dil.";#N/A,#N/A,FALSE,"Dil. AVP"}
Name _________________hd1: {#N/A,#N/A,FALSE,"Calc";#N/A,#N/A,FALSE,"Sensitivity";#N/A,#N/A,FALSE,"LT Earn.Dil.";#N/A,#N/A,FALSE,"Dil. AVP"}
Name _________________hd1: {#N/A,#N/A,FALSE,"Calc";#N/A,#N/A,FALSE,"Sensitivity";#N/A,#N/A,FALSE,"LT Earn.Dil.";#N/A,#N/A,FALSE,"Dil. AVP"}
Name _________________hd1: {#N/A,#N/A,FALSE,"Calc";#N/A,#N/A,FALSE,"Sensitivity";#N/A,#N/A,FALSE,"LT Earn.Dil.";#N/A,#N/A,FALSE,"Dil. AVP"}
Name _________________hd2: {#N/A,#N/A,FALSE,"Calc";#N/A,#N/A,FALSE,"Sensitivity";#N/A,#N/A,FALSE,"LT Earn.Dil.";#N/A,#N/A,FALSE,"Dil. AVP"}
Name _________________hd2: {#N/A,#N/A,FALSE,"Calc";#N/A,#N/A,FALSE,"Sensitivity";#N/A,#N/A,FALSE,"LT Earn.Dil.";#N/A,#N/A,FALSE,"Dil. AVP"}
Name _________________hd2: {#N/A,#N/A,FALSE,"Calc";#N/A,#N/A,FALSE,"Sensitivity";#N/A,#N/A,FALSE,"LT Earn.Dil.";#N/A,#N/A,FALSE,"Dil. AVP"}
Name _________________P1: #N/A
Name ________________df1: {#N/A,#N/A,FALSE,"Calc";#N/A,#N/A,FALSE,"Sensitivity";#N/A,#N/A,FALSE,"LT Earn.Dil.";#N/A,#N/A,FALSE,"Dil. AVP"}
Name ________________df1: {#N/A,#N/A,FALSE,"Calc";#N/A,#N/A,FALSE,"Sensitivity";#N/A,#N/A,FALSE,"LT Earn.Dil.";#N/A,#N/A,FALSE,"Dil. AVP"}
Name ________________df1: {#N/A,#N/A,FALSE,"Calc";#N/A,#N/A,FALSE,"Sensitivity";#N/A,#N/A,FALSE,"LT Earn.Dil.";#N/A,#N/A,FALSE,"Dil. AVP"}
Name ________________df2: {#N/A,#N/A,FALSE,"Calc";#N/A,#N/A,FALSE,"Sensitivity";#N/A,#N/A,FALSE,"LT Earn.Dil.";#N/A,#N/A,FALSE,"Dil. AVP"}
Name ________________df2: {#N/A,#N/A,FALSE,"Calc";#N/A,#N/A,FALSE,"Sensitivity";#N/A,#N/A,FALSE,"LT Earn.Dil.";#N/A,#N/A,FALSE,"Dil. AVP"}
Name ________________df2: {#N/A,#N/A,FALSE,"Calc";#N/A,#N/A,FALSE,"Sensitivity";#N/A,#N/A,FALSE,"LT Earn.Dil.";#N/A,#N/A,FALSE,"Dil. AVP"}
Name ________________hd1: {#N/A,#N/A,FALSE,"Calc";#N/A,#N/A,FALSE,"Sensitivity";#N/A,#N/A,FALSE,"LT Earn.Dil.";#N/A,#N/A,FALSE,"Dil. AVP"}
Name ________________hd1: {#N/A,#N/A,FALSE,"Calc";#N/A,#N/A,FALSE,"Sensitivity";#N/A,#N/A,FALSE,"LT Earn.Dil.";#N/A,#N/A,FALSE,"Dil. AVP"}

Sheet Summary
A1: 301 E. ATLANTIC POMPANO BEACH | AP1: FONT KEY
AP2: Blue = Input cell
AP3: Black = Text or formula cell
G4: BUYER'S PREFERRED | S4: PROJECTED STRIKE | AE4: OPTIMISTIC | AP4: Red = Link to Garden input
D5: LAND, UNIT INVENTORY & VALUATION | AP5: Green = Link to Summary input
D6: (Subject to site plan approval)
E7: Land Area | G7: ='Low Budget'!$H$6 -> 2.3362029 | S7: ='Middle Budget'!$H$6 -> 2.3362029 | AE7: ='High Budget'!$H$6 -> 2.3362029
E8: Density | G8: ='Low Budget'!$H$7 -> 149.81575 | S8: ='Middle Budget'!$H$7 -> 149.81575 | AE8: ='High Budget'!$H$7 -> 149.81575
E9: Total Units | G9: ='Low Budget'!$H$11 -> 350 | S9: ='Middle Budget'!$H$11 -> 350 | AE9: ='High Budget'!$H$11 -> 350
E10: Average Unit Size | G10: ='Low NOI'!$H$14 -> 750 | S10: ='Middle NOI'!$H$14 -> 750 | AE10: ='High NOI'!$H$14 -> 750
E11: Net Rentable Area | G11: ='Low NOI'!$I$14 -> 262500 | S11: ='Middle NOI'!$I$14 -> 262500 | AE11: ='High NOI'!$I$14 -> 262500
E12: Total Land Value | G12: =G13*G9 -> 12250000 | S12: =S13*S9 -> 13300000 | AE12: =AE13*AE9 -> 14875000
E13: Land Value Per Unit | G13: 35000 | S13: 38000 | AE13: 42500
E14: Land Value Per Acre | G14: =G12/G7 -> 5243551.3 | S14: =S12/S7 -> 5692998.6 | AE14: =AE12/AE7 -> 6367169.5
E15: Un-Trended ROC (NOI w/ developer RE taxes) | G15: ='Low Budget'!$V$29 -> 0.065602891 | S15: ='Middle Budget'!$V$29 -> 0.064949134 | AE15: ='High Budget'!$V$29 -> 0.06399257
E16: Net Profit as % of Cost (excl. operating cash flow) | G16: ='Low Budget'!$V$30 -> 0.3620037 | S16: ='Middle Budget'!$V$30 -> 0.34843083 | AE16: ='High Budget'!$V$30 -> 0.32857128
E17: IRR on Sale (incl. operating cash flow) | G17: ='Low Budget'!$V$31 -> 0.24813606 | S17: ='Middle Budget'!$V$31 -> 0.24086857 | AE17: ='High Budget'!$V$31 -> 0.23005278
E18: Equity Multiple on Sale (incl. operating cash flow) | G18: ='Low Budget'!$V$32 -> 2.0922063 | S18: ='Middle Budget'!$V$32 -> 2.0519088 | AE18: ='High Budget'!$V$32 -> 1.9929463
E19: Investment Period | G19: ='Low Budget'!$H$27 -> 40 | S19: ='Middle Budget'!$H$27 -> 40 | AE19: ='High Budget'!$H$27 -> 40
D21: RENT & NOI | G21: Studio | I21: 1BR | K21: 2BR | M21: Total | S21: Studio | U21: 1BR | W21: 2BR | Y21: Total | AE21: Studio | AG21: 1BR | AI21: 2BR | AK21: Total
E22: Unit Count | G22: ='Low NOI'!F10 -> 70 | I22: ='Low NOI'!F11 -> 140 | K22: ='Low NOI'!F12 -> 140 | M22: ='Low NOI'!F14 -> 350 | S22: 70 | U22: 140 | W22: 140 | Y22: =S22+U22+W22 -> 350 | AE22: ='High NOI'!F10 -> 70 | AG22: ='High NOI'!F11 -> 140 | AI22: ='High NOI'!F12 -> 140 | AK22: ='Low NOI'!F14 -> 350
E23: % of Total Units | G23: =G22/$M$22 -> 0.2 | I23: =I22/$M$22 -> 0.4 | K23: =K22/$M$22 -> 0.4 | M23: =G23+I23+K23 -> 1 | S23: =S22/$Y$22 -> 0.2 | U23: =U22/$Y$22 -> 0.4 | W23: =W22/$Y$22 -> 0.4 | Y23: =S23+U23+W23 -> 1 | AE23: =AE22/$AK$22 -> 0.2 | AG23: =AG22/$AK$22 -> 0.4 | AI23: =AI22/$AK$22 -> 0.4 | AK23: =AE23+AG23+AI23 -> 1
E24: Average SF Per Unit | G24: ='Low NOI'!$H$10 -> 500 | I24: ='Low NOI'!$H$11 -> 675 | K24: ='Low NOI'!$H$12 -> 950 | M24: ='Low NOI'!$H$14 -> 750 | S24: 500 | U24: 675 | W24: 950 | Y24: ='Middle NOI'!$H$14 -> 750 | AE24: ='High NOI'!$H$10 -> 500 | AG24: ='High NOI'!$H$11 -> 675 | AI24: ='High NOI'!$H$12 -> 950 | AK24: ='High NOI'!$H$14 -> 750
E25: Un-Trended Average Rent Per Unit | G25: =S25 -> 2100 | I25: =U25 -> 2650 | K25: =W25 -> 3150 | M25: ='Low NOI'!K14 -> 2740 | S25: 2100 | U25: 2650 | W25: 3150 | Y25: ='Middle NOI'!K14 -> 2740 | AE25: =S25 -> 2100 | AG25: =U25 -> 2650 | AI25: =W25 -> 3150 | AK25: ='High NOI'!K14 -> 2740
E26: Un-Trended Average Rent Per SF | G26: ='Low NOI'!M10 -> 4.2 | I26: ='Low NOI'!M11 -> 3.9259259 | K26: ='Low NOI'!M12 -> 3.3157895 | M26: ='Low NOI'!M14 -> 3.6533333 | S26: ='Middle NOI'!M10 -> 4.2 | U26: ='Middle NOI'!M11 -> 3.9259259 | W26: ='Middle NOI'!M12 -> 3.3157895 | Y26: ='Middle NOI'!M14 -> 3.6533333 | AE26: ='High NOI'!M10 -> 4.2 | AG26: ='High NOI'!M11 -> 3.9259259 | AI26: ='High NOI'!M12 -> 3.3157895 | AK26: ='High NOI'!M14 -> 3.6533333
E28: Un-Trended NOI (w/ developer RE taxes) | G28: ='Low Budget'!$H$16 -> 7738141.7 | I28: =I105 -> 0.67241412 | S28: ='Middle Budget'!$H$16 -> 7738141.7 | U28: =U105 -> 0.67241412 | AE28: ='High Budget'!$H$16 -> 7738141.7 | AG28: =AG105 -> 0.67241412
D30: LEASE-UP & EXIT VALUE
E31: Lease-Up Velocity | G31: =$S$31 -> 12 | I31: ='Low Budget'!$H$25 -> 25.576923 | S31: 12 | U31: ='Middle Budget'!$H$25 -> 25.576923 | AE31: =$S$31 -> 12 | AG31: ='High Budget'!$H$25 -> 25.576923
E32: Market Cap Rate | G32: =$S$32 -> 0.0475 | S32: 0.0475 | AE32: =$S$32 -> 0.0475
E33: Stabilized Value (trended) | G33: ='Low Budget'!$R$18 -> 1.6268776e+08 | I33: =G33/G9 -> 464822.17 | S33: ='Middle Budget'!$R$18 -> 1.6268776e+08 | U33: =S33/S9 -> 464822.17 | AE33: ='High Budget'!$R$18 -> 1.6268776e+08 | AG33: =AE33/AE9 -> 464822.17
I34: =G33/G11 -> 619.7629 | U34: =S33/S11 -> 619.7629 | AG34: =AE33/AE11 -> 619.7629
D35: DEVELOPMENT COSTS
E36: Hard Costs (excl. impact fees, permits, utility connect) | G36: =$S$36 -> 315 | I36: =G67/G9 -> 248062.5 | K36: ='Low Budget'!$L$76/'Low Budget'!$H$9 -> 165.375 | S36: 315 | U36: =S67/S9 -> 248062.5 | W36: ='Middle Budget'!$L$76/'Middle Budget'!$H$9 -> 165.375 | AE36: =$S$36 -> 315 | AG36: =AE67/AE9 -> 248062.5 | AI36: ='High Budget'!$L$76/'High Budget'!$H$9 -> 165.375
E37: Hard Cost Contingency | G37: =$S$37 -> 0.05 | S37: 0.05 | AE37: =$S$37 -> 0.05
E38: Soft Costs as % of Hard Cost Excluding Financing | G38: ='Low Budget'!$L$88/'Low Budget'!$L$76 -> 0.14093274 | S38: ='Middle Budget'!$L$88/'Middle Budget'!$L$76 -> 0.1413273 | AE38: ='High Budget'!$L$88/'High Budget'!$L$76 -> 0.14191912
E39: Soft Costs as % of Hard Cost Including Financing | G39: =('Low Budget'!$L$88+'Low Budget'!$L$98+'Low Budget'!$L$102+'Low Budget'!$L$108)/'Low Budget'!$L$76 -> 0.21748441 | S39: =('Middle Budget'!$L$88+'Middle Budget'!$L$98+'Middle Budget'!$L$102+'Middle Budget'!$L$108)/'Middle Budget'!$L$76 -> 0.21906569 | AE39: =('High Budget'!$L$88+'High Budget'!$L$98+'High Budget'!$L$102+'High Budget'!$L$108)/'High Budget'!$L$76 -> 0.2214376
E40: Developer Fee as % of Cost Excl. Land & Financing | G40: =$S$40 -> 0.03 | I40: ='Low Budget'!$L$87 -> 2885182.1 | S40: 0.03 | U40: ='Middle Budget'!$L$87 -> 2886179.9 | AE40: =$S$40 -> 0.03 | AG40: ='High Budget'!$L$87 -> 2887676.5
E41: Developer Fee as % of Total Cost | G41: ='Low Budget'!$R$87 -> 0.024460174 | S41: ='Middle Budget'!R87 -> 0.024224793 | AE41: ='High Budget'!R87 -> 0.02388039
E42: Construction Period | G42: =$S$42 -> 24 | S42: 24 | AE42: =$S$42 -> 24
E43: Total Development Cost (including land) | G43: ='Low Budget'!$L$110 -> 1.1795428e+08 | I43: =G43/G9 -> 337012.23 | S43: ='Middle Budget'!$L$110 -> 1.1914157e+08 | U43: =S43/S9 -> 340404.48 | AE43: ='High Budget'!$L$110 -> 1.209225e+08 | AG43: =AE43/AE9 -> 345492.86
I44: =G43/G11 -> 449.34963 | U44: =S43/S11 -> 453.87264 | AG44: =AE43/AE11 -> 460.65715
D46: DEVELOPMENT CAPITALIZATION | G46: Total | I46: % Cost | K46: Un-Trended DY | M46: % Stab. Value | S46: Total | U46: % Cost | W46: Un-Trended DY | Y46: % Stab. Value | AE46: Total | AG46: % Cost | AI46: Un-Trended DY | AK46: % Stab. Value
K47: Developer RE Tax | M47: Market Value RE Tax | W47: Developer RE Tax | Y47: Market Value RE Tax | AI47: Developer RE Tax | AK47: Market Value RE Tax
E48: Construction Loan | G48: ='Low Budget'!$L$48 -> 76421910 | I48: ='Low Budget'!$R$48 -> 0.65 | K48: ='Low Budget'!$T$48 -> 0.10125554 | M48: ='Low Budget'!$V$48 -> 0.47336249 | S48: ='Middle Budget'!$L$48 -> 77191148 | U48: ='Middle Budget'!$R$48 -> 0.65 | W48: ='Middle Budget'!$T$48 -> 0.10024649 | Y48: ='Middle Budget'!$V$48 -> 0.4781272 | AE48: ='High Budget'!$L$48 -> 78345005 | AG48: ='High Budget'!$R$48 -> 0.65 | AI48: ='High Budget'!$T$48 -> 0.09877007 | AK48: ='High Budget'!$V$48 -> 0.48527427
E49: Equity | G49: ='Low Budget'!$L$49 -> 41150259 | I49: ='Low Budget'!$R$49 -> 0.35 | S49: ='Middle Budget'!$L$49 -> 41564464 | U49: ='Middle Budget'!$R$49 -> 0.35 | AE49: ='High Budget'!$L$49 -> 42185772 | AG49: ='High Budget'!$R$49 -> 0.35
G50: =SUM(G48:G49) -> 1.1757217e+08 | I50: ='Low Budget'!$R$50 -> 1 | S50: =SUM(S48:S49) -> 1.1875561e+08 | U50: ='Middle Budget'!$R$50 -> 1 | AE50: =SUM(AE48:AE49) -> 1.2053078e+08 | AG50: ='High Budget'!$R$50 -> 1
E51: Reconciliation to Total Cost:
E52: Total Capitalized Cost | G52: =G50 -> 1.1757217e+08 | S52: =S50 -> 1.1875561e+08 | AE52: =AE50 -> 1.2053078e+08
E53: Add: Lender Minimum Interest | G53: ='Low Budget'!$L$106 -> 0 | S53: ='Middle Budget'!$L$106 -> 0 | AE53: ='High Budget'!$L$106 -> 0
E54: Add: Lender Exit Fee | G54: ='Low Budget'!$L$107 -> 382109.55 | S54: ='Middle Budget'!$L$107 -> 385955.74 | AE54: ='High Budget'!$L$107 -> 391725.03
E55: Total Cost | G55: =SUM(G52:G54) -> 1.1795428e+08 | S55: =SUM(S52:S54) -> 1.1914157e+08 | AE55: =SUM(AE52:AE54) -> 1.209225e+08
G59: =$G$4 -> BUYER'S PREFERRED | S59: =$S$4 -> PROJECTED STRIKE | AE59: =$AE$4 -> OPTIMISTIC
D61: NET PROFIT - MERCHANT BUILD | G61: Total | I61: Per Unit | K61: Per SF | S61: Total | U61: Per Unit | W61: Per SF | AE61: Total | AG61: Per Unit | AI61: Per SF
E62: Market Value at Sale Date | G62: ='Low Budget'!$R$18 -> 1.6268776e+08 | I62: =G62/G$9 -> 464822.17 | K62: =G62/G$11 -> 619.7629 | S62: ='Middle Budget'!$R$18 -> 1.6268776e+08 | U62: =S62/S$9 -> 464822.17 | W62: =S62/S$11 -> 619.7629 | AE62: ='High Budget'!$R$18 -> 1.6268776e+08 | AG62: =AE62/AE$9 -> 464822.17 | AI62: =AE62/AE$11 -> 619.7629
E63: Less: Selling Costs | G63: ='Low Budget'!$R$19 -> -2033597 | I63: =G63/G$9 -> -5810.2772 | K63: =G63/G$11 -> -7.7470362 | S63: ='Middle Budget'!$R$19 -> -2033597 | U63: =S63/S$9 -> -5810.2772 | W63: =S63/S$11 -> -7.7470362 | AE63: ='High Budget'!$R$19 -> -2033597 | AG63: =AE63/AE$9 -> -5810.2772 | AI63: =AE63/AE$11 -> -7.7470362
E64: Net Sale Proceeds | G64: =SUM(G62:G63) -> 1.6065416e+08 | I64: =G64/G$9 -> 459011.9 | K64: =G64/G$11 -> 612.01586 | S64: =SUM(S62:S63) -> 1.6065416e+08 | U64: =S64/S$9 -> 459011.9 | W64: =S64/S$11 -> 612.01586 | AE64: =SUM(AE62:AE63) -> 1.6065416e+08 | AG64: =AE64/AE$9 -> 459011.9 | AI64: =AE64/AE$11 -> 612.01586
E66: Land | G66: ='Low Budget'!$L$71 -> 12250000 | I66: =G66/G$9 -> 35000 | K66: =G66/G$11 -> 46.666667 | S66: ='Middle Budget'!$L$71 -> 13300000 | U66: =S66/S$9 -> 38000 | W66: =S66/S$11 -> 50.666667 | AE66: ='High Budget'!$L$71 -> 14875000 | AG66: =AE66/AE$9 -> 42500 | AI66: =AE66/AE$11 -> 56.666667
E67: Hard Costs | G67: ='Low Budget'!$L$76 -> 86821875 | I67: =G67/G$9 -> 248062.5 | K67: =G67/G$11 -> 330.75 | S67: ='Middle Budget'!$L$76 -> 86821875 | U67: =S67/S$9 -> 248062.5 | W67: =S67/S$11 -> 330.75 | AE67: ='High Budget'!$L$76 -> 86821875 | AG67: =AE67/AE$9 -> 248062.5 | AI67: =AE67/AE$11 -> 330.75
E68: Soft Costs | G68: ='Low Budget'!$L$88 -> 12236045 | I68: =G68/G$9 -> 34960.129 | K68: =G68/G$11 -> 46.613505 | S68: ='Middle Budget'!$L$88 -> 12270301 | U68: =S68/S$9 -> 35058.002 | W68: =S68/S$11 -> 46.744003 | AE68: ='High Budget'!$L$88 -> 12321684 | AG68: =AE68/AE$9 -> 35204.812 | AI68: =AE68/AE$11 -> 46.93975
E69: Financing Costs (incl. exit fee and min. int.) | G69: ='Low Budget'!$L$98+'Low Budget'!$L$102+'Low Budget'!$L$108 -> 6646359 | I69: =G69/G$9 -> 18989.597 | K69: =G69/G$11 -> 25.319463 | S69: ='Middle Budget'!$L$98+'Middle Budget'!$L$102+'Middle Budget'!$L$108 -> 6749392.8 | U69: =S69/S$9 -> 19283.979 | W69: =S69/S$11 -> 25.711972 | AE69: ='High Budget'!$L$98+'High Budget'!$L$102+'High Budget'!$L$108 -> 6903943.4 | AG69: =AE69/AE$9 -> 19725.553 | AI69: =AE69/AE$11 -> 26.300737
E70: Total Cost | G70: =SUM(G66:G69) -> 1.1795428e+08 | I70: =G70/G$9 -> 337012.23 | K70: =G70/G$11 -> 449.34963 | S70: =SUM(S66:S69) -> 1.1914157e+08 | U70: =S70/S$9 -> 340404.48 | W70: =S70/S$11 -> 453.87264 | AE70: =SUM(AE66:AE69) -> 1.209225e+08 | AG70: =AE70/AE$9 -> 345492.86 | AI70: =AE70/AE$11 -> 460.65715
E72: Net Profit | G72: =G64-G70 -> 42699885 | I72: =G72/G$9 -> 121999.67 | K72: =G72/G$11 -> 162.66623 | S72: =S64-S70 -> 41512595 | U72: =S72/S$9 -> 118607.42 | W72: =S72/S$11 -> 158.14322 | AE72: =AE64-AE70 -> 39731661 | AG72: =AE72/AE$9 -> 113519.03 | AI72: =AE72/AE$11 -> 151.35871
E73: Add: Operating Cash Flow After Debt Service | G73: ='Low Budget'!R23 -> 2244685.6 | I73: =G73/G$9 -> 6413.3874 | K73: =G73/G$11 -> 8.5511832 | S73: ='Middle Budget'!R23 -> 2209429 | U73: =S73/S$9 -> 6312.6542 | W73: =S73/S$11 -> 8.4168723 | AE73: ='High Budget'!R23 -> 2156544 | AG73: =AE73/AE$9 -> 6161.5544 | AI73: =AE73/AE$11 -> 8.2154059
E74: Total Net Profit | G74: =SUM(G72:G73) -> 44944570 | I74: =G74/G$9 -> 128413.06 | K74: =G74/G$11 -> 171.21741 | S74: =SUM(S72:S73) -> 43722024 | U74: =S74/S$9 -> 124920.07 | W74: =S74/S$11 -> 166.56009 | AE74: =SUM(AE72:AE73) -> 41888205 | AG74: =AE74/AE$9 -> 119680.59 | AI74: =AE74/AE$11 -> 159.57412
D76: RETURNS - PERMANENT REFINANCING | G76: Interest Only | I76: Amortizing | S76: Interest Only | U76: Amortizing | AE76: Interest Only | AG76: Amortizing
E77: NOI w/ Developer RE Tax at Refi Date | G77: ='Low Budget'!$H$122 -> 8480558.3 | I77: ='Low Budget'!$H$122 -> 8480558.3 | S77: ='Middle Budget'!$H$122 -> 8480558.3 | U77: ='Middle Budget'!$H$122 -> 8480558.3 | AE77: ='High Budget'!$H$122 -> 8480558.3 | AG77: ='High Budget'!$H$122 -> 8480558.3
E78: Less: Debt Service | G78: =-'Low Budget'!$H$131 -> -5570650.9 | I78: =-'Low Budget'!$H$132 -> -6784446.6 | S78: =-'Middle Budget'!$H$131 -> -5570650.9 | U78: =-'Middle Budget'!$H$132 -> -6784446.6 | AE78: =-'High Budget'!$H$131 -> -5570650.9 | AG78: =-'High Budget'!$H$132 -> -6784446.6
E79: Net Cash Flow | G79: =SUM(G77:G78) -> 2909907.4 | I79: =SUM(I77:I78) -> 1696111.7 | S79: =SUM(S77:S78) -> 2909907.4 | U79: =SUM(U77:U78) -> 1696111.7 | AE79: =SUM(AE77:AE78) -> 2909907.4 | AG79: =SUM(AG77:AG78) -> 1696111.7
E81: Return on Net Equity Invested | G81: ='Low Budget'!$L$155 -> 0.14069565 | I81: ='Low Budget'!$H$155 -> 0.082007948 | S81: ='Middle Budget'!$L$155 -> 0.13289198 | U81: ='Middle Budget'!$H$155 -> 0.077459385 | AE81: ='High Budget'!$L$155 -> 0.12268492 | AG81: ='High Budget'!$H$155 -> 0.071509947
D83: NET OPERATING INCOME | G83: Stabilized Un-Trended | K83: ='Low Budget'!$H$26 -> 37 | S83: Stabilized Un-Trended | W83: ='Middle Budget'!$H$26 -> 37 | AE83: Stabilized Un-Trended | AI83: ='High Budget'!$H$26 -> 37
H85: Avg. Rent Per SF: | I85: ='Low NOI'!$M$14 -> 3.6533333 | L85: Avg. Rent Per SF: | M85: =LOOKUP(K$83,'Low ICF'!$K$3:$EX$3,'Low ICF'!$K$35:$EX$35)/G11 -> 4.0019416 | T85: Avg. Rent Per SF: | U85: ='Middle NOI'!$M$14 -> 3.6533333 | X85: Avg. Rent Per SF: | Y85: =LOOKUP(W$83,'Middle ICF'!$K$3:$EX$3,'Middle ICF'!$K$35:$EX$35)/S11 -> 4.0019416 | AF85: Avg. Rent Per SF: | AG85: ='High NOI'!$M$14 -> 3.6533333 | AJ85: Avg. Rent Per SF: | AK85: =LOOKUP(AI$83,'High ICF'!$K$3:$EX$3,'High ICF'!$K$35:$EX$35)/AE11 -> 4.0019416
H86: Avg. Rent Per Unit: | I86: ='Low NOI'!$K$14 -> 2740 | L86: Avg. Rent Per Unit: | M86: =LOOKUP(K$83,'Low ICF'!$K$3:$EX$3,'Low ICF'!$K$35:$EX$35)/G9 -> 3001.4562 | T86: Avg. Rent Per Unit: | U86: ='Middle NOI'!$K$14 -> 2740 | X86: Avg. Rent Per Unit: | Y86: =LOOKUP(W$83,'Middle ICF'!$K$3:$EX$3,'Middle ICF'!$K$35:$EX$35)/S9 -> 3001.4562 | AF86: Avg. Rent Per Unit: | AG86: ='High NOI'!$K$14 -> 2740 | AJ86: Avg. Rent Per Unit: | AK86: =LOOKUP(AI$83,'High ICF'!$K$3:$EX$3,'High ICF'!$K$35:$EX$35)/AE9 -> 3001.4562
E88: Gross Potential Rent | G88: ='Low NOI'!$K$33 -> 11508000 | K88: =LOOKUP(K$83,'Low ICF'!$K$3:$EX$3,'Low ICF'!$K$35:$EX$35)*12 -> 12606116 | S88: ='Middle NOI'!$K$33 -> 11508000 | W88: =LOOKUP(W$83,'Middle ICF'!$K$3:$EX$3,'Middle ICF'!$K$35:$EX$35)*12 -> 12606116 | AE88: ='High NOI'!$K$33 -> 11508000 | AI88: =LOOKUP(AI$83,'High ICF'!$K$3:$EX$3,'High ICF'!$K$35:$EX$35)*12 -> 12606116
E89: Loss to Lease, Vacancy & Collection Loss | G89: ='Low NOI'!$K$34+'Low NOI'!$K$37+'Low NOI'!$K$38 -> -604170 | I89: =-G89/G88 -> 0.0525 | K89: =(LOOKUP(K$83,'Low ICF'!$K$3:$EX$3,'Low ICF'!$K$36:$EX$36)+LOOKUP(K$83,'Low ICF'!$K$3:$EX$3,'Low ICF'!$K$39:$EX$39)+LOOKUP(K$83,'Low ICF'!$K$3:$EX$3,'Low ICF'!$K$40:$EX$40))*12 -> -787567.09 | M89: =-K89/K88 -> 0.062475 | S89: ='Middle NOI'!$K$34+'Middle NOI'!$K$37+'Middle NOI'!$K$38 -> -604170 | U89: =-S89/S88 -> 0.0525 | W89: =(LOOKUP(W$83,'Middle ICF'!$K$3:$EX$3,'Middle ICF'!$K$36:$EX$36)+LOOKUP(W$83,'Middle ICF'!$K$3:$EX$3,'Middle ICF'!$K$39:$EX$39)+LOOKUP(W$83,'Middle ICF'!$K$3:$EX$3,'Middle ICF'!$K$40:$EX$40))*12 -> -787567.09 | Y89: =-W89/W88 -> 0.062475 | AE89: ='High NOI'!$K$34+'High NOI'!$K$37+'High NOI'!$K$38 -> -604170 | AG89: =-AE89/AE88 -> 0.0525 | AI89: =(LOOKUP(AI$83,'High ICF'!$K$3:$EX$3,'High ICF'!$K$36:$EX$36)+LOOKUP(AI$83,'High ICF'!$K$3:$EX$3,'High ICF'!$K$39:$EX$39)+LOOKUP(AI$83,'High ICF'!$K$3:$EX$3,'High ICF'!$K$40:$EX$40))*12 -> -787567.09 | AK89: =-AI89/AI88 -> 0.062475
E90: Net Rental Income | G90: =SUM(G88:G89) -> 10903830 | K90: =SUM(K88:K89) -> 11818549 | S90: =SUM(S88:S89) -> 10903830 | W90: =SUM(W88:W89) -> 11818549 | AE90: =SUM(AE88:AE89) -> 10903830 | AI90: =SUM(AI88:AI89) -> 11818549
E91: Other Income | G91: ='Low NOI'!$K$40+'Low NOI'!$K$41 -> 679945 | I91: =G91/G$9 -> 1942.7 | K91: =(LOOKUP(K$83,'Low ICF'!$K$3:$EX$3,'Low ICF'!$K$42:$EX$42)+LOOKUP(K$83,'Low ICF'!$K$3:$EX$3,'Low ICF'!$K$43:$EX$43))*12 -> 740259.01 | M91: =K91/G$9 -> 2115.0257 | S91: ='Middle NOI'!$K$40+'Middle NOI'!$K$41 -> 679945 | U91: =S91/S$9 -> 1942.7 | W91: =(LOOKUP(W$83,'Middle ICF'!$K$3:$EX$3,'Middle ICF'!$K$42:$EX$42)+LOOKUP(W$83,'Middle ICF'!$K$3:$EX$3,'Middle ICF'!$K$43:$EX$43))*12 -> 740259.01 | Y91: =W91/S$9 -> 2115.0257 | AE91: ='High NOI'!$K$40+'High NOI'!$K$41 -> 679945 | AG91: =AE91/AE$9 -> 1942.7 | AI91: =(LOOKUP(AI$83,'High ICF'!$K$3:$EX$3,'High ICF'!$K$42:$EX$42)+LOOKUP(AI$83,'High ICF'!$K$3:$EX$3,'High ICF'!$K$43:$EX$43))*12 -> 740259.01 | AK91: =AI91/AE$9 -> 2115.0257
E92: Total Revenue | G92: =SUM(G90:G91) -> 11583775 | K92: =SUM(K90:K91) -> 12558808 | S92: =SUM(S90:S91) -> 11583775 | W92: =SUM(W90:W91) -> 12558808 | AE92: =SUM(AE90:AE91) -> 11583775 | AI92: =SUM(AI90:AI91) -> 12558808
E93: Payroll | G93: ='Low NOI'!$K$46 -> 538200 | I93: =G93/G$9 -> 1537.7143 | K93: =LOOKUP(K$83,'Low ICF'!$K$3:$EX$3,'Low ICF'!$K$48:$EX$48)*12 -> 580776.38 | M93: =K93/G$9 -> 1659.3611 | S93: ='Middle NOI'!$K$46 -> 538200 | U93: =S93/S$9 -> 1537.7143 | W93: =LOOKUP(W$83,'Middle ICF'!$K$3:$EX$3,'Middle ICF'!$K$48:$EX$48)*12 -> 580776.38 | Y93: =W93/S$9 -> 1659.3611 | AE93: ='High NOI'!$K$46 -> 538200 | AG93: =AE93/AE$9 -> 1537.7143 | AI93: =LOOKUP(AI$83,'High ICF'!$K$3:$EX$3,'High ICF'!$K$48:$EX$48)*12 -> 580776.38 | AK93: =AI93/AE$9 -> 1659.3611
E94: General & Administrative | G94: ='Low NOI'!$K$47 -> 87500 | I94: =G94/G$9 -> 250 | K94: =LOOKUP(K$83,'Low ICF'!$K$3:$EX$3,'Low ICF'!$K$49:$EX$49)*12 -> 94422.024 | M94: =K94/G$9 -> 269.77721 | S94: ='Middle NOI'!$K$47 -> 87500 | U94: =S94/S$9 -> 250 | W94: =LOOKUP(W$83,'Middle ICF'!$K$3:$EX$3,'Middle ICF'!$K$49:$EX$49)*12 -> 94422.024 | Y94: =W94/S$9 -> 269.77721 | AE94: ='High NOI'!$K$47 -> 87500 | AG94: =AE94/AE$9 -> 250 | AI94: =LOOKUP(AI$83,'High ICF'!$K$3:$EX$3,'High ICF'!$K$49:$EX$49)*12 -> 94422.024 | AK94: =AI94/AE$9 -> 269.77721
E95: Repairs & Maintenance | G95: ='Low NOI'!$K$48 -> 87500 | I95: =G95/G$9 -> 250 | K95: =LOOKUP(K$83,'Low ICF'!$K$3:$EX$3,'Low ICF'!$K$50:$EX$50)*12 -> 94422.024 | M95: =K95/G$9 -> 269.77721 | S95: ='Middle NOI'!$K$48 -> 87500 | U95: =S95/S$9 -> 250 | W95: =LOOKUP(W$83,'Middle ICF'!$K$3:$EX$3,'Middle ICF'!$K$50:$EX$50)*12 -> 94422.024 | Y95: =W95/S$9 -> 269.77721 | AE95: ='High NOI'!$K$48 -> 87500 | AG95: =AE95/AE$9 -> 250 | AI95: =LOOKUP(AI$83,'High ICF'!$K$3:$EX$3,'High ICF'!$K$50:$EX$50)*12 -> 94422.024 | AK95: =AI95/AE$9 -> 269.77721
E96: Contract Services | G96: ='Low NOI'!$K$49 -> 175000 | I96: =G96/G$9 -> 500 | K96: =LOOKUP(K$83,'Low ICF'!$K$3:$EX$3,'Low ICF'!$K$51:$EX$51)*12 -> 188844.05 | M96: =K96/G$9 -> 539.55442 | S96: ='Middle NOI'!$K$49 -> 175000 | U96: =S96/S$9 -> 500 | W96: =LOOKUP(W$83,'Middle ICF'!$K$3:$EX$3,'Middle ICF'!$K$51:$EX$51)*12 -> 188844.05 | Y96: =W96/S$9 -> 539.55442 | AE96: ='High NOI'!$K$49 -> 175000 | AG96: =AE96/AE$9 -> 500 | AI96: =LOOKUP(AI$83,'High ICF'!$K$3:$EX$3,'High ICF'!$K$51:$EX$51)*12 -> 188844.05 | AK96: =AI96/AE$9 -> 539.55442
E97: Turnover | G97: ='Low NOI'!$K$50 -> 87500 | I97: =G97/G$9 -> 250 | K97: =LOOKUP(K$83,'Low ICF'!$K$3:$EX$3,'Low ICF'!$K$52:$EX$52)*12 -> 94422.024 | M97: =K97/G$9 -> 269.77721 | S97: ='Middle NOI'!$K$50 -> 87500 | U97: =S97/S$9 -> 250 | W97: =LOOKUP(W$83,'Middle ICF'!$K$3:$EX$3,'Middle ICF'!$K$52:$EX$52)*12 -> 94422.024 | Y97: =W97/S$9 -> 269.77721 | AE97: ='High NOI'!$K$50 -> 87500 | AG97: =AE97/AE$9 -> 250 | AI97: =LOOKUP(AI$83,'High ICF'!$K$3:$EX$3,'High ICF'!$K$52:$EX$52)*12 -> 94422.024 | AK97: =AI97/AE$9 -> 269.77721
E98: Utilities | G98: ='Low NOI'!$K$51 -> 350000 | I98: =G98/G$9 -> 1000 | K98: =LOOKUP(K$83,'Low ICF'!$K$3:$EX$3,'Low ICF'!$K$53:$EX$53)*12 -> 377688.1 | M98: =K98/G$9 -> 1079.1088 | S98: ='Middle NOI'!$K$51 -> 350000 | U98: =S98/S$9 -> 1000 | W98: =LOOKUP(W$83,'Middle ICF'!$K$3:$EX$3,'Middle ICF'!$K$53:$EX$53)*12 -> 377688.1 | Y98: =W98/S$9 -> 1079.1088 | AE98: ='High NOI'!$K$51 -> 350000 | AG98: =AE98/AE$9 -> 1000 | AI98: =LOOKUP(AI$83,'High ICF'!$K$3:$EX$3,'High ICF'!$K$53:$EX$53)*12 -> 377688.1 | AK98: =AI98/AE$9 -> 1079.1088
E99: Leasing & Marketing | G99: ='Low NOI'!$K$52 -> 87500 | I99: =G99/G$9 -> 250 | K99: =LOOKUP(K$83,'Low ICF'!$K$3:$EX$3,'Low ICF'!$K$54:$EX$54)*12 -> 94422.024 | M99: =K99/G$9 -> 269.77721 | S99: ='Middle NOI'!$K$52 -> 87500 | U99: =S99/S$9 -> 250 | W99: =LOOKUP(W$83,'Middle ICF'!$K$3:$EX$3,'Middle ICF'!$K$54:$EX$54)*12 -> 94422.024 | Y99: =W99/S$9 -> 269.77721 | AE99: ='High NOI'!$K$52 -> 87500 | AG99: =AE99/AE$9 -> 250 | AI99: =LOOKUP(AI$83,'High ICF'!$K$3:$EX$3,'High ICF'!$K$54:$EX$54)*12 -> 94422.024 | AK99: =AI99/AE$9 -> 269.77721
E100: Management Fee | G100: ='Low NOI'!$K$53 -> 231675.5 | I100: =G100/G92 -> 0.02 | K100: =LOOKUP(K$83,'Low ICF'!$K$3:$EX$3,'Low ICF'!$K$55:$EX$55)*12 -> 251176.16 | M100: =K100/K92 -> 0.02 | S100: ='Middle NOI'!$K$53 -> 231675.5 | U100: =S100/S92 -> 0.02 | W100: =LOOKUP(W$83,'Middle ICF'!$K$3:$EX$3,'Middle ICF'!$K$55:$EX$55)*12 -> 251176.16 | Y100: =W100/W92 -> 0.02 | AE100: ='High NOI'!$K$53 -> 231675.5 | AG100: =AE100/AE92 -> 0.02 | AI100: =LOOKUP(AI$83,'High ICF'!$K$3:$EX$3,'High ICF'!$K$55:$EX$55)*12 -> 251176.16 | AK100: =AI100/AI92 -> 0.02
E101: Insurance | G101: ='Low NOI'!$K$54 -> 612500 | I101: =G101/G$9 -> 1750 | K101: =LOOKUP(K$83,'Low ICF'!$K$3:$EX$3,'Low ICF'!$K$56:$EX$56)*12 -> 660954.17 | M101: =K101/G$9 -> 1888.4405 | S101: ='Middle NOI'!$K$54 -> 612500 | U101: =S101/S$9 -> 1750 | W101: =LOOKUP(W$83,'Middle ICF'!$K$3:$EX$3,'Middle ICF'!$K$56:$EX$56)*12 -> 660954.17 | Y101: =W101/S$9 -> 1888.4405 | AE101: ='High NOI'!$K$54 -> 612500 | AG101: =AE101/AE$9 -> 1750 | AI101: =LOOKUP(AI$83,'High ICF'!$K$3:$EX$3,'High ICF'!$K$56:$EX$56)*12 -> 660954.17 | AK101: =AI101/AE$9 -> 1888.4405
E102: Property Tax (developer) | G102: ='Low NOI'!$K$55 -> 1518257.8 | I102: =G102/G$9 -> 4337.8794 | K102: =LOOKUP(K$83,'Low ICF'!$K$3:$EX$3,'Low ICF'!$K$57:$EX$57)*12 -> 1638365.4 | M102: =K102/G$9 -> 4681.044 | S102: ='Middle NOI'!$K$55 -> 1518257.8 | U102: =S102/S$9 -> 4337.8794 | W102: =LOOKUP(W$83,'Middle ICF'!$K$3:$EX$3,'Middle ICF'!$K$57:$EX$57)*12 -> 1638365.4 | Y102: =W102/S$9 -> 4681.044 | AE102: ='High NOI'!$K$55 -> 1518257.8 | AG102: =AE102/AE$9 -> 4337.8794 | AI102: =LOOKUP(AI$83,'High ICF'!$K$3:$EX$3,'High ICF'!$K$57:$EX$57)*12 -> 1638365.4 | AK102: =AI102/AE$9 -> 4681.044
E103: Replacement Reserve | G103: ='Low NOI'!$K$60 -> 70000 | I103: =G103/G$9 -> 200 | K103: =LOOKUP(K$83,'Low ICF'!$K$3:$EX$3,'Low ICF'!$K$58:$EX$58)*12 -> 70000 | M103: =K103/G$9 -> 200 | S103: ='Middle NOI'!$K$60 -> 70000 | U103: =S103/S$9 -> 200 | W103: =LOOKUP(W$83,'Middle ICF'!$K$3:$EX$3,'Middle ICF'!$K$58:$EX$58)*12 -> 70000 | Y103: =W103/S$9 -> 200 | AE103: ='High NOI'!$K$60 -> 70000 | AG103: =AE103/AE$9 -> 200 | AI103: =LOOKUP(AI$83,'High ICF'!$K$3:$EX$3,'High ICF'!$K$58:$EX$58)*12 -> 70000 | AK103: =AI103/AE$9 -> 200
E104: Total Expenses | G104: =SUM(G93:G103) -> 3845633.3 | I104: =G104/G$9 -> 10987.524 | K104: =SUM(K93:K103) -> 4145492.3 | M104: =K104/G$9 -> 11844.264 | S104: =SUM(S93:S103) -> 3845633.3 | U104: =S104/S$9 -> 10987.524 | W104: =SUM(W93:W103) -> 4145492.3 | Y104: =W104/S$9 -> 11844.264 | AE104: =SUM(AE93:AE103) -> 3845633.3 | AG104: =AE104/AE$9 -> 10987.524 | AI104: =SUM(AI93:AI103) -> 4145492.3 | AK104: =AI104/AE$9 -> 11844.264
E105: Net Operating Income | G105: =IF(ABS(G92-G104-'Low NOI'!$K$62)<1,G92-G104,"ERROR") -> 7738141.7 | I105: =G105/G88 -> 0.67241412 | K105: =IF(ABS((K92-K104)-(LOOKUP(K$83,'Low ICF'!$K$3:$EX$3,'Low ICF'!$K$61:$EX$61)*12))<1,K92-K104,"ERROR") -> 8413315.5 | M105: =K105/K88 -> 0.6673995 | S105: =IF(ABS(S92-S104-'Middle NOI'!$K$62)<1,S92-S104,"ERROR") -> 7738141.7 | U105: =S105/S88 -> 0.67241412 | W105: =IF(ABS((W92-W104)-(LOOKUP(W$83,'Middle ICF'!$K$3:$EX$3,'Middle ICF'!$K$61:$EX$61)*12))<1,W92-W104,"ERROR") -> 8413315.5 | Y105: =W105/W88 -> 0.6673995 | AE105: =IF(ABS(AE92-AE104-'High NOI'!$K$62)<1,AE92-AE104,"ERROR") -> 7738141.7 | AG105: =AE105/AE88 -> 0.67241412 | AI105: =IF(ABS((AI92-AI104)-(LOOKUP(AI$83,'High ICF'!$K$3:$EX$3,'High ICF'!$K$61:$EX$61)*12))<1,AI92-AI104,"ERROR") -> 8413315.5 | AK105: =AI105/AI88 -> 0.6673995
H108: Payroll FTE Per Unit: | I108: ='Low Payroll'!$P$13 -> 1 | T108: Payroll FTE Per Unit: | U108: ='Middle Payroll'!$P$13 -> 1 | AF108: Payroll FTE Per Unit: | AG108: ='High Payroll'!$P$13 -> 1

Sheet BOV TABLES
A1: =Summary!A1 -> 301 E. ATLANTIC POMPANO BEACH
G4: BUYER'S PREFERRED | O4: PROJECTED STRIKE | W4: OPTIMISTIC
D5: VALUATION
D6: (Subject to site plan approval)
E7: Total Land Value | G7: =Summary!G12 -> 12250000 | O7: =Summary!S12 -> 13300000 | W7: =Summary!AE12 -> 14875000
E8: Land Value Per Unit | G8: =Summary!G13 -> 35000 | O8: =Summary!S13 -> 38000 | W8: =Summary!AE13 -> 42500
E9: Land Value Per Acre | G9: =Summary!G14 -> 5243551.3 | O9: =Summary!S14 -> 5692998.6 | W9: =Summary!AE14 -> 6367169.5
D11: RETURNS - MERCHANT BUILD
E12: Un-Trended ROC (NOI w/ developer RE taxes) | G12: =Summary!G15 -> 0.065602891 | O12: =Summary!S15 -> 0.064949134 | W12: =Summary!AE15 -> 0.06399257
E13: Net Profit as % of Cost (excl. net op. CF) | G13: =Summary!G16 -> 0.3620037 | O13: =Summary!S16 -> 0.34843083 | W13: =Summary!AE16 -> 0.32857128
E14: IRR on Sale (incl. net op. CF) | G14: =Summary!G17 -> 0.24813606 | O14: =Summary!S17 -> 0.24086857 | W14: =Summary!AE17 -> 0.23005278
E15: Equity Multiple on Sale (incl. net op. CF) | G15: =Summary!G18 -> 2.0922063 | O15: =Summary!S18 -> 2.0519088 | W15: =Summary!AE18 -> 1.9929463
E16: Investment Period | G16: =Summary!G19 -> 40 | O16: =Summary!S19 -> 40 | W16: =Summary!AE19 -> 40
D18: LAND AREA & UNIT INVENTORY
E19: Land Area | G19: =Summary!G7 -> 2.3362029 | O19: =Summary!S7 -> 2.3362029 | W19: =Summary!AE7 -> 2.3362029
E20: Density | G20: ='Low Budget'!$H$7 -> 149.81575 | O20: ='Middle Budget'!$H$7 -> 149.81575 | W20: ='High Budget'!$H$7 -> 149.81575
E21: Height | G21: ='Low Budget'!$H$8 -> 8 | O21: ='Middle Budget'!$H$8 -> 8 | W21: ='Low Budget'!$H$8 -> 8
E22: Gross Building Area | G22: ='Low Budget'!$H$9 -> 525000 | O22: ='Middle Budget'!$H$9 -> 525000 | W22: ='Low Budget'!$H$9 -> 525000
E23: Building Efficiency | G23: ='Low Budget'!$H$10 -> 0.5 | O23: ='Middle Budget'!$H$10 -> 0.5 | W23: ='Low Budget'!$H$10 -> 0.5
E24: Unit Count | G24: =Summary!G9 -> 350 | O24: =Summary!S9 -> 350 | W24: =Summary!AE9 -> 350
E25: Average Unit Size | G25: =Summary!G10 -> 750 | O25: =Summary!S10 -> 750 | W25: =Summary!AE10 -> 750
E26: Net Rentable Area | G26: =Summary!G11 -> 262500 | O26: =Summary!S11 -> 262500 | W26: =Summary!AE11 -> 262500
D28: RENT & NOI
E29: Un-Trended Average Rent Per Unit | G29: =Summary!M25 -> 2740 | O29: =Summary!Y25 -> 2740 | W29: =Summary!AK25 -> 2740
E30: Un-Trended Average Rent Per SF | G30: =Summary!M26 -> 3.6533333 | O30: =Summary!Y26 -> 3.6533333 | W30: =Summary!AK26 -> 3.6533333
E31: Un-Trended NOI (w/ developer RE taxes) | G31: =Summary!G28 -> 7738141.7 | I31: =Summary!I28 -> 0.67241412 | O31: =Summary!S28 -> 7738141.7 | Q31: =Summary!U28 -> 0.67241412 | W31: =Summary!AE28 -> 7738141.7 | Y31: =Summary!AG28 -> 0.67241412
D33: LEASE-UP & STABILIZED VALUE
E34: Lease-Up Velocity | G34: =Summary!G31 -> 12 | I34: =Summary!I31 -> 25.576923 | O34: =Summary!S31 -> 12 | Q34: =Summary!U31 -> 25.576923 | W34: =Summary!AE31 -> 12 | Y34: =Summary!AG31 -> 25.576923
E35: Market Cap Rate | G35: =Summary!G32 -> 0.0475 | O35: =Summary!S32 -> 0.0475 | W35: =Summary!AE32 -> 0.0475
E36: Stabilized Value (trended) | G36: =Summary!G33 -> 1.6268776e+08 | I36: =Summary!I33 -> 464822.17 | O36: =Summary!S33 -> 1.6268776e+08 | Q36: =Summary!U33 -> 464822.17 | W36: =Summary!AE33 -> 1.6268776e+08 | Y36: =Summary!AG33 -> 464822.17
I37: =Summary!I34 -> 619.7629 | Q37: =Summary!U34 -> 619.7629 | Y37: =Summary!AG34 -> 619.7629
D38: DEVELOPMENT COST ASSUMPTIONS
E39: Hard Costs (excl. impact fees, permits, utility connect) | G39: =Summary!G36 -> 315 | I39: =Summary!I36 -> 248062.5 | K39: ='Low Budget'!$L$76/'Low Budget'!$H$9 -> 165.375 | O39: =Summary!S36 -> 315 | Q39: =Summary!U36 -> 248062.5 | S39: ='Middle Budget'!$L$76/'Middle Budget'!$H$9 -> 165.375 | W39: =Summary!AE36 -> 315 | Y39: =Summary!AG36 -> 248062.5 | AA39: ='High Budget'!$L$76/'High Budget'!$H$9 -> 165.375
E40: Hard Cost Contingency | G40: =Summary!G37 -> 0.05 | O40: =Summary!S37 -> 0.05 | W40: =Summary!AE37 -> 0.05
E41: Developer Fee as % of Cost Excl. Land & Financing | G41: =Summary!G40 -> 0.03 | I41: =Summary!I40 -> 2885182.1 | O41: =Summary!S40 -> 0.03 | Q41: =Summary!U40 -> 2886179.9 | W41: =Summary!AE40 -> 0.03 | Y41: =Summary!AG40 -> 2887676.5
E42: Construction Period | G42: =Summary!G42 -> 24 | O42: =Summary!S42 -> 24 | W42: =Summary!AE42 -> 24
E43: Total Development Cost (land, hard and soft) | G43: =Summary!G43 -> 1.1795428e+08 | I43: =Summary!I43 -> 337012.23 | O43: =Summary!S43 -> 1.1914157e+08 | Q43: =Summary!U43 -> 340404.48 | W43: =Summary!AE43 -> 1.209225e+08 | Y43: =Summary!AG43 -> 345492.86
I44: =Summary!I44 -> 449.34963 | Q44: =Summary!U44 -> 453.87264 | Y44: =Summary!AG44 -> 460.65715
G48: =$G$4 -> BUYER'S PREFERRED | O48: =$O$4 -> PROJECTED STRIKE | W48: =$W$4 -> OPTIMISTIC
D50: DEVELOPMENT CAPITALIZATION | G50: Total | I50: % Cost | O50: Total | Q50: % Cost | W50: Total | Y50: % Cost
E52: Loan | G52: =Summary!G48 -> 76421910 | I52: =Summary!I48 -> 0.65 | O52: =Summary!S48 -> 77191148 | Q52: =Summary!U48 -> 0.65 | W52: =Summary!AE48 -> 78345005 | Y52: =Summary!AG48 -> 0.65
E53: Equity | G53: =Summary!G49 -> 41150259 | I53: =Summary!I49 -> 0.35 | O53: =Summary!S49 -> 41564464 | Q53: =Summary!U49 -> 0.35 | W53: =Summary!AE49 -> 42185772 | Y53: =Summary!AG49 -> 0.35
G54: =Summary!G50 -> 1.1757217e+08 | I54: =Summary!I50 -> 1 | O54: =Summary!S50 -> 1.1875561e+08 | Q54: =Summary!U50 -> 1 | W54: =Summary!AE50 -> 1.2053078e+08 | Y54: =Summary!AG50 -> 1
E55: Reconciliation to Total Cost:
E56: Total Capitalized Cost | G56: =Summary!G52 -> 1.1757217e+08 | O56: =Summary!S52 -> 1.1875561e+08 | W56: =Summary!AE52 -> 1.2053078e+08
E57: Add: Lender Minimum Interest | G57: =Summary!G53 -> 0 | O57: =Summary!S53 -> 0 | W57: =Summary!AE53 -> 0
E58: Add: Lender Exit Fee | G58: =Summary!G54 -> 382109.55 | O58: =Summary!S54 -> 385955.74 | W58: =Summary!AE54 -> 391725.03
E59: Total Cost | G59: =Summary!G55 -> 1.1795428e+08 | O59: =Summary!S55 -> 1.1914157e+08 | W59: =Summary!AE55 -> 1.209225e+08
D62: NET PROFIT - MERCHANT BUILD | G62: Total | I62: Per Unit | K62: Per SF | O62: Total | Q62: Per Unit | S62: Per SF | W62: Total | Y62: Per Unit | AA62: Per SF
E63: Market Value at Sale Date | G63: =Summary!G62 -> 1.6268776e+08 | I63: =Summary!I62 -> 464822.17 | K63: =Summary!K62 -> 619.7629 | O63: =Summary!S62 -> 1.6268776e+08 | Q63: =Summary!U62 -> 464822.17 | S63: =Summary!W62 -> 619.7629 | W63: =Summary!AE62 -> 1.6268776e+08 | Y63: =Summary!AG62 -> 464822.17 | AA63: =Summary!AI62 -> 619.7629
E64: Less: Selling Costs | G64: =Summary!G63 -> -2033597 | I64: =Summary!I63 -> -5810.2772 | K64: =Summary!K63 -> -7.7470362 | O64: =Summary!S63 -> -2033597 | Q64: =Summary!U63 -> -5810.2772 | S64: =Summary!W63 -> -7.7470362 | W64: =Summary!AE63 -> -2033597 | Y64: =Summary!AG63 -> -5810.2772 | AA64: =Summary!AI63 -> -7.7470362
E65: Net Sale Proceeds | G65: =Summary!G64 -> 1.6065416e+08 | I65: =Summary!I64 -> 459011.9 | K65: =Summary!K64 -> 612.01586 | O65: =Summary!S64 -> 1.6065416e+08 | Q65: =Summary!U64 -> 459011.9 | S65: =Summary!W64 -> 612.01586 | W65: =Summary!AE64 -> 1.6065416e+08 | Y65: =Summary!AG64 -> 459011.9 | AA65: =Summary!AI64 -> 612.01586
E67: Land | G67: =Summary!G66 -> 12250000 | I67: =Summary!I66 -> 35000 | K67: =Summary!K66 -> 46.666667 | O67: =Summary!S66 -> 13300000 | Q67: =Summary!U66 -> 38000 | S67: =Summary!W66 -> 50.666667 | W67: =Summary!AE66 -> 14875000 | Y67: =Summary!AG66 -> 42500 | AA67: =Summary!AI66 -> 56.666667
E68: Hard Costs | G68: =Summary!G67 -> 86821875 | I68: =Summary!I67 -> 248062.5 | K68: =Summary!K67 -> 330.75 | O68: =Summary!S67 -> 86821875 | Q68: =Summary!U67 -> 248062.5 | S68: =Summary!W67 -> 330.75 | W68: =Summary!AE67 -> 86821875 | Y68: =Summary!AG67 -> 248062.5 | AA68: =Summary!AI67 -> 330.75
E69: Soft Costs | G69: =Summary!G68 -> 12236045 | I69: =Summary!I68 -> 34960.129 | K69: =Summary!K68 -> 46.613505 | O69: =Summary!S68 -> 12270301 | Q69: =Summary!U68 -> 35058.002 | S69: =Summary!W68 -> 46.744003 | W69: =Summary!AE68 -> 12321684 | Y69: =Summary!AG68 -> 35204.812 | AA69: =Summary!AI68 -> 46.93975
E70: Financing Costs (incl. exit fee and min. int.) | G70: =Summary!G69 -> 6646359 | I70: =Summary!I69 -> 18989.597 | K70: =Summary!K69 -> 25.319463 | O70: =Summary!S69 -> 6749392.8 | Q70: =Summary!U69 -> 19283.979 | S70: =Summary!W69 -> 25.711972 | W70: =Summary!AE69 -> 6903943.4 | Y70: =Summary!AG69 -> 19725.553 | AA70: =Summary!AI69 -> 26.300737
E71: Total Cost | G71: =Summary!G70 -> 1.1795428e+08 | I71: =Summary!I70 -> 337012.23 | K71: =Summary!K70 -> 449.34963 | O71: =Summary!S70 -> 1.1914157e+08 | Q71: =Summary!U70 -> 340404.48 | S71: =Summary!W70 -> 453.87264 | W71: =Summary!AE70 -> 1.209225e+08 | Y71: =Summary!AG70 -> 345492.86 | AA71: =Summary!AI70 -> 460.65715
E73: Net Profit | G73: =Summary!G72 -> 42699885 | I73: =Summary!I72 -> 121999.67 | K73: =Summary!K72 -> 162.66623 | O73: =Summary!S72 -> 41512595 | Q73: =Summary!U72 -> 118607.42 | S73: =Summary!W72 -> 158.14322 | W73: =Summary!AE72 -> 39731661 | Y73: =Summary!AG72 -> 113519.03 | AA73: =Summary!AI72 -> 151.35871
E74: Add: Operating Cash Flow After Debt Service | G74: =Summary!G73 -> 2244685.6 | I74: =Summary!I73 -> 6413.3874 | K74: =Summary!K73 -> 8.5511832 | O74: =Summary!S73 -> 2209429 | Q74: =Summary!U73 -> 6312.6542 | S74: =Summary!W73 -> 8.4168723 | W74: =Summary!AE73 -> 2156544 | Y74: =Summary!AG73 -> 6161.5544 | AA74: =Summary!AI73 -> 8.2154059
E75: Total Net Profit | G75: =Summary!G74 -> 44944570 | I75: =Summary!I74 -> 128413.06 | K75: =Summary!K74 -> 171.21741 | O75: =Summary!S74 -> 43722024 | Q75: =Summary!U74 -> 124920.07 | S75: =Summary!W74 -> 166.56009 | W75: =Summary!AE74 -> 41888205 | Y75: =Summary!AG74 -> 119680.59 | AA75: =Summary!AI74 -> 159.57412

Sheet Middle Budget
A1: =Summary!$A$1&" - "&Summary!$S$4 -> 301 E. ATLANTIC POMPANO BEACH - PROJECTED STRIKE | Z1: FONT KEY
Z2: Blue = Input cell
Z3: Red = Link to Summary
C4: UNIT SUMMARY | L4: PROJECTED PROFIT ON SALE AT STABILIZATION | Z4: Black = Text or formula cell
E6: Development Land Area | H6: =(54965+46800)/43560 -> 2.3362029
E7: Density | H7: =H11/H6 -> 149.81575 | L7: Stabilized Value | T7: Sale / Refi | V7: Stabilization
E8: Height | H8: 8 | T8: =H27 -> 40 | V8: =H26 -> 37
E9: Gross Building Area | H9: =H12/H10 -> 525000 | L9: NOI with Developer Property Taxes | R9: RE Tax | T9: =LOOKUP(H27,'Middle ICF'!K3:EX3,'Middle ICF'!K61:EX61)*12 -> 8480558.3 | V9: =LOOKUP(H26,'Middle ICF'!K3:EX3,'Middle ICF'!K61:EX61)*12 -> 8413315.5
E10: Building Efficiency | H10: 0.5 | L10: Add Back: Developer Property Taxes | R10: Reassessment | T10: =LOOKUP(H27,'Middle ICF'!K3:EX3,'Middle ICF'!K57:EX57)*12 -> 1648510.6 | V10: =LOOKUP(H26,'Middle ICF'!K3:EX3,'Middle ICF'!K57:EX57)*12 -> 1638365.4
E11: Unit Count - Total | H11: ='Middle NOI'!F14 -> 350 | L11: Less: Taxes with Market Value Reassessment | R11: 0.75 | T11: =-T14*$R$11*$R$12*(1-R13) -> -2401400.2 | V11: =-V14*R11*R12*(1-R13) -> -2383053.1
E12: Net Rentable Area | H12: ='Middle NOI'!I14 -> 262500 | L12: NOI After Market Value Tax Reassessment | R12: 0.0205011 | T12: =SUM(T9:T11) -> 7727668.7 | V12: =SUM(V9:V11) -> 7668627.8
E13: Average Unit Size | H13: =H12/H11 -> 750 | L13: Market Cap Rate | R13: 0.04 | T13: =Summary!S32 -> 0.0475 | V13: =Summary!S32 -> 0.0475
E14: Un-Trended Average Rent Per Unit | H14: ='Middle NOI'!K14 -> 2740 | L14: Estimated Market Value | T14: =IF(ABS(T13)>0,T12/T13,0) -> 1.6268776e+08 | V14: =IF(ABS(V13)>0,V12/V13,0) -> 1.614448e+08
E15: Un-Trended Average Rent Per SF | H15: ='Middle NOI'!M14 -> 3.6533333
E16: Un-Trended NOI (developer property taxes) | H16: ='Middle NOI'!K62 -> 7738141.7 | L16: Net Profit on Sale at Stabilization
R17: Total | T17: Per Unit | V17: Per SF
C18: PROJECTED TIMING | L18: Value at Sale Date | R18: =T14 -> 1.6268776e+08 | T18: =R18/$H$11 -> 464822.17 | V18: =R18/$H$12 -> 619.7629
L19: 0.0125 | R19: =R18*-L19 -> -2033597 | T19: =R19/$H$11 -> -5810.2772 | V19: =R19/$H$12 -> -7.7470362
E20: Hard Cost Draws Start | H20: 1 | L20: Net Sale Proceeds | R20: =SUM(R18:R19) -> 1.6065416e+08 | T20: =R20/$H$11 -> 459011.9 | V20: =R20/$H$12 -> 612.01586
E21: Hard Cost Draws End | H21: =Summary!S42 -> 24 | L21: Less: Total Land & Development Cost | R21: =-L110 -> -1.1914157e+08 | T21: =R21/$H$11 -> -340404.48 | V21: =R21/$H$12 -> -453.87264
E22: Soft Cost Draws Start Excl. Op. Deficit | H22: 1 | L22: Net Profit on Sale | R22: =SUM(R20:R21) -> 41512595 | T22: =R22/$H$11 -> 118607.42 | V22: =R22/$H$12 -> 158.14322
E23: 2 | H23: =H21+E23 -> 26 | L23: Add: Operating Cash Flow After Debt Service | R23: ='Middle ICF'!I104-'Middle ICF'!I115 -> 2209429 | T23: =R23/$H$11 -> 6312.6542 | V23: =R23/$H$12 -> 8.4168723
E24: 1 | H24: =H21+E24 -> 25 | L24: Total Net Profit | R24: =SUM(R22:R23) -> 43722024 | T24: =R24/$H$11 -> 124920.07 | V24: =R24/$H$12 -> 166.56009
E25: Average Monthly Move-Ins | H25: =(H11*(1-'Middle NOI'!$Y$9))/(H26-H24+1) -> 25.576923
E26: =Summary!S31 -> 12 | H26: =H24+E26 -> 37 | L26: RETURN METRICS
E27: 3 | H27: =H26+E27 -> 40
L28: Merchant Build
C29: CONSTRUCTION FINANCING ASSUMPTIONS | L29: Untrended Return on Cost (NOI with developer property taxes) | V29: =H16/L110 -> 0.064949134
L30: Net Profit as % of Cost (excl. net op. CF) | V30: =IF(ABS(R21)>0,-R22/R21,0) -> 0.34843083
E31: Maximum Loan to Cost | H31: 0.65 | L31: IRR on Sale at Stabilization (incl. net op. CF) | V31: ='Middle ICF'!F110 -> 0.24086857
E32: Maximum % of Stabilized Value | H32: 0.55 | L32: Equity Multiple on Sale at Stabilization (incl. net op. CF) | V32: =(R24+L49)/L49 -> 2.0519088
E33: Minimum Un-Trended Debt Yield (NOI with developer property taxes) | H33: 0.085
E34: Interest Rate - Projected Average Index | H34: 0.035 | L34: Permanent Refinancing
E35: Interest Rate - Spread | H35: 0.025 | L35: Post-Permanent Refinancing Cash-on-Cash Return - Interest Only | V35: =L155 -> 0.13289198
E36: Interest Rate - Total | H36: =H34+H35 -> 0.06 | L36: Post-Permanent Refinancing Cash-on-Cash Return - Amortizing | V36: =H155 -> 0.077459385
E37: Minimum Interest - Months | H37: 12
E38: Minimum Interest - Amount | H38: =L48*H36/12*H37 -> 4631468.9
E39: Origination Fee | H39: 0.01
E40: Exit Fee | H40: 0.005
B44: SOURCES & USES | T44: Untrended | V44: % Stabilized
F45: At Closing | H45: Post-Closing | L45: Total | N45: Per Unit | P45: Per SF | R45: % of Cost | T45: Stabilized DY | V45: Value
T46: Developer RE Tax | V46: Market Value RE Tax
D47: Sources:
E48: Construction Loan | F48: =F58-F49 -> 0 | H48: =L48-F48 -> 77191148 | L48: =MIN(H31*L58,H32*V14,H16/H33) -> 77191148 | N48: =L48/$H$11 -> 220546.14 | P48: =L48/$H$12 -> 294.06152 | R48: =L48/$L$58 -> 0.65 | T48: =H16/L48 -> 0.10024649 | V48: =L48/$V$14 -> 0.4781272
E49: Equity | F49: =IF(L49<F58,L49,F58) -> 16178241 | H49: =L49-F49 -> 25386224 | L49: =L58-L48 -> 41564464 | N49: =L49/$H$11 -> 118755.61 | P49: =L49/$H$12 -> 158.34082 | R49: =L49/$L$58 -> 0.35
F50: =SUM(F48:F49) -> 16178241 | H50: =L50-F50 -> 1.0257737e+08 | L50: =SUM(L48:L49) -> 1.1875561e+08 | N50: =L50/$H$11 -> 339301.75 | P50: =L50/$H$12 -> 452.40233 | R50: =SUM(R48:R49) -> 1
D51: Uses:
E52: Land | F52: =L52 -> 13300000 | H52: =L52-F52 -> 0 | L52: =L71 -> 13300000 | N52: =L52/$H$11 -> 38000 | P52: =L52/$H$12 -> 50.666667
E53: Financing Closing Costs | F53: =L53 -> 1678240.8 | H53: =L53-F53 -> 0 | L53: =L98 -> 1678240.8 | N53: =L53/$H$11 -> 4794.9738 | P53: =L53/$H$12 -> 6.3932984
E54: Hard Costs | F54: 0 | H54: =L54-F54 -> 86821875 | L54: =L76 -> 86821875 | N54: =L54/$H$11 -> 248062.5 | P54: =L54/$H$12 -> 330.75
E55: Soft Costs (excl. operating deficit) | F55: 1200000 | H55: =L55-F55 -> 11020301 | L55: =L88-L85 -> 12220301 | N55: =L55/$H$11 -> 34915.145 | P55: =L55/$H$12 -> 46.553527
E56: Operating Deficit | F56: 0 | H56: =L56-F56 -> 50000 | L56: =L85 -> 50000 | N56: =L56/$H$11 -> 142.85714 | P56: =L56/$H$12 -> 0.19047619
E57: Interest Reserve | F57: 0 | H57: =L57-F57 -> 4685196.2 | L57: =L102 -> 4685196.2 | N57: =L57/$H$11 -> 13386.275 | P57: =L57/$H$12 -> 17.848366
F58: =SUM(F52:F57) -> 16178241 | H58: =L58-F58 -> 1.0257737e+08 | L58: =IF(ABS(SUM(L52:L57)-L104)<1,SUM(L52:L57),"ERROR") -> 1.1875561e+08 | N58: =L58/$H$11 -> 339301.75 | P58: =L58/$H$12 -> 452.40233
E60: Reconciliation to Total Cost:
E61: Total Capitalized Cost | L61: =L58 -> 1.1875561e+08
E62: Add: Lender Minimum Interest | L62: =L106 -> 0
E63: Add: Lender Exit Fee | L63: =L107 -> 385955.74
E64: Total Cost | L64: =SUM(L61:L63) -> 1.1914157e+08
B68: DEVELOPMENT BUDGET
L69: Total Cost | N69: Per Unit | P69: Per SF
D71: Land | L71: =Summary!S12 -> 13300000 | N71: =L71/$H$11 -> 38000 | P71: =L71/$H$12 -> 50.666667
D73: Hard Costs
E74: =Summary!S36 -> 315 | L74: =E74*H12 -> 82687500 | N74: =L74/$H$11 -> 236250 | P74: =L74/$H$12 -> 315
E75: =Summary!S37 -> 0.05 | L75: =L74*E75 -> 4134375 | N75: =L75/$H$11 -> 11812.5 | P75: =L75/$H$12 -> 15.75
F76: Impact Fees & Utility Connection | L76: =SUM(L74:L75) -> 86821875 | N76: =L76/$H$11 -> 248062.5 | P76: =L76/$H$12 -> 330.75
D77: Soft Costs | F77: Unit Mix for County Calc.
E78: Architectural & Engineering | F78: Studio/1BR | H78: 2BR+ | L78: 1250000 | N78: =L78/$H$11 -> 3571.4286 | P78: =L78/$H$12 -> 4.7619048
E79: Legal & Consultants | F79: ='Middle NOI'!F10+'Middle NOI'!F11 -> 210 | H79: ='Middle NOI'!F12 -> 140 | L79: 500000 | N79: =L79/$H$11 -> 1428.5714 | P79: =L79/$H$12 -> 1.9047619
E80: Advertising & Marketing | F80: County - School | L80: 250000 | N80: =L80/$H$11 -> 714.28571 | P80: =L80/$H$12 -> 0.95238095
E81: =L71*R11*R12*(1-R13) -> 196318.53 | F81: 375 | H81: 1475 | L81: =E81/12*H24 -> 408996.95 | N81: =L81/$H$11 -> 1168.5627 | P81: =L81/$H$12 -> 1.5580836
E82: 0.02 | F82: =$F$79*F81 -> 78750 | H82: =$H$79*H81 -> 206500 | L82: =E82*L76 -> 1736437.5 | N82: =L82/$H$11 -> 4961.25 | P82: =L82/$H$12 -> 6.615
E83: =G96/H11 -> 11767.634 | F83: Total School: | G83: =F82+H82 -> 285250 | L83: =E83*H11 -> 4118672 | N83: =L83/$H$11 -> 11767.634 | P83: =L83/$H$12 -> 15.690179
E84: =(106750+(0.009*(L76-10000000)))/L76 -> 0.0091929237 | F84: City - Recreational / Park | L84: =E84*L76 -> 798146.88 | N84: =L84/$H$11 -> 2280.4196 | P84: =L84/$H$12 -> 3.0405595
E85: 50000 | F85: 617 | H85: 617 | L85: ='Middle ICF'!I73+'Middle ICF'!I74 -> 50000 | N85: =L85/$H$11 -> 142.85714 | P85: =L85/$H$12 -> 0.19047619
E86: 0.03 | F86: =$F$79*F85 -> 129570 | H86: =$H$79*H85 -> 86380 | L86: =SUM(L78:L84)*E86 -> 271867.6 | N86: =L86/$H$11 -> 776.76457 | P86: =L86/$H$12 -> 1.0356861
E87: =Summary!S40 -> 0.03 | F87: Total Rec.: | G87: =F86+H86 -> 215950 | L87: =E87*(L76+SUM(L78:L86)) -> 2886179.9 | N87: =L87/$H$11 -> 8246.2282 | P87: =L87/$H$12 -> 10.994971 | R87: =L87/L110 -> 0.024224793
F88: City - Fire/Law/Transport | L88: =SUM(L78:L87) -> 12270301 | N88: =L88/$H$11 -> 35058.002 | P88: =L88/$H$12 -> 46.744003 | R88: =L88/L76 -> 0.1413273
D89: Financing Closing Costs | F89: 0 | R89: =(L88+L98+L102+L108)/L76 -> 0.21906569
E90: =H39 -> 0.01 | F90: =$H$11*F89 -> 0 | L90: =E90*L48 -> 771911.48 | N90: =L90/$H$11 -> 2205.4614 | P90: =L90/$H$12 -> 2.9406152
E91: 0 | F91: County Affordable Housing | L91: =E91*L48 -> 0 | N91: =L91/$H$11 -> 0 | P91: =L91/$H$12 -> 0
E92: Lender Due Diligence Costs | F92: 10000 | L92: 5000 | N92: =L92/$H$11 -> 14.285714 | P92: =L92/$H$12 -> 0.019047619
E93: Third Party Reports (incl. lender cost review) | F93: =$H$11*F92 -> 3500000 | L93: 50000 | N93: =L93/$H$11 -> 142.85714 | P93: =L93/$H$12 -> 0.19047619
E94: 0 | F94: Utility Connections | L94: =E94*L48 -> 0 | N94: =L94/$H$11 -> 0 | P94: =L94/$H$12 -> 0
E95: 0.0055 | F95: 117472 | L95: =E95*L48 -> 424551.32 | N95: =L95/$H$11 -> 1213.0038 | P95: =L95/$H$12 -> 1.6173383
E96: Title Insurance (see formula) | F96: Total Fees: | G96: =G83+G87+F90+F93+F95 -> 4118672 | L96: =IF(L48<10000000,(15075+((L48-5000000)/1000*2.25))*1.1,(26325+((L48-10000000)/1000*2))*1.1) -> 176778.03 | N96: =L96/$H$11 -> 505.08008 | P96: =L96/$H$12 -> 0.6734401
E97: Legal & Other Closing Costs | L97: 250000 | N97: =L97/$H$11 -> 714.28571 | P97: =L97/$H$12 -> 0.95238095
L98: =SUM(L90:L97) -> 1678240.8 | N98: =L98/$H$11 -> 4794.9738 | P98: =L98/$H$12 -> 6.3932984
D99: Interest Reserve
E100: Projected Interest Expense | L100: ='Middle ICF'!I90 -> 9189830.5 | N100: =L100/$H$11 -> 26256.659 | P100: =L100/$H$12 -> 35.008878
E101: Projected Operating Income Offset | L101: ='Middle ICF'!I91 -> -4504634.3 | N101: =L101/$H$11 -> -12870.384 | P101: =L101/$H$12 -> -17.160512
L102: =SUM(L100:L101) -> 4685196.2 | N102: =L102/$H$11 -> 13386.275 | P102: =L102/$H$12 -> 17.848366
E104: Total Cost Capitalized with Debt & Equity | L104: =L71+L76+L88+L98+L102 -> 1.1875561e+08 | N104: =L104/$H$11 -> 339301.75 | P104: =L104/$H$12 -> 452.40233
F105: Minimum Interest
E106: Lender Minimum Interest | F106: Minimum Interest | H106: =H38 -> 4631468.9 | L106: =H108 -> 0 | N106: =L106/$H$11 -> 0 | P106: =L106/$H$12 -> 0
E107: Lender Exit Fee | F107: Interest Incurred | H107: =L100 -> 9189830.5 | L107: =L48*H40 -> 385955.74 | N107: =L107/$H$11 -> 1102.7307 | P107: =L107/$H$12 -> 1.4703076
F108: Additional Due | H108: =IF(H106<=H107,0,H106-H107) -> 0 | L108: =SUM(L106:L107) -> 385955.74 | N108: =L108/$H$11 -> 1102.7307 | P108: =L108/$H$12 -> 1.4703076
E110: Total Cost | L110: =L104+L108 -> 1.1914157e+08 | N110: =L110/$H$11 -> 340404.48 | P110: =L110/$H$12 -> 453.87264
B114: PERMANENT LOAN ANALYSIS
H115: Stabilization
...

Sheet Middle NOI
A1: ='Middle Budget'!A1 -> 301 E. ATLANTIC POMPANO BEACH - PROJECTED STRIKE
B5: UNIT MIX & MARKET RENT | R5: OPERATING ASSUMPTIONS
K6: Untrended Rent
S7: Annual Rent & Other Income Growth | Y7: 0.03
F8: Units | G8: % Units | H8: Avg. SF | I8: Total SF | K8: Per Unit | M8: Per SF | O8: Total $ | S8: Loss-to-Lease (% of market rent) | Y8: 0.01
S9: Stabilized Vacancy (% of market rent) | Y9: 0.05
E10: Studio | F10: =Summary!S22 -> 70 | G10: =F10/$F$14 -> 0.2 | H10: =Summary!S24 -> 500 | I10: =F10*H10 -> 35000 | K10: =Summary!S25 -> 2100 | M10: =O10/I10 -> 4.2 | O10: =F10*K10 -> 147000 | S10: Collection Loss (% of GPR) | Y10: 0.0025
E11: One Bedroom | F11: =Summary!U22 -> 140 | G11: =F11/$F$14 -> 0.4 | H11: =Summary!U24 -> 675 | I11: =F11*H11 -> 94500 | K11: =Summary!U25 -> 2650 | M11: =O11/I11 -> 3.9259259 | O11: =F11*K11 -> 371000 | S11: Annual Operating Expense Growth | Y11: 0.025
E12: Two Bedroom | F12: =Summary!W22 -> 140 | G12: =F12/$F$14 -> 0.4 | H12: =Summary!W24 -> 950 | I12: =F12*H12 -> 133000 | K12: =Summary!W25 -> 3150 | M12: =O12/I12 -> 3.3157895 | O12: =F12*K12 -> 441000 | S12: 0.75 | Y12: 0.25
S13: Management Fee (% of total revenue) | Y13: 0.02
F14: =SUM(F10:F13) -> 350 | G14: =SUM(G10:G13) -> 1 | H14: =I14/F14 -> 750 | I14: =SUM(I10:I13) -> 262500 | K14: =O14/F14 -> 2740 | M14: =O14/I14 -> 3.6533333 | O14: =SUM(O10:O13) -> 959000 | S14: Management Fee Monthly Minimum Until Stabilization | Y14: 5000
S15: Replacement Reserve Per Unit Annually | Y15: 200
S19: Year of Operations
B20: PROJECTED OPERATING RESULTS | S20: 1 | U20: 2 | W20: 3 | Y20: 4 | AA20: 5
S21: =LOOKUP('Middle ICF'!$C$14,'Middle ICF'!$K$3:$EX$3,'Middle ICF'!$K$6:$EX$6) -> Lease-Up | U21: =LOOKUP('Middle ICF'!$C$14+12,'Middle ICF'!$K$3:$EX$3,'Middle ICF'!$K$6:$EX$6) -> Stabilized | W21: =LOOKUP('Middle ICF'!$C$14+24,'Middle ICF'!$K$3:$EX$3,'Middle ICF'!$K$6:$EX$6) -> Stabilized | Y21: =LOOKUP('Middle ICF'!$C$14+36,'Middle ICF'!$K$3:$EX$3,'Middle ICF'!$K$6:$EX$6) -> Stabilized | AA21: =LOOKUP('Middle ICF'!$C$14+48,'Middle ICF'!$K$3:$EX$3,'Middle ICF'!$K$6:$EX$6) -> Stabilized
R23: Beginning Avg. Monthly Rent: | S23: =LOOKUP('Middle ICF'!$C$14+1,'Middle ICF'!$K$3:$EX$3,'Middle ICF'!$K$28:$EX$28) -> 2921.2219 | U23: =LOOKUP('Middle ICF'!$C$14+1+12,'Middle ICF'!$K$3:$EX$3,'Middle ICF'!$K$28:$EX$28) -> 3008.8586 | W23: =LOOKUP('Middle ICF'!$C$14+1+24,'Middle ICF'!$K$3:$EX$3,'Middle ICF'!$K$28:$EX$28) -> 3099.1243 | Y23: =LOOKUP('Middle ICF'!$C$14+1+36,'Middle ICF'!$K$3:$EX$3,'Middle ICF'!$K$28:$EX$28) -> 3192.0981 | AA23: =LOOKUP('Middle ICF'!$C$14+1+48,'Middle ICF'!$K$3:$EX$3,'Middle ICF'!$K$28:$EX$28) -> 3287.861
R24: Ending Avg. Monthly Rent: | S24: =LOOKUP('Middle ICF'!$C$14+12,'Middle ICF'!$K$3:$EX$3,'Middle ICF'!$K$28:$EX$28) -> 3001.4562 | U24: =LOOKUP('Middle ICF'!$C$14+12+12,'Middle ICF'!$K$3:$EX$3,'Middle ICF'!$K$28:$EX$28) -> 3091.4999 | W24: =LOOKUP('Middle ICF'!$C$14+12+24,'Middle ICF'!$K$3:$EX$3,'Middle ICF'!$K$28:$EX$28) -> 3184.2448 | Y24: =LOOKUP('Middle ICF'!$C$14+12+36,'Middle ICF'!$K$3:$EX$3,'Middle ICF'!$K$28:$EX$28) -> 3279.7722 | AA24: =LOOKUP('Middle ICF'!$C$14+12+48,'Middle ICF'!$K$3:$EX$3,'Middle ICF'!$K$28:$EX$28) -> 3378.1654
R25: Rent Growth % (begin to begin): | S25: 0 | U25: =(U23-S23)/S23 -> 0.03 | W25: =(W23-U23)/U23 -> 0.03 | Y25: =(Y23-W23)/W23 -> 0.03 | AA25: =(AA23-Y23)/Y23 -> 0.03
R26: Average Vacancy: | S26: =-S37/S33 -> 0.44977804 | U26: =-U37/U33 -> 0.05 | W26: =-W37/W33 -> 0.05 | Y26: =-Y37/Y33 -> 0.05 | AA26: =-AA37/AA33 -> 0.05
R27: NOI as % of Market Rent: | S27: =S62/S33 -> 0.3437779 | U27: =U62/U33 -> 0.64432249 | W27: =W62/W33 -> 0.64595275 | Y27: =Y62/Y33 -> 0.64757123 | AA27: =AA62/AA33 -> 0.6491781
R28: NOI Growth: | S28: 0 | U28: =(U62-S62)/S62 -> 0.93046781 | W28: =(W62-U62)/U62 -> 0.032606093 | Y28: =(Y62-W62)/W62 -> 0.032580737 | AA28: =(AA62-Y62)/Y62 -> 0.032555825
K30: Untrended
C31: Income | K31: Total | M31: Per Unit | O31: % Mkt
E33: Market Rent | K33: =F14*K14*12 -> 11508000 | M33: =K33/$F$14 -> 32880 | O33: =K33/K$33 -> 1 | S33: =SUMIF('Middle ICF'!$K$5:$EX$5,S$20,'Middle ICF'!$K35:$EX35) -> 12436932 | U33: =SUMIF('Middle ICF'!$K$5:$EX$5,U$20,'Middle ICF'!$K35:$EX35) -> 12810040 | W33: =SUMIF('Middle ICF'!$K$5:$EX$5,W$20,'Middle ICF'!$K35:$EX35) -> 13194341 | Y33: =SUMIF('Middle ICF'!$K$5:$EX$5,Y$20,'Middle ICF'!$K35:$EX35) -> 13590172 | AA33: =SUMIF('Middle ICF'!$K$5:$EX$5,AA$20,'Middle ICF'!$K35:$EX35) -> 13997877
D34: (a) | E34: Loss-to-Lease | K34: 0 | M34: =K34/$F$14 -> 0 | O34: =K34/K$33 -> 0 | S34: =SUMIF('Middle ICF'!$K$5:$EX$5,S$20,'Middle ICF'!$K36:$EX36) -> -10505.097 | U34: =SUMIF('Middle ICF'!$K$5:$EX$5,U$20,'Middle ICF'!$K36:$EX36) -> -128100.4 | W34: =SUMIF('Middle ICF'!$K$5:$EX$5,W$20,'Middle ICF'!$K36:$EX36) -> -131943.41 | Y34: =SUMIF('Middle ICF'!$K$5:$EX$5,Y$20,'Middle ICF'!$K36:$EX36) -> -135901.72 | AA34: =SUMIF('Middle ICF'!$K$5:$EX$5,AA$20,'Middle ICF'!$K36:$EX36) -> -139978.77
E35: Gross Potential Rent | K35: =SUM(K33:K34) -> 11508000 | M35: =K35/$F$14 -> 32880 | O35: =K35/K$33 -> 1 | S35: =SUM(S33:S34) -> 12426427 | U35: =SUM(U33:U34) -> 12681940 | W35: =SUM(W33:W34) -> 13062398 | Y35: =SUM(Y33:Y34) -> 13454270 | AA35: =SUM(AA33:AA34) -> 13857898
E37: Vacancy | K37: =-K33*$Y9 -> -575400 | M37: =K37/$F$14 -> -1644 | O37: =K37/K$33 -> -0.05 | S37: =SUMIF('Middle ICF'!$K$5:$EX$5,S$20,'Middle ICF'!$K39:$EX39) -> -5593859 | U37: =SUMIF('Middle ICF'!$K$5:$EX$5,U$20,'Middle ICF'!$K39:$EX39) -> -640502.01 | W37: =SUMIF('Middle ICF'!$K$5:$EX$5,W$20,'Middle ICF'!$K39:$EX39) -> -659717.07 | Y37: =SUMIF('Middle ICF'!$K$5:$EX$5,Y$20,'Middle ICF'!$K39:$EX39) -> -679508.58 | AA37: =SUMIF('Middle ICF'!$K$5:$EX$5,AA$20,'Middle ICF'!$K39:$EX39) -> -699893.84
E38: Collection Loss | K38: =-K35*$Y10 -> -28770 | M38: =K38/$F$14 -> -82.2 | O38: =K38/K$33 -> -0.0025 | S38: =SUMIF('Middle ICF'!$K$5:$EX$5,S$20,'Middle ICF'!$K40:$EX40) -> -31066.068 | U38: =SUMIF('Middle ICF'!$K$5:$EX$5,U$20,'Middle ICF'!$K40:$EX40) -> -31704.85 | W38: =SUMIF('Middle ICF'!$K$5:$EX$5,W$20,'Middle ICF'!$K40:$EX40) -> -32655.995 | Y38: =SUMIF('Middle ICF'!$K$5:$EX$5,Y$20,'Middle ICF'!$K40:$EX40) -> -33635.675 | AA38: =SUMIF('Middle ICF'!$K$5:$EX$5,AA$20,'Middle ICF'!$K40:$EX40) -> -34644.745
E39: Net Rental Income | K39: =SUM(K35:K38) -> 10903830 | M39: =K39/$F$14 -> 31153.8 | O39: =K39/K$33 -> 0.9475 | S39: =SUM(S35:S38) -> 6801502 | U39: =SUM(U35:U38) -> 12009733 | W39: =SUM(W35:W38) -> 12370025 | Y39: =SUM(Y35:Y38) -> 12741126 | AA39: =SUM(AA35:AA38) -> 13123359
E40: 0.8 | K40: =E40*K51 -> 280000 | M40: =K40/$F$14 -> 800 | O40: =K40/K$33 -> 0.0243309 | S40: =SUMIF('Middle ICF'!$K$5:$EX$5,S$20,'Middle ICF'!$K42:$EX42) -> 298757.72 | U40: =SUMIF('Middle ICF'!$K$5:$EX$5,U$20,'Middle ICF'!$K42:$EX42) -> 306226.66 | W40: =SUMIF('Middle ICF'!$K$5:$EX$5,W$20,'Middle ICF'!$K42:$EX42) -> 313882.33 | Y40: =SUMIF('Middle ICF'!$K$5:$EX$5,Y$20,'Middle ICF'!$K42:$EX42) -> 321729.39 | AA40: =SUMIF('Middle ICF'!$K$5:$EX$5,AA$20,'Middle ICF'!$K42:$EX42) -> 329772.62
E41: Parking & Other Income | K41: ='Middle OtherInc'!M21 -> 399945 | M41: =K41/$F$14 -> 1142.7 | O41: =K41/K$33 -> 0.03475365 | S41: =SUMIF('Middle ICF'!$K$5:$EX$5,S$20,'Middle ICF'!$K43:$EX43) -> 239647.22 | U41: =SUMIF('Middle ICF'!$K$5:$EX$5,U$20,'Middle ICF'!$K43:$EX43) -> 445195.65 | W41: =SUMIF('Middle ICF'!$K$5:$EX$5,W$20,'Middle ICF'!$K43:$EX43) -> 458551.52 | Y41: =SUMIF('Middle ICF'!$K$5:$EX$5,Y$20,'Middle ICF'!$K43:$EX43) -> 472308.06 | AA41: =SUMIF('Middle ICF'!$K$5:$EX$5,AA$20,'Middle ICF'!$K43:$EX43) -> 486477.31
D42: Total Revenue | K42: =SUM(K39:K41) -> 11583775 | M42: =K42/$F$14 -> 33096.5 | O42: =K42/K$33 -> 1.0065845 | S42: =S39+S41 -> 7041149.3 | U42: =U39+U41 -> 12454929 | W42: =W39+W41 -> 12828576 | Y42: =Y39+Y41 -> 13213434 | AA42: =AA39+AA41 -> 13609837
C44: Operating Expenses
E46: Payroll | K46: ='Middle Payroll'!R11 -> 538200 | M46: =K46/$F$14 -> 1537.7143 | O46: =K46/K$33 -> 0.046767466 | S46: =SUMIF('Middle ICF'!$K$5:$EX$5,S$20,'Middle ICF'!$K48:$EX48) -> 574255.02 | U46: =SUMIF('Middle ICF'!$K$5:$EX$5,U$20,'Middle ICF'!$K48:$EX48) -> 588611.39 | W46: =SUMIF('Middle ICF'!$K$5:$EX$5,W$20,'Middle ICF'!$K48:$EX48) -> 603326.68 | Y46: =SUMIF('Middle ICF'!$K$5:$EX$5,Y$20,'Middle ICF'!$K48:$EX48) -> 618409.84 | AA46: =SUMIF('Middle ICF'!$K$5:$EX$5,AA$20,'Middle ICF'!$K48:$EX48) -> 633870.09 | AC46: =SUMIF('Middle ICF'!$K$5:$EX$5,AC$20,'Middle ICF'!$K48:$EX48) -> 0
E47: General & Administrative | K47: =$F$14*M47 -> 87500 | M47: 250 | O47: =K47/K$33 -> 0.0076034063 | S47: =SUMIF('Middle ICF'!$K$5:$EX$5,S$20,'Middle ICF'!$K49:$EX49) -> 93361.787 | U47: =SUMIF('Middle ICF'!$K$5:$EX$5,U$20,'Middle ICF'!$K49:$EX49) -> 95695.832 | W47: =SUMIF('Middle ICF'!$K$5:$EX$5,W$20,'Middle ICF'!$K49:$EX49) -> 98088.228 | Y47: =SUMIF('Middle ICF'!$K$5:$EX$5,Y$20,'Middle ICF'!$K49:$EX49) -> 100540.43 | AA47: =SUMIF('Middle ICF'!$K$5:$EX$5,AA$20,'Middle ICF'!$K49:$EX49) -> 103053.94 | AC47: =SUMIF('Middle ICF'!$K$5:$EX$5,AC$20,'Middle ICF'!$K49:$EX49) -> 0
E48: Repairs & Maintenance | K48: =$F$14*M48 -> 87500 | M48: 250 | O48: =K48/K$33 -> 0.0076034063 | S48: =SUMIF('Middle ICF'!$K$5:$EX$5,S$20,'Middle ICF'!$K50:$EX50) -> 7868.502 | U48: =SUMIF('Middle ICF'!$K$5:$EX$5,U$20,'Middle ICF'!$K50:$EX50) -> 95695.832 | W48: =SUMIF('Middle ICF'!$K$5:$EX$5,W$20,'Middle ICF'!$K50:$EX50) -> 98088.228 | Y48: =SUMIF('Middle ICF'!$K$5:$EX$5,Y$20,'Middle ICF'!$K50:$EX50) -> 100540.43 | AA48: =SUMIF('Middle ICF'!$K$5:$EX$5,AA$20,'Middle ICF'!$K50:$EX50) -> 103053.94 | AC48: =SUMIF('Middle ICF'!$K$5:$EX$5,AC$20,'Middle ICF'!$K50:$EX50) -> 0
E49: Contract Services | K49: =$F$14*M49 -> 175000 | M49: 500 | O49: =K49/K$33 -> 0.015206813 | S49: =SUMIF('Middle ICF'!$K$5:$EX$5,S$20,'Middle ICF'!$K51:$EX51) -> 186723.57 | U49: =SUMIF('Middle ICF'!$K$5:$EX$5,U$20,'Middle ICF'!$K51:$EX51) -> 191391.66 | W49: =SUMIF('Middle ICF'!$K$5:$EX$5,W$20,'Middle ICF'!$K51:$EX51) -> 196176.46 | Y49: =SUMIF('Middle ICF'!$K$5:$EX$5,Y$20,'Middle ICF'!$K51:$EX51) -> 201080.87 | AA49: =SUMIF('Middle ICF'!$K$5:$EX$5,AA$20,'Middle ICF'!$K51:$EX51) -> 206107.89 | AC49: =SUMIF('Middle ICF'!$K$5:$EX$5,AC$20,'Middle ICF'!$K51:$EX51) -> 0
E50: Turnover | K50: =$F$14*M50 -> 87500 | M50: 250 | O50: =K50/K$33 -> 0.0076034063 | S50: =SUMIF('Middle ICF'!$K$5:$EX$5,S$20,'Middle ICF'!$K52:$EX52) -> 7868.502 | U50: =SUMIF('Middle ICF'!$K$5:$EX$5,U$20,'Middle ICF'!$K52:$EX52) -> 95695.832 | W50: =SUMIF('Middle ICF'!$K$5:$EX$5,W$20,'Middle ICF'!$K52:$EX52) -> 98088.228 | Y50: =SUMIF('Middle ICF'!$K$5:$EX$5,Y$20,'Middle ICF'!$K52:$EX52) -> 100540.43 | AA50: =SUMIF('Middle ICF'!$K$5:$EX$5,AA$20,'Middle ICF'!$K52:$EX52) -> 103053.94
E51: Utilities | K51: =$F$14*M51 -> 350000 | M51: 1000 | O51: =K51/K$33 -> 0.030413625 | S51: =SUMIF('Middle ICF'!$K$5:$EX$5,S$20,'Middle ICF'!$K53:$EX53) -> 373447.15 | U51: =SUMIF('Middle ICF'!$K$5:$EX$5,U$20,'Middle ICF'!$K53:$EX53) -> 382783.33 | W51: =SUMIF('Middle ICF'!$K$5:$EX$5,W$20,'Middle ICF'!$K53:$EX53) -> 392352.91 | Y51: =SUMIF('Middle ICF'!$K$5:$EX$5,Y$20,'Middle ICF'!$K53:$EX53) -> 402161.73 | AA51: =SUMIF('Middle ICF'!$K$5:$EX$5,AA$20,'Middle ICF'!$K53:$EX53) -> 412215.78
E52: Leasing & Marketing | K52: =$F$14*M52 -> 87500 | M52: 250 | O52: =K52/K$33 -> 0.0076034063 | S52: =SUMIF('Middle ICF'!$K$5:$EX$5,S$20,'Middle ICF'!$K54:$EX54) -> 93361.787 | U52: =SUMIF('Middle ICF'!$K$5:$EX$5,U$20,'Middle ICF'!$K54:$EX54) -> 95695.832 | W52: =SUMIF('Middle ICF'!$K$5:$EX$5,W$20,'Middle ICF'!$K54:$EX54) -> 98088.228 | Y52: =SUMIF('Middle ICF'!$K$5:$EX$5,Y$20,'Middle ICF'!$K54:$EX54) -> 100540.43 | AA52: =SUMIF('Middle ICF'!$K$5:$EX$5,AA$20,'Middle ICF'!$K54:$EX54) -> 103053.94 | AC52: =SUMIF('Middle ICF'!$K$5:$EX$5,AC$20,'Middle ICF'!$K54:$EX54) -> 0
E53: Management Fee | K53: =K42*Y13 -> 231675.5 | M53: =K53/$F$14 -> 661.93 | O53: =K53/K$33 -> 0.020131691 | S53: =SUMIF('Middle ICF'!$K$5:$EX$5,S$20,'Middle ICF'!$K55:$EX55) -> 75931.346 | U53: =SUMIF('Middle ICF'!$K$5:$EX$5,U$20,'Middle ICF'!$K55:$EX55) -> 255223.11 | W53: =SUMIF('Middle ICF'!$K$5:$EX$5,W$20,'Middle ICF'!$K55:$EX55) -> 262849.18 | Y53: =SUMIF('Middle ICF'!$K$5:$EX$5,Y$20,'Middle ICF'!$K55:$EX55) -> 270703.26 | AA53: =SUMIF('Middle ICF'!$K$5:$EX$5,AA$20,'Middle ICF'!$K55:$EX55) -> 278792.19 | AC53: =SUMIF('Middle ICF'!$K$5:$EX$5,AC$20,'Middle ICF'!$K55:$EX55) -> 0
E54: Insurance | K54: =$F$14*M54 -> 612500 | M54: 1750 | O54: =K54/K$33 -> 0.053223844 | S54: =SUMIF('Middle ICF'!$K$5:$EX$5,S$20,'Middle ICF'!$K56:$EX56) -> 653532.51 | U54: =SUMIF('Middle ICF'!$K$5:$EX$5,U$20,'Middle ICF'!$K56:$EX56) -> 669870.82 | W54: =SUMIF('Middle ICF'!$K$5:$EX$5,W$20,'Middle ICF'!$K56:$EX56) -> 686617.59 | Y54: =SUMIF('Middle ICF'!$K$5:$EX$5,Y$20,'Middle ICF'!$K56:$EX56) -> 703783.03 | AA54: =SUMIF('Middle ICF'!$K$5:$EX$5,AA$20,'Middle ICF'!$K56:$EX56) -> 721377.61 | AC54: =SUMIF('Middle ICF'!$K$5:$EX$5,AC$20,'Middle ICF'!$K56:$EX56) -> 0
E55: Property Taxes (developer ownership) | K55: ='Middle RETax'!G23 -> 1518257.8 | M55: =K55/$F$14 -> 4337.8794 | O55: =K55/K$33 -> 0.13193064 | S55: =SUMIF('Middle ICF'!$K$5:$EX$5,S$20,'Middle ICF'!$K57:$EX57) -> 693423.31 | U55: =SUMIF('Middle ICF'!$K$5:$EX$5,U$20,'Middle ICF'!$K57:$EX57) -> 1660467.9 | W55: =SUMIF('Middle ICF'!$K$5:$EX$5,W$20,'Middle ICF'!$K57:$EX57) -> 1701979.6 | Y55: =SUMIF('Middle ICF'!$K$5:$EX$5,Y$20,'Middle ICF'!$K57:$EX57) -> 1744529.1 | AA55: =SUMIF('Middle ICF'!$K$5:$EX$5,AA$20,'Middle ICF'!$K57:$EX57) -> 1788142.3 | AC55: =SUMIF('Middle ICF'!$K$5:$EX$5,AC$20,'Middle ICF'!$K57:$EX57) -> 0
D56: Total Operating Expenses | K56: =SUM(K46:K55) -> 3775633.3 | M56: =K56/$F$14 -> 10787.524 | O56: =K56/K$33 -> 0.3280877 | S56: =SUM(S46:S55) -> 2759773.5 | U56: =SUM(U46:U55) -> 4131131.5 | W56: =SUM(W46:W55) -> 4235655.3 | Y56: =SUM(Y46:Y55) -> 4342829.6 | AA56: =SUM(AA46:AA55) -> 4452721.7
C58: Net Operating Income Before Reserves | K58: =K42-K56 -> 7808141.7 | M58: =K58/$F$14 -> 22308.976 | O58: =K58/K$33 -> 0.67849685 | S58: =S42-S56 -> 4281375.8 | U58: =U42-U56 -> 8323797.1 | W58: =W42-W56 -> 8592921.1 | Y58: =Y42-Y56 -> 8870604.2 | AA58: =AA42-AA56 -> 9157115.1
E60: Less: Replacement Reserve | K60: =Y15*F14 -> 70000 | M60: =K60/$F$14 -> 200 | O60: =K60/K$33 -> 0.0060827251 | S60: =SUMIF('Middle ICF'!$K$5:$EX$5,S$20,'Middle ICF'!$K58:$EX58) -> 5833.3333 | U60: =SUMIF('Middle ICF'!$K$5:$EX$5,U$20,'Middle ICF'!$K58:$EX58) -> 70000 | W60: =SUMIF('Middle ICF'!$K$5:$EX$5,W$20,'Middle ICF'!$K58:$EX58) -> 70000 | Y60: =SUMIF('Middle ICF'!$K$5:$EX$5,Y$20,'Middle ICF'!$K58:$EX58) -> 70000 | AA60: =SUMIF('Middle ICF'!$K$5:$EX$5,AA$20,'Middle ICF'!$K58:$EX58) -> 70000
C62: Net Operating Income | K62: =K58-K60 -> 7738141.7 | M62: =K62/$F$14 -> 22108.976 | O62: =K62/K$33 -> 0.67241412 | S62: =S58-S60 -> 4275542.5 | U62: =U58-U60 -> 8253797.1 | W62: =W58-W60 -> 8522921.1 | Y62: =Y58-Y60 -> 8800604.2 | AA62: =AA58-AA60 -> 9087115.1
C65: (a) | D65: Loss-to-Lease is not applied to stabilized untrended results snapshot above, only to projected results starting at stabilization.

Sheet Middle OtherInc
A1: ='Middle Budget'!A1 -> 301 E. ATLANTIC POMPANO BEACH - PROJECTED STRIKE
B4: PARKING & OTHER INCOME
F5: Assumptions | M5: Annual Total
F6: ='Middle Budget'!H11 -> 350
D8: Reserved Parking | F8: 95 | H8: 0.25 | J8: - | M8: =F8*$F$6*H8*12 -> 99750
D9: Vehicle Registration Fee | F9: 30 | H9: =$H$10 -> 0.45 | J9: 1.5 | M9: =F9*J9*$F$6*H9 -> 7087.5
D10: Application Fees | F10: 150 | H10: 0.45 | J10: - | M10: =F10*$F$6*H10 -> 23625
D11: Pet Fees | F11: 300 | H11: =$H$10 -> 0.45 | J11: 0.25 | M11: =F11*$F$6*H11*J11 -> 11812.5
D12: Pet Rent | F12: 25 | H12: 0.25 | J12: - | M12: =F12*$F$6*H12*12 -> 26250
D13: Trash Collection | F13: 20 | H13: 1 | J13: =1-'Middle NOI'!$Y$9 -> 0.95 | M13: =F13*$F$6*H13*J13*12 -> 79800
D14: Pest Control | F14: 5 | H14: 1 | J14: =1-'Middle NOI'!$Y$9 -> 0.95 | M14: =F14*$F$6*H14*J14*12 -> 19950
D15: Late Fees & NSF Fees | F15: 125 | H15: 5 | J15: - | M15: =F15*H15*12 -> 7500
D16: Lease Termination Fees | F16: ='Middle NOI'!K14 -> 2740 | H16: 3 | J16: - | M16: =F16*H16 -> 8220
D17: Cleaning & Damage Charges | F17: 500 | H17: 2 | J17: - | M17: =F17*H17*12 -> 12000
D18: Cable Revenue Share | F18: 25 | H18: 1 | J18: =1-'Middle NOI'!$Y$9 -> 0.95 | M18: =F18*$F$6*H18*J18*12 -> 99750
D19: Keys & FOBs Replacement | F19: 50 | H19: 2 | J19: - | M19: =F19*H19*12 -> 1200
D20: Clubhouse Rental | F20: 250 | H20: 1 | J20: - | M20: =F20*H20*12 -> 3000
M21: =SUM(M8:M20) -> 399945
M23: =M21/$F$6/12 -> 95.225

Sheet Middle Payroll
A1: ='Middle Budget'!A1 -> 301 E. ATLANTIC POMPANO BEACH - PROJECTED STRIKE
B3: PRO FORMA PAYROLL
L4: Burden & OT | N4: Total Expense
F5: Annual Salary | H5: Bonus | J5: Total Comp. | L5: 0.3 | N5: Per FTE | P5: Full Time Equiv. | R5: Total Expense
D6: Property Manager | F6: 75000 | H6: =F6*0.1 -> 7500 | J6: =F6+H6 -> 82500 | L6: =J6*$L$5 -> 24750 | N6: =J6+L6 -> 107250 | P6: 1 | R6: =N6*P6 -> 107250
D7: Assistant Manager | F7: 60000 | H7: 0 | J7: =F7+H7 -> 60000 | L7: =J7*$L$5 -> 18000 | N7: =J7+L7 -> 78000 | P7: 1 | R7: =N7*P7 -> 78000
D8: Leasing Consultant | F8: 45000 | H8: 0 | J8: =F8+H8 -> 45000 | L8: =J8*$L$5 -> 13500 | N8: =J8+L8 -> 58500 | P8: 2 | R8: =N8*P8 -> 117000
D9: Supervisor | F9: 65000 | H9: =F9*0.1 -> 6500 | J9: =F9+H9 -> 71500 | L9: =J9*$L$5 -> 21450 | N9: =J9+L9 -> 92950 | P9: 1 | R9: =N9*P9 -> 92950
D10: Technician | F10: 55000 | H10: 0 | J10: =F10+H10 -> 55000 | L10: =J10*$L$5 -> 16500 | N10: =J10+L10 -> 71500 | P10: 2 | R10: =N10*P10 -> 143000
P11: =SUM(P6:P10) -> 7 | R11: =SUM(R6:R10) -> 538200
P13: =P11/('Middle Budget'!H11/50) -> 1 | R13: =R11/'Middle Budget'!H11 -> 1537.7143

Sheet Middle RETax
A1: ='Middle Budget'!A1 -> 301 E. ATLANTIC POMPANO BEACH - PROJECTED STRIKE
B5: PROPERTY TAX ESTIMATE AT COMPLETION UNDER DEVELOPER OWNERSHIP
E7: ='Middle Budget'!H24+1 -> 26 | G7: =LOOKUP(E7,'Middle ICF'!K3:EX3,'Middle ICF'!K35:EX35)*12 -> 12269132
E8: 0.1 | G8: =-E8*G7 -> -1226913.2
G9: =SUM(G7:G8) -> 11042219
E10: 0.4 | G10: =-E10*G9 -> -4416887.5
G11: =SUM(G9:G10) -> 6625331.3
D13: (a) | E13: County Appraiser Market Cap Rate | G13: 0.0525
E14: Tax Rate | G14: ='Middle Budget'!R12 -> 0.0205011
E15: County Appraiser Cap Rate | G15: =SUM(G13:G14) -> 0.0730011
E17: County Appraiser Gross Assessed Value | G17: =G11/G15 -> 90756595
E18: 0.15 | G18: =-$E$18*G17 -> -13613489
E19: Net Assessed Value | G19: =SUM(G17:G18) -> 77143106
E20: Tax Rate | G20: =G14 -> 0.0205011
E21: Tax Expense Before Early Payment Discount | G21: =G19*G20 -> 1581518.5
E22: 0.04 | G22: =-$E$22*G21 -> -63260.741
G23: =SUM(G21:G22) -> 1518257.8
F25: =G23/'Middle Budget'!$H$11 -> 4337.8794
D27: (a) | E27: County appraiser typically uses a cap rate above actual market cap rates for property tax assessment purposes.
B31: PROPERTY TAX ESTIMATE AT COMPLETION UNDER DEVELOPER OWNERSHIP - PERCENT OF COST
E33: Hard Costs | G33: ='Middle Budget'!L74 -> 82687500
E34: Reassessment as % of Total Cost | G34: 0.9
G35: =G33*G34 -> 74418750
E36: Tax Rate | G36: =G14 -> 0.0205011
G37: =G35*G36 -> 1525666.2
E38: =$E$22 -> 0.04 | G38: =G37*-E38 -> -61026.649
G39: =SUM(G37:G38) -> 1464639.6
F41: =G39/'Middle Budget'!$H$11 -> 4184.6845

Sheet Middle ICF
A1: ='Middle Budget'!A1 -> 301 E. ATLANTIC POMPANO BEACH - PROJECTED STRIKE
I3: Investment Period | J3: Closing | K3: 1 | L3: =K3+1 -> 2 | M3: =L3+1 -> 3 | N3: =M3+1 -> 4 | O3: =N3+1 -> 5 | P3: =O3+1 -> 6 | Q3: =P3+1 -> 7 | R3: =Q3+1 -> 8 | S3: =R3+1 -> 9 | ... EX3: =EW3+1 -> 144
I4: Date | J4: 46388 | K4: =EDATE(J4,1) -> 46419 | L4: =EDATE(K4,1) -> 46447 | M4: =EDATE(L4,1) -> 46478 | N4: =EDATE(M4,1) -> 46508 | O4: =EDATE(N4,1) -> 46539 | P4: =EDATE(O4,1) -> 46569 | Q4: =EDATE(P4,1) -> 46600 | R4: =EDATE(Q4,1) -> 46631 | ... EX4: =EDATE(EW4,1) -> 50771
I5: Year of Operations | K5: =IF(K3>=$C$14,ROUNDUP((K3-$C$14)/12,0),0) -> 0 | L5: =IF(L3>=$C$14,ROUNDUP((L3-$C$14)/12,0),0) -> 0 | M5: =IF(M3>=$C$14,ROUNDUP((M3-$C$14)/12,0),0) -> 0 | N5: =IF(N3>=$C$14,ROUNDUP((N3-$C$14)/12,0),0) -> 0 | O5: =IF(O3>=$C$14,ROUNDUP((O3-$C$14)/12,0),0) -> 0 | P5: =IF(P3>=$C$14,ROUNDUP((P3-$C$14)/12,0),0) -> 0 | Q5: =IF(Q3>=$C$14,ROUNDUP((Q3-$C$14)/12,0),0) -> 0 | R5: =IF(R3>=$C$14,ROUNDUP((R3-$C$14)/12,0),0) -> 0 | ... EX5: =IF(EX3>=$C$14,ROUNDUP((EX3-$C$14)/12,0),0) -> 10
I6: Status | K6: =IF(K3<$C$14,"Dev.",IF(AND(K3>=$C$14,K3<$C$16),"Lease-Up","Stabilized")) -> Dev. | L6: =IF(L3<$C$14,"Dev.",IF(AND(L3>=$C$14,L3<$C$16),"Lease-Up","Stabilized")) -> Dev. | M6: =IF(M3<$C$14,"Dev.",IF(AND(M3>=$C$14,M3<$C$16),"Lease-Up","Stabilized")) -> Dev. | N6: =IF(N3<$C$14,"Dev.",IF(AND(N3>=$C$14,N3<$C$16),"Lease-Up","Stabilized")) -> Dev. | O6: =IF(O3<$C$14,"Dev.",IF(AND(O3>=$C$14,O3<$C$16),"Lease-Up","Stabilized")) -> Dev. | P6: =IF(P3<$C$14,"Dev.",IF(AND(P3>=$C$14,P3<$C$16),"Lease-Up","Stabilized")) -> Dev. | Q6: =IF(Q3<$C$14,"Dev.",IF(AND(Q3>=$C$14,Q3<$C$16),"Lease-Up","Stabilized")) -> Dev. | R6: =IF(R3<$C$14,"Dev.",IF(AND(R3>=$C$14,R3<$C$16),"Lease-Up","Stabilized")) -> Dev. | ... EX6: =IF(EX3<$C$14,"Dev.",IF(AND(EX3>=$C$14,EX3<$C$16),"Lease-Up","Stabilized")) -> Stabilized
B8: Unit Count & Timing Summary (from Ops & SU tabs)
C9: ='Middle NOI'!F14 -> 350
C10: ='Middle Budget'!H20 -> 1
C11: ='Middle Budget'!H21 -> 24
C12: ='Middle Budget'!H22 -> 1
C13: ='Middle Budget'!H23 -> 26
C14: ='Middle Budget'!H24 -> 25
C15: ='Middle Budget'!H25 -> 25.576923
C16: ='Middle Budget'!H26 -> 37
C17: ='Middle Budget'!H27 -> 40
B19: UNIT OCCUPANCY & AVERAGE MONTHLY BASE RENT
C21: Occupied Units - Beginning | K21: 0 | L21: =K23 -> 0 | M21: =L23 -> 0 | N21: =M23 -> 0 | O21: =N23 -> 0 | P21: =O23 -> 0 | Q21: =P23 -> 0 | R21: =Q23 -> 0 | S21: =R23 -> 0 | ... EX21: =EW23 -> 332.5
C22: Move-ins | I22: =SUM(K22:EX22) -> 332.5 | K22: =IF(AND(K3>=$C$14,K3<=$C$16),$C$15,0) -> 0 | L22: =IF(AND(L3>=$C$14,L3<=$C$16),$C$15,0) -> 0 | M22: =IF(AND(M3>=$C$14,M3<=$C$16),$C$15,0) -> 0 | N22: =IF(AND(N3>=$C$14,N3<=$C$16),$C$15,0) -> 0 | O22: =IF(AND(O3>=$C$14,O3<=$C$16),$C$15,0) -> 0 | P22: =IF(AND(P3>=$C$14,P3<=$C$16),$C$15,0) -> 0 | Q22: =IF(AND(Q3>=$C$14,Q3<=$C$16),$C$15,0) -> 0 | R22: =IF(AND(R3>=$C$14,R3<=$C$16),$C$15,0) -> 0 | ... EX22: =IF(AND(EX3>=$C$14,EX3<=$C$16),$C$15,0) -> 0
C23: Occupied Units - Ending | I23: =I22/C9 -> 0.95 | K23: =SUM(K21:K22) -> 0 | L23: =SUM(L21:L22) -> 0 | M23: =SUM(M21:M22) -> 0 | N23: =SUM(N21:N22) -> 0 | O23: =SUM(O21:O22) -> 0 | P23: =SUM(P21:P22) -> 0 | Q23: =SUM(Q21:Q22) -> 0 | R23: =SUM(R21:R22) -> 0 | ... EX23: =SUM(EX21:EX22) -> 332.5
C24: Vacant Units | K24: =$C$9-K23 -> 350 | L24: =$C$9-L23 -> 350 | M24: =$C$9-M23 -> 350 | N24: =$C$9-N23 -> 350 | O24: =$C$9-O23 -> 350 | P24: =$C$9-P23 -> 350 | Q24: =$C$9-Q23 -> 350 | R24: =$C$9-R23 -> 350 | ... EX24: =$C$9-EX23 -> 17.5
C25: Total | K25: =SUM(K23:K24) -> 350 | L25: =SUM(L23:L24) -> 350 | M25: =SUM(M23:M24) -> 350 | N25: =SUM(N23:N24) -> 350 | O25: =SUM(O23:O24) -> 350 | P25: =SUM(P23:P24) -> 350 | Q25: =SUM(Q23:Q24) -> 350 | R25: =SUM(R23:R24) -> 350 | ... EX25: =SUM(EX23:EX24) -> 350
J27: Occupancy: | K27: =K23/$C$9 -> 0 | L27: =L23/$C$9 -> 0 | M27: =M23/$C$9 -> 0 | N27: =N23/$C$9 -> 0 | O27: =O23/$C$9 -> 0 | P27: =P23/$C$9 -> 0 | Q27: =Q23/$C$9 -> 0 | R27: =R23/$C$9 -> 0 | ... EX27: =EX23/$C$9 -> 0.95
J28: Avg. Base Rent: | K28: =IF(K27>0,K35/$C$9,0) -> 0 | L28: =IF(L27>0,L35/$C$9,0) -> 0 | M28: =IF(M27>0,M35/$C$9,0) -> 0 | N28: =IF(N27>0,N35/$C$9,0) -> 0 | O28: =IF(O27>0,O35/$C$9,0) -> 0 | P28: =IF(P27>0,P35/$C$9,0) -> 0 | Q28: =IF(Q27>0,Q35/$C$9,0) -> 0 | R28: =IF(R27>0,R35/$C$9,0) -> 0 | ... EX28: =IF(EX27>0,EX35/$C$9,0) -> 3906.5848
B30: OPERATING INCOME
F32: From Ops Tab
B33: Income | G33: Stabilized
F34: Untrended | G34: Assumptions
C35: Market Rent | F35: ='Middle NOI'!K33 -> 11508000 | G35: ='Middle NOI'!$Y$7 -> 0.03 | K35: =IF(K$5>0,($F35/12)*(1+((1+$G35)^(1/12))-1)^K$3,0) -> 0 | L35: =IF(L$5>0,($F35/12)*(1+((1+$G35)^(1/12))-1)^L$3,0) -> 0 | M35: =IF(M$5>0,($F35/12)*(1+((1+$G35)^(1/12))-1)^M$3,0) -> 0 | N35: =IF(N$5>0,($F35/12)*(1+((1+$G35)^(1/12))-1)^N$3,0) -> 0 | O35: =IF(O$5>0,($F35/12)*(1+((1+$G35)^(1/12))-1)^O$3,0) -> 0 | P35: =IF(P$5>0,($F35/12)*(1+((1+$G35)^(1/12))-1)^P$3,0) -> 0 | Q35: =IF(Q$5>0,($F35/12)*(1+((1+$G35)^(1/12))-1)^Q$3,0) -> 0 | R35: =IF(R$5>0,($F35/12)*(1+((1+$G35)^(1/12))-1)^R$3,0) -> 0 | ... EX35: =IF(EX$5>0,($F35/12)*(1+((1+$G35)^(1/12))-1)^EX$3,0) -> 1367304.7
C36: Loss to Lease (starts at stabilization) | F36: ='Middle NOI'!K34 -> 0 | G36: ='Middle NOI'!Y8 -> 0.01 | K36: =IF(K$35=0,0,IF(K$27<(1-$G$39),0,K$35*-$G36)) -> 0 | L36: =IF(L$35=0,0,IF(L$27<(1-$G$39),0,L$35*-$G36)) -> 0 | M36: =IF(M$35=0,0,IF(M$27<(1-$G$39),0,M$35*-$G36)) -> 0 | N36: =IF(N$35=0,0,IF(N$27<(1-$G$39),0,N$35*-$G36)) -> 0 | O36: =IF(O$35=0,0,IF(O$27<(1-$G$39),0,O$35*-$G36)) -> 0 | P36: =IF(P$35=0,0,IF(P$27<(1-$G$39),0,P$35*-$G36)) -> 0 | Q36: =IF(Q$35=0,0,IF(Q$27<(1-$G$39),0,Q$35*-$G36)) -> 0 | R36: =IF(R$35=0,0,IF(R$27<(1-$G$39),0,R$35*-$G36)) -> 0 | ... EX36: =IF(EX$35=0,0,IF(EX$27<(1-$G$39),0,EX$35*-$G36)) -> -13673.047
C37: Gross Potential Rent | F37: =SUM(F35:F36) -> 11508000 | K37: =SUM(K35:K36) -> 0 | L37: =SUM(L35:L36) -> 0 | M37: =SUM(M35:M36) -> 0 | N37: =SUM(N35:N36) -> 0 | O37: =SUM(O35:O36) -> 0 | P37: =SUM(P35:P36) -> 0 | Q37: =SUM(Q35:Q36) -> 0 | R37: =SUM(R35:R36) -> 0 | ... EX37: =SUM(EX35:EX36) -> 1353631.6
C39: Vacancy | F39: ='Middle NOI'!K37 -> -575400 | G39: ='Middle NOI'!Y9 -> 0.05 | K39: =IF(K$35=0,0,-K$35*(1-K$27)) -> 0 | L39: =IF(L$35=0,0,-L$35*(1-L$27)) -> 0 | M39: =IF(M$35=0,0,-M$35*(1-M$27)) -> 0 | N39: =IF(N$35=0,0,-N$35*(1-N$27)) -> 0 | O39: =IF(O$35=0,0,-O$35*(1-O$27)) -> 0 | P39: =IF(P$35=0,0,-P$35*(1-P$27)) -> 0 | Q39: =IF(Q$35=0,0,-Q$35*(1-Q$27)) -> 0 | R39: =IF(R$35=0,0,-R$35*(1-R$27)) -> 0 | ... EX39: =IF(EX$35=0,0,-EX$35*(1-EX$27)) -> -68365.235
C40: Collection Loss | F40: ='Middle NOI'!K38 -> -28770 | G40: ='Middle NOI'!Y10 -> 0.0025 | K40: =IF(K$37=0,0,-K$37*$G40) -> 0 | L40: =IF(L$37=0,0,-L$37*$G40) -> 0 | M40: =IF(M$37=0,0,-M$37*$G40) -> 0 | N40: =IF(N$37=0,0,-N$37*$G40) -> 0 | O40: =IF(O$37=0,0,-O$37*$G40) -> 0 | P40: =IF(P$37=0,0,-P$37*$G40) -> 0 | Q40: =IF(Q$37=0,0,-Q$37*$G40) -> 0 | R40: =IF(R$37=0,0,-R$37*$G40) -> 0 | ... EX40: =IF(EX$37=0,0,-EX$37*$G40) -> -3384.0791
C41: Net Rental Income | F41: =F37+F39+F40 -> 10903830 | K41: =K37+K39+K40 -> 0 | L41: =L37+L39+L40 -> 0 | M41: =M37+M39+M40 -> 0 | N41: =N37+N39+N40 -> 0 | O41: =O37+O39+O40 -> 0 | P41: =P37+P39+P40 -> 0 | Q41: =Q37+Q39+Q40 -> 0 | R41: =R37+R39+R40 -> 0 | ... EX41: =EX37+EX39+EX40 -> 1281882.3
C42: RUBS Income | F42: ='Middle NOI'!K40 -> 280000 | G42: ='Middle NOI'!E40 -> 0.8 | H42: Variable % utilities expense | K42: =$G$42*K53 -> 0 | L42: =$G$42*L53 -> 0 | M42: =$G$42*M53 -> 0 | N42: =$G$42*N53 -> 0 | O42: =$G$42*O53 -> 0 | P42: =$G$42*P53 -> 0 | Q42: =$G$42*Q53 -> 0 | R42: =$G$42*R53 -> 0 | ... EX42: =$G$42*EX53 -> 31380.739
C43: Other Income | F43: ='Middle NOI'!K41 -> 399945 | G43: ='Middle NOI'!$Y$7 -> 0.03 | H43: Variable occupancy | K43: =IF(K27<(1-$G$39),(($F43/12)*(1+((1+$G43)^(1/12))-1)^K$3)*K27,($F43/12)*(1+((1+$G43)^(1/12))-1)^K$3) -> 0 | L43: =IF(L27<(1-$G$39),(($F43/12)*(1+((1+$G43)^(1/12))-1)^L$3)*L27,($F43/12)*(1+((1+$G43)^(1/12))-1)^L$3) -> 0 | M43: =IF(M27<(1-$G$39),(($F43/12)*(1+((1+$G43)^(1/12))-1)^M$3)*M27,($F43/12)*(1+((1+$G43)^(1/12))-1)^M$3) -> 0 | N43: =IF(N27<(1-$G$39),(($F43/12)*(1+((1+$G43)^(1/12))-1)^N$3)*N27,($F43/12)*(1+((1+$G43)^(1/12))-1)^N$3) -> 0 | O43: =IF(O27<(1-$G$39),(($F43/12)*(1+((1+$G43)^(1/12))-1)^O$3)*O27,($F43/12)*(1+((1+$G43)^(1/12))-1)^O$3) -> 0 | P43: =IF(P27<(1-$G$39),(($F43/12)*(1+((1+$G43)^(1/12))-1)^P$3)*P27,($F43/12)*(1+((1+$G43)^(1/12))-1)^P$3) -> 0 | Q43: =IF(Q27<(1-$G$39),(($F43/12)*(1+((1+$G43)^(1/12))-1)^Q$3)*Q27,($F43/12)*(1+((1+$G43)^(1/12))-1)^Q$3) -> 0 | R43: =IF(R27<(1-$G$39),(($F43/12)*(1+((1+$G43)^(1/12))-1)^R$3)*R27,($F43/12)*(1+((1+$G43)^(1/12))-1)^R$3) -> 0 | ... EX43: =IF(EX27<(1-$G$39),(($F43/12)*(1+((1+$G43)^(1/12))-1)^EX$3)*EX27,($F43/12)*(1+((1+$G43)^(1/12))-1)^EX$3) -> 47518.828
C44: Total Revenue | F44: =SUM(F41:F43) -> 11583775 | K44: =SUM(K41:K43) -> 0 | L44: =SUM(L41:L43) -> 0 | M44: =SUM(M41:M43) -> 0 | N44: =SUM(N41:N43) -> 0 | O44: =SUM(O41:O43) -> 0 | P44: =SUM(P41:P43) -> 0 | Q44: =SUM(Q41:Q43) -> 0 | R44: =SUM(R41:R43) -> 0 | ... EX44: =SUM(EX41:EX43) -> 1360781.9
B46: Operating Expenses
C48: Payroll | F48: ='Middle NOI'!K46 -> 538200 | G48: ='Middle NOI'!$Y$11 -> 0.025 | H48: Fixed | K48: =IF(K$5>0,($F48/12)*(1+((1+$G48)^(1/12))-1)^K$3,0) -> 0 | L48: =IF(L$5>0,($F48/12)*(1+((1+$G48)^(1/12))-1)^L$3,0) -> 0 | M48: =IF(M$5>0,($F48/12)*(1+((1+$G48)^(1/12))-1)^M$3,0) -> 0 | N48: =IF(N$5>0,($F48/12)*(1+((1+$G48)^(1/12))-1)^N$3,0) -> 0 | O48: =IF(O$5>0,($F48/12)*(1+((1+$G48)^(1/12))-1)^O$3,0) -> 0 | P48: =IF(P$5>0,($F48/12)*(1+((1+$G48)^(1/12))-1)^P$3,0) -> 0 | Q48: =IF(Q$5>0,($F48/12)*(1+((1+$G48)^(1/12))-1)^Q$3,0) -> 0 | R48: =IF(R$5>0,($F48/12)*(1+((1+$G48)^(1/12))-1)^R$3,0) -> 0 | ... EX48: =IF(EX$5>0,($F48/12)*(1+((1+$G48)^(1/12))-1)^EX$3,0) -> 60318.264
C49: General & Administrative | F49: ='Middle NOI'!K47 -> 87500 | G49: ='Middle NOI'!$Y$11 -> 0.025 | H49: Fixed | K49: =IF(K$5>0,($F49/12)*(1+((1+$G49)^(1/12))-1)^K$3,0) -> 0 | L49: =IF(L$5>0,($F49/12)*(1+((1+$G49)^(1/12))-1)^L$3,0) -> 0 | M49: =IF(M$5>0,($F49/12)*(1+((1+$G49)^(1/12))-1)^M$3,0) -> 0 | N49: =IF(N$5>0,($F49/12)*(1+((1+$G49)^(1/12))-1)^N$3,0) -> 0 | O49: =IF(O$5>0,($F49/12)*(1+((1+$G49)^(1/12))-1)^O$3,0) -> 0 | P49: =IF(P$5>0,($F49/12)*(1+((1+$G49)^(1/12))-1)^P$3,0) -> 0 | Q49: =IF(Q$5>0,($F49/12)*(1+((1+$G49)^(1/12))-1)^Q$3,0) -> 0 | R49: =IF(R$5>0,($F49/12)*(1+((1+$G49)^(1/12))-1)^R$3,0) -> 0 | ... EX49: =IF(EX$5>0,($F49/12)*(1+((1+$G49)^(1/12))-1)^EX$3,0) -> 9806.481
C50: Repairs & Maintenance | F50: ='Middle NOI'!K48 -> 87500 | G50: ='Middle NOI'!$Y$11 -> 0.025 | H50: Fixed post-stabilization | K50: =IF(K$27<(1-$G$39),0,($F50/12)*(1+((1+$G50)^(1/12))-1)^K$3) -> 0 | L50: =IF(L$27<(1-$G$39),0,($F50/12)*(1+((1+$G50)^(1/12))-1)^L$3) -> 0 | M50: =IF(M$27<(1-$G$39),0,($F50/12)*(1+((1+$G50)^(1/12))-1)^M$3) -> 0 | N50: =IF(N$27<(1-$G$39),0,($F50/12)*(1+((1+$G50)^(1/12))-1)^N$3) -> 0 | O50: =IF(O$27<(1-$G$39),0,($F50/12)*(1+((1+$G50)^(1/12))-1)^O$3) -> 0 | P50: =IF(P$27<(1-$G$39),0,($F50/12)*(1+((1+$G50)^(1/12))-1)^P$3) -> 0 | Q50: =IF(Q$27<(1-$G$39),0,($F50/12)*(1+((1+$G50)^(1/12))-1)^Q$3) -> 0 | R50: =IF(R$27<(1-$G$39),0,($F50/12)*(1+((1+$G50)^(1/12))-1)^R$3) -> 0 | ... EX50: =IF(EX$27<(1-$G$39),0,($F50/12)*(1+((1+$G50)^(1/12))-1)^EX$3) -> 9806.481
C51: Contract Services | F51: ='Middle NOI'!K49 -> 175000 | G51: ='Middle NOI'!$Y$11 -> 0.025 | H51: Fixed | K51: =IF(K$5>0,($F51/12)*(1+((1+$G51)^(1/12))-1)^K$3,0) -> 0 | L51: =IF(L$5>0,($F51/12)*(1+((1+$G51)^(1/12))-1)^L$3,0) -> 0 | M51: =IF(M$5>0,($F51/12)*(1+((1+$G51)^(1/12))-1)^M$3,0) -> 0 | N51: =IF(N$5>0,($F51/12)*(1+((1+$G51)^(1/12))-1)^N$3,0) -> 0 | O51: =IF(O$5>0,($F51/12)*(1+((1+$G51)^(1/12))-1)^O$3,0) -> 0 | P51: =IF(P$5>0,($F51/12)*(1+((1+$G51)^(1/12))-1)^P$3,0) -> 0 | Q51: =IF(Q$5>0,($F51/12)*(1+((1+$G51)^(1/12))-1)^Q$3,0) -> 0 | R51: =IF(R$5>0,($F51/12)*(1+((1+$G51)^(1/12))-1)^R$3,0) -> 0 | ... EX51: =IF(EX$5>0,($F51/12)*(1+((1+$G51)^(1/12))-1)^EX$3,0) -> 19612.962
C52: Turnover | F52: ='Middle NOI'!K50 -> 87500 | G52: ='Middle NOI'!$Y$11 -> 0.025 | H52: Fixed post-stabilization | K52: =IF(K$27<(1-$G$39),0,($F52/12)*(1+((1+$G52)^(1/12))-1)^K$3) -> 0 | L52: =IF(L$27<(1-$G$39),0,($F52/12)*(1+((1+$G52)^(1/12))-1)^L$3) -> 0 | M52: =IF(M$27<(1-$G$39),0,($F52/12)*(1+((1+$G52)^(1/12))-1)^M$3) -> 0 | N52: =IF(N$27<(1-$G$39),0,($F52/12)*(1+((1+$G52)^(1/12))-1)^N$3) -> 0 | O52: =IF(O$27<(1-$G$39),0,($F52/12)*(1+((1+$G52)^(1/12))-1)^O$3) -> 0 | P52: =IF(P$27<(1-$G$39),0,($F52/12)*(1+((1+$G52)^(1/12))-1)^P$3) -> 0 | Q52: =IF(Q$27<(1-$G$39),0,($F52/12)*(1+((1+$G52)^(1/12))-1)^Q$3) -> 0 | R52: =IF(R$27<(1-$G$39),0,($F52/12)*(1+((1+$G52)^(1/12))-1)^R$3) -> 0 | ... EX52: =IF(EX$27<(1-$G$39),0,($F52/12)*(1+((1+$G52)^(1/12))-1)^EX$3) -> 9806.481
C53: Utilities | F53: ='Middle NOI'!K51 -> 350000 | G53: ='Middle NOI'!$Y$11 -> 0.025 | H53: Fixed | K53: =IF(K$5>0,($F53/12)*(1+((1+$G53)^(1/12))-1)^K$3,0) -> 0 | L53: =IF(L$5>0,($F53/12)*(1+((1+$G53)^(1/12))-1)^L$3,0) -> 0 | M53: =IF(M$5>0,($F53/12)*(1+((1+$G53)^(1/12))-1)^M$3,0) -> 0 | N53: =IF(N$5>0,($F53/12)*(1+((1+$G53)^(1/12))-1)^N$3,0) -> 0 | O53: =IF(O$5>0,($F53/12)*(1+((1+$G53)^(1/12))-1)^O$3,0) -> 0 | P53: =IF(P$5>0,($F53/12)*(1+((1+$G53)^(1/12))-1)^P$3,0) -> 0 | Q53: =IF(Q$5>0,($F53/12)*(1+((1+$G53)^(1/12))-1)^Q$3,0) -> 0 | R53: =IF(R$5>0,($F53/12)*(1+((1+$G53)^(1/12))-1)^R$3,0) -> 0 | ... EX53: =IF(EX$5>0,($F53/12)*(1+((1+$G53)^(1/12))-1)^EX$3,0) -> 39225.924
C54: Leasing & Marketing | F54: ='Middle NOI'!K52 -> 87500 | G54: ='Middle NOI'!$Y$11 -> 0.025 | H54: Fixed | K54: =IF(K$5>0,($F54/12)*(1+((1+$G54)^(1/12))-1)^K$3,0) -> 0 | L54: =IF(L$5>0,($F54/12)*(1+((1+$G54)^(1/12))-1)^L$3,0) -> 0 | M54: =IF(M$5>0,($F54/12)*(1+((1+$G54)^(1/12))-1)^M$3,0) -> 0 | N54: =IF(N$5>0,($F54/12)*(1+((1+$G54)^(1/12))-1)^N$3,0) -> 0 | O54: =IF(O$5>0,($F54/12)*(1+((1+$G54)^(1/12))-1)^O$3,0) -> 0 | P54: =IF(P$5>0,($F54/12)*(1+((1+$G54)^(1/12))-1)^P$3,0) -> 0 | Q54: =IF(Q$5>0,($F54/12)*(1+((1+$G54)^(1/12))-1)^Q$3,0) -> 0 | R54: =IF(R$5>0,($F54/12)*(1+((1+$G54)^(1/12))-1)^R$3,0) -> 0 | ... EX54: =IF(EX$5>0,($F54/12)*(1+((1+$G54)^(1/12))-1)^EX$3,0) -> 9806.481
C55: ='Middle NOI'!Y14 -> 5000 | F55: ='Middle NOI'!K53 -> 231675.5 | G55: ='Middle NOI'!$Y$13 -> 0.02 | H55: Min. lease-up, then variable | K55: =IF(K$5>0,IF(K$27<(1-$G$39),$C$55,$G$55*K$44),0) -> 0 | L55: =IF(L$5>0,IF(L$27<(1-$G$39),$C$55,$G$55*L$44),0) -> 0 | M55: =IF(M$5>0,IF(M$27<(1-$G$39),$C$55,$G$55*M$44),0) -> 0 | N55: =IF(N$5>0,IF(N$27<(1-$G$39),$C$55,$G$55*N$44),0) -> 0 | O55: =IF(O$5>0,IF(O$27<(1-$G$39),$C$55,$G$55*O$44),0) -> 0 | P55: =IF(P$5>0,IF(P$27<(1-$G$39),$C$55,$G$55*P$44),0) -> 0 | Q55: =IF(Q$5>0,IF(Q$27<(1-$G$39),$C$55,$G$55*Q$44),0) -> 0 | R55: =IF(R$5>0,IF(R$27<(1-$G$39),$C$55,$G$55*R$44),0) -> 0 | ... EX55: =IF(EX$5>0,IF(EX$27<(1-$G$39),$C$55,$G$55*EX$44),0) -> 27215.638
C56: Insurance | D56: Property Tax in Lease-Up | F56: ='Middle NOI'!K54 -> 612500 | G56: ='Middle NOI'!$Y$11 -> 0.025 | H56: Fixed | K56: =IF(K$5>0,($F56/12)*(1+((1+$G56)^(1/12))-1)^K$3,0) -> 0 | L56: =IF(L$5>0,($F56/12)*(1+((1+$G56)^(1/12))-1)^L$3,0) -> 0 | M56: =IF(M$5>0,($F56/12)*(1+((1+$G56)^(1/12))-1)^M$3,0) -> 0 | N56: =IF(N$5>0,($F56/12)*(1+((1+$G56)^(1/12))-1)^N$3,0) -> 0 | O56: =IF(O$5>0,($F56/12)*(1+((1+$G56)^(1/12))-1)^O$3,0) -> 0 | P56: =IF(P$5>0,($F56/12)*(1+((1+$G56)^(1/12))-1)^P$3,0) -> 0 | Q56: =IF(Q$5>0,($F56/12)*(1+((1+$G56)^(1/12))-1)^Q$3,0) -> 0 | R56: =IF(R$5>0,($F56/12)*(1+((1+$G56)^(1/12))-1)^R$3,0) -> 0 | ... EX56: =IF(EX$5>0,($F56/12)*(1+((1+$G56)^(1/12))-1)^EX$3,0) -> 68645.367
C57: Property Taxes | D57: ='Middle NOI'!Y12 -> 0.25 | F57: ='Middle NOI'!K55 -> 1518257.8 | G57: ='Middle NOI'!$Y$11 -> 0.025 | H57: Min. lease-up, then fixed | K57: =IF(K$5>0,IF(K$27<$D$58,$D$57*$F$57/12,($F57/12)*(1+((1+$G57)^(1/12))-1)^K$3),0) -> 0 | L57: =IF(L$5>0,IF(L$27<$D$58,$D$57*$F$57/12,($F57/12)*(1+((1+$G57)^(1/12))-1)^L$3),0) -> 0 | M57: =IF(M$5>0,IF(M$27<$D$58,$D$57*$F$57/12,($F57/12)*(1+((1+$G57)^(1/12))-1)^M$3),0) -> 0 | N57: =IF(N$5>0,IF(N$27<$D$58,$D$57*$F$57/12,($F57/12)*(1+((1+$G57)^(1/12))-1)^N$3),0) -> 0 | O57: =IF(O$5>0,IF(O$27<$D$58,$D$57*$F$57/12,($F57/12)*(1+((1+$G57)^(1/12))-1)^O$3),0) -> 0 | P57: =IF(P$5>0,IF(P$27<$D$58,$D$57*$F$57/12,($F57/12)*(1+((1+$G57)^(1/12))-1)^P$3),0) -> 0 | Q57: =IF(Q$5>0,IF(Q$27<$D$58,$D$57*$F$57/12,($F57/12)*(1+((1+$G57)^(1/12))-1)^Q$3),0) -> 0 | R57: =IF(R$5>0,IF(R$27<$D$58,$D$57*$F$57/12,($F57/12)*(1+((1+$G57)^(1/12))-1)^R$3),0) -> 0 | ... EX57: =IF(EX$5>0,IF(EX$27<$D$58,$D$57*$F$57/12,($F57/12)*(1+((1+$G57)^(1/12))-1)^EX$3),0) -> 170157.33
C58: Replacement Reserve (starts at stabilization) | D58: ='Middle NOI'!S12 -> 0.75 | F58: ='Middle NOI'!K60 -> 70000 | G58: ='Middle NOI'!Y15 -> 200 | H58: Fixed post-stabilization | K58: =IF(K$5=0,0,IF(K$27<(1-$G$39),0,$G58*$C$9/12)) -> 0 | L58: =IF(L$5=0,0,IF(L$27<(1-$G$39),0,$G58*$C$9/12)) -> 0 | M58: =IF(M$5=0,0,IF(M$27<(1-$G$39),0,$G58*$C$9/12)) -> 0 | N58: =IF(N$5=0,0,IF(N$27<(1-$G$39),0,$G58*$C$9/12)) -> 0 | O58: =IF(O$5=0,0,IF(O$27<(1-$G$39),0,$G58*$C$9/12)) -> 0 | P58: =IF(P$5=0,0,IF(P$27<(1-$G$39),0,$G58*$C$9/12)) -> 0 | Q58: =IF(Q$5=0,0,IF(Q$27<(1-$G$39),0,$G58*$C$9/12)) -> 0 | R58: =IF(R$5=0,0,IF(R$27<(1-$G$39),0,$G58*$C$9/12)) -> 0 | ... EX58: =IF(EX$5=0,0,IF(EX$27<(1-$G$39),0,$G58*$C$9/12)) -> 5833.3333
C59: Total Operating Expenses | F59: =SUM(F48:F58) -> 3845633.3 | K59: =SUM(K48:K58) -> 0 | L59: =SUM(L48:L58) -> 0 | M59: =SUM(M48:M58) -> 0 | N59: =SUM(N48:N58) -> 0 | O59: =SUM(O48:O58) -> 0 | P59: =SUM(P48:P58) -> 0 | Q59: =SUM(Q48:Q58) -> 0 | R59: =SUM(R48:R58) -> 0 | ... EX59: =SUM(EX48:EX58) -> 430234.74
C61: Net Operating Income | F61: =F44-F59 -> 7738141.7 | K61: =K44-K59 -> 0 | L61: =L44-L59 -> 0 | M61: =M44-M59 -> 0 | N61: =N44-N59 -> 0 | O61: =O44-O59 -> 0 | P61: =P44-P59 -> 0 | Q61: =Q44-Q59 -> 0 | R61: =R44-R59 -> 0 | ... EX61: =EX44-EX59 -> 930547.16
J63: NOI Annualized | K63: =K61*12 -> 0 | L63: =L61*12 -> 0 | M63: =M61*12 -> 0 | N63: =N61*12 -> 0 | O63: =O61*12 -> 0 | P63: =P61*12 -> 0 | Q63: =Q61*12 -> 0 | R63: =R61*12 -> 0 | ... EX63: =EX61*12 -> 11166566
J64: T-12 NOI | K64: 0 | L64: 0 | M64: 0 | N64: 0 | O64: 0 | P64: 0 | Q64: 0 | R64: 0 | S64: 0 | T64: 0 | U64: 0 | V64: =SUM(K61:V61) -> 0 | W64: =SUM(L61:W61) -> 0 | X64: =SUM(M61:X61) -> 0 | Y64: =SUM(N61:Y61) -> 0 | Z64: =SUM(O61:Z61) -> 0 | AA64: =SUM(P61:AA61) -> 0 | AB64: =SUM(Q61:AB61) -> 0 | AC64: =SUM(R61:AC61) -> 0 | ... EX64: =SUM(EM61:EX61) -> 11006124
B65: DEVELOPMENT COSTS BEFORE INTEREST
I67: Total | J67: Closing
B69: Land Valuation | I69: =SUM(J69:EX69) -> 13300000 | J69: ='Middle Budget'!F52 -> 13300000 | K69: 0 | L69: 0 | M69: 0 | N69: 0 | O69: 0 | P69: 0 | Q69: 0 | R69: 0 | S69: 0 | T69: 0 | U69: 0 | V69: 0 | W69: 0 | X69: 0 | Y69: 0 | Z69: 0 | AA69: 0 | AB69: 0 | AC69: 0 | AD69: 0 | AE69: 0 | AF69: 0 | AG69: 0 | AH69: 0 | AI69: 0 | AJ69: 0 | AK69: 0 | AL69: 0 | AM69: 0 | AN69: 0 | AO69: 0 | AP69: 0 | AQ69: 0 | AR69: 0 | AS69: 0 | AT69: 0 | AU69: 0 | AV69: 0 | AW69: 0 | AX69: 0 | AY69: 0 | AZ69: 0 | BA69: 0 | BB69: 0 | BC69: 0 | BD69: 0 | BE69: 0 | BF69: 0 | BG69: 0 | BH69: 0 | BI69: 0 | BJ69: 0 | BK69: 0 | BL69: 0 | BM69: 0 | BN69: 0 | BO69: 0 | BP69: 0 | BQ69: 0 | BR69: 0 | BS69: 0 | BT69: 0 | BU69: 0 | BV69: 0 | BW69: 0 | BX69: 0 | BY69: 0 | BZ69: 0 | CA69: 0 | CB69: 0 | CC69: 0 | CD69: 0 | CE69: 0 | CF69: 0 | CG69: 0 | CH69: 0 | CI69: 0 | CJ69: 0 | CK69: 0 | CL69: 0 | CM69: 0 | CN69: 0 | CO69: 0 | CP69: 0 | CQ69: 0 | CR69: 0 | CS69: 0 | CT69: 0 | CU69: 0 | CV69: 0 | CW69: 0 | CX69: 0 | CY69: 0 | CZ69: 0 | DA69: 0 | DB69: 0 | DC69: 0 | DD69: 0 | DE69: 0 | DF69: 0 | DG69: 0 | DH69: 0 | DI69: 0 | DJ69: 0 | DK69: 0 | DL69: 0 | DM69: 0 | DN69: 0 | DO69: 0 | DP69: 0 | DQ69: 0 | DR69: 0 | DS69: 0 | DT69: 0 | DU69: 0 | DV69: 0 | DW69: 0 | DX69: 0 | DY69: 0 | DZ69: 0 | EA69: 0 | EB69: 0 | EC69: 0 | ED69: 0 | EE69: 0 | EF69: 0 | EG69: 0 | EH69: 0 | EI69: 0 | EJ69: 0 | EK69: 0 | EL69: 0 | EM69: 0 | EN69: 0 | EO69: 0 | EP69: 0 | EQ69: 0 | ER69: 0 | ES69: 0 | ET69: 0 | EU69: 0 | EV69: 0 | EW69: 0 | EX69: 0
B70: Financing Closing Costs | I70: =SUM(J70:EX70) -> 1678240.8 | J70: ='Middle Budget'!F53 -> 1678240.8 | K70: 0 | L70: 0 | M70: 0 | N70: 0 | O70: 0 | P70: 0 | Q70: 0 | R70: 0 | S70: 0 | T70: 0 | U70: 0 | V70: 0 | W70: 0 | X70: 0 | Y70: 0 | Z70: 0 | AA70: 0 | AB70: 0 | AC70: 0 | AD70: 0 | AE70: 0 | AF70: 0 | AG70: 0 | AH70: 0 | AI70: 0 | AJ70: 0 | AK70: 0 | AL70: 0 | AM70: 0 | AN70: 0 | AO70: 0 | AP70: 0 | AQ70: 0 | AR70: 0 | AS70: 0 | AT70: 0 | AU70: 0 | AV70: 0 | AW70: 0 | AX70: 0 | AY70: 0 | AZ70: 0 | BA70: 0 | BB70: 0 | BC70: 0 | BD70: 0 | BE70: 0 | BF70: 0 | BG70: 0 | BH70: 0 | BI70: 0 | BJ70: 0 | BK70: 0 | BL70: 0 | BM70: 0 | BN70: 0 | BO70: 0 | BP70: 0 | BQ70: 0 | BR70: 0 | BS70: 0 | BT70: 0 | BU70: 0 | BV70: 0 | BW70: 0 | BX70: 0 | BY70: 0 | BZ70: 0 | CA70: 0 | CB70: 0 | CC70: 0 | CD70: 0 | CE70: 0 | CF70: 0 | CG70: 0 | CH70: 0 | CI70: 0 | CJ70: 0 | CK70: 0 | CL70: 0 | CM70: 0 | CN70: 0 | CO70: 0 | CP70: 0 | CQ70: 0 | CR70: 0 | CS70: 0 | CT70: 0 | CU70: 0 | CV70: 0 | CW70: 0 | CX70: 0 | CY70: 0 | CZ70: 0 | DA70: 0 | DB70: 0 | DC70: 0 | DD70: 0 | DE70: 0 | DF70: 0 | DG70: 0 | DH70: 0 | DI70: 0 | DJ70: 0 | DK70: 0 | DL70: 0 | DM70: 0 | DN70: 0 | DO70: 0 | DP70: 0 | DQ70: 0 | DR70: 0 | DS70: 0 | DT70: 0 | DU70: 0 | DV70: 0 | DW70: 0 | DX70: 0 | DY70: 0 | DZ70: 0 | EA70: 0 | EB70: 0 | EC70: 0 | ED70: 0 | EE70: 0 | EF70: 0 | EG70: 0 | EH70: 0 | EI70: 0 | EJ70: 0 | EK70: 0 | EL70: 0 | EM70: 0 | EN70: 0 | EO70: 0 | EP70: 0 | EQ70: 0 | ER70: 0 | ES70: 0 | ET70: 0 | EU70: 0 | EV70: 0 | EW70: 0 | EX70: 0
B71: Hard Costs | I71: =SUM(J71:EX71) -> 86821875 | J71: ='Middle Budget'!F54 -> 0 | K71: =IF(AND(K$3>=$C$10,K$3<=$C$11),'Middle Budget'!$H$54/($C$11-$C$10+1),0) -> 3617578.1 | L71: =IF(AND(L$3>=$C$10,L$3<=$C$11),'Middle Budget'!$H$54/($C$11-$C$10+1),0) -> 3617578.1 | M71: =IF(AND(M$3>=$C$10,M$3<=$C$11),'Middle Budget'!$H$54/($C$11-$C$10+1),0) -> 3617578.1 | N71: =IF(AND(N$3>=$C$10,N$3<=$C$11),'Middle Budget'!$H$54/($C$11-$C$10+1),0) -> 3617578.1 | O71: =IF(AND(O$3>=$C$10,O$3<=$C$11),'Middle Budget'!$H$54/($C$11-$C$10+1),0) -> 3617578.1 | P71: =IF(AND(P$3>=$C$10,P$3<=$C$11),'Middle Budget'!$H$54/($C$11-$C$10+1),0) -> 3617578.1 | Q71: =IF(AND(Q$3>=$C$10,Q$3<=$C$11),'Middle Budget'!$H$54/($C$11-$C$10+1),0) -> 3617578.1 | R71: =IF(AND(R$3>=$C$10,R$3<=$C$11),'Middle Budget'!$H$54/($C$11-$C$10+1),0) -> 3617578.1 | ... EX71: =IF(AND(EX$3>=$C$10,EX$3<=$C$11),'Middle Budget'!$H$54/($C$11-$C$10+1),0) -> 0
B72: Soft Costs | I72: =SUM(J72:EX72) -> 12220301 | J72: ='Middle Budget'!F55 -> 1200000 | K72: =IF(AND(K$3>=$C$12,K$3<=$C$13),'Middle Budget'!$H$55/($C$13-$C$12+1),0) -> 423857.72 | L72: =IF(AND(L$3>=$C$12,L$3<=$C$13),'Middle Budget'!$H$55/($C$13-$C$12+1),0) -> 423857.72 | M72: =IF(AND(M$3>=$C$12,M$3<=$C$13),'Middle Budget'!$H$55/($C$13-$C$12+1),0) -> 423857.72 | N72: =IF(AND(N$3>=$C$12,N$3<=$C$13),'Middle Budget'!$H$55/($C$13-$C$12+1),0) -> 423857.72 | O72: =IF(AND(O$3>=$C$12,O$3<=$C$13),'Middle Budget'!$H$55/($C$13-$C$12+1),0) -> 423857.72 | P72: =IF(AND(P$3>=$C$12,P$3<=$C$13),'Middle Budget'!$H$55/($C$13-$C$12+1),0) -> 423857.72 | Q72: =IF(AND(Q$3>=$C$12,Q$3<=$C$13),'Middle Budget'!$H$55/($C$13-$C$12+1),0) -> 423857.72 | R72: =IF(AND(R$3>=$C$12,R$3<=$C$13),'Middle Budget'!$H$55/($C$13-$C$12+1),0) -> 423857.72 | ... EX72: =IF(AND(EX$3>=$C$12,EX$3<=$C$13),'Middle Budget'!$H$55/($C$13-$C$12+1),0) -> 0
B73: Operating Deficit Projection (sum of months with negative NOI) | I73: =SUM(J73:EX73) -> 22646.575 | J73: 0 | K73: =IF(K61<0,-K61,0) -> 0 | L73: =IF(L61<0,-L61,0) -> 0 | M73: =IF(M61<0,-M61,0) -> 0 | N73: =IF(N61<0,-N61,0) -> 0 | O73: =IF(O61<0,-O61,0) -> 0 | P73: =IF(P61<0,-P61,0) -> 0 | Q73: =IF(Q61<0,-Q61,0) -> 0 | R73: =IF(R61<0,-R61,0) -> 0 | ... EX73: =IF(EX61<0,-EX61,0) -> 0
B74: Operating Deficit Contingency (budget minimum) | I74: =SUM(J74:EX74) -> 27353.425 | J74: 0 | K74: =IF(AND(K$3>=$C$14,K$3<$C$16),IF($I$73>='Middle Budget'!$E$85,0,('Middle Budget'!$E$85-$I$73)/($C$16-$C$14)),0) -> 0 | L74: =IF(AND(L$3>=$C$14,L$3<$C$16),IF($I$73>='Middle Budget'!$E$85,0,('Middle Budget'!$E$85-$I$73)/($C$16-$C$14)),0) -> 0 | M74: =IF(AND(M$3>=$C$14,M$3<$C$16),IF($I$73>='Middle Budget'!$E$85,0,('Middle Budget'!$E$85-$I$73)/($C$16-$C$14)),0) -> 0 | N74: =IF(AND(N$3>=$C$14,N$3<$C$16),IF($I$73>='Middle Budget'!$E$85,0,('Middle Budget'!$E$85-$I$73)/($C$16-$C$14)),0) -> 0 | O74: =IF(AND(O$3>=$C$14,O$3<$C$16),IF($I$73>='Middle Budget'!$E$85,0,('Middle Budget'!$E$85-$I$73)/($C$16-$C$14)),0) -> 0 | P74: =IF(AND(P$3>=$C$14,P$3<$C$16),IF($I$73>='Middle Budget'!$E$85,0,('Middle Budget'!$E$85-$I$73)/($C$16-$C$14)),0) -> 0 | Q74: =IF(AND(Q$3>=$C$14,Q$3<$C$16),IF($I$73>='Middle Budget'!$E$85,0,('Middle Budget'!$E$85-$I$73)/($C$16-$C$14)),0) -> 0 | R74: =IF(AND(R$3>=$C$14,R$3<$C$16),IF($I$73>='Middle Budget'!$E$85,0,('Middle Budget'!$E$85-$I$73)/($C$16-$C$14)),0) -> 0 | ... EX74: =IF(AND(EX$3>=$C$14,EX$3<$C$16),IF($I$73>='Middle Budget'!$E$85,0,('Middle Budget'!$E$85-$I$73)/($C$16-$C$14)),0) -> 0
C75: Total Cost Before Interest Reserve | I75: =SUM(I69:I74) -> 1.1407042e+08 | J75: =SUM(J69:J74) -> 16178241 | K75: =SUM(K69:K74) -> 4041435.8 | L75: =SUM(L69:L74) -> 4041435.8 | M75: =SUM(M69:M74) -> 4041435.8 | N75: =SUM(N69:N74) -> 4041435.8 | O75: =SUM(O69:O74) -> 4041435.8 | P75: =SUM(P69:P74) -> 4041435.8 | ... EX75: =SUM(EX69:EX74) -> 0
B78: SCENARIO A: CAPITALIZATION - PRIORITIZED DEBT FUNDING
B80: Description of cash flow use and funding priorities:
B81: 1 | C81: Costs excluding interest are funded by unused equity available after closing.
B82: 2 | C82: Costs excluding interest after depletion of equity are funded by senior loan.
B83: 3 | C83: Operating income first pays interest expense. Unpaid interest is added to loan balance.
B84: 4 | C84: Operating income after interest goes to pay principal loan balance.
I85: Total | J85: Closing
C87: Total Cost Before Interest Reserve | I87: =SUM(J87:EX87) -> 1.1407042e+08 | J87: =J$75 -> 16178241 | K87: =K$75 -> 4041435.8 | L87: =L$75 -> 4041435.8 | M87: =M$75 -> 4041435.8 | N87: =N$75 -> 4041435.8 | O87: =O$75 -> 4041435.8 | P87: =P$75 -> 4041435.8 | Q87: =Q$75 -> 4041435.8 | ... EX87: =EX$75 -> 0
B89: Senior Interest Reserve
C90: Interest Expense | D90: Senior Loan Interest | I90: =SUM(J90:EX90) -> 9189830.5 | J90: 0 | K90: =J119*$D91/12 -> 0 | L90: =K119*$D91/12 -> 0 | M90: =L119*$D91/12 -> 0 | N90: =M119*$D91/12 -> 0 | O90: =N119*$D91/12 -> 0 | P90: =O119*$D91/12 -> 0 | Q90: =P119*$D91/12 -> 0 | R90: =Q119*$D91/12 -> 14519.136 | ... EX90: =EW119*$D91/12 -> 0
C91: Less: Operating Cash Flow | D91: ='Middle Budget'!H36 -> 0.06 | I91: =SUM(J91:EX91) -> -4504634.3 | J91: 0 | K91: =IF(AND(K90>0,K$61>0),IF(K90>K$61,-K$61,-K90),0) -> 0 | L91: =IF(AND(L90>0,L$61>0),IF(L90>L$61,-L$61,-L90),0) -> 0 | M91: =IF(AND(M90>0,M$61>0),IF(M90>M$61,-M$61,-M90),0) -> 0 | N91: =IF(AND(N90>0,N$61>0),IF(N90>N$61,-N$61,-N90),0) -> 0 | O91: =IF(AND(O90>0,O$61>0),IF(O90>O$61,-O$61,-O90),0) -> 0 | P91: =IF(AND(P90>0,P$61>0),IF(P90>P$61,-P$61,-P90),0) -> 0 | Q91: =IF(AND(Q90>0,Q$61>0),IF(Q90>Q$61,-Q$61,-Q90),0) -> 0 | R91: =IF(AND(R90>0,R$61>0),IF(R90>R$61,-R$61,-R90),0) -> 0 | ... EX91: =IF(AND(EX90>0,EX$61>0),IF(EX90>EX$61,-EX$61,-EX90),0) -> 0
I92: =SUM(I90:I91) -> 4685196.2 | J92: =SUM(J90:J91) -> 0 | K92: =SUM(K90:K91) -> 0 | L92: =SUM(L90:L91) -> 0 | M92: =SUM(M90:M91) -> 0 | N92: =SUM(N90:N91) -> 0 | O92: =SUM(O90:O91) -> 0 | P92: =SUM(P90:P91) -> 0 | ... EX92: =SUM(EX90:EX91) -> 0
B94: Total Cost Capitalized (cost before lender minimum interest) | I94: =I87+I92 -> 1.1875561e+08 | J94: =J87+J92 -> 16178241 | K94: =K87+K92 -> 4041435.8 | L94: =L87+L92 -> 4041435.8 | M94: =M87+M92 -> 4041435.8 | N94: =N87+N92 -> 4041435.8 | O94: =O87+O92 -> 4041435.8 | P94: =P87+P92 -> 4041435.8 | ... EX94: =EX87+EX92 -> 0
I95: =IF(ABS(I94-'Middle Budget'!L104)<1,"OK","ERROR") -> OK
B96: Equity Escrow (draws reduce balance)
C97: Beginning Balance | J97: ='Middle Budget'!L49 -> 41564464 | K97: =J99 -> 25386224 | L97: =K99 -> 21344788 | M97: =L99 -> 17303352 | N97: =M99 -> 13261916 | O97: =N99 -> 9220480.3 | P97: =O99 -> 5179044.4 | Q97: =P99 -> 1137608.6 | R97: =Q99 -> 0 | ... EX97: =EW99 -> 0
C98: Draws | J98: =-'Middle Budget'!F49 -> -16178241 | K98: =IF(AND(K97>0,K87>0),IF(K87<=K97,-K87,-K97),0) -> -4041435.8 | L98: =IF(AND(L97>0,L87>0),IF(L87<=L97,-L87,-L97),0) -> -4041435.8 | M98: =IF(AND(M97>0,M87>0),IF(M87<=M97,-M87,-M97),0) -> -4041435.8 | N98: =IF(AND(N97>0,N87>0),IF(N87<=N97,-N87,-N97),0) -> -4041435.8 | O98: =IF(AND(O97>0,O87>0),IF(O87<=O97,-O87,-O97),0) -> -4041435.8 | P98: =IF(AND(P97>0,P87>0),IF(P87<=P97,-P87,-P97),0) -> -4041435.8 | Q98: =IF(AND(Q97>0,Q87>0),IF(Q87<=Q97,-Q87,-Q97),0) -> -1137608.6 | R98: =IF(AND(R97>0,R87>0),IF(R87<=R97,-R87,-R97),0) -> 0 | ... EX98: =IF(AND(EX97>0,EX87>0),IF(EX87<=EX97,-EX87,-EX97),0) -> 0
C99: Ending Balance | J99: =SUM(J97:J98) -> 25386224 | K99: =SUM(K97:K98) -> 21344788 | L99: =SUM(L97:L98) -> 17303352 | M99: =SUM(M97:M98) -> 13261916 | N99: =SUM(N97:N98) -> 9220480.3 | O99: =SUM(O97:O98) -> 5179044.4 | P99: =SUM(P97:P98) -> 1137608.6 | Q99: =SUM(Q97:Q98) -> 0 | ... EX99: =SUM(EX97:EX98) -> 0
B101: Equity Balance | D101: Profit on Sale
C102: Beginning Balance | D102: Sale Price | F102: ='Middle Budget'!R18 -> 1.6268776e+08 | J102: 0 | K102: =J106 -> -41564464 | L102: =K106 -> -41564464 | M102: =L106 -> -41564464 | N102: =M106 -> -41564464 | O102: =N106 -> -41564464 | P102: =O106 -> -41564464 | Q102: =P106 -> -41564464 | R102: =Q106 -> -41564464 | ... EX102: =EW106 -> 43722011
C103: Initial Investment | D103: Sale Costs | F103: ='Middle Budget'!R19 -> -2033597 | I103: =SUM(J103:EX103) -> -41564464 | J103: =-'Middle Budget'!L49 -> -41564464 | K103: 0 | L103: 0 | M103: 0 | N103: 0 | O103: 0 | P103: 0 | Q103: 0 | R103: 0 | S103: 0 | T103: 0 | U103: 0 | V103: 0 | W103: 0 | X103: 0 | Y103: 0 | Z103: 0 | AA103: 0 | AB103: 0 | AC103: 0 | AD103: 0 | AE103: 0 | AF103: 0 | AG103: 0 | AH103: 0 | AI103: 0 | AJ103: 0 | AK103: 0 | AL103: 0 | AM103: 0 | AN103: 0 | AO103: 0 | AP103: 0 | AQ103: 0 | AR103: 0 | AS103: 0 | AT103: 0 | AU103: 0 | AV103: 0 | AW103: 0 | AX103: 0 | AY103: 0 | AZ103: 0 | BA103: 0 | BB103: 0 | BC103: 0 | BD103: 0 | BE103: 0 | BF103: 0 | BG103: 0 | BH103: 0 | BI103: 0 | BJ103: 0 | BK103: 0 | BL103: 0 | BM103: 0 | BN103: 0 | BO103: 0 | BP103: 0 | BQ103: 0 | BR103: 0 | BS103: 0 | BT103: 0 | BU103: 0 | BV103: 0 | BW103: 0 | BX103: 0 | BY103: 0 | BZ103: 0 | CA103: 0 | CB103: 0 | CC103: 0 | CD103: 0 | CE103: 0 | CF103: 0 | CG103: 0 | CH103: 0 | CI103: 0 | CJ103: 0 | CK103: 0 | CL103: 0 | CM103: 0 | CN103: 0 | CO103: 0 | CP103: 0 | CQ103: 0 | CR103: 0 | CS103: 0 | CT103: 0 | CU103: 0 | CV103: 0 | CW103: 0 | CX103: 0 | CY103: 0 | CZ103: 0 | DA103: 0 | DB103: 0 | DC103: 0 | DD103: 0 | DE103: 0 | DF103: 0 | DG103: 0 | DH103: 0 | DI103: 0 | DJ103: 0 | DK103: 0 | DL103: 0 | DM103: 0 | DN103: 0 | DO103: 0 | DP103: 0 | DQ103: 0 | DR103: 0 | DS103: 0 | DT103: 0 | DU103: 0 | DV103: 0 | DW103: 0 | DX103: 0 | DY103: 0 | DZ103: 0 | EA103: 0 | EB103: 0 | EC103: 0 | ED103: 0 | EE103: 0 | EF103: 0 | EG103: 0 | EH103: 0 | EI103: 0 | EJ103: 0 | EK103: 0 | EL103: 0 | EM103: 0 | EN103: 0 | EO103: 0 | EP103: 0 | EQ103: 0 | ER103: 0 | ES103: 0 | ET103: 0 | EU103: 0 | EV103: 0 | EW103: 0 | EX103: 0
C104: Post-Stabilization Operating CF After Debt Service | D104: Net Price | F104: =SUM(F102:F103) -> 1.6065416e+08 | I104: =SUM(J104:EX104) -> 975172.93 | J104: 0 | K104: =IF(AND(K3>$C$16,K3<=$C$17),IF((K$61+K91)>0,K$61+K91,0),0) -> 0 | L104: =IF(AND(L3>$C$16,L3<=$C$17),IF((L$61+L91)>0,L$61+L91,0),0) -> 0 | M104: =IF(AND(M3>$C$16,M3<=$C$17),IF((M$61+M91)>0,M$61+M91,0),0) -> 0 | N104: =IF(AND(N3>$C$16,N3<=$C$17),IF((N$61+N91)>0,N$61+N91,0),0) -> 0 | O104: =IF(AND(O3>$C$16,O3<=$C$17),IF((O$61+O91)>0,O$61+O91,0),0) -> 0 | P104: =IF(AND(P3>$C$16,P3<=$C$17),IF((P$61+P91)>0,P$61+P91,0),0) -> 0 | Q104: =IF(AND(Q3>$C$16,Q3<=$C$17),IF((Q$61+Q91)>0,Q$61+Q91,0),0) -> 0 | R104: =IF(AND(R3>$C$16,R3<=$C$17),IF((R$61+R91)>0,R$61+R91,0),0) -> 0 | ... EX104: =IF(AND(EX3>$C$16,EX3<=$C$17),IF((EX$61+EX91)>0,EX$61+EX91,0),0) -> 0
C105: Return of Equity & Profit on Sale | D105: Total Cost | F105: ='Middle Budget'!R21 -> -1.1914157e+08 | I105: =SUM(J105:EX105) -> 84311316 | J105: 0 | K105: =IF(K$3=$C$17,$F$104+K118,0) -> 0 | L105: =IF(L$3=$C$17,$F$104+L118,0) -> 0 | M105: =IF(M$3=$C$17,$F$104+M118,0) -> 0 | N105: =IF(N$3=$C$17,$F$104+N118,0) -> 0 | O105: =IF(O$3=$C$17,$F$104+O118,0) -> 0 | P105: =IF(P$3=$C$17,$F$104+P118,0) -> 0 | Q105: =IF(Q$3=$C$17,$F$104+Q118,0) -> 0 | R105: =IF(R$3=$C$17,$F$104+R118,0) -> 0 | ... EX105: =IF(EX$3=$C$17,$F$104+EX118,0) -> 0
C106: Ending Balance | D106: Profit on Sale | F106: =SUM(F104:F105) -> 41512595 | I106: =SUM(I103:I105) -> 43722024 | J106: =SUM(J102:J105) -> -41564464 | K106: =SUM(K102:K105) -> -41564464 | L106: =SUM(L102:L105) -> -41564464 | M106: =SUM(M102:M105) -> -41564464 | N106: =SUM(N102:N105) -> -41564464 | O106: =SUM(O102:O105) -> -41564464 | P106: =SUM(P102:P105) -> -41564464 | Q106: =SUM(Q102:Q105) -> -41564464 | ... EX106: =SUM(EX102:EX105) -> 43722011
D107: Cash Flow After Debt Service | F107: =I104-I115 -> 2209429
C108: Net Equity Cash Flow | F108: =SUM(F106:F107) -> 43722024 | I108: =SUM(J108:EX108) -> 43722024 | J108: =SUM(J103:J105) -> -41564464 | K108: =SUM(K103:K105) -> 0 | L108: =SUM(L103:L105) -> 0 | M108: =SUM(M103:M105) -> 0 | N108: =SUM(N103:N105) -> 0 | O108: =SUM(O103:O105) -> 0 | P108: =SUM(P103:P105) -> 0 | Q108: =SUM(Q103:Q105) -> 0 | ... EX108: =SUM(EX103:EX105) -> 0
I109: =IF(ABS(I108-F108)<1,"OK","ERROR") -> OK
D110: IRR | F110: =XIRR(J108:EX108,$J$4:$EX$4) -> 0.24086857
B111: Construction Loan (draws increase balance)
C112: Beginning Balance | D112: Loan Commitment | J112: 0 | K112: =J119 -> 0 | L112: =K119 -> 0 | M112: =L119 -> 0 | N112: =M119 -> 0 | O112: =N119 -> 0 | P112: =O119 -> 0 | Q112: =P119 -> 0 | R112: =Q119 -> 2903827.3 | ... EX112: =EW119 -> 0
C113: Draws - Hard & Soft Costs Excl. Interest | D113: HC & SC | F113: =F115-F114 -> 72505952 | I113: =SUM(J113:EX113) -> 72505952 | J113: ='Middle Budget'!F48 -> 0 | K113: =K87+K98 -> 0 | L113: =L87+L98 -> 0 | M113: =M87+M98 -> 0 | N113: =N87+N98 -> 0 | O113: =O87+O98 -> 0 | P113: =P87+P98 -> 0 | Q113: =Q87+Q98 -> 2903827.3 | R113: =R87+R98 -> 4041435.8 | ... EX113: =EX87+EX98 -> 0
C114: Draws - Interest Expense | D114: Interest | F114: ='Middle Budget'!L57 -> 4685196.2 | I114: =SUM(J114:EX114) -> 4685196.2 | J114: =J92 -> 0 | K114: =K92 -> 0 | L114: =L92 -> 0 | M114: =M92 -> 0 | N114: =N92 -> 0 | O114: =O92 -> 0 | P114: =P92 -> 0 | Q114: =Q92 -> 0 | ... EX114: =EX92 -> 0
C115: Pre-Stabilization - Operating CF After Debt Service | D115: Total | F115: ='Middle Budget'!L48 -> 77191148 | I115: =SUM(J115:EX115) -> -1234256 | J115: 0 | K115: =IF(K3<=$C$16,IF(AND(SUM(K112:K114)>0,(K$61+K91)>0),IF(SUM(K112:K114)>(K$61+K91),-(K$61+K91),-SUM(K112:K114)),0),0) -> 0 | L115: =IF(L3<=$C$16,IF(AND(SUM(L112:L114)>0,(L$61+L91)>0),IF(SUM(L112:L114)>(L$61+L91),-(L$61+L91),-SUM(L112:L114)),0),0) -> 0 | M115: =IF(M3<=$C$16,IF(AND(SUM(M112:M114)>0,(M$61+M91)>0),IF(SUM(M112:M114)>(M$61+M91),-(M$61+M91),-SUM(M112:M114)),0),0) -> 0 | N115: =IF(N3<=$C$16,IF(AND(SUM(N112:N114)>0,(N$61+N91)>0),IF(SUM(N112:N114)>(N$61+N91),-(N$61+N91),-SUM(N112:N114)),0),0) -> 0 | O115: =IF(O3<=$C$16,IF(AND(SUM(O112:O114)>0,(O$61+O91)>0),IF(SUM(O112:O114)>(O$61+O91),-(O$61+O91),-SUM(O112:O114)),0),0) -> 0 | P115: =IF(P3<=$C$16,IF(AND(SUM(P112:P114)>0,(P$61+P91)>0),IF(SUM(P112:P114)>(P$61+P91),-(P$61+P91),-SUM(P112:P114)),0),0) -> 0 | Q115: =IF(Q3<=$C$16,IF(AND(SUM(Q112:Q114)>0,(Q$61+Q91)>0),IF(SUM(Q112:Q114)>(Q$61+Q91),-(Q$61+Q91),-SUM(Q112:Q114)),0),0) -> 0 | R115: =IF(R3<=$C$16,IF(AND(SUM(R112:R114)>0,(R$61+R91)>0),IF(SUM(R112:R114)>(R$61+R91),-(R$61+R91),-SUM(R112:R114)),0),0) -> 0 | ... EX115: =IF(EX3<=$C$16,IF(AND(SUM(EX112:EX114)>0,(EX$61+EX91)>0),IF(SUM(EX112:EX114)>(EX$61+EX91),-(EX$61+EX91),-SUM(EX112:EX114)),0),0) -> 0
C116: Lender Minimum Interest | F116: =IF(ABS(F115-I113-I114)<1,"OK","ERROR") -> OK | I116: =SUM(J116:EX116) -> 0 | J116: 0 | K116: =IF(K$3=$C$17,'Middle Budget'!$L$106,0) -> 0 | L116: =IF(L$3=$C$17,'Middle Budget'!$L$106,0) -> 0 | M116: =IF(M$3=$C$17,'Middle Budget'!$L$106,0) -> 0 | N116: =IF(N$3=$C$17,'Middle Budget'!$L$106,0) -> 0 | O116: =IF(O$3=$C$17,'Middle Budget'!$L$106,0) -> 0 | P116: =IF(P$3=$C$17,'Middle Budget'!$L$106,0) -> 0 | Q116: =IF(Q$3=$C$17,'Middle Budget'!$L$106,0) -> 0 | R116: =IF(R$3=$C$17,'Middle Budget'!$L$106,0) -> 0 | ... EX116: =IF(EX$3=$C$17,'Middle Budget'!$L$106,0) -> 0
C117: Lender Exit Fee | I117: =SUM(J117:EX117) -> 385955.74 | J117: 0 | K117: =IF(K$3=$C$17,'Middle Budget'!$L$107,0) -> 0 | L117: =IF(L$3=$C$17,'Middle Budget'!$L$107,0) -> 0 | M117: =IF(M$3=$C$17,'Middle Budget'!$L$107,0) -> 0 | N117: =IF(N$3=$C$17,'Middle Budget'!$L$107,0) -> 0 | O117: =IF(O$3=$C$17,'Middle Budget'!$L$107,0) -> 0 | P117: =IF(P$3=$C$17,'Middle Budget'!$L$107,0) -> 0 | Q117: =IF(Q$3=$C$17,'Middle Budget'!$L$107,0) -> 0 | R117: =IF(R$3=$C$17,'Middle Budget'!$L$107,0) -> 0 | ... EX117: =IF(EX$3=$C$17,'Middle Budget'!$L$107,0) -> 0
C118: Loan Repayment at Sale | I118: =SUM(J118:EX118) -> -76342848 | J118: 0 | K118: =IF(K$3=$C$17,-SUM(K112:K117),0) -> 0 | L118: =IF(L$3=$C$17,-SUM(L112:L117),0) -> 0 | M118: =IF(M$3=$C$17,-SUM(M112:M117),0) -> 0 | N118: =IF(N$3=$C$17,-SUM(N112:N117),0) -> 0 | O118: =IF(O$3=$C$17,-SUM(O112:O117),0) -> 0 | P118: =IF(P$3=$C$17,-SUM(P112:P117),0) -> 0 | Q118: =IF(Q$3=$C$17,-SUM(Q112:Q117),0) -> 0 | R118: =IF(R$3=$C$17,-SUM(R112:R117),0) -> 0 | ... EX118: =IF(EX$3=$C$17,-SUM(EX112:EX117),0) -> 0
C119: Ending Balance | I119: =SUM(I113:I118) -> -6.9141388e-06 | J119: =SUM(J112:J118) -> 0 | K119: =SUM(K112:K118) -> 0 | L119: =SUM(L112:L118) -> 0 | M119: =SUM(M112:M118) -> 0 | N119: =SUM(N112:N118) -> 0 | O119: =SUM(O112:O118) -> 0 | P119: =SUM(P112:P118) -> 0 | Q119: =SUM(Q112:Q118) -> 2903827.3 | ... EX119: =SUM(EX112:EX118) -> 0

Sheet Low Budget
A1: =Summary!$A$1&" - "&Summary!$G$4 -> 301 E. ATLANTIC POMPANO BEACH - BUYER'S PREFERRED | Z1: FONT KEY
Z2: Blue = Input cell
Z3: Red = Link to Summary
C4: UNIT SUMMARY | L4: PROJECTED PROFIT ON SALE AT STABILIZATION | Z4: Orange = Link to Middle scenario
Z5: Black = Text or formula cell
E6: Development Land Area | H6: ='Middle Budget'!H6 -> 2.3362029
E7: Density | H7: =H11/H6 -> 149.81575 | L7: Stabilized Value | T7: Sale / Refi | V7: Stabilization
E8: Height | H8: ='Middle Budget'!H8 -> 8 | T8: =H27 -> 40 | V8: =H26 -> 37
E9: Gross Building Area | H9: =H12/H10 -> 525000 | L9: NOI with Developer Property Taxes | R9: RE Tax | T9: =LOOKUP(H27,'Low ICF'!K3:EX3,'Low ICF'!K61:EX61)*12 -> 8480558.3 | V9: =LOOKUP(H26,'Low ICF'!K3:EX3,'Low ICF'!K61:EX61)*12 -> 8413315.5
E10: Building Efficiency | H10: ='Middle Budget'!H10 -> 0.5 | L10: Add Back: Developer Property Taxes | R10: Reassessment | T10: =LOOKUP(H27,'Low ICF'!K3:EX3,'Low ICF'!K57:EX57)*12 -> 1648510.6 | V10: =LOOKUP(H26,'Low ICF'!K3:EX3,'Low ICF'!K57:EX57)*12 -> 1638365.4
E11: Unit Count - Total | H11: ='Low NOI'!F14 -> 350 | L11: Less: Taxes with Market Value Reassessment | R11: ='Middle Budget'!R11 -> 0.75 | T11: =-T14*$R$11*$R$12*(1-R13) -> -2401400.2 | V11: =-V14*R11*R12*(1-R13) -> -2383053.1
E12: Net Rentable Area | H12: ='Low NOI'!I14 -> 262500 | L12: NOI After Market Value Tax Reassessment | R12: ='Middle Budget'!R12 -> 0.0205011 | T12: =SUM(T9:T11) -> 7727668.7 | V12: =SUM(V9:V11) -> 7668627.8
E13: Average Unit Size | H13: =H12/H11 -> 750 | L13: Market Cap Rate | R13: ='Middle Budget'!R13 -> 0.04 | T13: =Summary!G32 -> 0.0475 | V13: =Summary!G32 -> 0.0475
E14: Un-Trended Average Rent Per Unit | H14: ='Low NOI'!K14 -> 2740 | L14: Estimated Market Value | T14: =IF(ABS(T13)>0,T12/T13,0) -> 1.6268776e+08 | V14: =IF(ABS(V13)>0,V12/V13,0) -> 1.614448e+08
E15: Un-Trended Average Rent Per SF | H15: ='Low NOI'!M14 -> 3.6533333
E16: Un-Trended NOI (developer property taxes) | H16: ='Low NOI'!K62 -> 7738141.7 | L16: Net Profit on Sale at Stabilization
R17: Total | T17: Per Unit | V17: Per SF
C18: PROJECTED TIMING | L18: Value at Sale Date | R18: =T14 -> 1.6268776e+08 | T18: =R18/$H$11 -> 464822.17 | V18: =R18/$H$12 -> 619.7629
L19: ='Middle Budget'!L19 -> 0.0125 | M19: ='Middle Budget'!M19 -> 0 | N19: ='Middle Budget'!N19 -> 0 | O19: ='Middle Budget'!O19 -> 0 | P19: ='Middle Budget'!P19 -> 0 | R19: =R18*-L19 -> -2033597 | T19: =R19/$H$11 -> -5810.2772 | V19: =R19/$H$12 -> -7.7470362
E20: Hard Cost Draws Start | H20: ='Middle Budget'!H20 -> 1 | L20: Net Sale Proceeds | R20: =SUM(R18:R19) -> 1.6065416e+08 | T20: =R20/$H$11 -> 459011.9 | V20: =R20/$H$12 -> 612.01586
E21: Hard Cost Draws End | H21: =Summary!G42 -> 24 | L21: Less: Total Land & Development Cost | R21: =-L110 -> -1.1795428e+08 | T21: =R21/$H$11 -> -337012.23 | V21: =R21/$H$12 -> -449.34963
E22: Soft Cost Draws Start Excl. Op. Deficit | H22: ='Middle Budget'!H22 -> 1 | L22: Net Profit on Sale | R22: =SUM(R20:R21) -> 42699885 | T22: =R22/$H$11 -> 121999.67 | V22: =R22/$H$12 -> 162.66623
E23: ='Middle Budget'!E23 -> 2 | H23: =H21+E23 -> 26 | L23: Add: Operating Cash Flow After Debt Service | R23: ='Low ICF'!I104-'Low ICF'!I115 -> 2244685.6 | T23: =R23/$H$11 -> 6413.3874 | V23: =R23/$H$12 -> 8.5511832
E24: ='Middle Budget'!E24 -> 1 | H24: =H21+E24 -> 25 | L24: Total Net Profit | R24: =SUM(R22:R23) -> 44944570 | T24: =R24/$H$11 -> 128413.06 | V24: =R24/$H$12 -> 171.21741
E25: Average Monthly Move-Ins | H25: =(H11*(1-'Low NOI'!$Y$9))/(H26-H24+1) -> 25.576923
E26: =Summary!G31 -> 12 | H26: =H24+E26 -> 37 | L26: RETURN METRICS
E27: ='Middle Budget'!E27 -> 3 | H27: =H26+E27 -> 40
L28: Merchant Build
C29: CONSTRUCTION FINANCING ASSUMPTIONS | L29: Untrended Return on Cost (NOI with developer property taxes) | V29: =H16/L110 -> 0.065602891
L30: Net Profit as % of Cost (excl. net op. CF) | V30: =IF(ABS(R21)>0,-R22/R21,0) -> 0.3620037
E31: Maximum Loan to Cost | H31: ='Middle Budget'!H31 -> 0.65 | L31: IRR on Sale at Stabilization (incl. net op. CF) | V31: ='Low ICF'!F110 -> 0.24813606
E32: Maximum % of Stabilized Value | H32: ='Middle Budget'!H32 -> 0.55 | L32: Equity Multiple on Sale at Stabilization (incl. net op. CF) | V32: =(R24+L49)/L49 -> 2.0922063
E33: Minimum Un-Trended Debt Yield (NOI with developer property taxes) | H33: ='Middle Budget'!H33 -> 0.085
E34: Interest Rate - Projected Average Index | H34: ='Middle Budget'!H34 -> 0.035 | L34: Permanent Refinancing
E35: Interest Rate - Spread | H35: ='Middle Budget'!H35 -> 0.025 | L35: Post-Permanent Refinancing Cash-on-Cash Return - Interest Only | V35: =L155 -> 0.14069565
E36: Interest Rate - Total | H36: =H34+H35 -> 0.06 | L36: Post-Permanent Refinancing Cash-on-Cash Return - Amortizing | V36: =H155 -> 0.082007948
E37: Minimum Interest - Months | H37: ='Middle Budget'!H37 -> 12
E38: Minimum Interest - Amount | H38: =L48*H36/12*H37 -> 4585314.6
E39: Origination Fee | H39: ='Middle Budget'!H39 -> 0.01
E40: Exit Fee | H40: ='Middle Budget'!H40 -> 0.005
B44: SOURCES & USES | T44: Untrended | V44: % Stabilized
F45: At Closing | H45: Post-Closing | L45: Total | N45: Per Unit | P45: Per SF | R45: % of Cost | T45: Stabilized DY | V45: Value
T46: Developer RE Tax | V46: Market Value RE Tax
D47: Sources:
E48: Construction Loan | F48: =F58-F49 -> 0 | H48: =L48-F48 -> 76421910 | L48: =MIN(H31*L58,H32*V14,H16/H33) -> 76421910 | N48: =L48/$H$11 -> 218348.31 | P48: =L48/$H$12 -> 291.13109 | R48: =L48/$L$58 -> 0.65 | T48: =H16/L48 -> 0.10125554 | V48: =L48/$V$14 -> 0.47336249
E49: Equity | F49: =IF(L49<F58,L49,F58) -> 15114625 | H49: =L49-F49 -> 26035634 | L49: =L58-L48 -> 41150259 | N49: =L49/$H$11 -> 117572.17 | P49: =L49/$H$12 -> 156.76289 | R49: =L49/$L$58 -> 0.35
F50: =SUM(F48:F49) -> 15114625 | H50: =L50-F50 -> 1.0245754e+08 | L50: =SUM(L48:L49) -> 1.1757217e+08 | N50: =L50/$H$11 -> 335920.48 | P50: =L50/$H$12 -> 447.89398 | R50: =SUM(R48:R49) -> 1
D51: Uses:
E52: Land | F52: =L52 -> 12250000 | H52: =L52-F52 -> 0 | L52: =L71 -> 12250000 | N52: =L52/$H$11 -> 35000 | P52: =L52/$H$12 -> 46.666667
E53: Financing Closing Costs | F53: =L53 -> 1664625.3 | H53: =L53-F53 -> 0 | L53: =L98 -> 1664625.3 | N53: =L53/$H$11 -> 4756.0723 | P53: =L53/$H$12 -> 6.3414298
E54: Hard Costs | F54: ='Middle Budget'!F54 -> 0 | H54: =L54-F54 -> 86821875 | L54: =L76 -> 86821875 | N54: =L54/$H$11 -> 248062.5 | P54: =L54/$H$12 -> 330.75
E55: Soft Costs (excl. operating deficit) | F55: ='Middle Budget'!F55 -> 1200000 | H55: =L55-F55 -> 10986045 | L55: =L88-L85 -> 12186045 | N55: =L55/$H$11 -> 34817.272 | P55: =L55/$H$12 -> 46.423029
E56: Operating Deficit | F56: ='Middle Budget'!F56 -> 0 | H56: =L56-F56 -> 50000 | L56: =L85 -> 50000 | N56: =L56/$H$11 -> 142.85714 | P56: =L56/$H$12 -> 0.19047619
E57: Interest Reserve | F57: ='Middle Budget'!F57 -> 0 | H57: =L57-F57 -> 4599624.1 | L57: =L102 -> 4599624.1 | N57: =L57/$H$11 -> 13141.783 | P57: =L57/$H$12 -> 17.522378
F58: =SUM(F52:F57) -> 15114625 | H58: =L58-F58 -> 1.0245754e+08 | L58: =IF(ABS(SUM(L52:L57)-L104)<1,SUM(L52:L57),"ERROR") -> 1.1757217e+08 | N58: =L58/$H$11 -> 335920.48 | P58: =L58/$H$12 -> 447.89398
E60: Reconciliation to Total Cost:
E61: Total Capitalized Cost | L61: =L58 -> 1.1757217e+08
E62: Add: Lender Minimum Interest | L62: =L106 -> 0
E63: Add: Lender Exit Fee | L63: =L107 -> 382109.55
E64: Total Cost | L64: =SUM(L61:L63) -> 1.1795428e+08
B68: DEVELOPMENT BUDGET
L69: Total Cost | N69: Per Unit | P69: Per SF
D71: Land | L71: =Summary!G12 -> 12250000 | N71: =L71/$H$11 -> 35000 | P71: =L71/$H$12 -> 46.666667
D73: Hard Costs
E74: =Summary!G36 -> 315 | L74: =E74*H12 -> 82687500 | N74: =L74/$H$11 -> 236250 | P74: =L74/$H$12 -> 315
E75: =Summary!G37 -> 0.05 | L75: =L74*E75 -> 4134375 | N75: =L75/$H$11 -> 11812.5 | P75: =L75/$H$12 -> 15.75
F76: Impact Fees & Utility Connection | L76: =SUM(L74:L75) -> 86821875 | N76: =L76/$H$11 -> 248062.5 | P76: =L76/$H$12 -> 330.75
D77: Soft Costs | F77: Unit Mix for County Calc.
E78: Architectural & Engineering | F78: Studio/1BR | H78: 2BR+ | L78: ='Middle Budget'!L78 -> 1250000 | N78: =L78/$H$11 -> 3571.4286 | P78: =L78/$H$12 -> 4.7619048
E79: Legal & Consultants | F79: ='Low NOI'!F10+'Low NOI'!F11 -> 210 | H79: ='Low NOI'!F12 -> 140 | L79: ='Middle Budget'!L79 -> 500000 | N79: =L79/$H$11 -> 1428.5714 | P79: =L79/$H$12 -> 1.9047619
E80: Advertising & Marketing | F80: County - School | L80: ='Middle Budget'!L80 -> 250000 | N80: =L80/$H$11 -> 714.28571 | P80: =L80/$H$12 -> 0.95238095
E81: =L71*R11*R12*(1-R13) -> 180819.7 | F81: ='Middle Budget'!F81 -> 375 | H81: ='Middle Budget'!H81 -> 1475 | L81: =E81/12*H24 -> 376707.71 | N81: =L81/$H$11 -> 1076.3077 | P81: =L81/$H$12 -> 1.435077
E82: ='Middle Budget'!E82 -> 0.02 | F82: =$F$79*F81 -> 78750 | H82: =$H$79*H81 -> 206500 | L82: =E82*L76 -> 1736437.5 | N82: =L82/$H$11 -> 4961.25 | P82: =L82/$H$12 -> 6.615
E83: =G96/H11 -> 11767.634 | F83: Total School: | G83: =F82+H82 -> 285250 | L83: =E83*H11 -> 4118672 | N83: =L83/$H$11 -> 11767.634 | P83: =L83/$H$12 -> 15.690179
E84: ='Middle Budget'!E84 -> 0.0091929237 | F84: City - Recreational / Park | L84: =E84*L76 -> 798146.88 | N84: =L84/$H$11 -> 2280.4196 | P84: =L84/$H$12 -> 3.0405595
E85: ='Middle Budget'!E85 -> 50000 | F85: ='Middle Budget'!F85 -> 617 | H85: ='Middle Budget'!H85 -> 617 | L85: ='Low ICF'!I73+'Low ICF'!I74 -> 50000 | N85: =L85/$H$11 -> 142.85714 | P85: =L85/$H$12 -> 0.19047619
E86: ='Middle Budget'!E86 -> 0.03 | F86: =$F$79*F85 -> 129570 | H86: =$H$79*H85 -> 86380 | L86: =SUM(L78:L84)*E86 -> 270898.92 | N86: =L86/$H$11 -> 773.99692 | P86: =L86/$H$12 -> 1.0319959
E87: =Summary!G40 -> 0.03 | F87: Total Rec.: | G87: =F86+H86 -> 215950 | L87: =E87*(L76+SUM(L78:L86)) -> 2885182.1 | N87: =L87/$H$11 -> 8243.3775 | P87: =L87/$H$12 -> 10.99117 | R87: =L87/L110 -> 0.024460174
F88: City - Fire/Law/Transport | L88: =SUM(L78:L87) -> 12236045 | N88: =L88/$H$11 -> 34960.129 | P88: =L88/$H$12 -> 46.613505 | R88: =L88/L76 -> 0.14093274
D89: Financing Closing Costs | F89: ='Middle Budget'!F89 -> 0 | R89: =(L88+L98+L102+L108)/L76 -> 0.21748441
E90: =H39 -> 0.01 | F90: =$H$11*F89 -> 0 | L90: =E90*L48 -> 764219.1 | N90: =L90/$H$11 -> 2183.4831 | P90: =L90/$H$12 -> 2.9113109
E91: ='Middle Budget'!E91 -> 0 | F91: County Affordable Housing | L91: =E91*L48 -> 0 | N91: =L91/$H$11 -> 0 | P91: =L91/$H$12 -> 0
E92: Lender Due Diligence Costs | F92: ='Middle Budget'!F92 -> 10000 | L92: ='Middle Budget'!L92 -> 5000 | N92: =L92/$H$11 -> 14.285714 | P92: =L92/$H$12 -> 0.019047619
E93: Third Party Reports (incl. lender cost review) | F93: =$H$11*F92 -> 3500000 | L93: ='Middle Budget'!L93 -> 50000 | N93: =L93/$H$11 -> 142.85714 | P93: =L93/$H$12 -> 0.19047619
E94: ='Middle Budget'!E94 -> 0 | F94: Utility Connections | L94: =E94*L48 -> 0 | N94: =L94/$H$11 -> 0 | P94: =L94/$H$12 -> 0
E95: ='Middle Budget'!E95 -> 0.0055 | F95: ='Middle Budget'!F95 -> 117472 | L95: =E95*L48 -> 420320.51 | N95: =L95/$H$11 -> 1200.9157 | P95: =L95/$H$12 -> 1.601221
E96: Title Insurance (see formula) | F96: Total Fees: | G96: =G83+G87+F90+F93+F95 -> 4118672 | L96: =IF(L48<10000000,(15075+((L48-5000000)/1000*2.25))*1.1,(26325+((L48-10000000)/1000*2))*1.1) -> 175085.7 | N96: =L96/$H$11 -> 500.24486 | P96: =L96/$H$12 -> 0.66699315
E97: Legal & Other Closing Costs | L97: ='Middle Budget'!L97 -> 250000 | N97: =L97/$H$11 -> 714.28571 | P97: =L97/$H$12 -> 0.95238095
L98: =SUM(L90:L97) -> 1664625.3 | N98: =L98/$H$11 -> 4756.0723 | P98: =L98/$H$12 -> 6.3414298
D99: Interest Reserve
E100: Projected Interest Expense | L100: ='Low ICF'!I90 -> 9069001.9 | N100: =L100/$H$11 -> 25911.434 | P100: =L100/$H$12 -> 34.548579
E101: Projected Operating Income Offset | L101: ='Low ICF'!I91 -> -4469377.7 | N101: =L101/$H$11 -> -12769.651 | P101: =L101/$H$12 -> -17.026201
L102: =SUM(L100:L101) -> 4599624.1 | N102: =L102/$H$11 -> 13141.783 | P102: =L102/$H$12 -> 17.522378
E104: Total Cost Capitalized with Debt & Equity | L104: =L71+L76+L88+L98+L102 -> 1.1757217e+08 | N104: =L104/$H$11 -> 335920.48 | P104: =L104/$H$12 -> 447.89398
F105: Minimum Interest
E106: Lender Minimum Interest | F106: Minimum Interest | H106: =H38 -> 4585314.6 | L106: =H108 -> 0 | N106: =L106/$H$11 -> 0 | P106: =L106/$H$12 -> 0
E107: Lender Exit Fee | F107: Interest Incurred | H107: =L100 -> 9069001.9 | L107: =L48*H40 -> 382109.55 | N107: =L107/$H$11 -> 1091.7416 | P107: =L107/$H$12 -> 1.4556554
F108: Additional Due | H108: =IF(H106<=H107,0,H106-H107) -> 0 | L108: =SUM(L106:L107) -> 382109.55 | N108: =L108/$H$11 -> 1091.7416 | P108: =L108/$H$12 -> 1.4556554
E110: Total Cost | L110: =L104+L108 -> 1.1795428e+08 | N110: =L110/$H$11 -> 337012.23 | P110: =L110/$H$12 -> 449.34963
B114: PERMANENT LOAN ANALYSIS
...

Sheet Low NOI
A1: ='Low Budget'!A1 -> 301 E. ATLANTIC POMPANO BEACH - BUYER'S PREFERRED
B5: UNIT MIX & MARKET RENT | R5: OPERATING ASSUMPTIONS
K6: Untrended Rent
S7: Annual Rent & Other Income Growth | Y7: ='Middle NOI'!Y7 -> 0.03
F8: Units | G8: % Units | H8: Avg. SF | I8: Total SF | K8: Per Unit | M8: Per SF | O8: Total $ | S8: Loss-to-Lease (% of market rent) | Y8: ='Middle NOI'!Y8 -> 0.01
S9: Stabilized Vacancy (% of market rent) | Y9: ='Middle NOI'!Y9 -> 0.05
E10: Studio | F10: ='Middle NOI'!F10 -> 70 | G10: =F10/$F$14 -> 0.2 | H10: ='Middle NOI'!H10 -> 500 | I10: =F10*H10 -> 35000 | K10: =Summary!G25 -> 2100 | M10: =O10/I10 -> 4.2 | O10: =F10*K10 -> 147000 | S10: Collection Loss (% of GPR) | Y10: ='Middle NOI'!Y10 -> 0.0025
E11: One Bedroom | F11: ='Middle NOI'!F11 -> 140 | G11: =F11/$F$14 -> 0.4 | H11: ='Middle NOI'!H11 -> 675 | I11: =F11*H11 -> 94500 | K11: =Summary!I25 -> 2650 | M11: =O11/I11 -> 3.9259259 | O11: =F11*K11 -> 371000 | S11: Annual Operating Expense Growth | Y11: ='Middle NOI'!Y11 -> 0.025
E12: Two Bedroom | F12: ='Middle NOI'!F12 -> 140 | G12: =F12/$F$14 -> 0.4 | H12: ='Middle NOI'!H12 -> 950 | I12: =F12*H12 -> 133000 | K12: =Summary!K25 -> 3150 | M12: =O12/I12 -> 3.3157895 | O12: =F12*K12 -> 441000 | S12: ='Middle NOI'!S12 -> 0.75 | T12: ='Middle NOI'!T12 -> 0 | U12: ='Middle NOI'!U12 -> 0 | V12: ='Middle NOI'!V12 -> 0 | W12: ='Middle NOI'!W12 -> 0 | Y12: ='Middle NOI'!Y12 -> 0.25
S13: Management Fee (% of total revenue) | Y13: ='Middle NOI'!Y13 -> 0.02
F14: =SUM(F10:F13) -> 350 | G14: =SUM(G10:G13) -> 1 | H14: =I14/F14 -> 750 | I14: =SUM(I10:I13) -> 262500 | K14: =O14/F14 -> 2740 | M14: =O14/I14 -> 3.6533333 | O14: =SUM(O10:O13) -> 959000 | S14: Management Fee Monthly Minimum Until Stabilization | Y14: ='Middle NOI'!Y14 -> 5000
S15: Replacement Reserve Per Unit Annually | Y15: ='Middle NOI'!Y15 -> 200
S19: Year of Operations
B20: PROJECTED OPERATING RESULTS | S20: 1 | U20: 2 | W20: 3 | Y20: 4 | AA20: 5
S21: =LOOKUP('Low ICF'!$C$14,'Low ICF'!$K$3:$EX$3,'Low ICF'!$K$6:$EX$6) -> Lease-Up | U21: =LOOKUP('Low ICF'!$C$14+12,'Low ICF'!$K$3:$EX$3,'Low ICF'!$K$6:$EX$6) -> Stabilized | W21: =LOOKUP('Low ICF'!$C$14+24,'Low ICF'!$K$3:$EX$3,'Low ICF'!$K$6:$EX$6) -> Stabilized | Y21: =LOOKUP('Low ICF'!$C$14+36,'Low ICF'!$K$3:$EX$3,'Low ICF'!$K$6:$EX$6) -> Stabilized | AA21: =LOOKUP('Low ICF'!$C$14+48,'Low ICF'!$K$3:$EX$3,'Low ICF'!$K$6:$EX$6) -> Stabilized
R23: Beginning Avg. Monthly Rent: | S23: =LOOKUP('Low ICF'!$C$14+1,'Low ICF'!$K$3:$EX$3,'Low ICF'!$K$28:$EX$28) -> 2921.2219 | U23: =LOOKUP('Low ICF'!$C$14+1+12,'Low ICF'!$K$3:$EX$3,'Low ICF'!$K$28:$EX$28) -> 3008.8586 | W23: =LOOKUP('Low ICF'!$C$14+1+24,'Low ICF'!$K$3:$EX$3,'Low ICF'!$K$28:$EX$28) -> 3099.1243 | Y23: =LOOKUP('Low ICF'!$C$14+1+36,'Low ICF'!$K$3:$EX$3,'Low ICF'!$K$28:$EX$28) -> 3192.0981 | AA23: =LOOKUP('Low ICF'!$C$14+1+48,'Low ICF'!$K$3:$EX$3,'Low ICF'!$K$28:$EX$28) -> 3287.861
R24: Ending Avg. Monthly Rent: | S24: =LOOKUP('Low ICF'!$C$14+12,'Low ICF'!$K$3:$EX$3,'Low ICF'!$K$28:$EX$28) -> 3001.4562 | U24: =LOOKUP('Low ICF'!$C$14+12+12,'Low ICF'!$K$3:$EX$3,'Low ICF'!$K$28:$EX$28) -> 3091.4999 | W24: =LOOKUP('Low ICF'!$C$14+12+24,'Low ICF'!$K$3:$EX$3,'Low ICF'!$K$28:$EX$28) -> 3184.2448 | Y24: =LOOKUP('Low ICF'!$C$14+12+36,'Low ICF'!$K$3:$EX$3,'Low ICF'!$K$28:$EX$28) -> 3279.7722 | AA24: =LOOKUP('Low ICF'!$C$14+12+48,'Low ICF'!$K$3:$EX$3,'Low ICF'!$K$28:$EX$28) -> 3378.1654
R25: Rent Growth % (begin to begin): | S25: 0 | U25: =(U23-S23)/S23 -> 0.03 | W25: =(W23-U23)/U23 -> 0.03 | Y25: =(Y23-W23)/W23 -> 0.03 | AA25: =(AA23-Y23)/Y23 -> 0.03
R26: Average Vacancy: | S26: =-S37/S33 -> 0.44977804 | U26: =-U37/U33 -> 0.05 | W26: =-W37/W33 -> 0.05 | Y26: =-Y37/Y33 -> 0.05 | AA26: =-AA37/AA33 -> 0.05
R27: NOI as % of Market Rent: | S27: =S62/S33 -> 0.3437779 | U27: =U62/U33 -> 0.64432249 | W27: =W62/W33 -> 0.64595275 | Y27: =Y62/Y33 -> 0.64757123 | AA27: =AA62/AA33 -> 0.6491781
R28: NOI Growth: | S28: 0 | U28: =(U62-S62)/S62 -> 0.93046781 | W28: =(W62-U62)/U62 -> 0.032606093 | Y28: =(Y62-W62)/W62 -> 0.032580737 | AA28: =(AA62-Y62)/Y62 -> 0.032555825
K30: Untrended
C31: Income | K31: Total | M31: Per Unit | O31: % Mkt
E33: Market Rent | K33: =F14*K14*12 -> 11508000 | M33: =K33/$F$14 -> 32880 | O33: =K33/K$33 -> 1 | S33: =SUMIF('Low ICF'!$K$5:$EX$5,S$20,'Low ICF'!$K35:$EX35) -> 12436932 | U33: =SUMIF('Low ICF'!$K$5:$EX$5,U$20,'Low ICF'!$K35:$EX35) -> 12810040 | W33: =SUMIF('Low ICF'!$K$5:$EX$5,W$20,'Low ICF'!$K35:$EX35) -> 13194341 | Y33: =SUMIF('Low ICF'!$K$5:$EX$5,Y$20,'Low ICF'!$K35:$EX35) -> 13590172 | AA33: =SUMIF('Low ICF'!$K$5:$EX$5,AA$20,'Low ICF'!$K35:$EX35) -> 13997877
D34: (a) | E34: Loss-to-Lease | K34: 0 | M34: =K34/$F$14 -> 0 | O34: =K34/K$33 -> 0 | S34: =SUMIF('Low ICF'!$K$5:$EX$5,S$20,'Low ICF'!$K36:$EX36) -> -10505.097 | U34: =SUMIF('Low ICF'!$K$5:$EX$5,U$20,'Low ICF'!$K36:$EX36) -> -128100.4 | W34: =SUMIF('Low ICF'!$K$5:$EX$5,W$20,'Low ICF'!$K36:$EX36) -> -131943.41 | Y34: =SUMIF('Low ICF'!$K$5:$EX$5,Y$20,'Low ICF'!$K36:$EX36) -> -135901.72 | AA34: =SUMIF('Low ICF'!$K$5:$EX$5,AA$20,'Low ICF'!$K36:$EX36) -> -139978.77
E35: Gross Potential Rent | K35: =SUM(K33:K34) -> 11508000 | M35: =K35/$F$14 -> 32880 | O35: =K35/K$33 -> 1 | S35: =SUM(S33:S34) -> 12426427 | U35: =SUM(U33:U34) -> 12681940 | W35: =SUM(W33:W34) -> 13062398 | Y35: =SUM(Y33:Y34) -> 13454270 | AA35: =SUM(AA33:AA34) -> 13857898
E37: Vacancy | K37: =-K33*$Y9 -> -575400 | M37: =K37/$F$14 -> -1644 | O37: =K37/K$33 -> -0.05 | S37: =SUMIF('Low ICF'!$K$5:$EX$5,S$20,'Low ICF'!$K39:$EX39) -> -5593859 | U37: =SUMIF('Low ICF'!$K$5:$EX$5,U$20,'Low ICF'!$K39:$EX39) -> -640502.01 | W37: =SUMIF('Low ICF'!$K$5:$EX$5,W$20,'Low ICF'!$K39:$EX39) -> -659717.07 | Y37: =SUMIF('Low ICF'!$K$5:$EX$5,Y$20,'Low ICF'!$K39:$EX39) -> -679508.58 | AA37: =SUMIF('Low ICF'!$K$5:$EX$5,AA$20,'Low ICF'!$K39:$EX39) -> -699893.84
E38: Collection Loss | K38: =-K35*$Y10 -> -28770 | M38: =K38/$F$14 -> -82.2 | O38: =K38/K$33 -> -0.0025 | S38: =SUMIF('Low ICF'!$K$5:$EX$5,S$20,'Low ICF'!$K40:$EX40) -> -31066.068 | U38: =SUMIF('Low ICF'!$K$5:$EX$5,U$20,'Low ICF'!$K40:$EX40) -> -31704.85 | W38: =SUMIF('Low ICF'!$K$5:$EX$5,W$20,'Low ICF'!$K40:$EX40) -> -32655.995 | Y38: =SUMIF('Low ICF'!$K$5:$EX$5,Y$20,'Low ICF'!$K40:$EX40) -> -33635.675 | AA38: =SUMIF('Low ICF'!$K$5:$EX$5,AA$20,'Low ICF'!$K40:$EX40) -> -34644.745
E39: Net Rental Income | K39: =SUM(K35:K38) -> 10903830 | M39: =K39/$F$14 -> 31153.8 | O39: =K39/K$33 -> 0.9475 | S39: =SUM(S35:S38) -> 6801502 | U39: =SUM(U35:U38) -> 12009733 | W39: =SUM(W35:W38) -> 12370025 | Y39: =SUM(Y35:Y38) -> 12741126 | AA39: =SUM(AA35:AA38) -> 13123359
E40: ='Middle NOI'!E40 -> 0.8 | K40: =E40*K51 -> 280000 | M40: =K40/$F$14 -> 800 | O40: =K40/K$33 -> 0.0243309 | S40: =SUMIF('Low ICF'!$K$5:$EX$5,S$20,'Low ICF'!$K42:$EX42) -> 298757.72 | U40: =SUMIF('Low ICF'!$K$5:$EX$5,U$20,'Low ICF'!$K42:$EX42) -> 306226.66 | W40: =SUMIF('Low ICF'!$K$5:$EX$5,W$20,'Low ICF'!$K42:$EX42) -> 313882.33 | Y40: =SUMIF('Low ICF'!$K$5:$EX$5,Y$20,'Low ICF'!$K42:$EX42) -> 321729.39 | AA40: =SUMIF('Low ICF'!$K$5:$EX$5,AA$20,'Low ICF'!$K42:$EX42) -> 329772.62
E41: Parking & Other Income | K41: ='Low OtherInc'!M21 -> 399945 | M41: =K41/$F$14 -> 1142.7 | O41: =K41/K$33 -> 0.03475365 | S41: =SUMIF('Low ICF'!$K$5:$EX$5,S$20,'Low ICF'!$K43:$EX43) -> 239647.22 | U41: =SUMIF('Low ICF'!$K$5:$EX$5,U$20,'Low ICF'!$K43:$EX43) -> 445195.65 | W41: =SUMIF('Low ICF'!$K$5:$EX$5,W$20,'Low ICF'!$K43:$EX43) -> 458551.52 | Y41: =SUMIF('Low ICF'!$K$5:$EX$5,Y$20,'Low ICF'!$K43:$EX43) -> 472308.06 | AA41: =SUMIF('Low ICF'!$K$5:$EX$5,AA$20,'Low ICF'!$K43:$EX43) -> 486477.31
D42: Total Revenue | K42: =SUM(K39:K41) -> 11583775 | M42: =K42/$F$14 -> 33096.5 | O42: =K42/K$33 -> 1.0065845 | S42: =S39+S41 -> 7041149.3 | U42: =U39+U41 -> 12454929 | W42: =W39+W41 -> 12828576 | Y42: =Y39+Y41 -> 13213434 | AA42: =AA39+AA41 -> 13609837
C44: Operating Expenses
E46: Payroll | K46: ='Low Payroll'!R11 -> 538200 | M46: =K46/$F$14 -> 1537.7143 | O46: =K46/K$33 -> 0.046767466 | S46: =SUMIF('Low ICF'!$K$5:$EX$5,S$20,'Low ICF'!$K48:$EX48) -> 574255.02 | U46: =SUMIF('Low ICF'!$K$5:$EX$5,U$20,'Low ICF'!$K48:$EX48) -> 588611.39 | W46: =SUMIF('Low ICF'!$K$5:$EX$5,W$20,'Low ICF'!$K48:$EX48) -> 603326.68 | Y46: =SUMIF('Low ICF'!$K$5:$EX$5,Y$20,'Low ICF'!$K48:$EX48) -> 618409.84 | AA46: =SUMIF('Low ICF'!$K$5:$EX$5,AA$20,'Low ICF'!$K48:$EX48) -> 633870.09 | AC46: =SUMIF('Low ICF'!$K$5:$EX$5,AC$20,'Low ICF'!$K48:$EX48) -> 0
E47: General & Administrative | K47: =$F$14*M47 -> 87500 | M47: ='Middle NOI'!M47 -> 250 | O47: =K47/K$33 -> 0.0076034063 | S47: =SUMIF('Low ICF'!$K$5:$EX$5,S$20,'Low ICF'!$K49:$EX49) -> 93361.787 | U47: =SUMIF('Low ICF'!$K$5:$EX$5,U$20,'Low ICF'!$K49:$EX49) -> 95695.832 | W47: =SUMIF('Low ICF'!$K$5:$EX$5,W$20,'Low ICF'!$K49:$EX49) -> 98088.228 | Y47: =SUMIF('Low ICF'!$K$5:$EX$5,Y$20,'Low ICF'!$K49:$EX49) -> 100540.43 | AA47: =SUMIF('Low ICF'!$K$5:$EX$5,AA$20,'Low ICF'!$K49:$EX49) -> 103053.94 | AC47: =SUMIF('Low ICF'!$K$5:$EX$5,AC$20,'Low ICF'!$K49:$EX49) -> 0
E48: Repairs & Maintenance | K48: =$F$14*M48 -> 87500 | M48: ='Middle NOI'!M48 -> 250 | O48: =K48/K$33 -> 0.0076034063 | S48: =SUMIF('Low ICF'!$K$5:$EX$5,S$20,'Low ICF'!$K50:$EX50) -> 7868.502 | U48: =SUMIF('Low ICF'!$K$5:$EX$5,U$20,'Low ICF'!$K50:$EX50) -> 95695.832 | W48: =SUMIF('Low ICF'!$K$5:$EX$5,W$20,'Low ICF'!$K50:$EX50) -> 98088.228 | Y48: =SUMIF('Low ICF'!$K$5:$EX$5,Y$20,'Low ICF'!$K50:$EX50) -> 100540.43 | AA48: =SUMIF('Low ICF'!$K$5:$EX$5,AA$20,'Low ICF'!$K50:$EX50) -> 103053.94 | AC48: =SUMIF('Low ICF'!$K$5:$EX$5,AC$20,'Low ICF'!$K50:$EX50) -> 0
E49: Contract Services | K49: =$F$14*M49 -> 175000 | M49: ='Middle NOI'!M49 -> 500 | O49: =K49/K$33 -> 0.015206813 | S49: =SUMIF('Low ICF'!$K$5:$EX$5,S$20,'Low ICF'!$K51:$EX51) -> 186723.57 | U49: =SUMIF('Low ICF'!$K$5:$EX$5,U$20,'Low ICF'!$K51:$EX51) -> 191391.66 | W49: =SUMIF('Low ICF'!$K$5:$EX$5,W$20,'Low ICF'!$K51:$EX51) -> 196176.46 | Y49: =SUMIF('Low ICF'!$K$5:$EX$5,Y$20,'Low ICF'!$K51:$EX51) -> 201080.87 | AA49: =SUMIF('Low ICF'!$K$5:$EX$5,AA$20,'Low ICF'!$K51:$EX51) -> 206107.89 | AC49: =SUMIF('Low ICF'!$K$5:$EX$5,AC$20,'Low ICF'!$K51:$EX51) -> 0
E50: Turnover | K50: =$F$14*M50 -> 87500 | M50: ='Middle NOI'!M50 -> 250 | O50: =K50/K$33 -> 0.0076034063 | S50: =SUMIF('Low ICF'!$K$5:$EX$5,S$20,'Low ICF'!$K52:$EX52) -> 7868.502 | U50: =SUMIF('Low ICF'!$K$5:$EX$5,U$20,'Low ICF'!$K52:$EX52) -> 95695.832 | W50: =SUMIF('Low ICF'!$K$5:$EX$5,W$20,'Low ICF'!$K52:$EX52) -> 98088.228 | Y50: =SUMIF('Low ICF'!$K$5:$EX$5,Y$20,'Low ICF'!$K52:$EX52) -> 100540.43 | AA50: =SUMIF('Low ICF'!$K$5:$EX$5,AA$20,'Low ICF'!$K52:$EX52) -> 103053.94
E51: Utilities | K51: =$F$14*M51 -> 350000 | M51: ='Middle NOI'!M51 -> 1000 | O51: =K51/K$33 -> 0.030413625 | S51: =SUMIF('Low ICF'!$K$5:$EX$5,S$20,'Low ICF'!$K53:$EX53) -> 373447.15 | U51: =SUMIF('Low ICF'!$K$5:$EX$5,U$20,'Low ICF'!$K53:$EX53) -> 382783.33 | W51: =SUMIF('Low ICF'!$K$5:$EX$5,W$20,'Low ICF'!$K53:$EX53) -> 392352.91 | Y51: =SUMIF('Low ICF'!$K$5:$EX$5,Y$20,'Low ICF'!$K53:$EX53) -> 402161.73 | AA51: =SUMIF('Low ICF'!$K$5:$EX$5,AA$20,'Low ICF'!$K53:$EX53) -> 412215.78
E52: Leasing & Marketing | K52: =$F$14*M52 -> 87500 | M52: ='Middle NOI'!M52 -> 250 | O52: =K52/K$33 -> 0.0076034063 | S52: =SUMIF('Low ICF'!$K$5:$EX$5,S$20,'Low ICF'!$K54:$EX54) -> 93361.787 | U52: =SUMIF('Low ICF'!$K$5:$EX$5,U$20,'Low ICF'!$K54:$EX54) -> 95695.832 | W52: =SUMIF('Low ICF'!$K$5:$EX$5,W$20,'Low ICF'!$K54:$EX54) -> 98088.228 | Y52: =SUMIF('Low ICF'!$K$5:$EX$5,Y$20,'Low ICF'!$K54:$EX54) -> 100540.43 | AA52: =SUMIF('Low ICF'!$K$5:$EX$5,AA$20,'Low ICF'!$K54:$EX54) -> 103053.94 | AC52: =SUMIF('Low ICF'!$K$5:$EX$5,AC$20,'Low ICF'!$K54:$EX54) -> 0
E53: Management Fee | K53: =K42*Y13 -> 231675.5 | M53: =K53/$F$14 -> 661.93 | O53: =K53/K$33 -> 0.020131691 | S53: =SUMIF('Low ICF'!$K$5:$EX$5,S$20,'Low ICF'!$K55:$EX55) -> 75931.346 | U53: =SUMIF('Low ICF'!$K$5:$EX$5,U$20,'Low ICF'!$K55:$EX55) -> 255223.11 | W53: =SUMIF('Low ICF'!$K$5:$EX$5,W$20,'Low ICF'!$K55:$EX55) -> 262849.18 | Y53: =SUMIF('Low ICF'!$K$5:$EX$5,Y$20,'Low ICF'!$K55:$EX55) -> 270703.26 | AA53: =SUMIF('Low ICF'!$K$5:$EX$5,AA$20,'Low ICF'!$K55:$EX55) -> 278792.19 | AC53: =SUMIF('Low ICF'!$K$5:$EX$5,AC$20,'Low ICF'!$K55:$EX55) -> 0
E54: Insurance | K54: =$F$14*M54 -> 612500 | M54: ='Middle NOI'!M54 -> 1750 | O54: =K54/K$33 -> 0.053223844 | S54: =SUMIF('Low ICF'!$K$5:$EX$5,S$20,'Low ICF'!$K56:$EX56) -> 653532.51 | U54: =SUMIF('Low ICF'!$K$5:$EX$5,U$20,'Low ICF'!$K56:$EX56) -> 669870.82 | W54: =SUMIF('Low ICF'!$K$5:$EX$5,W$20,'Low ICF'!$K56:$EX56) -> 686617.59 | Y54: =SUMIF('Low ICF'!$K$5:$EX$5,Y$20,'Low ICF'!$K56:$EX56) -> 703783.03 | AA54: =SUMIF('Low ICF'!$K$5:$EX$5,AA$20,'Low ICF'!$K56:$EX56) -> 721377.61 | AC54: =SUMIF('Low ICF'!$K$5:$EX$5,AC$20,'Low ICF'!$K56:$EX56) -> 0
E55: Property Taxes (developer ownership) | K55: ='Low RETax'!G23 -> 1518257.8 | M55: =K55/$F$14 -> 4337.8794 | O55: =K55/K$33 -> 0.13193064 | S55: =SUMIF('Low ICF'!$K$5:$EX$5,S$20,'Low ICF'!$K57:$EX57) -> 693423.31 | U55: =SUMIF('Low ICF'!$K$5:$EX$5,U$20,'Low ICF'!$K57:$EX57) -> 1660467.9 | W55: =SUMIF('Low ICF'!$K$5:$EX$5,W$20,'Low ICF'!$K57:$EX57) -> 1701979.6 | Y55: =SUMIF('Low ICF'!$K$5:$EX$5,Y$20,'Low ICF'!$K57:$EX57) -> 1744529.1 | AA55: =SUMIF('Low ICF'!$K$5:$EX$5,AA$20,'Low ICF'!$K57:$EX57) -> 1788142.3 | AC55: =SUMIF('Low ICF'!$K$5:$EX$5,AC$20,'Low ICF'!$K57:$EX57) -> 0
D56: Total Operating Expenses | K56: =SUM(K46:K55) -> 3775633.3 | M56: =K56/$F$14 -> 10787.524 | O56: =K56/K$33 -> 0.3280877 | S56: =SUM(S46:S55) -> 2759773.5 | U56: =SUM(U46:U55) -> 4131131.5 | W56: =SUM(W46:W55) -> 4235655.3 | Y56: =SUM(Y46:Y55) -> 4342829.6 | AA56: =SUM(AA46:AA55) -> 4452721.7
C58: Net Operating Income Before Reserves | K58: =K42-K56 -> 7808141.7 | M58: =K58/$F$14 -> 22308.976 | O58: =K58/K$33 -> 0.67849685 | S58: =S42-S56 -> 4281375.8 | U58: =U42-U56 -> 8323797.1 | W58: =W42-W56 -> 8592921.1 | Y58: =Y42-Y56 -> 8870604.2 | AA58: =AA42-AA56 -> 9157115.1
E60: Less: Replacement Reserve | K60: =Y15*F14 -> 70000 | M60: =K60/$F$14 -> 200 | O60: =K60/K$33 -> 0.0060827251 | S60: =SUMIF('Low ICF'!$K$5:$EX$5,S$20,'Low ICF'!$K58:$EX58) -> 5833.3333 | U60: =SUMIF('Low ICF'!$K$5:$EX$5,U$20,'Low ICF'!$K58:$EX58) -> 70000 | W60: =SUMIF('Low ICF'!$K$5:$EX$5,W$20,'Low ICF'!$K58:$EX58) -> 70000 | Y60: =SUMIF('Low ICF'!$K$5:$EX$5,Y$20,'Low ICF'!$K58:$EX58) -> 70000 | AA60: =SUMIF('Low ICF'!$K$5:$EX$5,AA$20,'Low ICF'!$K58:$EX58) -> 70000
C62: Net Operating Income | K62: =K58-K60 -> 7738141.7 | M62: =K62/$F$14 -> 22108.976 | O62: =K62/K$33 -> 0.67241412 | S62: =S58-S60 -> 4275542.5 | U62: =U58-U60 -> 8253797.1 | W62: =W58-W60 -> 8522921.1 | Y62: =Y58-Y60 -> 8800604.2 | AA62: =AA58-AA60 -> 9087115.1
C65: (a) | D65: Loss-to-Lease is not applied to stabilized untrended results snapshot above, only to projected results starting at stabilization.

Sheet Low OtherInc
A1: ='Low Budget'!A1 -> 301 E. ATLANTIC POMPANO BEACH - BUYER'S PREFERRED
B4: PARKING & OTHER INCOME
F5: Assumptions | M5: Annual Total
F6: ='Low Budget'!H11 -> 350
D8: Reserved Parking | F8: ='Middle OtherInc'!F8 -> 95 | H8: ='Middle OtherInc'!H8 -> 0.25 | J8: - | M8: =F8*$F$6*H8*12 -> 99750
D9: Vehicle Registration Fee | F9: ='Middle OtherInc'!F9 -> 30 | H9: =$H$10 -> 0.45 | J9: ='Middle OtherInc'!J9 -> 1.5 | M9: =F9*J9*$F$6*H9 -> 7087.5
D10: Application Fees | F10: ='Middle OtherInc'!F10 -> 150 | H10: ='Middle OtherInc'!H10 -> 0.45 | J10: - | M10: =F10*$F$6*H10 -> 23625
D11: Pet Fees | F11: ='Middle OtherInc'!F11 -> 300 | H11: =$H$10 -> 0.45 | J11: ='Middle OtherInc'!J11 -> 0.25 | M11: =F11*$F$6*H11*J11 -> 11812.5
D12: Pet Rent | F12: ='Middle OtherInc'!F12 -> 25 | H12: ='Middle OtherInc'!H12 -> 0.25 | J12: - | M12: =F12*$F$6*H12*12 -> 26250
D13: Trash Collection | F13: ='Middle OtherInc'!F13 -> 20 | H13: ='Middle OtherInc'!H13 -> 1 | J13: =1-'Low NOI'!$Y$9 -> 0.95 | M13: =F13*$F$6*H13*J13*12 -> 79800
D14: Pest Control | F14: ='Middle OtherInc'!F14 -> 5 | H14: ='Middle OtherInc'!H14 -> 1 | J14: =1-'Low NOI'!$Y$9 -> 0.95 | M14: =F14*$F$6*H14*J14*12 -> 19950
D15: Late Fees & NSF Fees | F15: ='Middle OtherInc'!F15 -> 125 | H15: ='Middle OtherInc'!H15 -> 5 | J15: - | M15: =F15*H15*12 -> 7500
D16: Lease Termination Fees | F16: ='Low NOI'!K14 -> 2740 | H16: ='Middle OtherInc'!H16 -> 3 | J16: - | M16: =F16*H16 -> 8220
D17: Cleaning & Damage Charges | F17: ='Middle OtherInc'!F17 -> 500 | H17: ='Middle OtherInc'!H17 -> 2 | J17: - | M17: =F17*H17*12 -> 12000
D18: Cable Revenue Share | F18: ='Middle OtherInc'!F18 -> 25 | H18: ='Middle OtherInc'!H18 -> 1 | J18: =1-'Low NOI'!$Y$9 -> 0.95 | M18: =F18*$F$6*H18*J18*12 -> 99750
D19: Keys & FOBs Replacement | F19: ='Middle OtherInc'!F19 -> 50 | H19: ='Middle OtherInc'!H19 -> 2 | J19: - | M19: =F19*H19*12 -> 1200
D20: Clubhouse Rental | F20: ='Middle OtherInc'!F20 -> 250 | H20: ='Middle OtherInc'!H20 -> 1 | J20: - | M20: =F20*H20*12 -> 3000
M21: =SUM(M8:M20) -> 399945
M23: =M21/$F$6/12 -> 95.225

Sheet Low Payroll
A1: ='Low Budget'!A1 -> 301 E. ATLANTIC POMPANO BEACH - BUYER'S PREFERRED
B3: PRO FORMA PAYROLL
L4: Burden & OT | N4: Total Expense
F5: Annual Salary | H5: Bonus | J5: Total Comp. | L5: ='Middle Payroll'!L5 -> 0.3 | N5: Per FTE | P5: Full Time Equiv. | R5: Total Expense
D6: Property Manager | F6: ='Middle Payroll'!F6 -> 75000 | H6: ='Middle Payroll'!H6 -> 7500 | J6: =F6+H6 -> 82500 | L6: =J6*$L$5 -> 24750 | N6: =J6+L6 -> 107250 | P6: ='Middle Payroll'!P6 -> 1 | R6: =N6*P6 -> 107250
D7: Assistant Manager | F7: ='Middle Payroll'!F7 -> 60000 | H7: ='Middle Payroll'!H7 -> 0 | J7: =F7+H7 -> 60000 | L7: =J7*$L$5 -> 18000 | N7: =J7+L7 -> 78000 | P7: ='Middle Payroll'!P7 -> 1 | R7: =N7*P7 -> 78000
D8: Leasing Consultant | F8: ='Middle Payroll'!F8 -> 45000 | H8: ='Middle Payroll'!H8 -> 0 | J8: =F8+H8 -> 45000 | L8: =J8*$L$5 -> 13500 | N8: =J8+L8 -> 58500 | P8: ='Middle Payroll'!P8 -> 2 | R8: =N8*P8 -> 117000
D9: Supervisor | F9: ='Middle Payroll'!F9 -> 65000 | H9: ='Middle Payroll'!H9 -> 6500 | J9: =F9+H9 -> 71500 | L9: =J9*$L$5 -> 21450 | N9: =J9+L9 -> 92950 | P9: ='Middle Payroll'!P9 -> 1 | R9: =N9*P9 -> 92950
D10: Technician | F10: ='Middle Payroll'!F10 -> 55000 | H10: ='Middle Payroll'!H10 -> 0 | J10: =F10+H10 -> 55000 | L10: =J10*$L$5 -> 16500 | N10: =J10+L10 -> 71500 | P10: ='Middle Payroll'!P10 -> 2 | R10: =N10*P10 -> 143000
P11: =SUM(P6:P10) -> 7 | R11: =SUM(R6:R10) -> 538200
P13: =P11/('Low Budget'!H11/50) -> 1 | R13: =R11/'Low Budget'!H11 -> 1537.7143

Sheet Low RETax
A1: ='Low Budget'!A1 -> 301 E. ATLANTIC POMPANO BEACH - BUYER'S PREFERRED
B5: PROPERTY TAX ESTIMATE AT COMPLETION UNDER DEVELOPER OWNERSHIP
E7: ='Low Budget'!H24+1 -> 26 | G7: =LOOKUP(E7,'Low ICF'!K3:EX3,'Low ICF'!K35:EX35)*12 -> 12269132
E8: ='Middle RETax'!E8 -> 0.1 | G8: =-E8*G7 -> -1226913.2
G9: =SUM(G7:G8) -> 11042219
E10: ='Middle RETax'!E10 -> 0.4 | G10: =-E10*G9 -> -4416887.5
G11: =SUM(G9:G10) -> 6625331.3
D13: (a) | E13: County Appraiser Market Cap Rate | G13: ='Middle RETax'!G13 -> 0.0525
E14: Tax Rate | G14: ='Low Budget'!R12 -> 0.0205011
E15: County Appraiser Cap Rate | G15: =SUM(G13:G14) -> 0.0730011
E17: County Appraiser Gross Assessed Value | G17: =G11/G15 -> 90756595
E18: ='Middle RETax'!E18 -> 0.15 | G18: =-$E$18*G17 -> -13613489
E19: Net Assessed Value | G19: =SUM(G17:G18) -> 77143106
E20: Tax Rate | G20: =G14 -> 0.0205011
E21: Tax Expense Before Early Payment Discount | G21: =G19*G20 -> 1581518.5
E22: ='Middle RETax'!E22 -> 0.04 | G22: =-$E$22*G21 -> -63260.741
G23: =SUM(G21:G22) -> 1518257.8
F25: =G23/'Low Budget'!$H$11 -> 4337.8794
D27: (a) | E27: County appraiser typically uses a cap rate above actual market cap rates for property tax assessment purposes.
B31: PROPERTY TAX ESTIMATE AT COMPLETION UNDER DEVELOPER OWNERSHIP - PERCENT OF COST
E33: Hard Costs | G33: ='Low Budget'!L74 -> 82687500
E34: Reassessment as % of Total Cost | G34: ='Middle RETax'!G34 -> 0.9
G35: =G33*G34 -> 74418750
E36: Tax Rate | G36: =G14 -> 0.0205011
G37: =G35*G36 -> 1525666.2
E38: =$E$22 -> 0.04 | G38: =G37*-E38 -> -61026.649
G39: =SUM(G37:G38) -> 1464639.6
F41: =G39/'Low Budget'!$H$11 -> 4184.6845

Sheet Low ICF
A1: ='Low Budget'!A1 -> 301 E. ATLANTIC POMPANO BEACH - BUYER'S PREFERRED
I3: Investment Period | J3: Closing | K3: 1 | L3: =K3+1 -> 2 | M3: =L3+1 -> 3 | N3: =M3+1 -> 4 | O3: =N3+1 -> 5 | P3: =O3+1 -> 6 | Q3: =P3+1 -> 7 | R3: =Q3+1 -> 8 | S3: =R3+1 -> 9 | ... EX3: =EW3+1 -> 144
I4: Date | J4: ='Middle ICF'!J4 -> 46388 | K4: =EDATE(J4,1) -> 46419 | L4: =EDATE(K4,1) -> 46447 | M4: =EDATE(L4,1) -> 46478 | N4: =EDATE(M4,1) -> 46508 | O4: =EDATE(N4,1) -> 46539 | P4: =EDATE(O4,1) -> 46569 | Q4: =EDATE(P4,1) -> 46600 | R4: =EDATE(Q4,1) -> 46631 | ... EX4: =EDATE(EW4,1) -> 50771
I5: Year of Operations | K5: =IF(K3>=$C$14,ROUNDUP((K3-$C$14)/12,0),0) -> 0 | L5: =IF(L3>=$C$14,ROUNDUP((L3-$C$14)/12,0),0) -> 0 | M5: =IF(M3>=$C$14,ROUNDUP((M3-$C$14)/12,0),0) -> 0 | N5: =IF(N3>=$C$14,ROUNDUP((N3-$C$14)/12,0),0) -> 0 | O5: =IF(O3>=$C$14,ROUNDUP((O3-$C$14)/12,0),0) -> 0 | P5: =IF(P3>=$C$14,ROUNDUP((P3-$C$14)/12,0),0) -> 0 | Q5: =IF(Q3>=$C$14,ROUNDUP((Q3-$C$14)/12,0),0) -> 0 | R5: =IF(R3>=$C$14,ROUNDUP((R3-$C$14)/12,0),0) -> 0 | ... EX5: =IF(EX3>=$C$14,ROUNDUP((EX3-$C$14)/12,0),0) -> 10
I6: Status | K6: =IF(K3<$C$14,"Dev.",IF(AND(K3>=$C$14,K3<$C$16),"Lease-Up","Stabilized")) -> Dev. | L6: =IF(L3<$C$14,"Dev.",IF(AND(L3>=$C$14,L3<$C$16),"Lease-Up","Stabilized")) -> Dev. | M6: =IF(M3<$C$14,"Dev.",IF(AND(M3>=$C$14,M3<$C$16),"Lease-Up","Stabilized")) -> Dev. | N6: =IF(N3<$C$14,"Dev.",IF(AND(N3>=$C$14,N3<$C$16),"Lease-Up","Stabilized")) -> Dev. | O6: =IF(O3<$C$14,"Dev.",IF(AND(O3>=$C$14,O3<$C$16),"Lease-Up","Stabilized")) -> Dev. | P6: =IF(P3<$C$14,"Dev.",IF(AND(P3>=$C$14,P3<$C$16),"Lease-Up","Stabilized")) -> Dev. | Q6: =IF(Q3<$C$14,"Dev.",IF(AND(Q3>=$C$14,Q3<$C$16),"Lease-Up","Stabilized")) -> Dev. | R6: =IF(R3<$C$14,"Dev.",IF(AND(R3>=$C$14,R3<$C$16),"Lease-Up","Stabilized")) -> Dev. | ... EX6: =IF(EX3<$C$14,"Dev.",IF(AND(EX3>=$C$14,EX3<$C$16),"Lease-Up","Stabilized")) -> Stabilized
B8: Unit Count & Timing Summary (from Ops & SU tabs)
C9: ='Low NOI'!F14 -> 350
C10: ='Low Budget'!H20 -> 1
C11: ='Low Budget'!H21 -> 24
C12: ='Low Budget'!H22 -> 1
C13: ='Low Budget'!H23 -> 26
C14: ='Low Budget'!H24 -> 25
C15: ='Low Budget'!H25 -> 25.576923
C16: ='Low Budget'!H26 -> 37
C17: ='Low Budget'!H27 -> 40
B19: UNIT OCCUPANCY & AVERAGE MONTHLY BASE RENT
C21: Occupied Units - Beginning | K21: 0 | L21: =K23 -> 0 | M21: =L23 -> 0 | N21: =M23 -> 0 | O21: =N23 -> 0 | P21: =O23 -> 0 | Q21: =P23 -> 0 | R21: =Q23 -> 0 | S21: =R23 -> 0 | ... EX21: =EW23 -> 332.5
C22: Move-ins | I22: =SUM(K22:EX22) -> 332.5 | K22: =IF(AND(K3>=$C$14,K3<=$C$16),$C$15,0) -> 0 | L22: =IF(AND(L3>=$C$14,L3<=$C$16),$C$15,0) -> 0 | M22: =IF(AND(M3>=$C$14,M3<=$C$16),$C$15,0) -> 0 | N22: =IF(AND(N3>=$C$14,N3<=$C$16),$C$15,0) -> 0 | O22: =IF(AND(O3>=$C$14,O3<=$C$16),$C$15,0) -> 0 | P22: =IF(AND(P3>=$C$14,P3<=$C$16),$C$15,0) -> 0 | Q22: =IF(AND(Q3>=$C$14,Q3<=$C$16),$C$15,0) -> 0 | R22: =IF(AND(R3>=$C$14,R3<=$C$16),$C$15,0) -> 0 | ... EX22: =IF(AND(EX3>=$C$14,EX3<=$C$16),$C$15,0) -> 0
C23: Occupied Units - Ending | I23: =I22/C9 -> 0.95 | K23: =SUM(K21:K22) -> 0 | L23: =SUM(L21:L22) -> 0 | M23: =SUM(M21:M22) -> 0 | N23: =SUM(N21:N22) -> 0 | O23: =SUM(O21:O22) -> 0 | P23: =SUM(P21:P22) -> 0 | Q23: =SUM(Q21:Q22) -> 0 | R23: =SUM(R21:R22) -> 0 | ... EX23: =SUM(EX21:EX22) -> 332.5
C24: Vacant Units | K24: =$C$9-K23 -> 350 | L24: =$C$9-L23 -> 350 | M24: =$C$9-M23 -> 350 | N24: =$C$9-N23 -> 350 | O24: =$C$9-O23 -> 350 | P24: =$C$9-P23 -> 350 | Q24: =$C$9-Q23 -> 350 | R24: =$C$9-R23 -> 350 | ... EX24: =$C$9-EX23 -> 17.5
C25: Total | K25: =SUM(K23:K24) -> 350 | L25: =SUM(L23:L24) -> 350 | M25: =SUM(M23:M24) -> 350 | N25: =SUM(N23:N24) -> 350 | O25: =SUM(O23:O24) -> 350 | P25: =SUM(P23:P24) -> 350 | Q25: =SUM(Q23:Q24) -> 350 | R25: =SUM(R23:R24) -> 350 | ... EX25: =SUM(EX23:EX24) -> 350
J27: Occupancy: | K27: =K23/$C$9 -> 0 | L27: =L23/$C$9 -> 0 | M27: =M23/$C$9 -> 0 | N27: =N23/$C$9 -> 0 | O27: =O23/$C$9 -> 0 | P27: =P23/$C$9 -> 0 | Q27: =Q23/$C$9 -> 0 | R27: =R23/$C$9 -> 0 | ... EX27: =EX23/$C$9 -> 0.95
J28: Avg. Base Rent: | K28: =IF(K27>0,K35/$C$9,0) -> 0 | L28: =IF(L27>0,L35/$C$9,0) -> 0 | M28: =IF(M27>0,M35/$C$9,0) -> 0 | N28: =IF(N27>0,N35/$C$9,0) -> 0 | O28: =IF(O27>0,O35/$C$9,0) -> 0 | P28: =IF(P27>0,P35/$C$9,0) -> 0 | Q28: =IF(Q27>0,Q35/$C$9,0) -> 0 | R28: =IF(R27>0,R35/$C$9,0) -> 0 | ... EX28: =IF(EX27>0,EX35/$C$9,0) -> 3906.5848
B30: OPERATING INCOME
F32: From Ops Tab
B33: Income | G33: Stabilized
F34: Untrended | G34: Assumptions
C35: Market Rent | F35: ='Low NOI'!K33 -> 11508000 | G35: ='Low NOI'!$Y$7 -> 0.03 | K35: =IF(K$5>0,($F35/12)*(1+((1+$G35)^(1/12))-1)^K$3,0) -> 0 | L35: =IF(L$5>0,($F35/12)*(1+((1+$G35)^(1/12))-1)^L$3,0) -> 0 | M35: =IF(M$5>0,($F35/12)*(1+((1+$G35)^(1/12))-1)^M$3,0) -> 0 | N35: =IF(N$5>0,($F35/12)*(1+((1+$G35)^(1/12))-1)^N$3,0) -> 0 | O35: =IF(O$5>0,($F35/12)*(1+((1+$G35)^(1/12))-1)^O$3,0) -> 0 | P35: =IF(P$5>0,($F35/12)*(1+((1+$G35)^(1/12))-1)^P$3,0) -> 0 | Q35: =IF(Q$5>0,($F35/12)*(1+((1+$G35)^(1/12))-1)^Q$3,0) -> 0 | R35: =IF(R$5>0,($F35/12)*(1+((1+$G35)^(1/12))-1)^R$3,0) -> 0 | ... EX35: =IF(EX$5>0,($F35/12)*(1+((1+$G35)^(1/12))-1)^EX$3,0) -> 1367304.7
C36: Loss to Lease (starts at stabilization) | F36: ='Low NOI'!K34 -> 0 | G36: ='Low NOI'!Y8 -> 0.01 | K36: =IF(K$35=0,0,IF(K$27<(1-$G$39),0,K$35*-$G36)) -> 0 | L36: =IF(L$35=0,0,IF(L$27<(1-$G$39),0,L$35*-$G36)) -> 0 | M36: =IF(M$35=0,0,IF(M$27<(1-$G$39),0,M$35*-$G36)) -> 0 | N36: =IF(N$35=0,0,IF(N$27<(1-$G$39),0,N$35*-$G36)) -> 0 | O36: =IF(O$35=0,0,IF(O$27<(1-$G$39),0,O$35*-$G36)) -> 0 | P36: =IF(P$35=0,0,IF(P$27<(1-$G$39),0,P$35*-$G36)) -> 0 | Q36: =IF(Q$35=0,0,IF(Q$27<(1-$G$39),0,Q$35*-$G36)) -> 0 | R36: =IF(R$35=0,0,IF(R$27<(1-$G$39),0,R$35*-$G36)) -> 0 | ... EX36: =IF(EX$35=0,0,IF(EX$27<(1-$G$39),0,EX$35*-$G36)) -> -13673.047
C37: Gross Potential Rent | F37: =SUM(F35:F36) -> 11508000 | K37: =SUM(K35:K36) -> 0 | L37: =SUM(L35:L36) -> 0 | M37: =SUM(M35:M36) -> 0 | N37: =SUM(N35:N36) -> 0 | O37: =SUM(O35:O36) -> 0 | P37: =SUM(P35:P36) -> 0 | Q37: =SUM(Q35:Q36) -> 0 | R37: =SUM(R35:R36) -> 0 | ... EX37: =SUM(EX35:EX36) -> 1353631.6
C39: Vacancy | F39: ='Low NOI'!K37 -> -575400 | G39: ='Low NOI'!Y9 -> 0.05 | K39: =IF(K$35=0,0,-K$35*(1-K$27)) -> 0 | L39: =IF(L$35=0,0,-L$35*(1-L$27)) -> 0 | M39: =IF(M$35=0,0,-M$35*(1-M$27)) -> 0 | N39: =IF(N$35=0,0,-N$35*(1-N$27)) -> 0 | O39: =IF(O$35=0,0,-O$35*(1-O$27)) -> 0 | P39: =IF(P$35=0,0,-P$35*(1-P$27)) -> 0 | Q39: =IF(Q$35=0,0,-Q$35*(1-Q$27)) -> 0 | R39: =IF(R$35=0,0,-R$35*(1-R$27)) -> 0 | ... EX39: =IF(EX$35=0,0,-EX$35*(1-EX$27)) -> -68365.235
C40: Collection Loss | F40: ='Low NOI'!K38 -> -28770 | G40: ='Low NOI'!Y10 -> 0.0025 | K40: =IF(K$37=0,0,-K$37*$G40) -> 0 | L40: =IF(L$37=0,0,-L$37*$G40) -> 0 | M40: =IF(M$37=0,0,-M$37*$G40) -> 0 | N40: =IF(N$37=0,0,-N$37*$G40) -> 0 | O40: =IF(O$37=0,0,-O$37*$G40) -> 0 | P40: =IF(P$37=0,0,-P$37*$G40) -> 0 | Q40: =IF(Q$37=0,0,-Q$37*$G40) -> 0 | R40: =IF(R$37=0,0,-R$37*$G40) -> 0 | ... EX40: =IF(EX$37=0,0,-EX$37*$G40) -> -3384.0791
C41: Net Rental Income | F41: =F37+F39+F40 -> 10903830 | K41: =K37+K39+K40 -> 0 | L41: =L37+L39+L40 -> 0 | M41: =M37+M39+M40 -> 0 | N41: =N37+N39+N40 -> 0 | O41: =O37+O39+O40 -> 0 | P41: =P37+P39+P40 -> 0 | Q41: =Q37+Q39+Q40 -> 0 | R41: =R37+R39+R40 -> 0 | ... EX41: =EX37+EX39+EX40 -> 1281882.3
C42: RUBS Income | F42: ='Low NOI'!K40 -> 280000 | G42: ='Low NOI'!E40 -> 0.8 | H42: Variable % utilities expense | K42: =$G$42*K53 -> 0 | L42: =$G$42*L53 -> 0 | M42: =$G$42*M53 -> 0 | N42: =$G$42*N53 -> 0 | O42: =$G$42*O53 -> 0 | P42: =$G$42*P53 -> 0 | Q42: =$G$42*Q53 -> 0 | R42: =$G$42*R53 -> 0 | ... EX42: =$G$42*EX53 -> 31380.739
C43: Other Income | F43: ='Low NOI'!K41 -> 399945 | G43: ='Low NOI'!$Y$7 -> 0.03 | H43: Variable occupancy | K43: =IF(K27<(1-$G$39),(($F43/12)*(1+((1+$G43)^(1/12))-1)^K$3)*K27,($F43/12)*(1+((1+$G43)^(1/12))-1)^K$3) -> 0 | L43: =IF(L27<(1-$G$39),(($F43/12)*(1+((1+$G43)^(1/12))-1)^L$3)*L27,($F43/12)*(1+((1+$G43)^(1/12))-1)^L$3) -> 0 | M43: =IF(M27<(1-$G$39),(($F43/12)*(1+((1+$G43)^(1/12))-1)^M$3)*M27,($F43/12)*(1+((1+$G43)^(1/12))-1)^M$3) -> 0 | N43: =IF(N27<(1-$G$39),(($F43/12)*(1+((1+$G43)^(1/12))-1)^N$3)*N27,($F43/12)*(1+((1+$G43)^(1/12))-1)^N$3) -> 0 | O43: =IF(O27<(1-$G$39),(($F43/12)*(1+((1+$G43)^(1/12))-1)^O$3)*O27,($F43/12)*(1+((1+$G43)^(1/12))-1)^O$3) -> 0 | P43: =IF(P27<(1-$G$39),(($F43/12)*(1+((1+$G43)^(1/12))-1)^P$3)*P27,($F43/12)*(1+((1+$G43)^(1/12))-1)^P$3) -> 0 | Q43: =IF(Q27<(1-$G$39),(($F43/12)*(1+((1+$G43)^(1/12))-1)^Q$3)*Q27,($F43/12)*(1+((1+$G43)^(1/12))-1)^Q$3) -> 0 | R43: =IF(R27<(1-$G$39),(($F43/12)*(1+((1+$G43)^(1/12))-1)^R$3)*R27,($F43/12)*(1+((1+$G43)^(1/12))-1)^R$3) -> 0 | ... EX43: =IF(EX27<(1-$G$39),(($F43/12)*(1+((1+$G43)^(1/12))-1)^EX$3)*EX27,($F43/12)*(1+((1+$G43)^(1/12))-1)^EX$3) -> 47518.828
C44: Total Revenue | F44: =SUM(F41:F43) -> 11583775 | K44: =SUM(K41:K43) -> 0 | L44: =SUM(L41:L43) -> 0 | M44: =SUM(M41:M43) -> 0 | N44: =SUM(N41:N43) -> 0 | O44: =SUM(O41:O43) -> 0 | P44: =SUM(P41:P43) -> 0 | Q44: =SUM(Q41:Q43) -> 0 | R44: =SUM(R41:R43) -> 0 | ... EX44: =SUM(EX41:EX43) -> 1360781.9
B46: Operating Expenses
C48: Payroll | F48: ='Low NOI'!K46 -> 538200 | G48: ='Low NOI'!$Y$11 -> 0.025 | H48: Fixed | K48: =IF(K$5>0,($F48/12)*(1+((1+$G48)^(1/12))-1)^K$3,0) -> 0 | L48: =IF(L$5>0,($F48/12)*(1+((1+$G48)^(1/12))-1)^L$3,0) -> 0 | M48: =IF(M$5>0,($F48/12)*(1+((1+$G48)^(1/12))-1)^M$3,0) -> 0 | N48: =IF(N$5>0,($F48/12)*(1+((1+$G48)^(1/12))-1)^N$3,0) -> 0 | O48: =IF(O$5>0,($F48/12)*(1+((1+$G48)^(1/12))-1)^O$3,0) -> 0 | P48: =IF(P$5>0,($F48/12)*(1+((1+$G48)^(1/12))-1)^P$3,0) -> 0 | Q48: =IF(Q$5>0,($F48/12)*(1+((1+$G48)^(1/12))-1)^Q$3,0) -> 0 | R48: =IF(R$5>0,($F48/12)*(1+((1+$G48)^(1/12))-1)^R$3,0) -> 0 | ... EX48: =IF(EX$5>0,($F48/12)*(1+((1+$G48)^(1/12))-1)^EX$3,0) -> 60318.264
C49: General & Administrative | F49: ='Low NOI'!K47 -> 87500 | G49: ='Low NOI'!$Y$11 -> 0.025 | H49: Fixed | K49: =IF(K$5>0,($F49/12)*(1+((1+$G49)^(1/12))-1)^K$3,0) -> 0 | L49: =IF(L$5>0,($F49/12)*(1+((1+$G49)^(1/12))-1)^L$3,0) -> 0 | M49: =IF(M$5>0,($F49/12)*(1+((1+$G49)^(1/12))-1)^M$3,0) -> 0 | N49: =IF(N$5>0,($F49/12)*(1+((1+$G49)^(1/12))-1)^N$3,0) -> 0 | O49: =IF(O$5>0,($F49/12)*(1+((1+$G49)^(1/12))-1)^O$3,0) -> 0 | P49: =IF(P$5>0,($F49/12)*(1+((1+$G49)^(1/12))-1)^P$3,0) -> 0 | Q49: =IF(Q$5>0,($F49/12)*(1+((1+$G49)^(1/12))-1)^Q$3,0) -> 0 | R49: =IF(R$5>0,($F49/12)*(1+((1+$G49)^(1/12))-1)^R$3,0) -> 0 | ... EX49: =IF(EX$5>0,($F49/12)*(1+((1+$G49)^(1/12))-1)^EX$3,0) -> 9806.481
C50: Repairs & Maintenance | F50: ='Low NOI'!K48 -> 87500 | G50: ='Low NOI'!$Y$11 -> 0.025 | H50: Fixed post-stabilization | K50: =IF(K$27<(1-$G$39),0,($F50/12)*(1+((1+$G50)^(1/12))-1)^K$3) -> 0 | L50: =IF(L$27<(1-$G$39),0,($F50/12)*(1+((1+$G50)^(1/12))-1)^L$3) -> 0 | M50: =IF(M$27<(1-$G$39),0,($F50/12)*(1+((1+$G50)^(1/12))-1)^M$3) -> 0 | N50: =IF(N$27<(1-$G$39),0,($F50/12)*(1+((1+$G50)^(1/12))-1)^N$3) -> 0 | O50: =IF(O$27<(1-$G$39),0,($F50/12)*(1+((1+$G50)^(1/12))-1)^O$3) -> 0 | P50: =IF(P$27<(1-$G$39),0,($F50/12)*(1+((1+$G50)^(1/12))-1)^P$3) -> 0 | Q50: =IF(Q$27<(1-$G$39),0,($F50/12)*(1+((1+$G50)^(1/12))-1)^Q$3) -> 0 | R50: =IF(R$27<(1-$G$39),0,($F50/12)*(1+((1+$G50)^(1/12))-1)^R$3) -> 0 | ... EX50: =IF(EX$27<(1-$G$39),0,($F50/12)*(1+((1+$G50)^(1/12))-1)^EX$3) -> 9806.481
C51: Contract Services | F51: ='Low NOI'!K49 -> 175000 | G51: ='Low NOI'!$Y$11 -> 0.025 | H51: Fixed | K51: =IF(K$5>0,($F51/12)*(1+((1+$G51)^(1/12))-1)^K$3,0) -> 0 | L51: =IF(L$5>0,($F51/12)*(1+((1+$G51)^(1/12))-1)^L$3,0) -> 0 | M51: =IF(M$5>0,($F51/12)*(1+((1+$G51)^(1/12))-1)^M$3,0) -> 0 | N51: =IF(N$5>0,($F51/12)*(1+((1+$G51)^(1/12))-1)^N$3,0) -> 0 | O51: =IF(O$5>0,($F51/12)*(1+((1+$G51)^(1/12))-1)^O$3,0) -> 0 | P51: =IF(P$5>0,($F51/12)*(1+((1+$G51)^(1/12))-1)^P$3,0) -> 0 | Q51: =IF(Q$5>0,($F51/12)*(1+((1+$G51)^(1/12))-1)^Q$3,0) -> 0 | R51: =IF(R$5>0,($F51/12)*(1+((1+$G51)^(1/12))-1)^R$3,0) -> 0 | ... EX51: =IF(EX$5>0,($F51/12)*(1+((1+$G51)^(1/12))-1)^EX$3,0) -> 19612.962
C52: Turnover | F52: ='Low NOI'!K50 -> 87500 | G52: ='Low NOI'!$Y$11 -> 0.025 | H52: Fixed post-stabilization | K52: =IF(K$27<(1-$G$39),0,($F52/12)*(1+((1+$G52)^(1/12))-1)^K$3) -> 0 | L52: =IF(L$27<(1-$G$39),0,($F52/12)*(1+((1+$G52)^(1/12))-1)^L$3) -> 0 | M52: =IF(M$27<(1-$G$39),0,($F52/12)*(1+((1+$G52)^(1/12))-1)^M$3) -> 0 | N52: =IF(N$27<(1-$G$39),0,($F52/12)*(1+((1+$G52)^(1/12))-1)^N$3) -> 0 | O52: =IF(O$27<(1-$G$39),0,($F52/12)*(1+((1+$G52)^(1/12))-1)^O$3) -> 0 | P52: =IF(P$27<(1-$G$39),0,($F52/12)*(1+((1+$G52)^(1/12))-1)^P$3) -> 0 | Q52: =IF(Q$27<(1-$G$39),0,($F52/12)*(1+((1+$G52)^(1/12))-1)^Q$3) -> 0 | R52: =IF(R$27<(1-$G$39),0,($F52/12)*(1+((1+$G52)^(1/12))-1)^R$3) -> 0 | ... EX52: =IF(EX$27<(1-$G$39),0,($F52/12)*(1+((1+$G52)^(1/12))-1)^EX$3) -> 9806.481
C53: Utilities | F53: ='Low NOI'!K51 -> 350000 | G53: ='Low NOI'!$Y$11 -> 0.025 | H53: Fixed | K53: =IF(K$5>0,($F53/12)*(1+((1+$G53)^(1/12))-1)^K$3,0) -> 0 | L53: =IF(L$5>0,($F53/12)*(1+((1+$G53)^(1/12))-1)^L$3,0) -> 0 | M53: =IF(M$5>0,($F53/12)*(1+((1+$G53)^(1/12))-1)^M$3,0) -> 0 | N53: =IF(N$5>0,($F53/12)*(1+((1+$G53)^(1/12))-1)^N$3,0) -> 0 | O53: =IF(O$5>0,($F53/12)*(1+((1+$G53)^(1/12))-1)^O$3,0) -> 0 | P53: =IF(P$5>0,($F53/12)*(1+((1+$G53)^(1/12))-1)^P$3,0) -> 0 | Q53: =IF(Q$5>0,($F53/12)*(1+((1+$G53)^(1/12))-1)^Q$3,0) -> 0 | R53: =IF(R$5>0,($F53/12)*(1+((1+$G53)^(1/12))-1)^R$3,0) -> 0 | ... EX53: =IF(EX$5>0,($F53/12)*(1+((1+$G53)^(1/12))-1)^EX$3,0) -> 39225.924
C54: Leasing & Marketing | F54: ='Low NOI'!K52 -> 87500 | G54: ='Low NOI'!$Y$11 -> 0.025 | H54: Fixed | K54: =IF(K$5>0,($F54/12)*(1+((1+$G54)^(1/12))-1)^K$3,0) -> 0 | L54: =IF(L$5>0,($F54/12)*(1+((1+$G54)^(1/12))-1)^L$3,0) -> 0 | M54: =IF(M$5>0,($F54/12)*(1+((1+$G54)^(1/12))-1)^M$3,0) -> 0 | N54: =IF(N$5>0,($F54/12)*(1+((1+$G54)^(1/12))-1)^N$3,0) -> 0 | O54: =IF(O$5>0,($F54/12)*(1+((1+$G54)^(1/12))-1)^O$3,0) -> 0 | P54: =IF(P$5>0,($F54/12)*(1+((1+$G54)^(1/12))-1)^P$3,0) -> 0 | Q54: =IF(Q$5>0,($F54/12)*(1+((1+$G54)^(1/12))-1)^Q$3,0) -> 0 | R54: =IF(R$5>0,($F54/12)*(1+((1+$G54)^(1/12))-1)^R$3,0) -> 0 | ... EX54: =IF(EX$5>0,($F54/12)*(1+((1+$G54)^(1/12))-1)^EX$3,0) -> 9806.481
C55: ='Low NOI'!Y14 -> 5000 | F55: ='Low NOI'!K53 -> 231675.5 | G55: ='Low NOI'!$Y$13 -> 0.02 | H55: Min. lease-up, then variable | K55: =IF(K$5>0,IF(K$27<(1-$G$39),$C$55,$G$55*K$44),0) -> 0 | L55: =IF(L$5>0,IF(L$27<(1-$G$39),$C$55,$G$55*L$44),0) -> 0 | M55: =IF(M$5>0,IF(M$27<(1-$G$39),$C$55,$G$55*M$44),0) -> 0 | N55: =IF(N$5>0,IF(N$27<(1-$G$39),$C$55,$G$55*N$44),0) -> 0 | O55: =IF(O$5>0,IF(O$27<(1-$G$39),$C$55,$G$55*O$44),0) -> 0 | P55: =IF(P$5>0,IF(P$27<(1-$G$39),$C$55,$G$55*P$44),0) -> 0 | Q55: =IF(Q$5>0,IF(Q$27<(1-$G$39),$C$55,$G$55*Q$44),0) -> 0 | R55: =IF(R$5>0,IF(R$27<(1-$G$39),$C$55,$G$55*R$44),0) -> 0 | ... EX55: =IF(EX$5>0,IF(EX$27<(1-$G$39),$C$55,$G$55*EX$44),0) -> 27215.638
C56: Insurance | D56: Property Tax in Lease-Up | F56: ='Low NOI'!K54 -> 612500 | G56: ='Low NOI'!$Y$11 -> 0.025 | H56: Fixed | K56: =IF(K$5>0,($F56/12)*(1+((1+$G56)^(1/12))-1)^K$3,0) -> 0 | L56: =IF(L$5>0,($F56/12)*(1+((1+$G56)^(1/12))-1)^L$3,0) -> 0 | M56: =IF(M$5>0,($F56/12)*(1+((1+$G56)^(1/12))-1)^M$3,0) -> 0 | N56: =IF(N$5>0,($F56/12)*(1+((1+$G56)^(1/12))-1)^N$3,0) -> 0 | O56: =IF(O$5>0,($F56/12)*(1+((1+$G56)^(1/12))-1)^O$3,0) -> 0 | P56: =IF(P$5>0,($F56/12)*(1+((1+$G56)^(1/12))-1)^P$3,0) -> 0 | Q56: =IF(Q$5>0,($F56/12)*(1+((1+$G56)^(1/12))-1)^Q$3,0) -> 0 | R56: =IF(R$5>0,($F56/12)*(1+((1+$G56)^(1/12))-1)^R$3,0) -> 0 | ... EX56: =IF(EX$5>0,($F56/12)*(1+((1+$G56)^(1/12))-1)^EX$3,0) -> 68645.367
C57: Property Taxes | D57: ='Low NOI'!Y12 -> 0.25 | F57: ='Low NOI'!K55 -> 1518257.8 | G57: ='Low NOI'!$Y$11 -> 0.025 | H57: Min. lease-up, then fixed | K57: =IF(K$5>0,IF(K$27<$D$58,$D$57*$F$57/12,($F57/12)*(1+((1+$G57)^(1/12))-1)^K$3),0) -> 0 | L57: =IF(L$5>0,IF(L$27<$D$58,$D$57*$F$57/12,($F57/12)*(1+((1+$G57)^(1/12))-1)^L$3),0) -> 0 | M57: =IF(M$5>0,IF(M$27<$D$58,$D$57*$F$57/12,($F57/12)*(1+((1+$G57)^(1/12))-1)^M$3),0) -> 0 | N57: =IF(N$5>0,IF(N$27<$D$58,$D$57*$F$57/12,($F57/12)*(1+((1+$G57)^(1/12))-1)^N$3),0) -> 0 | O57: =IF(O$5>0,IF(O$27<$D$58,$D$57*$F$57/12,($F57/12)*(1+((1+$G57)^(1/12))-1)^O$3),0) -> 0 | P57: =IF(P$5>0,IF(P$27<$D$58,$D$57*$F$57/12,($F57/12)*(1+((1+$G57)^(1/12))-1)^P$3),0) -> 0 | Q57: =IF(Q$5>0,IF(Q$27<$D$58,$D$57*$F$57/12,($F57/12)*(1+((1+$G57)^(1/12))-1)^Q$3),0) -> 0 | R57: =IF(R$5>0,IF(R$27<$D$58,$D$57*$F$57/12,($F57/12)*(1+((1+$G57)^(1/12))-1)^R$3),0) -> 0 | ... EX57: =IF(EX$5>0,IF(EX$27<$D$58,$D$57*$F$57/12,($F57/12)*(1+((1+$G57)^(1/12))-1)^EX$3),0) -> 170157.33
C58: Replacement Reserve (starts at stabilization) | D58: ='Low NOI'!S12 -> 0.75 | F58: ='Low NOI'!K60 -> 70000 | G58: ='Low NOI'!Y15 -> 200 | H58: Fixed post-stabilization | K58: =IF(K$5=0,0,IF(K$27<(1-$G$39),0,$G58*$C$9/12)) -> 0 | L58: =IF(L$5=0,0,IF(L$27<(1-$G$39),0,$G58*$C$9/12)) -> 0 | M58: =IF(M$5=0,0,IF(M$27<(1-$G$39),0,$G58*$C$9/12)) -> 0 | N58: =IF(N$5=0,0,IF(N$27<(1-$G$39),0,$G58*$C$9/12)) -> 0 | O58: =IF(O$5=0,0,IF(O$27<(1-$G$39),0,$G58*$C$9/12)) -> 0 | P58: =IF(P$5=0,0,IF(P$27<(1-$G$39),0,$G58*$C$9/12)) -> 0 | Q58: =IF(Q$5=0,0,IF(Q$27<(1-$G$39),0,$G58*$C$9/12)) -> 0 | R58: =IF(R$5=0,0,IF(R$27<(1-$G$39),0,$G58*$C$9/12)) -> 0 | ... EX58: =IF(EX$5=0,0,IF(EX$27<(1-$G$39),0,$G58*$C$9/12)) -> 5833.3333
C59: Total Operating Expenses | F59: =SUM(F48:F58) -> 3845633.3 | K59: =SUM(K48:K58) -> 0 | L59: =SUM(L48:L58) -> 0 | M59: =SUM(M48:M58) -> 0 | N59: =SUM(N48:N58) -> 0 | O59: =SUM(O48:O58) -> 0 | P59: =SUM(P48:P58) -> 0 | Q59: =SUM(Q48:Q58) -> 0 | R59: =SUM(R48:R58) -> 0 | ... EX59: =SUM(EX48:EX58) -> 430234.74
C61: Net Operating Income | F61: =F44-F59 -> 7738141.7 | K61: =K44-K59 -> 0 | L61: =L44-L59 -> 0 | M61: =M44-M59 -> 0 | N61: =N44-N59 -> 0 | O61: =O44-O59 -> 0 | P61: =P44-P59 -> 0 | Q61: =Q44-Q59 -> 0 | R61: =R44-R59 -> 0 | ... EX61: =EX44-EX59 -> 930547.16
J63: NOI Annualized | K63: =K61*12 -> 0 | L63: =L61*12 -> 0 | M63: =M61*12 -> 0 | N63: =N61*12 -> 0 | O63: =O61*12 -> 0 | P63: =P61*12 -> 0 | Q63: =Q61*12 -> 0 | R63: =R61*12 -> 0 | ... EX63: =EX61*12 -> 11166566
J64: T-12 NOI | K64: 0 | L64: 0 | M64: 0 | N64: 0 | O64: 0 | P64: 0 | Q64: 0 | R64: 0 | S64: 0 | T64: 0 | U64: 0 | V64: =SUM(K61:V61) -> 0 | W64: =SUM(L61:W61) -> 0 | X64: =SUM(M61:X61) -> 0 | Y64: =SUM(N61:Y61) -> 0 | Z64: =SUM(O61:Z61) -> 0 | AA64: =SUM(P61:AA61) -> 0 | AB64: =SUM(Q61:AB61) -> 0 | AC64: =SUM(R61:AC61) -> 0 | ... EX64: =SUM(EM61:EX61) -> 11006124
B65: DEVELOPMENT COSTS BEFORE INTEREST
I67: Total | J67: Closing
B69: Land Valuation | I69: =SUM(J69:EX69) -> 12250000 | J69: ='Low Budget'!F52 -> 12250000 | K69: 0 | L69: 0 | M69: 0 | N69: 0 | O69: 0 | P69: 0 | Q69: 0 | R69: 0 | S69: 0 | T69: 0 | U69: 0 | V69: 0 | W69: 0 | X69: 0 | Y69: 0 | Z69: 0 | AA69: 0 | AB69: 0 | AC69: 0 | AD69: 0 | AE69: 0 | AF69: 0 | AG69: 0 | AH69: 0 | AI69: 0 | AJ69: 0 | AK69: 0 | AL69: 0 | AM69: 0 | AN69: 0 | AO69: 0 | AP69: 0 | AQ69: 0 | AR69: 0 | AS69: 0 | AT69: 0 | AU69: 0 | AV69: 0 | AW69: 0 | AX69: 0 | AY69: 0 | AZ69: 0 | BA69: 0 | BB69: 0 | BC69: 0 | BD69: 0 | BE69: 0 | BF69: 0 | BG69: 0 | BH69: 0 | BI69: 0 | BJ69: 0 | BK69: 0 | BL69: 0 | BM69: 0 | BN69: 0 | BO69: 0 | BP69: 0 | BQ69: 0 | BR69: 0 | BS69: 0 | BT69: 0 | BU69: 0 | BV69: 0 | BW69: 0 | BX69: 0 | BY69: 0 | BZ69: 0 | CA69: 0 | CB69: 0 | CC69: 0 | CD69: 0 | CE69: 0 | CF69: 0 | CG69: 0 | CH69: 0 | CI69: 0 | CJ69: 0 | CK69: 0 | CL69: 0 | CM69: 0 | CN69: 0 | CO69: 0 | CP69: 0 | CQ69: 0 | CR69: 0 | CS69: 0 | CT69: 0 | CU69: 0 | CV69: 0 | CW69: 0 | CX69: 0 | CY69: 0 | CZ69: 0 | DA69: 0 | DB69: 0 | DC69: 0 | DD69: 0 | DE69: 0 | DF69: 0 | DG69: 0 | DH69: 0 | DI69: 0 | DJ69: 0 | DK69: 0 | DL69: 0 | DM69: 0 | DN69: 0 | DO69: 0 | DP69: 0 | DQ69: 0 | DR69: 0 | DS69: 0 | DT69: 0 | DU69: 0 | DV69: 0 | DW69: 0 | DX69: 0 | DY69: 0 | DZ69: 0 | EA69: 0 | EB69: 0 | EC69: 0 | ED69: 0 | EE69: 0 | EF69: 0 | EG69: 0 | EH69: 0 | EI69: 0 | EJ69: 0 | EK69: 0 | EL69: 0 | EM69: 0 | EN69: 0 | EO69: 0 | EP69: 0 | EQ69: 0 | ER69: 0 | ES69: 0 | ET69: 0 | EU69: 0 | EV69: 0 | EW69: 0 | EX69: 0
B70: Financing Closing Costs | I70: =SUM(J70:EX70) -> 1664625.3 | J70: ='Low Budget'!F53 -> 1664625.3 | K70: 0 | L70: 0 | M70: 0 | N70: 0 | O70: 0 | P70: 0 | Q70: 0 | R70: 0 | S70: 0 | T70: 0 | U70: 0 | V70: 0 | W70: 0 | X70: 0 | Y70: 0 | Z70: 0 | AA70: 0 | AB70: 0 | AC70: 0 | AD70: 0 | AE70: 0 | AF70: 0 | AG70: 0 | AH70: 0 | AI70: 0 | AJ70: 0 | AK70: 0 | AL70: 0 | AM70: 0 | AN70: 0 | AO70: 0 | AP70: 0 | AQ70: 0 | AR70: 0 | AS70: 0 | AT70: 0 | AU70: 0 | AV70: 0 | AW70: 0 | AX70: 0 | AY70: 0 | AZ70: 0 | BA70: 0 | BB70: 0 | BC70: 0 | BD70: 0 | BE70: 0 | BF70: 0 | BG70: 0 | BH70: 0 | BI70: 0 | BJ70: 0 | BK70: 0 | BL70: 0 | BM70: 0 | BN70: 0 | BO70: 0 | BP70: 0 | BQ70: 0 | BR70: 0 | BS70: 0 | BT70: 0 | BU70: 0 | BV70: 0 | BW70: 0 | BX70: 0 | BY70: 0 | BZ70: 0 | CA70: 0 | CB70: 0 | CC70: 0 | CD70: 0 | CE70: 0 | CF70: 0 | CG70: 0 | CH70: 0 | CI70: 0 | CJ70: 0 | CK70: 0 | CL70: 0 | CM70: 0 | CN70: 0 | CO70: 0 | CP70: 0 | CQ70: 0 | CR70: 0 | CS70: 0 | CT70: 0 | CU70: 0 | CV70: 0 | CW70: 0 | CX70: 0 | CY70: 0 | CZ70: 0 | DA70: 0 | DB70: 0 | DC70: 0 | DD70: 0 | DE70: 0 | DF70: 0 | DG70: 0 | DH70: 0 | DI70: 0 | DJ70: 0 | DK70: 0 | DL70: 0 | DM70: 0 | DN70: 0 | DO70: 0 | DP70: 0 | DQ70: 0 | DR70: 0 | DS70: 0 | DT70: 0 | DU70: 0 | DV70: 0 | DW70: 0 | DX70: 0 | DY70: 0 | DZ70: 0 | EA70: 0 | EB70: 0 | EC70: 0 | ED70: 0 | EE70: 0 | EF70: 0 | EG70: 0 | EH70: 0 | EI70: 0 | EJ70: 0 | EK70: 0 | EL70: 0 | EM70: 0 | EN70: 0 | EO70: 0 | EP70: 0 | EQ70: 0 | ER70: 0 | ES70: 0 | ET70: 0 | EU70: 0 | EV70: 0 | EW70: 0 | EX70: 0
B71: Hard Costs | I71: =SUM(J71:EX71) -> 86821875 | J71: ='Low Budget'!F54 -> 0 | K71: =IF(AND(K$3>=$C$10,K$3<=$C$11),'Low Budget'!$H$54/($C$11-$C$10+1),0) -> 3617578.1 | L71: =IF(AND(L$3>=$C$10,L$3<=$C$11),'Low Budget'!$H$54/($C$11-$C$10+1),0) -> 3617578.1 | M71: =IF(AND(M$3>=$C$10,M$3<=$C$11),'Low Budget'!$H$54/($C$11-$C$10+1),0) -> 3617578.1 | N71: =IF(AND(N$3>=$C$10,N$3<=$C$11),'Low Budget'!$H$54/($C$11-$C$10+1),0) -> 3617578.1 | O71: =IF(AND(O$3>=$C$10,O$3<=$C$11),'Low Budget'!$H$54/($C$11-$C$10+1),0) -> 3617578.1 | P71: =IF(AND(P$3>=$C$10,P$3<=$C$11),'Low Budget'!$H$54/($C$11-$C$10+1),0) -> 3617578.1 | Q71: =IF(AND(Q$3>=$C$10,Q$3<=$C$11),'Low Budget'!$H$54/($C$11-$C$10+1),0) -> 3617578.1 | R71: =IF(AND(R$3>=$C$10,R$3<=$C$11),'Low Budget'!$H$54/($C$11-$C$10+1),0) -> 3617578.1 | ... EX71: =IF(AND(EX$3>=$C$10,EX$3<=$C$11),'Low Budget'!$H$54/($C$11-$C$10+1),0) -> 0
B72: Soft Costs | I72: =SUM(J72:EX72) -> 12186045 | J72: ='Low Budget'!F55 -> 1200000 | K72: =IF(AND(K$3>=$C$12,K$3<=$C$13),'Low Budget'!$H$55/($C$13-$C$12+1),0) -> 422540.2 | L72: =IF(AND(L$3>=$C$12,L$3<=$C$13),'Low Budget'!$H$55/($C$13-$C$12+1),0) -> 422540.2 | M72: =IF(AND(M$3>=$C$12,M$3<=$C$13),'Low Budget'!$H$55/($C$13-$C$12+1),0) -> 422540.2 | N72: =IF(AND(N$3>=$C$12,N$3<=$C$13),'Low Budget'!$H$55/($C$13-$C$12+1),0) -> 422540.2 | O72: =IF(AND(O$3>=$C$12,O$3<=$C$13),'Low Budget'!$H$55/($C$13-$C$12+1),0) -> 422540.2 | P72: =IF(AND(P$3>=$C$12,P$3<=$C$13),'Low Budget'!$H$55/($C$13-$C$12+1),0) -> 422540.2 | Q72: =IF(AND(Q$3>=$C$12,Q$3<=$C$13),'Low Budget'!$H$55/($C$13-$C$12+1),0) -> 422540.2 | R72: =IF(AND(R$3>=$C$12,R$3<=$C$13),'Low Budget'!$H$55/($C$13-$C$12+1),0) -> 422540.2 | ... EX72: =IF(AND(EX$3>=$C$12,EX$3<=$C$13),'Low Budget'!$H$55/($C$13-$C$12+1),0) -> 0
B73: Operating Deficit Projection (sum of months with negative NOI) | I73: =SUM(J73:EX73) -> 22646.575 | J73: 0 | K73: =IF(K61<0,-K61,0) -> 0 | L73: =IF(L61<0,-L61,0) -> 0 | M73: =IF(M61<0,-M61,0) -> 0 | N73: =IF(N61<0,-N61,0) -> 0 | O73: =IF(O61<0,-O61,0) -> 0 | P73: =IF(P61<0,-P61,0) -> 0 | Q73: =IF(Q61<0,-Q61,0) -> 0 | R73: =IF(R61<0,-R61,0) -> 0 | ... EX73: =IF(EX61<0,-EX61,0) -> 0
B74: Operating Deficit Contingency (budget minimum) | I74: =SUM(J74:EX74) -> 27353.425 | J74: 0 | K74: =IF(AND(K$3>=$C$14,K$3<$C$16),IF($I$73>='Low Budget'!$E$85,0,('Low Budget'!$E$85-$I$73)/($C$16-$C$14)),0) -> 0 | L74: =IF(AND(L$3>=$C$14,L$3<$C$16),IF($I$73>='Low Budget'!$E$85,0,('Low Budget'!$E$85-$I$73)/($C$16-$C$14)),0) -> 0 | M74: =IF(AND(M$3>=$C$14,M$3<$C$16),IF($I$73>='Low Budget'!$E$85,0,('Low Budget'!$E$85-$I$73)/($C$16-$C$14)),0) -> 0 | N74: =IF(AND(N$3>=$C$14,N$3<$C$16),IF($I$73>='Low Budget'!$E$85,0,('Low Budget'!$E$85-$I$73)/($C$16-$C$14)),0) -> 0 | O74: =IF(AND(O$3>=$C$14,O$3<$C$16),IF($I$73>='Low Budget'!$E$85,0,('Low Budget'!$E$85-$I$73)/($C$16-$C$14)),0) -> 0 | P74: =IF(AND(P$3>=$C$14,P$3<$C$16),IF($I$73>='Low Budget'!$E$85,0,('Low Budget'!$E$85-$I$73)/($C$16-$C$14)),0) -> 0 | Q74: =IF(AND(Q$3>=$C$14,Q$3<$C$16),IF($I$73>='Low Budget'!$E$85,0,('Low Budget'!$E$85-$I$73)/($C$16-$C$14)),0) -> 0 | R74: =IF(AND(R$3>=$C$14,R$3<$C$16),IF($I$73>='Low Budget'!$E$85,0,('Low Budget'!$E$85-$I$73)/($C$16-$C$14)),0) -> 0 | ... EX74: =IF(AND(EX$3>=$C$14,EX$3<$C$16),IF($I$73>='Low Budget'!$E$85,0,('Low Budget'!$E$85-$I$73)/($C$16-$C$14)),0) -> 0
C75: Total Cost Before Interest Reserve | I75: =SUM(I69:I74) -> 1.1297255e+08 | J75: =SUM(J69:J74) -> 15114625 | K75: =SUM(K69:K74) -> 4040118.3 | L75: =SUM(L69:L74) -> 4040118.3 | M75: =SUM(M69:M74) -> 4040118.3 | N75: =SUM(N69:N74) -> 4040118.3 | O75: =SUM(O69:O74) -> 4040118.3 | P75: =SUM(P69:P74) -> 4040118.3 | ... EX75: =SUM(EX69:EX74) -> 0
B78: SCENARIO A: CAPITALIZATION - PRIORITIZED DEBT FUNDING
B80: Description of cash flow use and funding priorities:
B81: 1 | C81: Costs excluding interest are funded by unused equity available after closing.
B82: 2 | C82: Costs excluding interest after depletion of equity are funded by senior loan.
B83: 3 | C83: Operating income first pays interest expense. Unpaid interest is added to loan balance.
B84: 4 | C84: Operating income after interest goes to pay principal loan balance.
I85: Total | J85: Closing
C87: Total Cost Before Interest Reserve | I87: =SUM(J87:EX87) -> 1.1297255e+08 | J87: =J$75 -> 15114625 | K87: =K$75 -> 4040118.3 | L87: =L$75 -> 4040118.3 | M87: =M$75 -> 4040118.3 | N87: =N$75 -> 4040118.3 | O87: =O$75 -> 4040118.3 | P87: =P$75 -> 4040118.3 | Q87: =Q$75 -> 4040118.3 | ... EX87: =EX$75 -> 0
B89: Senior Interest Reserve
C90: Interest Expense | D90: Senior Loan Interest | I90: =SUM(J90:EX90) -> 9069001.9 | J90: 0 | K90: =J119*$D91/12 -> 0 | L90: =K119*$D91/12 -> 0 | M90: =L119*$D91/12 -> 0 | N90: =M119*$D91/12 -> 0 | O90: =N119*$D91/12 -> 0 | P90: =O119*$D91/12 -> 0 | Q90: =P119*$D91/12 -> 0 | R90: =Q119*$D91/12 -> 11225.971 | ... EX90: =EW119*$D91/12 -> 0
C91: Less: Operating Cash Flow | D91: ='Low Budget'!H36 -> 0.06 | I91: =SUM(J91:EX91) -> -4469377.7 | J91: 0 | K91: =IF(AND(K90>0,K$61>0),IF(K90>K$61,-K$61,-K90),0) -> 0 | L91: =IF(AND(L90>0,L$61>0),IF(L90>L$61,-L$61,-L90),0) -> 0 | M91: =IF(AND(M90>0,M$61>0),IF(M90>M$61,-M$61,-M90),0) -> 0 | N91: =IF(AND(N90>0,N$61>0),IF(N90>N$61,-N$61,-N90),0) -> 0 | O91: =IF(AND(O90>0,O$61>0),IF(O90>O$61,-O$61,-O90),0) -> 0 | P91: =IF(AND(P90>0,P$61>0),IF(P90>P$61,-P$61,-P90),0) -> 0 | Q91: =IF(AND(Q90>0,Q$61>0),IF(Q90>Q$61,-Q$61,-Q90),0) -> 0 | R91: =IF(AND(R90>0,R$61>0),IF(R90>R$61,-R$61,-R90),0) -> 0 | ... EX91: =IF(AND(EX90>0,EX$61>0),IF(EX90>EX$61,-EX$61,-EX90),0) -> 0
I92: =SUM(I90:I91) -> 4599624.1 | J92: =SUM(J90:J91) -> 0 | K92: =SUM(K90:K91) -> 0 | L92: =SUM(L90:L91) -> 0 | M92: =SUM(M90:M91) -> 0 | N92: =SUM(N90:N91) -> 0 | O92: =SUM(O90:O91) -> 0 | P92: =SUM(P90:P91) -> 0 | ... EX92: =SUM(EX90:EX91) -> 0
B94: Total Cost Capitalized (cost before lender minimum interest) | I94: =I87+I92 -> 1.1757217e+08 | J94: =J87+J92 -> 15114625 | K94: =K87+K92 -> 4040118.3 | L94: =L87+L92 -> 4040118.3 | M94: =M87+M92 -> 4040118.3 | N94: =N87+N92 -> 4040118.3 | O94: =O87+O92 -> 4040118.3 | P94: =P87+P92 -> 4040118.3 | ... EX94: =EX87+EX92 -> 0
I95: =IF(ABS(I94-'Low Budget'!L104)<1,"OK","ERROR") -> OK
B96: Equity Escrow (draws reduce balance)
C97: Beginning Balance | J97: ='Low Budget'!L49 -> 41150259 | K97: =J99 -> 26035634 | L97: =K99 -> 21995516 | M97: =L99 -> 17955397 | N97: =M99 -> 13915279 | O97: =N99 -> 9875160.8 | P97: =O99 -> 5835042.4 | Q97: =P99 -> 1794924.1 | R97: =Q99 -> 0 | ... EX97: =EW99 -> 0
C98: Draws | J98: =-'Low Budget'!F49 -> -15114625 | K98: =IF(AND(K97>0,K87>0),IF(K87<=K97,-K87,-K97),0) -> -4040118.3 | L98: =IF(AND(L97>0,L87>0),IF(L87<=L97,-L87,-L97),0) -> -4040118.3 | M98: =IF(AND(M97>0,M87>0),IF(M87<=M97,-M87,-M97),0) -> -4040118.3 | N98: =IF(AND(N97>0,N87>0),IF(N87<=N97,-N87,-N97),0) -> -4040118.3 | O98: =IF(AND(O97>0,O87>0),IF(O87<=O97,-O87,-O97),0) -> -4040118.3 | P98: =IF(AND(P97>0,P87>0),IF(P87<=P97,-P87,-P97),0) -> -4040118.3 | Q98: =IF(AND(Q97>0,Q87>0),IF(Q87<=Q97,-Q87,-Q97),0) -> -1794924.1 | R98: =IF(AND(R97>0,R87>0),IF(R87<=R97,-R87,-R97),0) -> 0 | ... EX98: =IF(AND(EX97>0,EX87>0),IF(EX87<=EX97,-EX87,-EX97),0) -> 0
C99: Ending Balance | J99: =SUM(J97:J98) -> 26035634 | K99: =SUM(K97:K98) -> 21995516 | L99: =SUM(L97:L98) -> 17955397 | M99: =SUM(M97:M98) -> 13915279 | N99: =SUM(N97:N98) -> 9875160.8 | O99: =SUM(O97:O98) -> 5835042.4 | P99: =SUM(P97:P98) -> 1794924.1 | Q99: =SUM(Q97:Q98) -> 0 | ... EX99: =SUM(EX97:EX98) -> 0
B101: Equity Balance | D101: Profit on Sale
C102: Beginning Balance | D102: Sale Price | F102: ='Low Budget'!R18 -> 1.6268776e+08 | J102: 0 | K102: =J106 -> -41150259 | L102: =K106 -> -41150259 | M102: =L106 -> -41150259 | N102: =M106 -> -41150259 | O102: =N106 -> -41150259 | P102: =O106 -> -41150259 | Q102: =P106 -> -41150259 | R102: =Q106 -> -41150259 | ... EX102: =EW106 -> 44944558
C103: Initial Investment | D103: Sale Costs | F103: ='Low Budget'!R19 -> -2033597 | I103: =SUM(J103:EX103) -> -41150259 | J103: =-'Low Budget'!L49 -> -41150259 | K103: 0 | L103: 0 | M103: 0 | N103: 0 | O103: 0 | P103: 0 | Q103: 0 | R103: 0 | S103: 0 | T103: 0 | U103: 0 | V103: 0 | W103: 0 | X103: 0 | Y103: 0 | Z103: 0 | AA103: 0 | AB103: 0 | AC103: 0 | AD103: 0 | AE103: 0 | AF103: 0 | AG103: 0 | AH103: 0 | AI103: 0 | AJ103: 0 | AK103: 0 | AL103: 0 | AM103: 0 | AN103: 0 | AO103: 0 | AP103: 0 | AQ103: 0 | AR103: 0 | AS103: 0 | AT103: 0 | AU103: 0 | AV103: 0 | AW103: 0 | AX103: 0 | AY103: 0 | AZ103: 0 | BA103: 0 | BB103: 0 | BC103: 0 | BD103: 0 | BE103: 0 | BF103: 0 | BG103: 0 | BH103: 0 | BI103: 0 | BJ103: 0 | BK103: 0 | BL103: 0 | BM103: 0 | BN103: 0 | BO103: 0 | BP103: 0 | BQ103: 0 | BR103: 0 | BS103: 0 | BT103: 0 | BU103: 0 | BV103: 0 | BW103: 0 | BX103: 0 | BY103: 0 | BZ103: 0 | CA103: 0 | CB103: 0 | CC103: 0 | CD103: 0 | CE103: 0 | CF103: 0 | CG103: 0 | CH103: 0 | CI103: 0 | CJ103: 0 | CK103: 0 | CL103: 0 | CM103: 0 | CN103: 0 | CO103: 0 | CP103: 0 | CQ103: 0 | CR103: 0 | CS103: 0 | CT103: 0 | CU103: 0 | CV103: 0 | CW103: 0 | CX103: 0 | CY103: 0 | CZ103: 0 | DA103: 0 | DB103: 0 | DC103: 0 | DD103: 0 | DE103: 0 | DF103: 0 | DG103: 0 | DH103: 0 | DI103: 0 | DJ103: 0 | DK103: 0 | DL103: 0 | DM103: 0 | DN103: 0 | DO103: 0 | DP103: 0 | DQ103: 0 | DR103: 0 | DS103: 0 | DT103: 0 | DU103: 0 | DV103: 0 | DW103: 0 | DX103: 0 | DY103: 0 | DZ103: 0 | EA103: 0 | EB103: 0 | EC103: 0 | ED103: 0 | EE103: 0 | EF103: 0 | EG103: 0 | EH103: 0 | EI103: 0 | EJ103: 0 | EK103: 0 | EL103: 0 | EM103: 0 | EN103: 0 | EO103: 0 | EP103: 0 | EQ103: 0 | ER103: 0 | ES103: 0 | ET103: 0 | EU103: 0 | EV103: 0 | EW103: 0 | EX103: 0
C104: Post-Stabilization Operating CF After Debt Service | D104: Net Price | F104: =SUM(F102:F103) -> 1.6065416e+08 | I104: =SUM(J104:EX104) -> 987062.01 | J104: 0 | K104: =IF(AND(K3>$C$16,K3<=$C$17),IF((K$61+K91)>0,K$61+K91,0),0) -> 0 | L104: =IF(AND(L3>$C$16,L3<=$C$17),IF((L$61+L91)>0,L$61+L91,0),0) -> 0 | M104: =IF(AND(M3>$C$16,M3<=$C$17),IF((M$61+M91)>0,M$61+M91,0),0) -> 0 | N104: =IF(AND(N3>$C$16,N3<=$C$17),IF((N$61+N91)>0,N$61+N91,0),0) -> 0 | O104: =IF(AND(O3>$C$16,O3<=$C$17),IF((O$61+O91)>0,O$61+O91,0),0) -> 0 | P104: =IF(AND(P3>$C$16,P3<=$C$17),IF((P$61+P91)>0,P$61+P91,0),0) -> 0 | Q104: =IF(AND(Q3>$C$16,Q3<=$C$17),IF((Q$61+Q91)>0,Q$61+Q91,0),0) -> 0 | R104: =IF(AND(R3>$C$16,R3<=$C$17),IF((R$61+R91)>0,R$61+R91,0),0) -> 0 | ... EX104: =IF(AND(EX3>$C$16,EX3<=$C$17),IF((EX$61+EX91)>0,EX$61+EX91,0),0) -> 0
C105: Return of Equity & Profit on Sale | D105: Total Cost | F105: ='Low Budget'!R21 -> -1.1795428e+08 | I105: =SUM(J105:EX105) -> 85107768 | J105: 0 | K105: =IF(K$3=$C$17,$F$104+K118,0) -> 0 | L105: =IF(L$3=$C$17,$F$104+L118,0) -> 0 | M105: =IF(M$3=$C$17,$F$104+M118,0) -> 0 | N105: =IF(N$3=$C$17,$F$104+N118,0) -> 0 | O105: =IF(O$3=$C$17,$F$104+O118,0) -> 0 | P105: =IF(P$3=$C$17,$F$104+P118,0) -> 0 | Q105: =IF(Q$3=$C$17,$F$104+Q118,0) -> 0 | R105: =IF(R$3=$C$17,$F$104+R118,0) -> 0 | ... EX105: =IF(EX$3=$C$17,$F$104+EX118,0) -> 0
C106: Ending Balance | D106: Profit on Sale | F106: =SUM(F104:F105) -> 42699885 | I106: =SUM(I103:I105) -> 44944570 | J106: =SUM(J102:J105) -> -41150259 | K106: =SUM(K102:K105) -> -41150259 | L106: =SUM(L102:L105) -> -41150259 | M106: =SUM(M102:M105) -> -41150259 | N106: =SUM(N102:N105) -> -41150259 | O106: =SUM(O102:O105) -> -41150259 | P106: =SUM(P102:P105) -> -41150259 | Q106: =SUM(Q102:Q105) -> -41150259 | ... EX106: =SUM(EX102:EX105) -> 44944558
D107: Cash Flow After Debt Service | F107: =I104-I115 -> 2244685.6
C108: Net Equity Cash Flow | F108: =SUM(F106:F107) -> 44944570 | I108: =SUM(J108:EX108) -> 44944570 | J108: =SUM(J103:J105) -> -41150259 | K108: =SUM(K103:K105) -> 0 | L108: =SUM(L103:L105) -> 0 | M108: =SUM(M103:M105) -> 0 | N108: =SUM(N103:N105) -> 0 | O108: =SUM(O103:O105) -> 0 | P108: =SUM(P103:P105) -> 0 | Q108: =SUM(Q103:Q105) -> 0 | ... EX108: =SUM(EX103:EX105) -> 0
I109: =IF(ABS(I108-F108)<1,"OK","ERROR") -> OK
D110: IRR | F110: =XIRR(J108:EX108,$J$4:$EX$4) -> 0.24813606
B111: Construction Loan (draws increase balance)
C112: Beginning Balance | D112: Loan Commitment | J112: 0 | K112: =J119 -> 0 | L112: =K119 -> 0 | M112: =L119 -> 0 | N112: =M119 -> 0 | O112: =N119 -> 0 | P112: =O119 -> 0 | Q112: =P119 -> 0 | R112: =Q119 -> 2245194.2 | ... EX112: =EW119 -> 0
C113: Draws - Hard & Soft Costs Excl. Interest | D113: HC & SC | F113: =F115-F114 -> 71822286 | I113: =SUM(J113:EX113) -> 71822286 | J113: ='Low Budget'!F48 -> 0 | K113: =K87+K98 -> 0 | L113: =L87+L98 -> 0 | M113: =M87+M98 -> 0 | N113: =N87+N98 -> 0 | O113: =O87+O98 -> 0 | P113: =P87+P98 -> 0 | Q113: =Q87+Q98 -> 2245194.2 | R113: =R87+R98 -> 4040118.3 | ... EX113: =EX87+EX98 -> 0
C114: Draws - Interest Expense | D114: Interest | F114: ='Low Budget'!L57 -> 4599624.1 | I114: =SUM(J114:EX114) -> 4599624.1 | J114: =J92 -> 0 | K114: =K92 -> 0 | L114: =L92 -> 0 | M114: =M92 -> 0 | N114: =N92 -> 0 | O114: =O92 -> 0 | P114: =P92 -> 0 | Q114: =Q92 -> 0 | ... EX114: =EX92 -> 0
C115: Pre-Stabilization - Operating CF After Debt Service | D115: Total | F115: ='Low Budget'!L48 -> 76421910 | I115: =SUM(J115:EX115) -> -1257623.6 | J115: 0 | K115: =IF(K3<=$C$16,IF(AND(SUM(K112:K114)>0,(K$61+K91)>0),IF(SUM(K112:K114)>(K$61+K91),-(K$61+K91),-SUM(K112:K114)),0),0) -> 0 | L115: =IF(L3<=$C$16,IF(AND(SUM(L112:L114)>0,(L$61+L91)>0),IF(SUM(L112:L114)>(L$61+L91),-(L$61+L91),-SUM(L112:L114)),0),0) -> 0 | M115: =IF(M3<=$C$16,IF(AND(SUM(M112:M114)>0,(M$61+M91)>0),IF(SUM(M112:M114)>(M$61+M91),-(M$61+M91),-SUM(M112:M114)),0),0) -> 0 | N115: =IF(N3<=$C$16,IF(AND(SUM(N112:N114)>0,(N$61+N91)>0),IF(SUM(N112:N114)>(N$61+N91),-(N$61+N91),-SUM(N112:N114)),0),0) -> 0 | O115: =IF(O3<=$C$16,IF(AND(SUM(O112:O114)>0,(O$61+O91)>0),IF(SUM(O112:O114)>(O$61+O91),-(O$61+O91),-SUM(O112:O114)),0),0) -> 0 | P115: =IF(P3<=$C$16,IF(AND(SUM(P112:P114)>0,(P$61+P91)>0),IF(SUM(P112:P114)>(P$61+P91),-(P$61+P91),-SUM(P112:P114)),0),0) -> 0 | Q115: =IF(Q3<=$C$16,IF(AND(SUM(Q112:Q114)>0,(Q$61+Q91)>0),IF(SUM(Q112:Q114)>(Q$61+Q91),-(Q$61+Q91),-SUM(Q112:Q114)),0),0) -> 0 | R115: =IF(R3<=$C$16,IF(AND(SUM(R112:R114)>0,(R$61+R91)>0),IF(SUM(R112:R114)>(R$61+R91),-(R$61+R91),-SUM(R112:R114)),0),0) -> 0 | ... EX115: =IF(EX3<=$C$16,IF(AND(SUM(EX112:EX114)>0,(EX$61+EX91)>0),IF(SUM(EX112:EX114)>(EX$61+EX91),-(EX$61+EX91),-SUM(EX112:EX114)),0),0) -> 0
C116: Lender Minimum Interest | F116: =IF(ABS(F115-I113-I114)<1,"OK","ERROR") -> OK | I116: =SUM(J116:EX116) -> 0 | J116: 0 | K116: =IF(K$3=$C$17,'Low Budget'!$L$106,0) -> 0 | L116: =IF(L$3=$C$17,'Low Budget'!$L$106,0) -> 0 | M116: =IF(M$3=$C$17,'Low Budget'!$L$106,0) -> 0 | N116: =IF(N$3=$C$17,'Low Budget'!$L$106,0) -> 0 | O116: =IF(O$3=$C$17,'Low Budget'!$L$106,0) -> 0 | P116: =IF(P$3=$C$17,'Low Budget'!$L$106,0) -> 0 | Q116: =IF(Q$3=$C$17,'Low Budget'!$L$106,0) -> 0 | R116: =IF(R$3=$C$17,'Low Budget'!$L$106,0) -> 0 | ... EX116: =IF(EX$3=$C$17,'Low Budget'!$L$106,0) -> 0
C117: Lender Exit Fee | I117: =SUM(J117:EX117) -> 382109.55 | J117: 0 | K117: =IF(K$3=$C$17,'Low Budget'!$L$107,0) -> 0 | L117: =IF(L$3=$C$17,'Low Budget'!$L$107,0) -> 0 | M117: =IF(M$3=$C$17,'Low Budget'!$L$107,0) -> 0 | N117: =IF(N$3=$C$17,'Low Budget'!$L$107,0) -> 0 | O117: =IF(O$3=$C$17,'Low Budget'!$L$107,0) -> 0 | P117: =IF(P$3=$C$17,'Low Budget'!$L$107,0) -> 0 | Q117: =IF(Q$3=$C$17,'Low Budget'!$L$107,0) -> 0 | R117: =IF(R$3=$C$17,'Low Budget'!$L$107,0) -> 0 | ... EX117: =IF(EX$3=$C$17,'Low Budget'!$L$107,0) -> 0
C118: Loan Repayment at Sale | I118: =SUM(J118:EX118) -> -75546396 | J118: 0 | K118: =IF(K$3=$C$17,-SUM(K112:K117),0) -> 0 | L118: =IF(L$3=$C$17,-SUM(L112:L117),0) -> 0 | M118: =IF(M$3=$C$17,-SUM(M112:M117),0) -> 0 | N118: =IF(N$3=$C$17,-SUM(N112:N117),0) -> 0 | O118: =IF(O$3=$C$17,-SUM(O112:O117),0) -> 0 | P118: =IF(P$3=$C$17,-SUM(P112:P117),0) -> 0 | Q118: =IF(Q$3=$C$17,-SUM(Q112:Q117),0) -> 0 | R118: =IF(R$3=$C$17,-SUM(R112:R117),0) -> 0 | ... EX118: =IF(EX$3=$C$17,-SUM(EX112:EX117),0) -> 0
C119: Ending Balance | I119: =SUM(I113:I118) -> -6.7800283e-06 | J119: =SUM(J112:J118) -> 0 | K119: =SUM(K112:K118) -> 0 | L119: =SUM(L112:L118) -> 0 | M119: =SUM(M112:M118) -> 0 | N119: =SUM(N112:N118) -> 0 | O119: =SUM(O112:O118) -> 0 | P119: =SUM(P112:P118) -> 0 | Q119: =SUM(Q112:Q118) -> 2245194.2 | ... EX119: =SUM(EX112:EX118) -> 0

Sheet High Budget
A1: =Summary!$A$1&" - "&Summary!$AE$4 -> 301 E. ATLANTIC POMPANO BEACH - OPTIMISTIC | Z1: FONT KEY
Z2: Blue = Input cell
Z3: Red = Link to Summary
C4: UNIT SUMMARY | L4: PROJECTED PROFIT ON SALE AT STABILIZATION | Z4: Orange = Link to Middle scenario
Z5: Black = Text or formula cell
E6: Development Land Area | H6: ='Middle Budget'!H6 -> 2.3362029
E7: Density | H7: =H11/H6 -> 149.81575 | L7: Stabilized Value | T7: Sale / Refi | V7: Stabilization
E8: Height | H8: ='Middle Budget'!H8 -> 8 | T8: =H27 -> 40 | V8: =H26 -> 37
E9: Gross Building Area | H9: =H12/H10 -> 525000 | L9: NOI with Developer Property Taxes | R9: RE Tax | T9: =LOOKUP(H27,'High ICF'!K3:EX3,'High ICF'!K61:EX61)*12 -> 8480558.3 | V9: =LOOKUP(H26,'High ICF'!K3:EX3,'High ICF'!K61:EX61)*12 -> 8413315.5
E10: Building Efficiency | H10: ='Middle Budget'!H10 -> 0.5 | L10: Add Back: Developer Property Taxes | R10: Reassessment | T10: =LOOKUP(H27,'High ICF'!K3:EX3,'High ICF'!K57:EX57)*12 -> 1648510.6 | V10: =LOOKUP(H26,'High ICF'!K3:EX3,'High ICF'!K57:EX57)*12 -> 1638365.4
E11: Unit Count - Total | H11: ='High NOI'!F14 -> 350 | L11: Less: Taxes with Market Value Reassessment | R11: ='Middle Budget'!R11 -> 0.75 | T11: =-T14*$R$11*$R$12*(1-R13) -> -2401400.2 | V11: =-V14*R11*R12*(1-R13) -> -2383053.1
E12: Net Rentable Area | H12: ='High NOI'!I14 -> 262500 | L12: NOI After Market Value Tax Reassessment | R12: ='Middle Budget'!R12 -> 0.0205011 | T12: =SUM(T9:T11) -> 7727668.7 | V12: =SUM(V9:V11) -> 7668627.8
E13: Average Unit Size | H13: =H12/H11 -> 750 | L13: Market Cap Rate | R13: ='Middle Budget'!R13 -> 0.04 | T13: =Summary!AE32 -> 0.0475 | V13: =Summary!AE32 -> 0.0475
E14: Un-Trended Average Rent Per Unit | H14: ='High NOI'!K14 -> 2740 | L14: Estimated Market Value | T14: =IF(ABS(T13)>0,T12/T13,0) -> 1.6268776e+08 | V14: =IF(ABS(V13)>0,V12/V13,0) -> 1.614448e+08
E15: Un-Trended Average Rent Per SF | H15: ='High NOI'!M14 -> 3.6533333
E16: Un-Trended NOI (developer property taxes) | H16: ='High NOI'!K62 -> 7738141.7 | L16: Net Profit on Sale at Stabilization
R17: Total | T17: Per Unit | V17: Per SF
C18: PROJECTED TIMING | L18: Value at Sale Date | R18: =T14 -> 1.6268776e+08 | T18: =R18/$H$11 -> 464822.17 | V18: =R18/$H$12 -> 619.7629
L19: ='Middle Budget'!L19 -> 0.0125 | M19: ='Middle Budget'!M19 -> 0 | N19: ='Middle Budget'!N19 -> 0 | O19: ='Middle Budget'!O19 -> 0 | P19: ='Middle Budget'!P19 -> 0 | R19: =R18*-L19 -> -2033597 | T19: =R19/$H$11 -> -5810.2772 | V19: =R19/$H$12 -> -7.7470362
E20: Hard Cost Draws Start | H20: ='Middle Budget'!H20 -> 1 | L20: Net Sale Proceeds | R20: =SUM(R18:R19) -> 1.6065416e+08 | T20: =R20/$H$11 -> 459011.9 | V20: =R20/$H$12 -> 612.01586
E21: Hard Cost Draws End | H21: =Summary!AE42 -> 24 | L21: Less: Total Land & Development Cost | R21: =-L110 -> -1.209225e+08 | T21: =R21/$H$11 -> -345492.86 | V21: =R21/$H$12 -> -460.65715
E22: Soft Cost Draws Start Excl. Op. Deficit | H22: ='Middle Budget'!H22 -> 1 | L22: Net Profit on Sale | R22: =SUM(R20:R21) -> 39731661 | T22: =R22/$H$11 -> 113519.03 | V22: =R22/$H$12 -> 151.35871
E23: ='Middle Budget'!E23 -> 2 | H23: =H21+E23 -> 26 | L23: Add: Operating Cash Flow After Debt Service | R23: ='High ICF'!I104-'High ICF'!I115 -> 2156544 | T23: =R23/$H$11 -> 6161.5544 | V23: =R23/$H$12 -> 8.2154059
E24: ='Middle Budget'!E24 -> 1 | H24: =H21+E24 -> 25 | L24: Total Net Profit | R24: =SUM(R22:R23) -> 41888205 | T24: =R24/$H$11 -> 119680.59 | V24: =R24/$H$12 -> 159.57412
E25: Average Monthly Move-Ins | H25: =(H11*(1-'High NOI'!$Y$9))/(H26-H24+1) -> 25.576923
E26: =Summary!AE31 -> 12 | H26: =H24+E26 -> 37 | L26: RETURN METRICS
E27: ='Middle Budget'!E27 -> 3 | H27: =H26+E27 -> 40
L28: Merchant Build
C29: CONSTRUCTION FINANCING ASSUMPTIONS | L29: Untrended Return on Cost (NOI with developer property taxes) | V29: =H16/L110 -> 0.06399257
L30: Net Profit as % of Cost (excl. net op. CF) | V30: =IF(ABS(R21)>0,-R22/R21,0) -> 0.32857128
E31: Maximum Loan to Cost | H31: ='Middle Budget'!H31 -> 0.65 | L31: IRR on Sale at Stabilization (incl. net op. CF) | V31: ='High ICF'!F110 -> 0.23005278
E32: Maximum % of Stabilized Value | H32: ='Middle Budget'!H32 -> 0.55 | L32: Equity Multiple on Sale at Stabilization (incl. net op. CF) | V32: =(R24+L49)/L49 -> 1.9929463
E33: Minimum Un-Trended Debt Yield (NOI with developer property taxes) | H33: ='Middle Budget'!H33 -> 0.085
E34: Interest Rate - Projected Average Index | H34: ='Middle Budget'!H34 -> 0.035 | L34: Permanent Refinancing
E35: Interest Rate - Spread | H35: ='Middle Budget'!H35 -> 0.025 | L35: Post-Permanent Refinancing Cash-on-Cash Return - Interest Only | V35: =L155 -> 0.12268492
E36: Interest Rate - Total | H36: =H34+H35 -> 0.06 | L36: Post-Permanent Refinancing Cash-on-Cash Return - Amortizing | V36: =H155 -> 0.071509947
E37: Minimum Interest - Months | H37: ='Middle Budget'!H37 -> 12
E38: Minimum Interest - Amount | H38: =L48*H36/12*H37 -> 4700700.3
E39: Origination Fee | H39: ='Middle Budget'!H39 -> 0.01
E40: Exit Fee | H40: ='Middle Budget'!H40 -> 0.005
B44: SOURCES & USES | T44: Untrended | V44: % Stabilized
F45: At Closing | H45: Post-Closing | L45: Total | N45: Per Unit | P45: Per SF | R45: % of Cost | T45: Stabilized DY | V45: Value
T46: Developer RE Tax | V46: Market Value RE Tax
D47: Sources:
E48: Construction Loan | F48: =F58-F49 -> 0 | H48: =L48-F48 -> 78345005 | L48: =MIN(H31*L58,H32*V14,H16/H33) -> 78345005 | N48: =L48/$H$11 -> 223842.87 | P48: =L48/$H$12 -> 298.45716 | R48: =L48/$L$58 -> 0.65 | T48: =H16/L48 -> 0.09877007 | V48: =L48/$V$14 -> 0.48527427
E49: Equity | F49: =IF(L49<F58,L49,F58) -> 17773664 | H49: =L49-F49 -> 24412108 | L49: =L58-L48 -> 42185772 | N49: =L49/$H$11 -> 120530.78 | P49: =L49/$H$12 -> 160.7077 | R49: =L49/$L$58 -> 0.35
F50: =SUM(F48:F49) -> 17773664 | H50: =L50-F50 -> 1.0275711e+08 | L50: =SUM(L48:L49) -> 1.2053078e+08 | N50: =L50/$H$11 -> 344373.65 | P50: =L50/$H$12 -> 459.16487 | R50: =SUM(R48:R49) -> 1
D51: Uses:
E52: Land | F52: =L52 -> 14875000 | H52: =L52-F52 -> 0 | L52: =L71 -> 14875000 | N52: =L52/$H$11 -> 42500 | P52: =L52/$H$12 -> 56.666667
E53: Financing Closing Costs | F53: =L53 -> 1698664.1 | H53: =L53-F53 -> 0 | L53: =L98 -> 1698664.1 | N53: =L53/$H$11 -> 4853.326 | P53: =L53/$H$12 -> 6.4711013
E54: Hard Costs | F54: ='Middle Budget'!F54 -> 0 | H54: =L54-F54 -> 86821875 | L54: =L76 -> 86821875 | N54: =L54/$H$11 -> 248062.5 | P54: =L54/$H$12 -> 330.75
E55: Soft Costs (excl. operating deficit) | F55: ='Middle Budget'!F55 -> 1200000 | H55: =L55-F55 -> 11071684 | L55: =L88-L85 -> 12271684 | N55: =L55/$H$11 -> 35061.955 | P55: =L55/$H$12 -> 46.749273
E56: Operating Deficit | F56: ='Middle Budget'!F56 -> 0 | H56: =L56-F56 -> 50000 | L56: =L85 -> 50000 | N56: =L56/$H$11 -> 142.85714 | P56: =L56/$H$12 -> 0.19047619
E57: Interest Reserve | F57: ='Middle Budget'!F57 -> 0 | H57: =L57-F57 -> 4813554.3 | L57: =L102 -> 4813554.3 | N57: =L57/$H$11 -> 13753.012 | P57: =L57/$H$12 -> 18.33735
F58: =SUM(F52:F57) -> 17773664 | H58: =L58-F58 -> 1.0275711e+08 | L58: =IF(ABS(SUM(L52:L57)-L104)<1,SUM(L52:L57),"ERROR") -> 1.2053078e+08 | N58: =L58/$H$11 -> 344373.65 | P58: =L58/$H$12 -> 459.16487
E60: Reconciliation to Total Cost:
E61: Total Capitalized Cost | L61: =L58 -> 1.2053078e+08
E62: Add: Lender Minimum Interest | L62: =L106 -> 0
E63: Add: Lender Exit Fee | L63: =L107 -> 391725.03
E64: Total Cost | L64: =SUM(L61:L63) -> 1.209225e+08
B68: DEVELOPMENT BUDGET
L69: Total Cost | N69: Per Unit | P69: Per SF
D71: Land | L71: =Summary!AE12 -> 14875000 | N71: =L71/$H$11 -> 42500 | P71: =L71/$H$12 -> 56.666667
D73: Hard Costs
E74: =Summary!AE36 -> 315 | L74: =E74*H12 -> 82687500 | N74: =L74/$H$11 -> 236250 | P74: =L74/$H$12 -> 315
E75: =Summary!AE37 -> 0.05 | L75: =L74*E75 -> 4134375 | N75: =L75/$H$11 -> 11812.5 | P75: =L75/$H$12 -> 15.75
F76: Impact Fees & Utility Connection | L76: =SUM(L74:L75) -> 86821875 | N76: =L76/$H$11 -> 248062.5 | P76: =L76/$H$12 -> 330.75
D77: Soft Costs | F77: Unit Mix for County Calc.
E78: Architectural & Engineering | F78: Studio/1BR | H78: 2BR+ | L78: ='Middle Budget'!L78 -> 1250000 | N78: =L78/$H$11 -> 3571.4286 | P78: =L78/$H$12 -> 4.7619048
E79: Legal & Consultants | F79: ='High NOI'!F10+'High NOI'!F11 -> 210 | H79: ='High NOI'!F12 -> 140 | L79: ='Middle Budget'!L79 -> 500000 | N79: =L79/$H$11 -> 1428.5714 | P79: =L79/$H$12 -> 1.9047619
E80: Advertising & Marketing | F80: County - School | L80: ='Middle Budget'!L80 -> 250000 | N80: =L80/$H$11 -> 714.28571 | P80: =L80/$H$12 -> 0.95238095
E81: =L71*R11*R12*(1-R13) -> 219566.78 | F81: ='Middle Budget'!F81 -> 375 | H81: ='Middle Budget'!H81 -> 1475 | L81: =E81/12*H24 -> 457430.79 | N81: =L81/$H$11 -> 1306.9451 | P81: =L81/$H$12 -> 1.7425935
E82: ='Middle Budget'!E82 -> 0.02 | F82: =$F$79*F81 -> 78750 | H82: =$H$79*H81 -> 206500 | L82: =E82*L76 -> 1736437.5 | N82: =L82/$H$11 -> 4961.25 | P82: =L82/$H$12 -> 6.615
E83: =G96/H11 -> 11767.634 | F83: Total School: | G83: =F82+H82 -> 285250 | L83: =E83*H11 -> 4118672 | N83: =L83/$H$11 -> 11767.634 | P83: =L83/$H$12 -> 15.690179
E84: ='Middle Budget'!E84 -> 0.0091929237 | F84: City - Recreational / Park | L84: =E84*L76 -> 798146.88 | N84: =L84/$H$11 -> 2280.4196 | P84: =L84/$H$12 -> 3.0405595
E85: ='Middle Budget'!E85 -> 50000 | F85: ='Middle Budget'!F85 -> 617 | H85: ='Middle Budget'!H85 -> 617 | L85: ='High ICF'!I73+'High ICF'!I74 -> 50000 | N85: =L85/$H$11 -> 142.85714 | P85: =L85/$H$12 -> 0.19047619
E86: ='Middle Budget'!E86 -> 0.03 | F86: =$F$79*F85 -> 129570 | H86: =$H$79*H85 -> 86380 | L86: =SUM(L78:L84)*E86 -> 273320.62 | N86: =L86/$H$11 -> 780.91604 | P86: =L86/$H$12 -> 1.0412214
E87: =Summary!AE40 -> 0.03 | F87: Total Rec.: | G87: =F86+H86 -> 215950 | L87: =E87*(L76+SUM(L78:L86)) -> 2887676.5 | N87: =L87/$H$11 -> 8250.5042 | P87: =L87/$H$12 -> 11.000672 | R87: =L87/L110 -> 0.02388039
F88: City - Fire/Law/Transport | L88: =SUM(L78:L87) -> 12321684 | N88: =L88/$H$11 -> 35204.812 | P88: =L88/$H$12 -> 46.93975 | R88: =L88/L76 -> 0.14191912
D89: Financing Closing Costs | F89: ='Middle Budget'!F89 -> 0 | R89: =(L88+L98+L102+L108)/L76 -> 0.2214376
E90: =H39 -> 0.01 | F90: =$H$11*F89 -> 0 | L90: =E90*L48 -> 783450.05 | N90: =L90/$H$11 -> 2238.4287 | P90: =L90/$H$12 -> 2.9845716
E91: ='Middle Budget'!E91 -> 0 | F91: County Affordable Housing | L91: =E91*L48 -> 0 | N91: =L91/$H$11 -> 0 | P91: =L91/$H$12 -> 0
E92: Lender Due Diligence Costs | F92: ='Middle Budget'!F92 -> 10000 | L92: ='Middle Budget'!L92 -> 5000 | N92: =L92/$H$11 -> 14.285714 | P92: =L92/$H$12 -> 0.019047619
E93: Third Party Reports (incl. lender cost review) | F93: =$H$11*F92 -> 3500000 | L93: ='Middle Budget'!L93 -> 50000 | N93: =L93/$H$11 -> 142.85714 | P93: =L93/$H$12 -> 0.19047619
E94: ='Middle Budget'!E94 -> 0 | F94: Utility Connections | L94: =E94*L48 -> 0 | N94: =L94/$H$11 -> 0 | P94: =L94/$H$12 -> 0
E95: ='Middle Budget'!E95 -> 0.0055 | F95: ='Middle Budget'!F95 -> 117472 | L95: =E95*L48 -> 430897.53 | N95: =L95/$H$11 -> 1231.1358 | P95: =L95/$H$12 -> 1.6415144
E96: Title Insurance (see formula) | F96: Total Fees: | G96: =G83+G87+F90+F93+F95 -> 4118672 | L96: =IF(L48<10000000,(15075+((L48-5000000)/1000*2.25))*1.1,(26325+((L48-10000000)/1000*2))*1.1) -> 179316.51 | N96: =L96/$H$11 -> 512.33289 | P96: =L96/$H$12 -> 0.68311052
E97: Legal & Other Closing Costs | L97: ='Middle Budget'!L97 -> 250000 | N97: =L97/$H$11 -> 714.28571 | P97: =L97/$H$12 -> 0.95238095
L98: =SUM(L90:L97) -> 1698664.1 | N98: =L98/$H$11 -> 4853.326 | P98: =L98/$H$12 -> 6.4711013
D99: Interest Reserve
E100: Projected Interest Expense | L100: ='High ICF'!I90 -> 9371073.6 | N100: =L100/$H$11 -> 26774.496 | P100: =L100/$H$12 -> 35.699328
E101: Projected Operating Income Offset | L101: ='High ICF'!I91 -> -4557519.3 | N101: =L101/$H$11 -> -13021.484 | P101: =L101/$H$12 -> -17.361978
L102: =SUM(L100:L101) -> 4813554.3 | N102: =L102/$H$11 -> 13753.012 | P102: =L102/$H$12 -> 18.33735
E104: Total Cost Capitalized with Debt & Equity | L104: =L71+L76+L88+L98+L102 -> 1.2053078e+08 | N104: =L104/$H$11 -> 344373.65 | P104: =L104/$H$12 -> 459.16487
F105: Minimum Interest
E106: Lender Minimum Interest | F106: Minimum Interest | H106: =H38 -> 4700700.3 | L106: =H108 -> 0 | N106: =L106/$H$11 -> 0 | P106: =L106/$H$12 -> 0
E107: Lender Exit Fee | F107: Interest Incurred | H107: =L100 -> 9371073.6 | L107: =L48*H40 -> 391725.03 | N107: =L107/$H$11 -> 1119.2144 | P107: =L107/$H$12 -> 1.4922858
F108: Additional Due | H108: =IF(H106<=H107,0,H106-H107) -> 0 | L108: =SUM(L106:L107) -> 391725.03 | N108: =L108/$H$11 -> 1119.2144 | P108: =L108/$H$12 -> 1.4922858
E110: Total Cost | L110: =L104+L108 -> 1.209225e+08 | N110: =L110/$H$11 -> 345492.86 | P110: =L110/$H$12 -> 460.65715
B114: PERMANENT LOAN ANALYSIS
...

Sheet High NOI
A1: ='High Budget'!A1 -> 301 E. ATLANTIC POMPANO BEACH - OPTIMISTIC
B5: UNIT MIX & MARKET RENT | R5: OPERATING ASSUMPTIONS
K6: Untrended Rent
S7: Annual Rent & Other Income Growth | Y7: ='Middle NOI'!Y7 -> 0.03
F8: Units | G8: % Units | H8: Avg. SF | I8: Total SF | K8: Per Unit | M8: Per SF | O8: Total $ | S8: Loss-to-Lease (% of market rent) | Y8: ='Middle NOI'!Y8 -> 0.01
S9: Stabilized Vacancy (% of market rent) | Y9: ='Middle NOI'!Y9 -> 0.05
E10: Studio | F10: ='Middle NOI'!F10 -> 70 | G10: =F10/$F$14 -> 0.2 | H10: ='Middle NOI'!H10 -> 500 | I10: =F10*H10 -> 35000 | K10: =Summary!AE25 -> 2100 | M10: =O10/I10 -> 4.2 | O10: =F10*K10 -> 147000 | S10: Collection Loss (% of GPR) | Y10: ='Middle NOI'!Y10 -> 0.0025
E11: One Bedroom | F11: ='Middle NOI'!F11 -> 140 | G11: =F11/$F$14 -> 0.4 | H11: ='Middle NOI'!H11 -> 675 | I11: =F11*H11 -> 94500 | K11: =Summary!AG25 -> 2650 | M11: =O11/I11 -> 3.9259259 | O11: =F11*K11 -> 371000 | S11: Annual Operating Expense Growth | Y11: ='Middle NOI'!Y11 -> 0.025
E12: Two Bedroom | F12: ='Middle NOI'!F12 -> 140 | G12: =F12/$F$14 -> 0.4 | H12: ='Middle NOI'!H12 -> 950 | I12: =F12*H12 -> 133000 | K12: =Summary!AI25 -> 3150 | M12: =O12/I12 -> 3.3157895 | O12: =F12*K12 -> 441000 | S12: ='Middle NOI'!S12 -> 0.75 | T12: ='Middle NOI'!T12 -> 0 | U12: ='Middle NOI'!U12 -> 0 | V12: ='Middle NOI'!V12 -> 0 | W12: ='Middle NOI'!W12 -> 0 | Y12: ='Middle NOI'!Y12 -> 0.25
S13: Management Fee (% of total revenue) | Y13: ='Middle NOI'!Y13 -> 0.02
F14: =SUM(F10:F13) -> 350 | G14: =SUM(G10:G13) -> 1 | H14: =I14/F14 -> 750 | I14: =SUM(I10:I13) -> 262500 | K14: =O14/F14 -> 2740 | M14: =O14/I14 -> 3.6533333 | O14: =SUM(O10:O13) -> 959000 | S14: Management Fee Monthly Minimum Until Stabilization | Y14: ='Middle NOI'!Y14 -> 5000
S15: Replacement Reserve Per Unit Annually | Y15: ='Middle NOI'!Y15 -> 200
S19: Year of Operations
B20: PROJECTED OPERATING RESULTS | S20: 1 | U20: 2 | W20: 3 | Y20: 4 | AA20: 5
S21: =LOOKUP('High ICF'!$C$14,'High ICF'!$K$3:$EX$3,'High ICF'!$K$6:$EX$6) -> Lease-Up | U21: =LOOKUP('High ICF'!$C$14+12,'High ICF'!$K$3:$EX$3,'High ICF'!$K$6:$EX$6) -> Stabilized | W21: =LOOKUP('High ICF'!$C$14+24,'High ICF'!$K$3:$EX$3,'High ICF'!$K$6:$EX$6) -> Stabilized | Y21: =LOOKUP('High ICF'!$C$14+36,'High ICF'!$K$3:$EX$3,'High ICF'!$K$6:$EX$6) -> Stabilized | AA21: =LOOKUP('High ICF'!$C$14+48,'High ICF'!$K$3:$EX$3,'High ICF'!$K$6:$EX$6) -> Stabilized
R23: Beginning Avg. Monthly Rent: | S23: =LOOKUP('High ICF'!$C$14+1,'High ICF'!$K$3:$EX$3,'High ICF'!$K$28:$EX$28) -> 2921.2219 | U23: =LOOKUP('High ICF'!$C$14+1+12,'High ICF'!$K$3:$EX$3,'High ICF'!$K$28:$EX$28) -> 3008.8586 | W23: =LOOKUP('High ICF'!$C$14+1+24,'High ICF'!$K$3:$EX$3,'High ICF'!$K$28:$EX$28) -> 3099.1243 | Y23: =LOOKUP('High ICF'!$C$14+1+36,'High ICF'!$K$3:$EX$3,'High ICF'!$K$28:$EX$28) -> 3192.0981 | AA23: =LOOKUP('High ICF'!$C$14+1+48,'High ICF'!$K$3:$EX$3,'High ICF'!$K$28:$EX$28) -> 3287.861
R24: Ending Avg. Monthly Rent: | S24: =LOOKUP('High ICF'!$C$14+12,'High ICF'!$K$3:$EX$3,'High ICF'!$K$28:$EX$28) -> 3001.4562 | U24: =LOOKUP('High ICF'!$C$14+12+12,'High ICF'!$K$3:$EX$3,'High ICF'!$K$28:$EX$28) -> 3091.4999 | W24: =LOOKUP('High ICF'!$C$14+12+24,'High ICF'!$K$3:$EX$3,'High ICF'!$K$28:$EX$28) -> 3184.2448 | Y24: =LOOKUP('High ICF'!$C$14+12+36,'High ICF'!$K$3:$EX$3,'High ICF'!$K$28:$EX$28) -> 3279.7722 | AA24: =LOOKUP('High ICF'!$C$14+12+48,'High ICF'!$K$3:$EX$3,'High ICF'!$K$28:$EX$28) -> 3378.1654
R25: Rent Growth % (begin to begin): | S25: 0 | U25: =(U23-S23)/S23 -> 0.03 | W25: =(W23-U23)/U23 -> 0.03 | Y25: =(Y23-W23)/W23 -> 0.03 | AA25: =(AA23-Y23)/Y23 -> 0.03
R26: Average Vacancy: | S26: =-S37/S33 -> 0.44977804 | U26: =-U37/U33 -> 0.05 | W26: =-W37/W33 -> 0.05 | Y26: =-Y37/Y33 -> 0.05 | AA26: =-AA37/AA33 -> 0.05
R27: NOI as % of Market Rent: | S27: =S62/S33 -> 0.3437779 | U27: =U62/U33 -> 0.64432249 | W27: =W62/W33 -> 0.64595275 | Y27: =Y62/Y33 -> 0.64757123 | AA27: =AA62/AA33 -> 0.6491781
R28: NOI Growth: | S28: 0 | U28: =(U62-S62)/S62 -> 0.93046781 | W28: =(W62-U62)/U62 -> 0.032606093 | Y28: =(Y62-W62)/W62 -> 0.032580737 | AA28: =(AA62-Y62)/Y62 -> 0.032555825
K30: Untrended
C31: Income | K31: Total | M31: Per Unit | O31: % Mkt
E33: Market Rent | K33: =F14*K14*12 -> 11508000 | M33: =K33/$F$14 -> 32880 | O33: =K33/K$33 -> 1 | S33: =SUMIF('High ICF'!$K$5:$EX$5,S$20,'High ICF'!$K35:$EX35) -> 12436932 | U33: =SUMIF('High ICF'!$K$5:$EX$5,U$20,'High ICF'!$K35:$EX35) -> 12810040 | W33: =SUMIF('High ICF'!$K$5:$EX$5,W$20,'High ICF'!$K35:$EX35) -> 13194341 | Y33: =SUMIF('High ICF'!$K$5:$EX$5,Y$20,'High ICF'!$K35:$EX35) -> 13590172 | AA33: =SUMIF('High ICF'!$K$5:$EX$5,AA$20,'High ICF'!$K35:$EX35) -> 13997877
D34: (a) | E34: Loss-to-Lease | K34: 0 | M34: =K34/$F$14 -> 0 | O34: =K34/K$33 -> 0 | S34: =SUMIF('High ICF'!$K$5:$EX$5,S$20,'High ICF'!$K36:$EX36) -> -10505.097 | U34: =SUMIF('High ICF'!$K$5:$EX$5,U$20,'High ICF'!$K36:$EX36) -> -128100.4 | W34: =SUMIF('High ICF'!$K$5:$EX$5,W$20,'High ICF'!$K36:$EX36) -> -131943.41 | Y34: =SUMIF('High ICF'!$K$5:$EX$5,Y$20,'High ICF'!$K36:$EX36) -> -135901.72 | AA34: =SUMIF('High ICF'!$K$5:$EX$5,AA$20,'High ICF'!$K36:$EX36) -> -139978.77
E35: Gross Potential Rent | K35: =SUM(K33:K34) -> 11508000 | M35: =K35/$F$14 -> 32880 | O35: =K35/K$33 -> 1 | S35: =SUM(S33:S34) -> 12426427 | U35: =SUM(U33:U34) -> 12681940 | W35: =SUM(W33:W34) -> 13062398 | Y35: =SUM(Y33:Y34) -> 13454270 | AA35: =SUM(AA33:AA34) -> 13857898
E37: Vacancy | K37: =-K33*$Y9 -> -575400 | M37: =K37/$F$14 -> -1644 | O37: =K37/K$33 -> -0.05 | S37: =SUMIF('High ICF'!$K$5:$EX$5,S$20,'High ICF'!$K39:$EX39) -> -5593859 | U37: =SUMIF('High ICF'!$K$5:$EX$5,U$20,'High ICF'!$K39:$EX39) -> -640502.01 | W37: =SUMIF('High ICF'!$K$5:$EX$5,W$20,'High ICF'!$K39:$EX39) -> -659717.07 | Y37: =SUMIF('High ICF'!$K$5:$EX$5,Y$20,'High ICF'!$K39:$EX39) -> -679508.58 | AA37: =SUMIF('High ICF'!$K$5:$EX$5,AA$20,'High ICF'!$K39:$EX39) -> -699893.84
E38: Collection Loss | K38: =-K35*$Y10 -> -28770 | M38: =K38/$F$14 -> -82.2 | O38: =K38/K$33 -> -0.0025 | S38: =SUMIF('High ICF'!$K$5:$EX$5,S$20,'High ICF'!$K40:$EX40) -> -31066.068 | U38: =SUMIF('High ICF'!$K$5:$EX$5,U$20,'High ICF'!$K40:$EX40) -> -31704.85 | W38: =SUMIF('High ICF'!$K$5:$EX$5,W$20,'High ICF'!$K40:$EX40) -> -32655.995 | Y38: =SUMIF('High ICF'!$K$5:$EX$5,Y$20,'High ICF'!$K40:$EX40) -> -33635.675 | AA38: =SUMIF('High ICF'!$K$5:$EX$5,AA$20,'High ICF'!$K40:$EX40) -> -34644.745
E39: Net Rental Income | K39: =SUM(K35:K38) -> 10903830 | M39: =K39/$F$14 -> 31153.8 | O39: =K39/K$33 -> 0.9475 | S39: =SUM(S35:S38) -> 6801502 | U39: =SUM(U35:U38) -> 12009733 | W39: =SUM(W35:W38) -> 12370025 | Y39: =SUM(Y35:Y38) -> 12741126 | AA39: =SUM(AA35:AA38) -> 13123359
E40: ='Middle NOI'!E40 -> 0.8 | K40: =E40*K51 -> 280000 | M40: =K40/$F$14 -> 800 | O40: =K40/K$33 -> 0.0243309 | S40: =SUMIF('High ICF'!$K$5:$EX$5,S$20,'High ICF'!$K42:$EX42) -> 298757.72 | U40: =SUMIF('High ICF'!$K$5:$EX$5,U$20,'High ICF'!$K42:$EX42) -> 306226.66 | W40: =SUMIF('High ICF'!$K$5:$EX$5,W$20,'High ICF'!$K42:$EX42) -> 313882.33 | Y40: =SUMIF('High ICF'!$K$5:$EX$5,Y$20,'High ICF'!$K42:$EX42) -> 321729.39 | AA40: =SUMIF('High ICF'!$K$5:$EX$5,AA$20,'High ICF'!$K42:$EX42) -> 329772.62
