Workbook
Name \a: #N/A
Name \C: #REF!
Name \E: #REF!
Name \L: #REF!
Name \m: #N/A
Name \P: #REF!
Name \Q: #REF!
Name \r: #REF!
Name \s: #REF!
Name \t: #REF!
Name \z: #N/A
Name _1: #REF!
Name _10: #REF!
Name _11: #REF!
Name _18WDCART: #N/A
Name _18WDFEE: #N/A
Name _18WECART: #N/A
Name _18WEFEE: #N/A
Name _2: #REF!
Name _3: #REF!
Name _4: #REF!
Name _5: #REF!
Name _6: #REF!
Name _7: #REF!
Name _8: #REF!
Name _9: #REF!
Name _9WDCART: #N/A
Name _9WDFEE: #N/A
Name _9WECART: #N/A
Name _9WEFEE: #N/A
Name _DLC141: #REF!
Name _Res1: #REF!
Name _SPL2: #REF!
Name _SPL3: #REF!
Name _Vst1: #REF!
Name a_1: #REF!
Name AACT: #REF!
Name AACTYTD: #REF!
Name AB_1: #REF!
Name AB_1: #REF!
Name AB_1: #REF!
Name AB_10: #REF!
Name AB_10: #REF!
Name AB_10: #REF!
Name AB_11: #REF!
Name AB_11: #REF!
Name AB_11: #REF!
Name AB_12: #REF!
Name AB_12: #REF!
Name AB_12: #REF!
Name AB_2: #REF!
Name AB_2: #REF!
Name AB_2: #REF!
Name AB_3: #REF!
Name AB_3: #REF!
Name AB_3: #REF!
Name AB_4: #REF!
Name AB_4: #REF!
Name AB_4: #REF!
Name AB_5: #REF!

Sheet Summary
B2: =+P_L!B2 -> Sentosa Epperson
B3: =+P_L!P2 -> Wesley Chapel, FL
B4: =+Detail!D67 -> 288 | S4: 45657
B5: =+Detail!G67 -> 294000
G6: Stabilized | J6: 1 | K6: =J6+1 -> 2 | L6: =K6+1 -> 3 | M6: =L6+1 -> 4 | N6: =M6+1 -> 5 | O6: =N6+1 -> 6 | P6: =O6+1 -> 7 | Q6: =P6+1 -> 8 | R6: =Q6+1 -> 9 | S6: =R6+1 -> 10
B7: Capitalization
B8: Purchase Cap Rate | C8: =Detail!M37 -> 0.057026737 | F8: Rent/Unit/Month | G8: =+Detail!H67 -> 1910.296 | J8: =J11/Detail!$C$8/12 -> 1916.2857 | K8: =K11/Detail!$C$8/12 -> 1966.0167 | L8: =L11/Detail!$C$8/12 -> 2025.8149 | M8: =M11/Detail!$C$8/12 -> 2087.432 | N8: =N11/Detail!$C$8/12 -> 2150.9233 | O8: =O11/Detail!$C$8/12 -> 2216.3457 | P8: =P11/Detail!$C$8/12 -> 2283.7579 | Q8: =Q11/Detail!$C$8/12 -> 2353.2206 | ... S8: =S11/Detail!$C$8/12 -> 2498.5486
B9: Purchase Price | C9: =Detail!H25 -> 71029066 | D9: =C9/$B$4 -> 246628.7 | F9: Rent/SF/Mnth | G9: =+Detail!I67 -> 1.8713104 | J9: =J8/Detail!$F$67 -> 1.8771778 | K9: =K8/Detail!$F$67 -> 1.9258939 | L9: =L8/Detail!$F$67 -> 1.9844718 | M9: =M8/Detail!$F$67 -> 2.0448314 | N9: =N8/Detail!$F$67 -> 2.1070269 | O9: =O8/Detail!$F$67 -> 2.1711141 | P9: =P8/Detail!$F$67 -> 2.2371506 | Q9: =Q8/Detail!$F$67 -> 2.3051957 | ... S9: =S8/Detail!$F$67 -> 2.4475578
B10: Closing Costs | C10: =Detail!H27 -> 0 | H10: % of GPR
B11: Total Costs | C11: =Detail!H28 -> 71029066 | F11: Gross Potential Rent | G11: =+P_L!E10 -> 6601983.1 | J11: =SUMIF('Cash Flow'!$E$13:$FS$13,J$6,'Cash Flow'!$E$39:$FS$39) -> 6622683.2 | K11: =SUMIF('Cash Flow'!$E$13:$FS$13,K$6,'Cash Flow'!$E$39:$FS$39) -> 6794553.6 | L11: =SUMIF('Cash Flow'!$E$13:$FS$13,L$6,'Cash Flow'!$E$39:$FS$39) -> 7001216.4 | M11: =SUMIF('Cash Flow'!$E$13:$FS$13,M$6,'Cash Flow'!$E$39:$FS$39) -> 7214165.1 | N11: =SUMIF('Cash Flow'!$E$13:$FS$13,N$6,'Cash Flow'!$E$39:$FS$39) -> 7433590.8 | O11: =SUMIF('Cash Flow'!$E$13:$FS$13,O$6,'Cash Flow'!$E$39:$FS$39) -> 7659690.6 | P11: =SUMIF('Cash Flow'!$E$13:$FS$13,P$6,'Cash Flow'!$E$39:$FS$39) -> 7892667.4 | Q11: =SUMIF('Cash Flow'!$E$13:$FS$13,Q$6,'Cash Flow'!$E$39:$FS$39) -> 8132730.5 | ... S11: =SUMIF('Cash Flow'!$E$13:$FS$13,S$6,'Cash Flow'!$E$39:$FS$39) -> 8634983.9
F12: Loss to Lease | G12: =J12 -> -84181.874 | J12: =SUMIF('Cash Flow'!E$13:$FS13,J$6,'Cash Flow'!$E$40:$FS$40) -> -84181.874 | K12: =SUMIF('Cash Flow'!F$13:$FS13,K$6,'Cash Flow'!$E$40:$FS$40) -> -120347.5 | L12: =SUMIF('Cash Flow'!G$13:$FS13,L$6,'Cash Flow'!$E$40:$FS$40) -> -66361.2 | M12: =SUMIF('Cash Flow'!H$13:$FS13,M$6,'Cash Flow'!$E$40:$FS$40) -> -40215.158 | N12: =SUMIF('Cash Flow'!I$13:$FS13,N$6,'Cash Flow'!$E$40:$FS$40) -> -48968.645 | O12: =SUMIF('Cash Flow'!J$13:$FS13,O$6,'Cash Flow'!$E$40:$FS$40) -> -57515.926 | P12: =SUMIF('Cash Flow'!K$13:$FS13,P$6,'Cash Flow'!$E$40:$FS$40) -> -58466.943 | Q12: =SUMIF('Cash Flow'!L$13:$FS13,Q$6,'Cash Flow'!$E$40:$FS$40) -> -59155.215 | ... S12: =SUMIF('Cash Flow'!N$13:$FS13,S$6,'Cash Flow'!$E$40:$FS$40) -> -62239.896
B13: GP Equity | C13: =C15-C14 -> 6007066.2 | D13: =C13/$C$15 -> 0.31734614 | F13: Vacancy | G13: =-G11*Detail!F33 -> -330099.16 | H13: =-G13/$G$11 -> 0.05 | J13: =SUMIF('Cash Flow'!E$13:$FS13,J$6,'Cash Flow'!$E$41:$FS$41) -> -331134.16 | K13: =SUMIF('Cash Flow'!F$13:$FS13,K$6,'Cash Flow'!$E$41:$FS$41) -> -338880.48 | L13: =SUMIF('Cash Flow'!G$13:$FS13,L$6,'Cash Flow'!$E$41:$FS$41) -> -348317.06 | M13: =SUMIF('Cash Flow'!H$13:$FS13,M$6,'Cash Flow'!$E$41:$FS$41) -> -358016.41 | N13: =SUMIF('Cash Flow'!I$13:$FS13,N$6,'Cash Flow'!$E$41:$FS$41) -> -367985.86 | O13: =SUMIF('Cash Flow'!J$13:$FS13,O$6,'Cash Flow'!$E$41:$FS$41) -> -378232.92 | P13: =SUMIF('Cash Flow'!K$13:$FS13,P$6,'Cash Flow'!$E$41:$FS$41) -> -388765.32 | Q13: =SUMIF('Cash Flow'!L$13:$FS13,Q$6,'Cash Flow'!$E$41:$FS$41) -> -399591.02 | ... S13: =SUMIF('Cash Flow'!N$13:$FS13,S$6,'Cash Flow'!$E$41:$FS$41) -> -422155.16
B14: LP Equity | C14: 12922000 | D14: =C14/$C$15 -> 0.68265386 | F14: Gross Rental Income | G14: =G11+G13+G12 -> 6187702.1 | H14: =-G14/$G$11 -> -0.937249 | J14: =SUM(J11:J13) -> 6207367.2 | K14: =SUM(K11:K13) -> 6335325.6 | L14: =SUM(L11:L13) -> 6586538.2 | M14: =SUM(M11:M13) -> 6815933.5 | N14: =SUM(N11:N13) -> 7016636.3 | O14: =SUM(O11:O13) -> 7223941.8 | P14: =SUM(P11:P13) -> 7445435.2 | Q14: =SUM(Q11:Q13) -> 7673984.2 | ... S14: =SUM(S11:S13) -> 8150588.8
B15: Total Equity | C15: =Detail!C22 -> 18929066 | D15: =C15/$C$17 -> 0.26649747 | F15: Non-Income Unit Loss | G15: =-G11/$B$4 -> -22923.553 | H15: =-G15/$G$11 -> 0.0034722222 | J15: =SUMIF('Cash Flow'!$E$13:$FS$13,J$6,'Cash Flow'!$E$57:$FS$57) -> -22995.428 | K15: =SUMIF('Cash Flow'!$E$13:$FS$13,K$6,'Cash Flow'!$E$57:$FS$57) -> -23592.2 | L15: =SUMIF('Cash Flow'!$E$13:$FS$13,L$6,'Cash Flow'!$E$57:$FS$57) -> -24309.779 | M15: =SUMIF('Cash Flow'!$E$13:$FS$13,M$6,'Cash Flow'!$E$57:$FS$57) -> -25049.184 | N15: =SUMIF('Cash Flow'!$E$13:$FS$13,N$6,'Cash Flow'!$E$57:$FS$57) -> -25811.079 | O15: =SUMIF('Cash Flow'!$E$13:$FS$13,O$6,'Cash Flow'!$E$57:$FS$57) -> -26596.148 | P15: =SUMIF('Cash Flow'!$E$13:$FS$13,P$6,'Cash Flow'!$E$57:$FS$57) -> -27405.095 | Q15: =SUMIF('Cash Flow'!$E$13:$FS$13,Q$6,'Cash Flow'!$E$57:$FS$57) -> -28238.648 | ... S15: =SUMIF('Cash Flow'!$E$13:$FS$13,S$6,'Cash Flow'!$E$57:$FS$57) -> -29982.583
B16: Debt | C16: =Detail!D22 -> 52100000 | D16: =C16/$C$17 -> 0.73350253 | F16: Collection Loss | G16: =-Detail!F36*G14 -> -61877.021 | H16: =-G16/$G$11 -> 0.00937249 | J16: =SUMIF('Cash Flow'!$E$13:$FS$13,J$6,'Cash Flow'!$E$43:$FS$43) -> -62073.672 | K16: =SUMIF('Cash Flow'!$E$13:$FS$13,K$6,'Cash Flow'!$E$43:$FS$43) -> -63377.623 | L16: =SUMIF('Cash Flow'!$E$13:$FS$13,L$6,'Cash Flow'!$E$43:$FS$43) -> -65931.177 | M16: =SUMIF('Cash Flow'!$E$13:$FS$13,M$6,'Cash Flow'!$E$43:$FS$43) -> -68125.928 | N16: =SUMIF('Cash Flow'!$E$13:$FS$13,N$6,'Cash Flow'!$E$43:$FS$43) -> -70087.994 | O16: =SUMIF('Cash Flow'!$E$13:$FS$13,O$6,'Cash Flow'!$E$43:$FS$43) -> -72179.184 | P16: =SUMIF('Cash Flow'!$E$13:$FS$13,P$6,'Cash Flow'!$E$43:$FS$43) -> -74391.771 | Q16: =SUMIF('Cash Flow'!$E$13:$FS$13,Q$6,'Cash Flow'!$E$43:$FS$43) -> -76662.604 | ... S16: =SUMIF('Cash Flow'!$E$13:$FS$13,S$6,'Cash Flow'!$E$43:$FS$43) -> -81394.662
B17: Total Capitalization | C17: =C15+C16 -> 71029066 | F17: Concession Loss | H17: =-G17/$G$11 -> 0 | J17: =SUMIF('Cash Flow'!$E$13:$FS$13,J$6,'Cash Flow'!$E$44:$FS$44) -> -414003.95 | K17: =SUMIF('Cash Flow'!$E$13:$FS$13,K$6,'Cash Flow'!$E$44:$FS$44) -> -158254.78 | L17: =SUMIF('Cash Flow'!$E$13:$FS$13,L$6,'Cash Flow'!$E$44:$FS$44) -> 0 | M17: =SUMIF('Cash Flow'!$E$13:$FS$13,M$6,'Cash Flow'!$E$44:$FS$44) -> 0 | N17: =SUMIF('Cash Flow'!$E$13:$FS$13,N$6,'Cash Flow'!$E$44:$FS$44) -> 0 | O17: =SUMIF('Cash Flow'!$E$13:$FS$13,O$6,'Cash Flow'!$E$44:$FS$44) -> 0 | P17: =SUMIF('Cash Flow'!$E$13:$FS$13,P$6,'Cash Flow'!$E$44:$FS$44) -> 0 | Q17: =SUMIF('Cash Flow'!$E$13:$FS$13,Q$6,'Cash Flow'!$E$44:$FS$44) -> 0 | ... S17: =SUMIF('Cash Flow'!$E$13:$FS$13,S$6,'Cash Flow'!$E$44:$FS$44) -> 0
F18: Amenity Income | G18: =+P_L!E17+P_L!E19+Detail!M83 -> 810388.8 | H18: =G18/$G$11 -> 0.1227493 | J18: =SUMIF('Cash Flow'!$E$13:$FS$13,J$6,'Cash Flow'!$E$56:$FS$56) -> 797131.61 | K18: =SUMIF('Cash Flow'!$E$13:$FS$13,K$6,'Cash Flow'!$E$56:$FS$56) -> 834026.69 | L18: =SUMIF('Cash Flow'!$E$13:$FS$13,L$6,'Cash Flow'!$E$56:$FS$56) -> 859394.41 | M18: =SUMIF('Cash Flow'!$E$13:$FS$13,M$6,'Cash Flow'!$E$56:$FS$56) -> 885533.71 | N18: =SUMIF('Cash Flow'!$E$13:$FS$13,N$6,'Cash Flow'!$E$56:$FS$56) -> 912468.07 | O18: =SUMIF('Cash Flow'!$E$13:$FS$13,O$6,'Cash Flow'!$E$56:$FS$56) -> 940221.66 | P18: =SUMIF('Cash Flow'!$E$13:$FS$13,P$6,'Cash Flow'!$E$56:$FS$56) -> 968819.4 | Q18: =SUMIF('Cash Flow'!$E$13:$FS$13,Q$6,'Cash Flow'!$E$56:$FS$56) -> 998286.97 | ... S18: =SUMIF('Cash Flow'!$E$13:$FS$13,S$6,'Cash Flow'!$E$56:$FS$56) -> 1059938.2
B20: Residual | F20: Effective Gross Income | G20: =SUM(G14:G19) -> 6913290.3 | H20: =G20/$G$11 -> 1.0471536 | J20: =SUM(J14:J19) -> 6505425.7 | K20: =SUM(K14:K19) -> 6924127.7 | L20: =SUM(L14:L19) -> 7355691.6 | M20: =SUM(M14:M19) -> 7608292.1 | N20: =SUM(N14:N19) -> 7833205.3 | O20: =SUM(O14:O19) -> 8065388.1 | P20: =SUM(P14:P19) -> 8312457.7 | Q20: =SUM(Q14:Q19) -> 8567370 | ... S20: =SUM(S14:S19) -> 9099149.8
B21: Exit Cap | C21: =Detail!M38 -> 0.05
B22: NOI | C22: =Detail!L22 -> 4636539.1 | F22: Variable Expenses | H22: % of EGI
B23: Sales Price | C23: =Detail!L24 -> 92730781 | D23: =C23/$B$4 -> 321981.88 | F23: Payroll | G23: =+P_L!E23 -> 481979 | H23: =G23/$G$20 -> 0.069717743 | J23: =SUMIF('Cash Flow'!$E$13:$FS$13,J$6,'Cash Flow'!$E60:$FS60) -> 482985.36 | K23: =SUMIF('Cash Flow'!$E$13:$FS$13,K$6,'Cash Flow'!$E60:$FS60) -> 491306.31 | L23: =SUMIF('Cash Flow'!$E$13:$FS$13,L$6,'Cash Flow'!$E60:$FS60) -> 501223.01 | M23: =SUMIF('Cash Flow'!$E$13:$FS$13,M$6,'Cash Flow'!$E60:$FS60) -> 511339.87 | N23: =SUMIF('Cash Flow'!$E$13:$FS$13,N$6,'Cash Flow'!$E60:$FS60) -> 521660.94 | O23: =SUMIF('Cash Flow'!$E$13:$FS$13,O$6,'Cash Flow'!$E60:$FS60) -> 532190.33 | P23: =SUMIF('Cash Flow'!$E$13:$FS$13,P$6,'Cash Flow'!$E60:$FS60) -> 542932.25 | Q23: =SUMIF('Cash Flow'!$E$13:$FS$13,Q$6,'Cash Flow'!$E60:$FS60) -> 553890.99 | ... S23: =SUMIF('Cash Flow'!$E$13:$FS$13,S$6,'Cash Flow'!$E60:$FS60) -> 576476.51
B24: Less Closing Costs | C24: =Detail!L26 -> -1159134.8 | D24: =Detail!M39 -> 0.0125 | F24: Administrative | G24: =+P_L!E27 -> 164269 | H24: =G24/$G$20 -> 0.023761334 | J24: =SUMIF('Cash Flow'!$E$13:$FS$13,J$6,'Cash Flow'!$E61:$FS61) -> 164611.99 | K24: =SUMIF('Cash Flow'!$E$13:$FS$13,K$6,'Cash Flow'!$E61:$FS61) -> 167447.95 | L24: =SUMIF('Cash Flow'!$E$13:$FS$13,L$6,'Cash Flow'!$E61:$FS61) -> 170827.78 | M24: =SUMIF('Cash Flow'!$E$13:$FS$13,M$6,'Cash Flow'!$E61:$FS61) -> 174275.83 | N24: =SUMIF('Cash Flow'!$E$13:$FS$13,N$6,'Cash Flow'!$E61:$FS61) -> 177793.47 | O24: =SUMIF('Cash Flow'!$E$13:$FS$13,O$6,'Cash Flow'!$E61:$FS61) -> 181382.12 | P24: =SUMIF('Cash Flow'!$E$13:$FS$13,P$6,'Cash Flow'!$E61:$FS61) -> 185043.2 | Q24: =SUMIF('Cash Flow'!$E$13:$FS$13,Q$6,'Cash Flow'!$E61:$FS61) -> 188778.18 | ... S24: =SUMIF('Cash Flow'!$E$13:$FS$13,S$6,'Cash Flow'!$E61:$FS61) -> 196475.82
B25: Net Proceeds | C25: =Detail!L27 -> 91571646 | F25: Utilities | G25: =+P_L!E24 -> 557957.03 | H25: =G25/$G$20 -> 0.080707884 | J25: =SUMIF('Cash Flow'!$E$13:$FS$13,J$6,'Cash Flow'!$E62:$FS62) -> 559122.03 | K25: =SUMIF('Cash Flow'!$E$13:$FS$13,K$6,'Cash Flow'!$E62:$FS62) -> 568754.68 | L25: =SUMIF('Cash Flow'!$E$13:$FS$13,L$6,'Cash Flow'!$E62:$FS62) -> 580234.62 | M25: =SUMIF('Cash Flow'!$E$13:$FS$13,M$6,'Cash Flow'!$E62:$FS62) -> 591946.28 | N25: =SUMIF('Cash Flow'!$E$13:$FS$13,N$6,'Cash Flow'!$E62:$FS62) -> 603894.34 | O25: =SUMIF('Cash Flow'!$E$13:$FS$13,O$6,'Cash Flow'!$E62:$FS62) -> 616083.56 | P25: =SUMIF('Cash Flow'!$E$13:$FS$13,P$6,'Cash Flow'!$E62:$FS62) -> 628518.81 | Q25: =SUMIF('Cash Flow'!$E$13:$FS$13,Q$6,'Cash Flow'!$E62:$FS62) -> 641205.05 | ... S25: =SUMIF('Cash Flow'!$E$13:$FS$13,S$6,'Cash Flow'!$E62:$FS62) -> 667350.91
F26: Turnover | G26: =+P_L!E28 -> 51840 | H26: =G26/$G$20 -> 0.0074986002 | J26: =SUMIF('Cash Flow'!$E$13:$FS$13,J$6,'Cash Flow'!$E63:$FS63) -> 51948.24 | K26: =SUMIF('Cash Flow'!$E$13:$FS$13,K$6,'Cash Flow'!$E63:$FS63) -> 52843.213 | L26: =SUMIF('Cash Flow'!$E$13:$FS$13,L$6,'Cash Flow'!$E63:$FS63) -> 53909.819 | M26: =SUMIF('Cash Flow'!$E$13:$FS$13,M$6,'Cash Flow'!$E63:$FS63) -> 54997.954 | N26: =SUMIF('Cash Flow'!$E$13:$FS$13,N$6,'Cash Flow'!$E63:$FS63) -> 56108.053 | O26: =SUMIF('Cash Flow'!$E$13:$FS$13,O$6,'Cash Flow'!$E63:$FS63) -> 57240.558 | P26: =SUMIF('Cash Flow'!$E$13:$FS$13,P$6,'Cash Flow'!$E63:$FS63) -> 58395.921 | Q26: =SUMIF('Cash Flow'!$E$13:$FS$13,Q$6,'Cash Flow'!$E63:$FS63) -> 59574.605 | ... S26: =SUMIF('Cash Flow'!$E$13:$FS$13,S$6,'Cash Flow'!$E63:$FS63) -> 62003.827
F27: Repairs and Maintenance | G27: =+P_L!E26 -> 151785 | H27: =G27/$G$20 -> 0.021955537 | J27: =SUMIF('Cash Flow'!$E$13:$FS$13,J$6,'Cash Flow'!$E64:$FS64) -> 152101.92 | K27: =SUMIF('Cash Flow'!$E$13:$FS$13,K$6,'Cash Flow'!$E64:$FS64) -> 154722.36 | L27: =SUMIF('Cash Flow'!$E$13:$FS$13,L$6,'Cash Flow'!$E64:$FS64) -> 157845.33 | M27: =SUMIF('Cash Flow'!$E$13:$FS$13,M$6,'Cash Flow'!$E64:$FS64) -> 161031.34 | N27: =SUMIF('Cash Flow'!$E$13:$FS$13,N$6,'Cash Flow'!$E64:$FS64) -> 164281.65 | O27: =SUMIF('Cash Flow'!$E$13:$FS$13,O$6,'Cash Flow'!$E64:$FS64) -> 167597.57 | P27: =SUMIF('Cash Flow'!$E$13:$FS$13,P$6,'Cash Flow'!$E64:$FS64) -> 170980.42 | Q27: =SUMIF('Cash Flow'!$E$13:$FS$13,Q$6,'Cash Flow'!$E64:$FS64) -> 174431.55 | ... S27: =SUMIF('Cash Flow'!$E$13:$FS$13,S$6,'Cash Flow'!$E64:$FS64) -> 181544.19
F28: Marketing & Advertising | G28: =+P_L!E29 -> 136800 | H28: =G28/$G$20 -> 0.019787973 | J28: =SUMIF('Cash Flow'!$E$13:$FS$13,J$6,'Cash Flow'!$E65:$FS65) -> 137085.63 | K28: =SUMIF('Cash Flow'!$E$13:$FS$13,K$6,'Cash Flow'!$E65:$FS65) -> 139447.37 | L28: =SUMIF('Cash Flow'!$E$13:$FS$13,L$6,'Cash Flow'!$E65:$FS65) -> 142262.02 | M28: =SUMIF('Cash Flow'!$E$13:$FS$13,M$6,'Cash Flow'!$E65:$FS65) -> 145133.49 | N28: =SUMIF('Cash Flow'!$E$13:$FS$13,N$6,'Cash Flow'!$E65:$FS65) -> 148062.92 | O28: =SUMIF('Cash Flow'!$E$13:$FS$13,O$6,'Cash Flow'!$E65:$FS65) -> 151051.47 | P28: =SUMIF('Cash Flow'!$E$13:$FS$13,P$6,'Cash Flow'!$E65:$FS65) -> 154100.35 | Q28: =SUMIF('Cash Flow'!$E$13:$FS$13,Q$6,'Cash Flow'!$E65:$FS65) -> 157210.76 | ... S28: =SUMIF('Cash Flow'!$E$13:$FS$13,S$6,'Cash Flow'!$E65:$FS65) -> 163621.21
F29: Contract Services | G29: =+P_L!E25 -> 30140 | H29: =G29/$G$20 -> 0.0043597185 | J29: =SUMIF('Cash Flow'!$E$13:$FS$13,J$6,'Cash Flow'!$E66:$FS66) -> 30202.931 | K29: =SUMIF('Cash Flow'!$E$13:$FS$13,K$6,'Cash Flow'!$E66:$FS66) -> 30723.272 | L29: =SUMIF('Cash Flow'!$E$13:$FS$13,L$6,'Cash Flow'!$E66:$FS66) -> 31343.402 | M29: =SUMIF('Cash Flow'!$E$13:$FS$13,M$6,'Cash Flow'!$E66:$FS66) -> 31976.048 | N29: =SUMIF('Cash Flow'!$E$13:$FS$13,N$6,'Cash Flow'!$E66:$FS66) -> 32621.464 | O29: =SUMIF('Cash Flow'!$E$13:$FS$13,O$6,'Cash Flow'!$E66:$FS66) -> 33279.907 | P29: =SUMIF('Cash Flow'!$E$13:$FS$13,P$6,'Cash Flow'!$E66:$FS66) -> 33951.641 | Q29: =SUMIF('Cash Flow'!$E$13:$FS$13,Q$6,'Cash Flow'!$E66:$FS66) -> 34636.933 | ... S29: =SUMIF('Cash Flow'!$E$13:$FS$13,S$6,'Cash Flow'!$E66:$FS66) -> 36049.293
F30: Fixed Expenses
F31: Management Fees | G31: =+P_L!E31 -> 190115.48 | H31: =G31/$G$20 -> 0.0275 | J31: =SUMIF('Cash Flow'!$E$13:$FS$13,J$6,'Cash Flow'!$E68:$FS68) -> 178899.21 | K31: =SUMIF('Cash Flow'!$E$13:$FS$13,K$6,'Cash Flow'!$E68:$FS68) -> 190480.52 | L31: =SUMIF('Cash Flow'!$E$13:$FS$13,L$6,'Cash Flow'!$E68:$FS68) -> 202462.46 | M31: =SUMIF('Cash Flow'!$E$13:$FS$13,M$6,'Cash Flow'!$E68:$FS68) -> 209136.16 | N31: =SUMIF('Cash Flow'!$E$13:$FS$13,N$6,'Cash Flow'!$E68:$FS68) -> 215197.63 | O31: =SUMIF('Cash Flow'!$E$13:$FS$13,O$6,'Cash Flow'!$E68:$FS68) -> 221632.53 | P31: =SUMIF('Cash Flow'!$E$13:$FS$13,P$6,'Cash Flow'!$E68:$FS68) -> 228420.49 | Q31: =SUMIF('Cash Flow'!$E$13:$FS$13,Q$6,'Cash Flow'!$E68:$FS68) -> 235390.27 | ... S31: =SUMIF('Cash Flow'!$E$13:$FS$13,S$6,'Cash Flow'!$E68:$FS68) -> 249920.75
F32: HOA | G32: =+P_L!E32 -> 14652 | H32: =G32/$G$20 -> 0.002119396 | J32: =SUMIF('Cash Flow'!$E$13:$FS$13,J$6,'Cash Flow'!$E70:$FS70) -> 14682.593 | K32: =SUMIF('Cash Flow'!$E$13:$FS$13,K$6,'Cash Flow'!$E70:$FS70) -> 14935.547 | L32: =SUMIF('Cash Flow'!$E$13:$FS$13,L$6,'Cash Flow'!$E70:$FS70) -> 15237.011 | M32: =SUMIF('Cash Flow'!$E$13:$FS$13,M$6,'Cash Flow'!$E70:$FS70) -> 15544.561 | N32: =SUMIF('Cash Flow'!$E$13:$FS$13,N$6,'Cash Flow'!$E70:$FS70) -> 15858.318 | O32: =SUMIF('Cash Flow'!$E$13:$FS$13,O$6,'Cash Flow'!$E70:$FS70) -> 16178.408 | P32: =SUMIF('Cash Flow'!$E$13:$FS$13,P$6,'Cash Flow'!$E70:$FS70) -> 16504.958 | Q32: =SUMIF('Cash Flow'!$E$13:$FS$13,Q$6,'Cash Flow'!$E70:$FS70) -> 16838.1 | ... S32: =SUMIF('Cash Flow'!$E$13:$FS$13,S$6,'Cash Flow'!$E70:$FS70) -> 17524.693
F33: RE Taxes | G33: =+P_L!E34 -> 723196.89 | H33: =G33/$G$20 -> 0.10460965 | J33: =SUMIF('Cash Flow'!$E$13:$FS$13,J$6,'Cash Flow'!$E69:$FS69) -> 724706.9 | K33: =SUMIF('Cash Flow'!$E$13:$FS$13,K$6,'Cash Flow'!$E69:$FS69) -> 737192.27 | L33: =SUMIF('Cash Flow'!$E$13:$FS$13,L$6,'Cash Flow'!$E69:$FS69) -> 752072.02 | M33: =SUMIF('Cash Flow'!$E$13:$FS$13,M$6,'Cash Flow'!$E69:$FS69) -> 767252.11 | N33: =SUMIF('Cash Flow'!$E$13:$FS$13,N$6,'Cash Flow'!$E69:$FS69) -> 782738.6 | O33: =SUMIF('Cash Flow'!$E$13:$FS$13,O$6,'Cash Flow'!$E69:$FS69) -> 798537.68 | P33: =SUMIF('Cash Flow'!$E$13:$FS$13,P$6,'Cash Flow'!$E69:$FS69) -> 814655.65 | Q33: =SUMIF('Cash Flow'!$E$13:$FS$13,Q$6,'Cash Flow'!$E69:$FS69) -> 831098.95 | ... S33: =SUMIF('Cash Flow'!$E$13:$FS$13,S$6,'Cash Flow'!$E69:$FS69) -> 864987.94
F34: Insurance - Property | G34: =+P_L!E33 -> 302400 | H34: =G34/$G$20 -> 0.043741834 | J34: =SUMIF('Cash Flow'!$E$13:$FS$13,J$6,'Cash Flow'!$E71:$FS71) -> 303031.4 | K34: =SUMIF('Cash Flow'!$E$13:$FS$13,K$6,'Cash Flow'!$E71:$FS71) -> 308252.08 | L34: =SUMIF('Cash Flow'!$E$13:$FS$13,L$6,'Cash Flow'!$E71:$FS71) -> 314473.95 | M34: =SUMIF('Cash Flow'!$E$13:$FS$13,M$6,'Cash Flow'!$E71:$FS71) -> 320821.4 | N34: =SUMIF('Cash Flow'!$E$13:$FS$13,N$6,'Cash Flow'!$E71:$FS71) -> 327296.97 | O34: =SUMIF('Cash Flow'!$E$13:$FS$13,O$6,'Cash Flow'!$E71:$FS71) -> 333903.25 | P34: =SUMIF('Cash Flow'!$E$13:$FS$13,P$6,'Cash Flow'!$E71:$FS71) -> 340642.87 | Q34: =SUMIF('Cash Flow'!$E$13:$FS$13,Q$6,'Cash Flow'!$E71:$FS71) -> 347518.53 | ... S34: =SUMIF('Cash Flow'!$E$13:$FS$13,S$6,'Cash Flow'!$E71:$FS71) -> 361688.99
F35: Capital Reserves | G35: =+P_L!E35 -> 57600 | H35: =G35/$G$20 -> 0.008331778 | J35: =SUMIF('Cash Flow'!$E$13:$FS$13,J$6,'Cash Flow'!$E72:$FS72) -> 57600 | K35: =SUMIF('Cash Flow'!$E$13:$FS$13,K$6,'Cash Flow'!$E72:$FS72) -> 57600 | L35: =SUMIF('Cash Flow'!$E$13:$FS$13,L$6,'Cash Flow'!$E72:$FS72) -> 57600 | M35: =SUMIF('Cash Flow'!$E$13:$FS$13,M$6,'Cash Flow'!$E72:$FS72) -> 57600 | N35: =SUMIF('Cash Flow'!$E$13:$FS$13,N$6,'Cash Flow'!$E72:$FS72) -> 57600 | O35: =SUMIF('Cash Flow'!$E$13:$FS$13,O$6,'Cash Flow'!$E72:$FS72) -> 57600 | P35: =SUMIF('Cash Flow'!$E$13:$FS$13,P$6,'Cash Flow'!$E72:$FS72) -> 57600 | Q35: =SUMIF('Cash Flow'!$E$13:$FS$13,Q$6,'Cash Flow'!$E72:$FS72) -> 57600 | ... S35: =SUMIF('Cash Flow'!$E$13:$FS$13,S$6,'Cash Flow'!$E72:$FS72) -> 57600
F36: Total Operating Expenses | G36: =SUM(G23:G35) -> 2862734.4 | H36: =G36/$G$20 -> 0.41409145 | J36: =SUM(J23:J35) -> 2856978.2 | K36: =SUM(K23:K35) -> 2913705.6 | L36: =SUM(L23:L35) -> 2979491.4 | M36: =SUM(M23:M35) -> 3041055.1 | N36: =SUM(N23:N35) -> 3103114.4 | O36: =SUM(O23:O35) -> 3166677.4 | P36: =SUM(P23:P35) -> 3231746.6 | Q36: =SUM(Q23:Q35) -> 3298173.9 | ... S36: =SUM(S23:S35) -> 3435244.1
F38: Net Operating Income | G38: =G20-G36 -> 4050555.9 | J38: =J20-J36 -> 3648447.5 | K38: =K20-K36 -> 4010422.1 | L38: =L20-L36 -> 4376200.2 | M38: =M20-M36 -> 4567237.1 | N38: =N20-N36 -> 4730091 | O38: =O20-O36 -> 4898710.7 | P38: =P20-P36 -> 5080711.2 | Q38: =Q20-Q36 -> 5269196 | ... S38: =S20-S36 -> 5663905.7
F39: NOI Growth | K39: =K38/J38-1 -> 0.099213315 | L39: =L38/K38-1 -> 0.091206877 | M39: =M38/L38-1 -> 0.043653602 | N39: =N38/M38-1 -> 0.035656981 | O39: =O38/N38-1 -> 0.03564831 | P39: =P38/O38-1 -> 0.037152721 | Q39: =Q38/P38-1 -> 0.037098132 | R39: =R38/Q38-1 -> 0.036882441 | S39: =S38/R38-1 -> 0.036673828
F40: Debt Service | J40: =-(SUMIF('Cash Flow'!$E$13:$FS13,J$6,'Cash Flow'!$E81:$FS81)+SUMIF('Cash Flow'!$E$13:$FS13,J$6,'Cash Flow'!$E82:$FS82)) -> -3037357.6 | K40: =-(SUMIF('Cash Flow'!$E$13:$FS13,K$6,'Cash Flow'!$E81:$FS81)+SUMIF('Cash Flow'!$E$13:$FS13,K$6,'Cash Flow'!$E82:$FS82)) -> -3045679.2 | L40: =-(SUMIF('Cash Flow'!$E$13:$FS13,L$6,'Cash Flow'!$E81:$FS81)+SUMIF('Cash Flow'!$E$13:$FS13,L$6,'Cash Flow'!$E82:$FS82)) -> -3037357.6 | M40: =-(SUMIF('Cash Flow'!$E$13:$FS13,M$6,'Cash Flow'!$E81:$FS81)+SUMIF('Cash Flow'!$E$13:$FS13,M$6,'Cash Flow'!$E82:$FS82)) -> -3037357.6 | N40: =-(SUMIF('Cash Flow'!$E$13:$FS13,N$6,'Cash Flow'!$E81:$FS81)+SUMIF('Cash Flow'!$E$13:$FS13,N$6,'Cash Flow'!$E82:$FS82)) -> 0 | O40: =-(SUMIF('Cash Flow'!$E$13:$FS13,O$6,'Cash Flow'!$E81:$FS81)+SUMIF('Cash Flow'!$E$13:$FS13,O$6,'Cash Flow'!$E82:$FS82)) -> 0 | P40: =-(SUMIF('Cash Flow'!$E$13:$FS13,P$6,'Cash Flow'!$E81:$FS81)+SUMIF('Cash Flow'!$E$13:$FS13,P$6,'Cash Flow'!$E82:$FS82)) -> 0 | Q40: =-(SUMIF('Cash Flow'!$E$13:$FS13,Q$6,'Cash Flow'!$E81:$FS81)+SUMIF('Cash Flow'!$E$13:$FS13,Q$6,'Cash Flow'!$E82:$FS82)) -> 0 | ... S40: =-(SUMIF('Cash Flow'!$E$13:$FS13,S$6,'Cash Flow'!$E81:$FS81)+SUMIF('Cash Flow'!$E$13:$FS13,S$6,'Cash Flow'!$E82:$FS82)) -> 0
F41: DSCR | J41: =-IFERROR(J38/J40,0) -> 1.2011913 | K41: =-IFERROR(K38/K40,0) -> 1.3167579 | L41: =-IFERROR(L38/L40,0) -> 1.4407919 | M41: =-IFERROR(M38/M40,0) -> 1.5036876 | N41: =-IFERROR(N38/N40,0) -> 0 | O41: =-IFERROR(O38/O40,0) -> 0 | P41: =-IFERROR(P38/P40,0) -> 0 | Q41: =-IFERROR(Q38/Q40,0) -> 0 | ... S41: =-IFERROR(S38/S40,0) -> 0
F43: Cash Flow After Debt Service | J43: =SUMIF('Cash Flow'!$E$13:$FS13,J$6,'Cash Flow'!$E84:$FS84) -> 611089.9 | K43: =SUMIF('Cash Flow'!$E$13:$FS13,K$6,'Cash Flow'!$E84:$FS84) -> 967179.66 | L43: =SUMIF('Cash Flow'!$E$13:$FS13,L$6,'Cash Flow'!$E84:$FS84) -> 1345422.1 | M43: =SUMIF('Cash Flow'!$E$13:$FS13,M$6,'Cash Flow'!$E84:$FS84) -> 1526538.7 | N43: =SUMIF('Cash Flow'!$E$13:$FS13,N$6,'Cash Flow'!$E84:$FS84) -> 0 | O43: =SUMIF('Cash Flow'!$E$13:$FS13,O$6,'Cash Flow'!$E84:$FS84) -> 0 | P43: =SUMIF('Cash Flow'!$E$13:$FS13,P$6,'Cash Flow'!$E84:$FS84) -> 0 | Q43: =SUMIF('Cash Flow'!$E$13:$FS13,Q$6,'Cash Flow'!$E84:$FS84) -> 0 | ... S43: =SUMIF('Cash Flow'!$E$13:$FS13,S$6,'Cash Flow'!$E84:$FS84) -> 0
F45: Equity Invested | J45: =C15 -> 18929066 | K45: =J45 -> 18929066 | L45: =K45 -> 18929066 | M45: =L45 -> 18929066 | N45: =M45 -> 18929066 | O45: 0 | P45: 0 | Q45: =P45 -> 0 | R45: =Q45 -> 0 | S45: =R45 -> 0
F46: Cash Yield | J46: =IFERROR(J43/J45,0) -> 0.032283151 | K46: =IFERROR(K43/K45,0) -> 0.051094949 | L46: =IFERROR(L43/L45,0) -> 0.071077043 | M46: =IFERROR(M43/M45,0) -> 0.080645218 | N46: =IFERROR(N43/N45,0) -> 0 | O46: =IFERROR(O43/O45,0) -> 0 | P46: =IFERROR(P43/P45,0) -> 0 | Q46: =IFERROR(Q43/Q45,0) -> 0 | ... S46: =IFERROR(S43/S45,0) -> 0
F50: Economics | J50: 1 | K50: =+J50+1 -> 2 | L50: =+K50+1 -> 3 | M50: =+L50+1 -> 4 | N50: =+M50+1 -> 5 | O50: =+N50+1 -> 6 | P50: =+O50+1 -> 7 | Q50: =+P50+1 -> 8 | R50: =+Q50+1 -> 9 | S50: =+R50+1 -> 10
F51: Equity Contribution | H51: =SUM(J51:S51) -> -18929066 | J51: =SUMIF('Cash Flow'!$E$13:$FS$13,J$50,'Cash Flow'!$E112:$FS112) -> -18929066 | K51: =SUMIF('Cash Flow'!$E$13:$FS$13,K$50,'Cash Flow'!$E112:$FS112) -> 0 | L51: =SUMIF('Cash Flow'!$E$13:$FS$13,L$50,'Cash Flow'!$E112:$FS112) -> 0 | M51: =SUMIF('Cash Flow'!$E$13:$FS$13,M$50,'Cash Flow'!$E112:$FS112) -> 0 | N51: =SUMIF('Cash Flow'!$E$13:$FS$13,N$50,'Cash Flow'!$E112:$FS112) -> 0 | O51: =SUMIF('Cash Flow'!$E$13:$FS$13,O$50,'Cash Flow'!$E112:$FS112) -> 0 | P51: =SUMIF('Cash Flow'!$E$13:$FS$13,P$50,'Cash Flow'!$E112:$FS112) -> 0 | Q51: =SUMIF('Cash Flow'!$E$13:$FS$13,Q$50,'Cash Flow'!$E112:$FS112) -> 0 | ... S51: =SUMIF('Cash Flow'!$E$13:$FS$13,S$50,'Cash Flow'!$E112:$FS112) -> 0
F52: Acquisition Loan Repayment | H52: =SUM(J52:S52) -> -52100000 | J52: =SUMIF('Cash Flow'!$E$13:$FS$13,J$50,'Cash Flow'!$E113:$FS113) -> 0 | K52: =SUMIF('Cash Flow'!$E$13:$FS$13,K$50,'Cash Flow'!$E113:$FS113) -> 0 | L52: =SUMIF('Cash Flow'!$E$13:$FS$13,L$50,'Cash Flow'!$E113:$FS113) -> 0 | M52: =SUMIF('Cash Flow'!$E$13:$FS$13,M$50,'Cash Flow'!$E113:$FS113) -> -52100000 | N52: =SUMIF('Cash Flow'!$E$13:$FS$13,N$50,'Cash Flow'!$E113:$FS113) -> 0 | O52: =SUMIF('Cash Flow'!$E$13:$FS$13,O$50,'Cash Flow'!$E113:$FS113) -> 0 | P52: =SUMIF('Cash Flow'!$E$13:$FS$13,P$50,'Cash Flow'!$E113:$FS113) -> 0 | Q52: =SUMIF('Cash Flow'!$E$13:$FS$13,Q$50,'Cash Flow'!$E113:$FS113) -> 0 | ... S52: =SUMIF('Cash Flow'!$E$13:$FS$13,S$50,'Cash Flow'!$E113:$FS113) -> 0
F53: Refinancing Loan Infusion | H53: =SUM(J53:S53) -> 0 | J53: =SUMIF('Cash Flow'!$E$13:$FS$13,J$50,'Cash Flow'!$E114:$FS114) -> 0 | K53: =SUMIF('Cash Flow'!$E$13:$FS$13,K$50,'Cash Flow'!$E114:$FS114) -> 0 | L53: =SUMIF('Cash Flow'!$E$13:$FS$13,L$50,'Cash Flow'!$E114:$FS114) -> 0 | M53: =SUMIF('Cash Flow'!$E$13:$FS$13,M$50,'Cash Flow'!$E114:$FS114) -> 0 | N53: =SUMIF('Cash Flow'!$E$13:$FS$13,N$50,'Cash Flow'!$E114:$FS114) -> 0 | O53: =SUMIF('Cash Flow'!$E$13:$FS$13,O$50,'Cash Flow'!$E114:$FS114) -> 0 | P53: =SUMIF('Cash Flow'!$E$13:$FS$13,P$50,'Cash Flow'!$E114:$FS114) -> 0 | Q53: =SUMIF('Cash Flow'!$E$13:$FS$13,Q$50,'Cash Flow'!$E114:$FS114) -> 0 | ... S53: =SUMIF('Cash Flow'!$E$13:$FS$13,S$50,'Cash Flow'!$E114:$FS114) -> 0
F54: Net Sale Proceeds | H54: =SUM(J54:S54) -> 91571646 | J54: =SUMIF('Cash Flow'!$E$13:$FS$13,J$50,'Cash Flow'!$E115:$FS115) -> 0 | K54: =SUMIF('Cash Flow'!$E$13:$FS$13,K$50,'Cash Flow'!$E115:$FS115) -> 0 | L54: =SUMIF('Cash Flow'!$E$13:$FS$13,L$50,'Cash Flow'!$E115:$FS115) -> 0 | M54: =SUMIF('Cash Flow'!$E$13:$FS$13,M$50,'Cash Flow'!$E115:$FS115) -> 91571646 | N54: =SUMIF('Cash Flow'!$E$13:$FS$13,N$50,'Cash Flow'!$E115:$FS115) -> 0 | O54: =SUMIF('Cash Flow'!$E$13:$FS$13,O$50,'Cash Flow'!$E115:$FS115) -> 0 | P54: =SUMIF('Cash Flow'!$E$13:$FS$13,P$50,'Cash Flow'!$E115:$FS115) -> 0 | Q54: =SUMIF('Cash Flow'!$E$13:$FS$13,Q$50,'Cash Flow'!$E115:$FS115) -> 0 | ... S54: =SUMIF('Cash Flow'!$E$13:$FS$13,S$50,'Cash Flow'!$E115:$FS115) -> 0
F55: Repayment of Loan | H55: =SUM(J55:S55) -> 0 | J55: =SUMIF('Cash Flow'!$E$13:$FS$13,J$50,'Cash Flow'!$E116:$FS116) -> 0 | K55: =SUMIF('Cash Flow'!$E$13:$FS$13,K$50,'Cash Flow'!$E116:$FS116) -> 0 | L55: =SUMIF('Cash Flow'!$E$13:$FS$13,L$50,'Cash Flow'!$E116:$FS116) -> 0 | M55: =SUMIF('Cash Flow'!$E$13:$FS$13,M$50,'Cash Flow'!$E116:$FS116) -> 0 | N55: =SUMIF('Cash Flow'!$E$13:$FS$13,N$50,'Cash Flow'!$E116:$FS116) -> 0 | O55: =SUMIF('Cash Flow'!$E$13:$FS$13,O$50,'Cash Flow'!$E116:$FS116) -> 0 | P55: =SUMIF('Cash Flow'!$E$13:$FS$13,P$50,'Cash Flow'!$E116:$FS116) -> 0 | Q55: =SUMIF('Cash Flow'!$E$13:$FS$13,Q$50,'Cash Flow'!$E116:$FS116) -> 0 | ... S55: =SUMIF('Cash Flow'!$E$13:$FS$13,S$50,'Cash Flow'!$E116:$FS116) -> 0
F56: CF after Debt Service | H56: =SUM(J56:S56) -> 4450230.3 | J56: =SUMIF('Cash Flow'!$E$13:$FS$13,J$50,'Cash Flow'!$E117:$FS117) -> 611089.9 | K56: =SUMIF('Cash Flow'!$E$13:$FS$13,K$50,'Cash Flow'!$E117:$FS117) -> 967179.66 | L56: =SUMIF('Cash Flow'!$E$13:$FS$13,L$50,'Cash Flow'!$E117:$FS117) -> 1345422.1 | M56: =SUMIF('Cash Flow'!$E$13:$FS$13,M$50,'Cash Flow'!$E117:$FS117) -> 1526538.7 | N56: =SUMIF('Cash Flow'!$E$13:$FS$13,N$50,'Cash Flow'!$E117:$FS117) -> 0 | O56: =SUMIF('Cash Flow'!$E$13:$FS$13,O$50,'Cash Flow'!$E117:$FS117) -> 0 | P56: =SUMIF('Cash Flow'!$E$13:$FS$13,P$50,'Cash Flow'!$E117:$FS117) -> 0 | Q56: =SUMIF('Cash Flow'!$E$13:$FS$13,Q$50,'Cash Flow'!$E117:$FS117) -> 0 | ... S56: =SUMIF('Cash Flow'!$E$13:$FS$13,S$50,'Cash Flow'!$E117:$FS117) -> 0
F57: ="Net Cash Flow to the Venture " -> Net Cash Flow to the Venture | H57: =SUM(J57:S57) -> 24992810 | J57: =SUM(J51:J56) -> -18317976 | K57: =SUM(K51:K56) -> 967179.66 | L57: =SUM(L51:L56) -> 1345422.1 | M57: =SUM(M51:M56) -> 40998185 | N57: =SUM(N51:N56) -> 0 | O57: =SUM(O51:O56) -> 0 | P57: =SUM(P51:P56) -> 0 | Q57: =SUM(Q51:Q56) -> 0 | ... S57: =SUM(S51:S56) -> 0
F60: Levered IRR | H60: ='Cash Flow'!C120 -> 0.25455542
F61: Equity Multiple | H61: ='Cash Flow'!C121 -> 2.3245639
F62: Total Return on Equity | H62: =-H57/J57 -> 1.3643871
F63: Gross Profit | H63: ='Cash Flow'!C122 -> 24992810
F64: % Profit - Operating | H64: =H56/H57 -> 0.17806042
F65: % Profit - Capital Event | H65: =SUM(J51:S55)/H63 -> 0.82193958

Sheet P_L
B2: =+Detail!C6 -> Sentosa Epperson | P2: =+Detail!C7 -> Wesley Chapel, FL
B5: UNTRENDED STABILIZED OPERATING INCOME STATEMENT
E6: 0
E7: Annual | I7: Month
E8: Total | F8: Per Unit | G8: Per NRSF | I8: Total | J8: Per Unit | K8: Per NRSF
B9: MULTIFAMILY | D9: % of GPR
B10: Gross Potential Rent | E10: =+Detail!M67 -> 6601983.1 | F10: =+E10/Detail!$C$8 -> 22923.553 | G10: =+E10/Detail!$C$10 -> 22.455725 | I10: =E10/12 -> 550165.26 | J10: =+I10/Detail!$C$8 -> 1910.296 | K10: =+I10/Detail!$C$10 -> 1.8713104
B11: Loss to Lease | D11: =IFERROR(ABS(E11/E$10),0) -> 0.012750998 | E11: =Summary!G12 -> -84181.874 | F11: =+E11/Detail!$C$8 -> -292.29817 | G11: =+E11/Detail!$C$10 -> -0.2863329 | I11: =E11/12 -> -7015.1561 | J11: =+I11/Detail!$C$8 -> -24.358181 | K11: =+I11/Detail!$C$10 -> -0.023861075
B12: Vacancy | D12: =IFERROR(ABS(E12/E$10),0) -> 0.05 | E12: =-E10*Detail!F33 -> -330099.16 | F12: =+E12/Detail!$C$8 -> -1146.1776 | G12: =+E12/Detail!$C$10 -> -1.1227862 | I12: =E12/12 -> -27508.263 | J12: =+I12/Detail!$C$8 -> -95.514802 | K12: =+I12/Detail!$C$10 -> -0.09356552
B13: Gross Rental Income | D13: =IFERROR(ABS(E13/E$10),0) -> 0.937249 | E13: =SUM(E10:E12) -> 6187702.1 | F13: =SUM(F10:F12) -> 21485.077 | G13: =SUM(G10:G12) -> 21.046606 | I13: =E13/12 -> 515641.84 | J13: =SUM(J10:J12) -> 1790.4231 | K13: =SUM(K10:K12) -> 1.7538838
B14: Non-Income Unit Loss | D14: =IFERROR(ABS(E14/E$10),0) -> 0.0034722222 | E14: =-E10/Detail!C8 -> -22923.553 | F14: =+E14/Detail!$C$8 -> -79.595668 | G14: =+E14/Detail!$C$10 -> -0.077971267 | I14: =E14/12 -> -1910.296 | J14: =+I14/Detail!$C$8 -> -6.6329724 | K14: =+I14/Detail!$C$10 -> -0.0064976056
B15: Collection Loss | D15: =IFERROR(ABS(E15/E$10),0) -> 0.00937249 | E15: =-E13*Detail!F36 -> -61877.021 | F15: =+E15/Detail!$C$8 -> -214.85077 | G15: =+E15/Detail!$C$10 -> -0.21046606 | I15: =E15/12 -> -5156.4184 | J15: =+I15/Detail!$C$8 -> -17.904231 | K15: =+I15/Detail!$C$10 -> -0.017538838
B16: Concession Loss | D16: =IFERROR(ABS(E16/E$10),0) -> 0 | E16: 0 | F16: =+E16/Detail!$C$8 -> 0 | G16: =+E16/Detail!$C$10 -> 0 | I16: =E16/12 -> 0 | J16: =+I16/Detail!$C$8 -> 0 | K16: =+I16/Detail!$C$10 -> 0
B17: Amenity Income | D17: =IFERROR(ABS(E17/E$10),0) -> 0.014788284 | E17: =+Detail!M75 -> 97632 | F17: =+E17/Detail!$C$8 -> 339 | G17: =+E17/Detail!$C$10 -> 0.33208163 | I17: =E17/12 -> 8136 | J17: =+I17/Detail!$C$8 -> 28.25 | K17: =+I17/Detail!$C$10 -> 0.027673469
B18: Monthly Recurring Income | D18: =IFERROR(ABS(E18/E$10),0) -> 0.10429666 | E18: =+Detail!M83 -> 688564.8 | F18: =+E18/Detail!$C$8 -> 2390.85 | G18: =+E18/Detail!$C$10 -> 2.3420571 | I18: =E18/12 -> 57380.4 | J18: =+I18/Detail!$C$8 -> 199.2375 | K18: =+I18/Detail!$C$10 -> 0.19517143
B19: Other Income | D19: =IFERROR(ABS(E19/E$10),0) -> 0.0036643535 | E19: =+Detail!M85 -> 24192 | F19: =+E19/Detail!$C$8 -> 84 | G19: =+E19/Detail!$C$10 -> 0.082285714 | I19: =E19/12 -> 2016 | J19: =+I19/Detail!$C$8 -> 7 | K19: =+I19/Detail!$C$10 -> 0.0068571429
B20: Effective Gross Income | D20: =IFERROR(ABS(E20/E$10),0) -> 1.0471536 | E20: =SUM(E13:E19) -> 6913290.3 | F20: =SUM(F13:F19) -> 24004.48 | G20: =SUM(G13:G19) -> 23.514593 | I20: =SUM(I13:I19) -> 576107.53 | J20: =SUM(J13:J19) -> 2000.3734 | K20: =SUM(K13:K19) -> 1.9595494
D21: % of EGI
B22: Variable Expenses
B23: Payroll | D23: =IFERROR(ABS(E23/E$20),0) -> 0.069717743 | E23: =+Detail!M98 -> 481979 | F23: =+E23/Detail!$C$8 -> 1673.5382 | G23: =+E23/Detail!$C$10 -> 1.6393844 | I23: =E23/12 -> 40164.917 | J23: =+I23/Detail!$C$8 -> 139.46152 | K23: =+I23/Detail!$C$10 -> 0.13661536
B24: Utilities | D24: =IFERROR(ABS(E24/E$20),0) -> 0.080707884 | E24: =+Detail!M99 -> 557957.03 | F24: =+E24/Detail!$C$8 -> 1937.3508 | G24: =+E24/Detail!$C$10 -> 1.897813 | I24: =E24/12 -> 46496.419 | J24: =+I24/Detail!$C$8 -> 161.4459 | K24: =+I24/Detail!$C$10 -> 0.15815109
B25: Contract Services | D25: =IFERROR(ABS(E25/E$20),0) -> 0.0043597185 | E25: =+Detail!M100 -> 30140 | F25: =+E25/Detail!$C$8 -> 104.65278 | G25: =+E25/Detail!$C$10 -> 0.10251701 | I25: =E25/12 -> 2511.6667 | J25: =+I25/Detail!$C$8 -> 8.7210648 | K25: =+I25/Detail!$C$10 -> 0.0085430839
B26: Maintenance | D26: =IFERROR(ABS(E26/E$20),0) -> 0.021955537 | E26: =+Detail!M101 -> 151785 | F26: =+E26/Detail!$C$8 -> 527.03125 | G26: =+E26/Detail!$C$10 -> 0.51627551 | I26: =E26/12 -> 12648.75 | J26: =+I26/Detail!$C$8 -> 43.919271 | K26: =+I26/Detail!$C$10 -> 0.043022959
B27: Administrative | D27: =IFERROR(ABS(E27/E$20),0) -> 0.023761334 | E27: =+Detail!M102 -> 164269 | F27: =+E27/Detail!$C$8 -> 570.37847 | G27: =+E27/Detail!$C$10 -> 0.5587381 | I27: =E27/12 -> 13689.083 | J27: =+I27/Detail!$C$8 -> 47.531539 | K27: =+I27/Detail!$C$10 -> 0.046561508
B28: Turnover | D28: =IFERROR(ABS(E28/E$20),0) -> 0.0074986002 | E28: =+Detail!M103 -> 51840 | F28: =+E28/Detail!$C$8 -> 180 | G28: =+E28/Detail!$C$10 -> 0.17632653 | I28: =E28/12 -> 4320 | J28: =+I28/Detail!$C$8 -> 15 | K28: =+I28/Detail!$C$10 -> 0.014693878
B29: Marketing | D29: =IFERROR(ABS(E29/E$20),0) -> 0.019787973 | E29: =+Detail!M104 -> 136800 | F29: =+E29/Detail!$C$8 -> 475 | G29: =+E29/Detail!$C$10 -> 0.46530612 | I29: =E29/12 -> 11400 | J29: =+I29/Detail!$C$8 -> 39.583333 | K29: =+I29/Detail!$C$10 -> 0.03877551
B30: Fixed Expenses
B31: Management Expense | D31: =IFERROR(ABS(E31/E$20),0) -> 0.0275 | E31: =+Detail!M107 -> 190115.48 | F31: =+E31/Detail!$C$8 -> 660.12321 | G31: =+E31/Detail!$C$10 -> 0.64665131 | I31: =E31/12 -> 15842.957 | J31: =+I31/Detail!$C$8 -> 55.010267 | K31: =+I31/Detail!$C$10 -> 0.053887609
B32: HOA | D32: =IFERROR(ABS(E32/E$20),0) -> 0.002119396 | E32: =+Detail!M108 -> 14652 | F32: =+E32/Detail!$C$8 -> 50.875 | G32: =+E32/Detail!$C$10 -> 0.049836735 | I32: =E32/12 -> 1221 | J32: =+I32/Detail!$C$8 -> 4.2395833 | K32: =+I32/Detail!$C$10 -> 0.0041530612
B33: Insurance | D33: =IFERROR(ABS(E33/E$20),0) -> 0.043741834 | E33: =+Detail!M109 -> 302400 | F33: =+E33/Detail!$C$8 -> 1050 | G33: =+E33/Detail!$C$10 -> 1.0285714 | I33: =E33/12 -> 25200 | J33: =+I33/Detail!$C$8 -> 87.5 | K33: =+I33/Detail!$C$10 -> 0.085714286
B34: Taxes | D34: =IFERROR(ABS(E34/E$20),0) -> 0.10460965 | E34: =+Detail!M110 -> 723196.89 | F34: =+E34/Detail!$C$8 -> 2511.1003 | G34: =+E34/Detail!$C$10 -> 2.4598534 | I34: =E34/12 -> 60266.408 | J34: =+I34/Detail!$C$8 -> 209.25836 | K34: =+I34/Detail!$C$10 -> 0.20498778
B35: Capital Reserves | D35: =IFERROR(ABS(E35/E$20),0) -> 0.008331778 | E35: =+Detail!M112 -> 57600 | F35: =+E35/Detail!$C$8 -> 200 | G35: =+E35/Detail!$C$10 -> 0.19591837 | I35: =E35/12 -> 4800 | J35: =+I35/Detail!$C$8 -> 16.666667 | K35: =+I35/Detail!$C$10 -> 0.016326531
B36: Total Operating Expenses | D36: =IFERROR(ABS(E36/E$20),0) -> 0.41409145 | E36: =SUM(E23:E35) -> 2862734.4 | F36: =SUM(F23:F35) -> 9940.05 | G36: =SUM(G23:G35) -> 9.7371919 | I36: =SUM(I23:I35) -> 238561.2 | J36: =SUM(J23:J35) -> 828.3375 | K36: =SUM(K23:K35) -> 0.81143265
B38: Multifamily NOI | D38: =IFERROR(ABS(E38/E$20),0) -> 0.58590855 | E38: =E20-E36 -> 4050555.9 | F38: =F20-F36 -> 14064.43 | G38: =G20-G36 -> 13.777401 | I38: =I20-I36 -> 337546.33 | J38: =J20-J36 -> 1172.0359 | K38: =K20-K36 -> 1.1481168
E40: =+E38-Summary!G38 -> 0

Sheet Detail
B2: =+Detail!C6 -> Sentosa Epperson | M2: =+P_L!P2 -> Wesley Chapel, FL
B5: PROGRAM | G5: TIMING | H5: Month # | I5: Date | K5: RETURN METRICS
B6: Project | C6: Sentosa Epperson | G6: Lease-up | H6: 0 | I6: 46174 | K6: IRR | M6: ='Cash Flow'!C120 -> 0.25455542
B7: City, State | C7: Wesley Chapel, FL | D7: Parking (Stalls) | G7: Acquisition | H7: 0 | I7: =+EOMONTH($I$6,H7) -> 46203 | K7: Multiple | M7: ='Cash Flow'!C121 -> 2.3245639
B8: Units | C8: =+Detail!D67 -> 288 | D8: Apartments | E8: 434 | G8: Refinance | H8: 47 | I8: =+EOMONTH($I$6,H8) -> 47634 | K8: Profit | M8: ='Cash Flow'!C122 -> 24992810
B9: Average NRSF/Unit | C9: =+Detail!F67 -> 1020.8333 | D9: Commercial | E9: 0 | G9: Disposition | H9: 47 | I9: =+EOMONTH($I$6,H9) -> 47634 | K9: Equity Investment | M9: =-C22 -> -18929066
B10: NRSF (Apts) | C10: =+Detail!G67 -> 294000 | D10: Total Stalls | E10: =SUM(E8:E9) -> 434
B11: NRSF (Coml) | C11: 0 | D11: Resi Ratio | E11: =E8/C8 -> 1.5069444
B12: NRSF (Total) | C12: =SUM(C10:C11) -> 294000 | D12: Comm. Ratio | E12: 0/1,000
B13: GSF (Total) | C13: =C12*1.15 -> 338100 | D13: Land (Gross Acres) | E13: 12
B14: Efficiency | C14: =C12/C13 -> 0.86956522 | D14: Land GSF | E14: =E13*43560 -> 522720
B15: Property Type | C15: Garden | D15: Land (Net Acres) | E15: 24
B16: Buildings | C16: 8 | D16: Land NSF | E16: =E15*43560 -> 1045440
B17: Stories | C17: 3 & 4 Stories | D17: Density (Units) | E17: =C8/E15 -> 12
B18: Constr. Type | C18: Type V | D18: FAR | E18: =C13/(E15*43560) -> 0.3234045
B20: CAPITALIZATION | C20: Equity | D20: Acquisition Loan | E20: Refinance | G20: ACQUISITION SUMMARY | K20: SALE SUMMARY
E21: NO | H21: Total | I21: $ / Unit | L21: Total | M21: $ / Unit
B22: Amount | C22: =$H$28*C23 -> 18929066 | D22: 52100000 | E22: =IF(E21="YES", -PV(E26/12, E27*12, (INDEX('Cash Flow'!$E$17:$FS$76, ROWS('Cash Flow'!$E$17:$E$76), MATCH(E25,'Cash Flow'!$E$17:$FS$17, 0))*12)/12/E29), 0) -> 0 | G22: Stabilized NOI | H22: =P_L!E38 -> 4050555.9 | I22: =H22/$D$67 -> 14064.43 | K22: SALE NOI | L22: =SUMIF('Cash Flow'!$E$17:$FS$17,$H$9,'Cash Flow'!$E$76:$FS$76)*12 -> 4636539.1 | M22: =L22/$D$67 -> 16099.094
B23: % of Total Cost | C23: =1-D23 -> 0.26649747 | D23: =D22/H28 -> 0.73350253 | K23: Cap Rate | L23: =M38 -> 0.05
B24: % of Equity | G24: Cap Rate | H24: =H22/H25 -> 0.057026737 | K24: Sale Price | L24: =L22/L23 -> 92730781 | M24: =L24/$D$67 -> 321981.88
B25: First Draw | D25: =+H7 -> 0 | E25: =H8 -> 47 | G25: Purchase Price | H25: 71029066 | I25: =H25/$D$67 -> 246628.7
B26: Interest Rate | D26: =3%+2.75% -> 0.0575 | E26: 0.05 | K26: Closing Costs | L26: =-L24*M39 -> -1159134.8 | M26: =L26/$D$67 -> -4024.7735
B27: Amortization (Yrs) | D27: 30 | E27: 30 | G27: Closing Costs | H27: =H25*L39 -> 0 | I27: =H27/$D$67 -> 0 | K27: Net Sale Proceeds | L27: =L24+L26 -> 91571646 | M27: =L27/$D$67 -> 317957.11
B28: Interest Only (Mts) | D28: 36 | E28: 12 | G28: Total Costs | H28: =H27+H25 -> 71029066 | I28: =H28/$D$67 -> 246628.7
B29: DSCR | D29: 1.1 | E29: 1.25
B30: 0.015 | E30: =IFERROR(-E22*B30, 0) -> 0
B32: GENERAL OPERATIONS
B33: General/Static Vacancy | F33: 0.05 | G33: Per Year | I33: Total Units | M33: =D67 -> 288
B34: Stabilized Occupancy | F34: =100%-$F$33 -> 0.95 | G34: Per Year | I34: Non-Income Units | M34: 1
B35: Turnover Rate | F35: 0.5 | G35: Per Year | I35: Rentable Units | M35: =M33-M34 -> 287
B36: Collection Loss | F36: 0.01 | G36: Per Year
B37: See Growth Rate Assumptions at bottom of tab for trending operation line items | I37: Purchase Price Cap Rate | M37: =H24 -> 0.057026737
I38: Residual Cap Rate | M38: 0.05
B39: Growth Rates commence at the start of building operations | I39: Closing Costs (Acq / Exit) | L39: 0 | M39: 0.0125
B41: MULTIFAMILY INCOME
B43: Unit Income
B45: Unit Type | D45: Quantity | G45: Total | H45: Base Rent / | I45: Base Rent / | J45: Base Rent / | K45: Base Rent | L45: Total Base
B46: BR / BA | C46: Description | D46: of Units | E46: Unit Mix | F46: NRSF / Unit | G46: NRSF | H46: Unit / Month | I46: / NRSF / Month | J46: Unit / Year | K46: / NRSF / Year | L46: Rent / Month | M46: Rent / Year
B47: 1 Bedroom/1 Bath | C47: A2 | D47: 66 | E47: =+D47/$D$67 -> 0.22916667 | F47: 813 | G47: =+F47*D47 -> 53658 | H47: 1706.88 | I47: =+H47/F47 -> 2.0994834 | J47: =+H47*12 -> 20482.56 | K47: =+M47/G47 -> 25.193801 | L47: =+H47*D47 -> 112654.08 | M47: =+J47*D47 -> 1351849
B48: 1 Bedroom/1 Bath | C48: A2S | D48: 66 | E48: =+D48/$D$67 -> 0.22916667 | F48: 886 | G48: =+F48*D48 -> 58476 | H48: 1679.67 | I48: =+H48/F48 -> 1.8957901 | J48: =+H48*12 -> 20156.04 | K48: =+M48/G48 -> 22.749481 | L48: =+H48*D48 -> 110858.22 | M48: =+J48*D48 -> 1330298.6
B49: 2 Bedroom/2 Bath | C49: B1 | D49: 66 | E49: =+D49/$D$67 -> 0.22916667 | F49: 1107 | G49: =+F49*D49 -> 73062 | H49: 2071.09 | I49: =+H49/F49 -> 1.8709033 | J49: =+H49*12 -> 24853.08 | K49: =+M49/G49 -> 22.45084 | L49: =+H49*D49 -> 136691.94 | M49: =+J49*D49 -> 1640303.3
B50: 2 Bedroom/2 Bath | C50: B1S | D50: 66 | E50: =+D50/$D$67 -> 0.22916667 | F50: 1180 | G50: =+F50*D50 -> 77880 | H50: 2000.53 | I50: =+H50/F50 -> 1.6953644 | J50: =+H50*12 -> 24006.36 | K50: =+M50/G50 -> 20.344373 | L50: =+H50*D50 -> 132034.98 | M50: =+J50*D50 -> 1584419.8
B51: 3 Bedroom/2 Bath | C51: C1 | D51: 12 | E51: =+D51/$D$67 -> 0.041666667 | F51: 1253 | G51: =+F51*D51 -> 15036 | H51: 2450.5 | I51: =+H51/F51 -> 1.9557063 | J51: =+H51*12 -> 29406 | K51: =+M51/G51 -> 23.468476 | L51: =+H51*D51 -> 29406 | M51: =+J51*D51 -> 352872
B52: 3 Bedroom/2 Bath | C52: C1S | D52: 12 | E52: =+D52/$D$67 -> 0.041666667 | F52: 1324 | G52: =+F52*D52 -> 15888 | H52: 2376.67 | I52: =+H52/F52 -> 1.795068 | J52: =+H52*12 -> 28520.04 | K52: =+M52/G52 -> 21.540816 | L52: =+H52*D52 -> 28520.04 | M52: =+J52*D52 -> 342240.48
D53: 0 | E53: =+D53/$D$67 -> 0 | G53: =+F53*D53 -> 0 | J53: =+H53*12 -> 0 | L53: =+H53*D53 -> 0 | M53: =+J53*D53 -> 0
D54: 0 | E54: =+D54/$D$67 -> 0 | G54: =+F54*D54 -> 0 | J54: =+H54*12 -> 0 | L54: =+H54*D54 -> 0 | M54: =+J54*D54 -> 0
D55: 0 | E55: =+D55/$D$67 -> 0 | G55: =+F55*D55 -> 0 | J55: =+H55*12 -> 0 | L55: =+H55*D55 -> 0 | M55: =+J55*D55 -> 0
D56: 0 | E56: =+D56/$D$67 -> 0 | G56: =+F56*D56 -> 0 | J56: =+H56*12 -> 0 | L56: =+H56*D56 -> 0 | M56: =+J56*D56 -> 0
D57: 0 | E57: =+D57/$D$67 -> 0 | G57: =+F57*D57 -> 0 | J57: =+H57*12 -> 0 | L57: =+H57*D57 -> 0 | M57: =+J57*D57 -> 0
E58: =+D58/$D$67 -> 0 | G58: =+F58*D58 -> 0 | J58: =+H58*12 -> 0 | L58: =+H58*D58 -> 0 | M58: =+J58*D58 -> 0
E59: =+D59/$D$67 -> 0 | G59: =+F59*D59 -> 0 | J59: =+H59*12 -> 0 | L59: =+H59*D59 -> 0 | M59: =+J59*D59 -> 0
E60: =+D60/$D$67 -> 0 | G60: =+F60*D60 -> 0 | J60: =+H60*12 -> 0 | L60: =+H60*D60 -> 0 | M60: =+J60*D60 -> 0
E61: =+D61/$D$67 -> 0 | G61: =+F61*D61 -> 0 | J61: =+H61*12 -> 0 | L61: =+H61*D61 -> 0 | M61: =+J61*D61 -> 0
B62: 0 | C62: 0 | D62: 0 | E62: 0 | F62: 0 | G62: 0 | H62: 0 | I62: 0 | J62: 0 | K62: 0 | L62: 0 | M62: 0
B63: 0 | C63: 0 | D63: 0 | E63: 0 | F63: 0 | G63: 0 | H63: 0 | I63: 0 | J63: 0 | K63: 0 | L63: 0 | M63: 0
B64: 0 | C64: 0 | D64: 0 | E64: 0 | F64: 0 | G64: 0 | H64: 0 | I64: 0 | J64: 0 | K64: 0 | L64: 0 | M64: 0
B65: 0 | C65: 0 | D65: 0 | E65: 0 | F65: 0 | G65: 0 | H65: 0 | I65: 0 | J65: 0 | K65: 0 | L65: 0 | M65: 0
B66: 0 | C66: 0 | D66: 0 | E66: 0 | F66: 0 | G66: 0 | H66: 0 | I66: 0 | J66: 0 | K66: 0 | L66: 0 | M66: 0
B67: Unit Income Average / Total | D67: =SUM(D47:D66) -> 288 | E67: =SUM(E47:E66) -> 1 | F67: =+G67/D67 -> 1020.8333 | G67: =SUM(G47:G66) -> 294000 | H67: =SUMPRODUCT(H47:H66,D47:D66)/D67 -> 1910.296 | I67: =+H67/F67 -> 1.8713104 | J67: =+H67*12 -> 22923.553 | K67: =SUMPRODUCT(K47:K66,G47:G66)/G67 -> 22.455725 | L67: =SUM(L47:L66) -> 550165.26 | M67: =SUM(M47:M66) -> 6601983.1
B69: Additional Income
B70: Type | D70: Quantity | E70: % of Units | F70: Rent / Month | H70: Rent / Unit / Month | I70: Rent / NRSF / Month | J70: Rent / Unit / Year | K70: Rent / NRSF / Year | L70: Total / Month | M70: Total / Year
B71: Pet Rent | D71: =+D67*30% -> 86.4 | E71: =+D71/$D$67 -> 0.3 | F71: 27.5 | H71: =+E71*F71 -> 8.25 | I71: =IFERROR(F71*E71/$F$67, 0) -> 0.0080816327 | J71: =+H71*12 -> 99 | K71: =+I71*12 -> 0.096979592 | L71: =+D71*F71 -> 2376 | M71: =+L71*12 -> 28512
B72: Garage | D72: 32 | E72: =+D72/$D$67 -> 0.11111111 | F72: =150*0.95 -> 142.5 | H72: =+E72*F72 -> 15.833333 | I72: =IFERROR(F72*E72/$F$67, 0) -> 0.015510204 | J72: =+H72*12 -> 190 | K72: =+I72*12 -> 0.18612245 | L72: =+D72*F72 -> 4560 | M72: =+L72*12 -> 54720
B73: Storage | D73: 24 | E73: =+D73/$D$67 -> 0.083333333 | F73: 50 | H73: =+E73*F73 -> 4.1666667 | I73: =IFERROR(F73*E73/$F$67, 0) -> 0.0040816327 | J73: =+H73*12 -> 50 | K73: =+I73*12 -> 0.048979592 | L73: =+D73*F73 -> 1200 | M73: =+L73*12 -> 14400
B74: Amenity Fee | D74: =+D67 -> 288 | E74: =+D74/$D$67 -> 1 | F74: 0 | H74: =+E74*F74 -> 0 | I74: =IFERROR(F74*E74/$F$67, 0) -> 0 | J74: =+H74*12 -> 0 | K74: =+I74*12 -> 0 | L74: =+D74*F74 -> 0 | M74: =+L74*12 -> 0
B75: Amenity Subtotal | H75: =SUM(H71:H74) -> 28.25 | I75: =SUM(I71:I74) -> 0.027673469 | J75: =SUM(J71:J74) -> 339 | K75: =SUM(K71:K74) -> 0.33208163 | L75: =SUM(L71:L74) -> 8136 | M75: =SUM(M71:M74) -> 97632
B77: Utilities | D77: =+D67 -> 288 | E77: =+D77/$D$67 -> 1 | F77: 65 | H77: =+E77*F77 -> 65 | I77: =IFERROR(F77*E77/$F$67, 0) -> 0.063673469 | J77: =+H77*12 -> 780 | K77: =+I77*12 -> 0.76408163 | L77: =+D77*F77 -> 18720 | M77: =+L77*12 -> 224640
B78: Revenue Sharing Contract | D78: =+D67*F34 -> 273.6 | E78: =+D78/$D$67 -> 0.95 | F78: 85 | H78: =+E78*F78 -> 80.75 | I78: =IFERROR(F78*E78/$F$67, 0) -> 0.079102041 | J78: =+H78*12 -> 969 | K78: =+I78*12 -> 0.94922449 | L78: =+D78*F78 -> 23256 | M78: =+L78*12 -> 279072
B79: Valet Trash | D79: =+D67*F34 -> 273.6 | E79: =+D79/$D$67 -> 0.95 | F79: 30 | H79: =+E79*F79 -> 28.5 | I79: =IFERROR(F79*E79/$F$67, 0) -> 0.027918367 | J79: =+H79*12 -> 342 | K79: =+I79*12 -> 0.33502041 | L79: =+D79*F79 -> 8208 | M79: =+L79*12 -> 98496
B80: Admin/App | D80: =+D67*65% -> 187.2 | E80: =+D80/$D$67 -> 0.65 | F80: 27 | H80: =+E80*F80 -> 17.55 | I80: =IFERROR(F80*E80/$F$67, 0) -> 0.017191837 | J80: =+H80*12 -> 210.6 | K80: =+I80*12 -> 0.20630204 | L80: =+D80*F80 -> 5054.4 | M80: =+L80*12 -> 60652.8
B81: Late, NSF, Termination | D81: =+D67 -> 288 | E81: =+D81/$D$67 -> 1 | F81: 5 | H81: =+E81*F81 -> 5 | I81: =IFERROR(F81*E81/$F$67, 0) -> 0.0048979592 | J81: =+H81*12 -> 60 | K81: =+I81*12 -> 0.05877551 | L81: =+D81*F81 -> 1440 | M81: =+L81*12 -> 17280
B82: Damages | D82: =+D67 -> 288 | E82: =+D82/$D$67 -> 1 | F82: 2.4375 | H82: =+E82*F82 -> 2.4375 | I82: =IFERROR(F82*E82/$F$67, 0) -> 0.0023877551 | J82: =+H82*12 -> 29.25 | K82: =+I82*12 -> 0.028653061 | L82: =+D82*F82 -> 702 | M82: =+L82*12 -> 8424
B83: Monthly Recurring Subtotal | H83: =SUM(H77:H82) -> 199.2375 | I83: =SUM(I77:I82) -> 0.19517143 | J83: =SUM(J77:J82) -> 2390.85 | K83: =SUM(K77:K82) -> 2.3420571 | L83: =SUM(L77:L82) -> 57380.4 | M83: =SUM(M77:M82) -> 688564.8
B85: Other Income Subtotal | D85: =+D67 -> 288 | E85: =+D85/$D$67 -> 1 | F85: 7 | H85: =+E85*F85 -> 7 | I85: =IFERROR(F85*E85/$F$67, 0) -> 0.0068571429 | J85: =+H85*12 -> 84 | K85: =+I85*12 -> 0.082285714 | L85: =+D85*F85 -> 2016 | M85: =+L85*12 -> 24192
B87: Additional Income Total | H87: =SUM(H75,H83,H85) -> 234.4875 | I87: =SUM(I75,I83,I85) -> 0.22970204 | J87: =SUM(J75,J83,J85) -> 2813.85 | K87: =SUM(K75,K83,K85) -> 2.7564245 | L87: =SUM(L75,L83,L85) -> 67532.4 | M87: =SUM(M75,M83,M85) -> 810388.8
B89: Potential Multifamily Income Total | H89: =H67+H87 -> 2144.7835 | I89: =I67+I87 -> 2.1010124 | J89: =J67+J87 -> 25737.403 | K89: =K67+K87 -> 25.212149 | L89: =L67+L87 -> 617697.66 | M89: =M67+M87 -> 7412371.9
B94: OPERATING EXPENSES
B96: MULTIFAMILY OPEX
B97: Expense Items | H97: Expense / Unit / Month | I97: Expense / NRSF / Month | J97: Expense / Unit / Year | K97: Expense / NRSF / Year | L97: Total / Month | M97: Total / Year
B98: Payroll | H98: =J98/12 -> 139.46152 | I98: =+H98/Detail!$F$67 -> 0.13661536 | J98: =+M98/Detail!$D$67 -> 1673.5382 | K98: =+J98/Detail!$F$67 -> 1.6393844 | L98: =M98/12 -> 40164.917 | M98: 481979
B99: Utilities | H99: =J99/12 -> 161.4459 | I99: =+H99/Detail!$F$67 -> 0.15815109 | J99: 1937.3508 | K99: =+J99/Detail!$F$67 -> 1.897813 | L99: =M99/12 -> 46496.419 | M99: =J99*Detail!$D$67 -> 557957.03
B100: Contract Services | H100: =J100/12 -> 8.7210648 | I100: =+H100/Detail!$F$67 -> 0.0085430839 | J100: =+M100/Detail!$D$67 -> 104.65278 | K100: =+J100/Detail!$F$67 -> 0.10251701 | L100: =M100/12 -> 2511.6667 | M100: 30140
B101: Maintenance | H101: =J101/12 -> 43.919271 | I101: =+H101/Detail!$F$67 -> 0.043022959 | J101: 527.03125 | K101: =+J101/Detail!$F$67 -> 0.51627551 | L101: =M101/12 -> 12648.75 | M101: =J101*Detail!$D$67 -> 151785
B102: Administrative | H102: =J102/12 -> 47.531539 | I102: =+H102/Detail!$F$67 -> 0.046561508 | J102: 570.37847 | K102: =+J102/Detail!$F$67 -> 0.5587381 | L102: =M102/12 -> 13689.083 | M102: =J102*Detail!$D$67 -> 164269
B103: Turnover | H103: =J103/12 -> 15 | I103: =+H103/Detail!$F$67 -> 0.014693878 | J103: 180 | K103: =+J103/Detail!$F$67 -> 0.17632653 | L103: =M103/12 -> 4320 | M103: =J103*Detail!$D$67 -> 51840
B104: Marketing | H104: =J104/12 -> 39.583333 | I104: =+H104/Detail!$F$67 -> 0.03877551 | J104: 475 | K104: =+J104/Detail!$F$67 -> 0.46530612 | L104: =M104/12 -> 11400 | M104: =J104*Detail!$D$67 -> 136800
B105: Subtotal Variable | H105: =SUM(H98:H104) -> 455.66263 | I105: =SUM(I98:I104) -> 0.44636339 | J105: =SUM(J98:J104) -> 5467.9515 | K105: =SUM(K98:K104) -> 5.3563607 | L105: =SUM(L98:L104) -> 131230.84 | M105: =SUM(M98:M104) -> 1574770
B107: =L128 -> 0.0275 | H107: =J107/12 -> 55.010267 | I107: =+H107/Detail!$F$67 -> 0.053887609 | J107: =+M107/Detail!$D$67 -> 660.12321 | K107: =+J107/Detail!$F$67 -> 0.64665131 | L107: =M107/12 -> 15842.957 | M107: =M128 -> 190115.48
B108: HOA | H108: =J108/12 -> 4.2395833 | I108: =+H108/Detail!$F$67 -> 0.0041530612 | J108: =+M108/Detail!$D$67 -> 50.875 | K108: =+J108/Detail!$F$67 -> 0.049836735 | L108: =M108/12 -> 1221 | M108: 14652
B109: Insurance | H109: =J109/12 -> 87.5 | I109: =+H109/Detail!$F$67 -> 0.085714286 | J109: 1050 | K109: =+J109/Detail!$F$67 -> 1.0285714 | L109: =M109/12 -> 25200 | M109: =J109*Detail!$D$67 -> 302400
B110: Taxes | H110: =J110/12 -> 209.25836 | I110: =+H110/Detail!$F$67 -> 0.20498778 | J110: =+M110/Detail!$D$67 -> 2511.1003 | K110: =+J110/Detail!$F$67 -> 2.4598534 | L110: =M110/12 -> 60266.408 | M110: =M136 -> 723196.89
B111: Subtotal Fixed | H111: =SUM(H107:H110) -> 356.00821 | I111: =SUM(I107:I110) -> 0.34874274 | J111: =SUM(J107:J110) -> 4272.0985 | K111: =SUM(K107:K110) -> 4.1849128 | L111: =SUM(L107:L110) -> 102530.36 | M111: =SUM(M107:M110) -> 1230364.4
B112: Capital Reserves | H112: =J112/12 -> 16.666667 | I112: =+H112/Detail!$F$67 -> 0.016326531 | J112: 200 | K112: =+J112/Detail!$F$67 -> 0.19591837 | L112: =M112/12 -> 4800 | M112: =J112*Detail!$D$67 -> 57600
B113: Operating Expense Total | H113: =SUM(H112, H111, H105) -> 828.3375 | I113: =SUM(I112, I111, I105) -> 0.81143265 | J113: =SUM(J112, J111, J105) -> 9940.05 | K113: =SUM(K112, K111, K105) -> 9.7371919 | L113: =SUM(L112, L111, L105) -> 238561.2 | M113: =SUM(M112, M111, M105) -> 2862734.4
B115: PAYROLL - variable | K115: UTILITIES
B116: Staffing Schedule | F116: Base Salary | G116: Perf Bonus | H116: Leasing Comm | I116: Emp Burden | J116: Annual | K116: Items | L116: Annual | M116: Recapture
B117: Prop Manager | F117: 0 | G117: 0 | H117: 0 | I117: 0 | J117: =SUM(F117:I117) -> 0 | K117: W/S | L117: 0 | M117: 0
B118: Asst Manager | F118: 0 | G118: 0 | H118: 0 | I118: 0 | J118: =SUM(F118:I118) -> 0 | K118: Elec - Common | L118: 0 | M118: 0
B119: Leasing | F119: 0 | G119: 0 | H119: 0 | I119: 0 | J119: =SUM(F119:I119) -> 0 | K119: Vac Electric | L119: 0 | M119: 0
B120: Leasing | F120: 0 | G120: 0 | H120: 0 | I120: 0 | J120: =SUM(F120:I120) -> 0 | K120: TV/Internet | L120: 0 | M120: 0
...

Sheet Cash Flow
E1: 3 | F1: 10 | G1: 10 | H1: 15 | I1: 15 | J1: 25 | K1: 25 | L1: 25 | M1: 25 | N1: 33 | O1: 27 | P1: 27 | Q1: 15 | R1: 8 | S1: 5 | T1: 5 | U1: 15 | V1: 20 | W1: 20 | X1: 18
B2: MONTHLY | FT2: =Detail!C6 -> Sentosa Epperson
B4: Monthly Operating Cash Flow
B5: Stabilization Date: | C5: =C11 -> 46203 | D5: =EOMONTH(E5,-1) -> 46173 | E5: =EOMONTH(Detail!I6,0) -> 46203 | F5: =EOMONTH(E5,1) -> 46234 | G5: =EOMONTH(F5,1) -> 46265 | H5: =EOMONTH(G5,1) -> 46295 | I5: =EOMONTH(H5,1) -> 46326 | J5: =EOMONTH(I5,1) -> 46356 | K5: =EOMONTH(J5,1) -> 46387 | L5: =EOMONTH(K5,1) -> 46418 | M5: =EOMONTH(L5,1) -> 46446 | ... FS5: =EOMONTH(FR5,1) -> 51379 | FT5: =YEAR(E5) -> 2026 | FU5: =FT5+1 -> 2027 | FV5: =FU5+1 -> 2028 | FW5: =FV5+1 -> 2029 | FX5: =FW5+1 -> 2030
B6: Mapping | E6: =E7&"-"&E8 -> 6-2026 | F6: =F7&"-"&F8 -> 7-2026 | G6: =G7&"-"&G8 -> 8-2026 | H6: =H7&"-"&H8 -> 9-2026 | I6: =I7&"-"&I8 -> 10-2026 | J6: =J7&"-"&J8 -> 11-2026 | K6: =K7&"-"&K8 -> 12-2026 | L6: =L7&"-"&L8 -> 1-2027 | ... FS6: =FS7&"-"&FS8 -> 8-2040
B7: Mapping | E7: =MONTH(E5) -> 6 | F7: =MONTH(F5) -> 7 | G7: =MONTH(G5) -> 8 | H7: =MONTH(H5) -> 9 | I7: =MONTH(I5) -> 10 | J7: =MONTH(J5) -> 11 | K7: =MONTH(K5) -> 12 | L7: =MONTH(L5) -> 1 | ... FS7: =MONTH(FS5) -> 8
B8: Mapping | E8: =YEAR(E5) -> 2026 | F8: =YEAR(F5) -> 2026 | G8: =YEAR(G5) -> 2026 | H8: =YEAR(H5) -> 2026 | I8: =YEAR(I5) -> 2026 | J8: =YEAR(J5) -> 2026 | K8: =YEAR(K5) -> 2026 | L8: =YEAR(L5) -> 2027 | ... FS8: =YEAR(FS5) -> 2040
B9: Mapping | E9: =ROUNDUP(MONTH(E5)/3,0) -> 2 | F9: =ROUNDUP(MONTH(F5)/3,0) -> 3 | G9: =ROUNDUP(MONTH(G5)/3,0) -> 3 | H9: =ROUNDUP(MONTH(H5)/3,0) -> 3 | I9: =ROUNDUP(MONTH(I5)/3,0) -> 4 | J9: =ROUNDUP(MONTH(J5)/3,0) -> 4 | K9: =ROUNDUP(MONTH(K5)/3,0) -> 4 | L9: =ROUNDUP(MONTH(L5)/3,0) -> 1 | ... FS9: =ROUNDUP(MONTH(FS5)/3,0) -> 3
B10: Mapping | C10: {=INDEX(E10:FS10,MATCH(TRUE,E10:FS10<>"",0))} -> 0 | E10: =IF(E31>94%,E17,"") -> 0 | F10: =IF(F31>94%,F17,"") -> 1 | G10: =IF(G31>94%,G17,"") -> 2 | H10: =IF(H31>94%,H17,"") -> 3 | I10: =IF(I31>94%,I17,"") -> 4 | J10: =IF(J31>94%,J17,"") -> 5 | K10: =IF(K31>94%,K17,"") -> 6 | L10: =IF(L31>94%,L17,"") -> 7 | ... FS10: =IF(FS31>94%,FS17,"") -> 170
B11: Mapping | C11: {=INDEX(E11:FS11,MATCH(TRUE,E11:FS11<>"",0))} -> 46203 | E11: =IF(E31>94%,E5,"") -> 46203 | F11: =IF(F31>94%,F5,"") -> 46234 | G11: =IF(G31>94%,G5,"") -> 46265 | H11: =IF(H31>94%,H5,"") -> 46295 | I11: =IF(I31>94%,I5,"") -> 46326 | J11: =IF(J31>94%,J5,"") -> 46356 | K11: =IF(K31>94%,K5,"") -> 46387 | L11: =IF(L31>94%,L5,"") -> 46418 | ... FS11: =IF(FS31>94%,FS5,"") -> 51379
B12: Year | E12: =+IF(E17>=Detail!$H$7,'Cash Flow'!D12+1,0) -> 1 | F12: =+IF(F17>=Detail!$H$7,'Cash Flow'!E12+1,0) -> 2 | G12: =+IF(G17>=Detail!$H$7,'Cash Flow'!F12+1,0) -> 3 | H12: =+IF(H17>=Detail!$H$7,'Cash Flow'!G12+1,0) -> 4 | I12: =+IF(I17>=Detail!$H$7,'Cash Flow'!H12+1,0) -> 5 | J12: =+IF(J17>=Detail!$H$7,'Cash Flow'!I12+1,0) -> 6 | K12: =+IF(K17>=Detail!$H$7,'Cash Flow'!J12+1,0) -> 7 | L12: =+IF(L17>=Detail!$H$7,'Cash Flow'!K12+1,0) -> 8 | ... FS12: =+IF(FS17>=Detail!$H$7,'Cash Flow'!FR12+1,0) -> 171
E13: =+ROUNDUP(E12/12,0) -> 1 | F13: =+ROUNDUP(F12/12,0) -> 1 | G13: =+ROUNDUP(G12/12,0) -> 1 | H13: =+ROUNDUP(H12/12,0) -> 1 | I13: =+ROUNDUP(I12/12,0) -> 1 | J13: =+ROUNDUP(J12/12,0) -> 1 | K13: =+ROUNDUP(K12/12,0) -> 1 | L13: =+ROUNDUP(L12/12,0) -> 1 | ... FS13: =+ROUNDUP(FS12/12,0) -> 15
B14: Growth Rate:
B15: Growth Rate Timing: Monthly | E15: =+IF(E5<Detail!$M$141,0,'Cash Flow'!D15+1) -> 0 | F15: =+IF(F5<Detail!$M$141,0,'Cash Flow'!E15+1) -> 0 | G15: =+IF(G5<Detail!$M$141,0,'Cash Flow'!F15+1) -> 0 | H15: =+IF(H5<Detail!$M$141,0,'Cash Flow'!G15+1) -> 0 | I15: =+IF(I5<Detail!$M$141,0,'Cash Flow'!H15+1) -> 0 | J15: =+IF(J5<Detail!$M$141,0,'Cash Flow'!I15+1) -> 0 | K15: =+IF(K5<Detail!$M$141,0,'Cash Flow'!J15+1) -> 0 | L15: =+IF(L5<Detail!$M$141,0,'Cash Flow'!K15+1) -> 1 | ... FS15: =+IF(FS5<Detail!$M$141,0,'Cash Flow'!FR15+1) -> 164
B16: Growth Rate Timing: Yearly | E16: =+ROUNDUP(E15/12,0) -> 0 | F16: =+ROUNDUP(F15/12,0) -> 0 | G16: =+ROUNDUP(G15/12,0) -> 0 | H16: =+ROUNDUP(H15/12,0) -> 0 | I16: =+ROUNDUP(I15/12,0) -> 0 | J16: =+ROUNDUP(J15/12,0) -> 0 | K16: =+ROUNDUP(K15/12,0) -> 0 | L16: =+ROUNDUP(L15/12,0) -> 1 | ... FS16: =+ROUNDUP(FS15/12,0) -> 14
B17: Month | E17: 0 | F17: =E17+1 -> 1 | G17: =F17+1 -> 2 | H17: =G17+1 -> 3 | I17: =H17+1 -> 4 | J17: =I17+1 -> 5 | K17: =J17+1 -> 6 | L17: =K17+1 -> 7 | M17: =L17+1 -> 8 | ... FS17: =FR17+1 -> 170 | FT17: Yr 1 Total | FU17: Yr 2 Total | FV17: Yr 3 Total | FW17: Yr 4 Total | FX17: Yr 5 Total
B18: Lease Expirations | E18: =288/12 -> 24 | F18: =288/12 -> 24 | G18: =288/12 -> 24 | H18: =288/12 -> 24 | I18: =288/12 -> 24 | J18: =288/12 -> 24 | K18: =288/12 -> 24 | L18: =288/12 -> 24 | ... P18: =288/12 -> 24 | Q18: 15 | R18: 20 | S18: 25 | T18: 25 | U18: 25 | V18: 25 | W18: 25.040394 | X18: 22.285726 | Y18: 20.597371 | Z18: =M22+M21 -> 24 | AA18: =N22+N21 -> 24 | AB18: =O22+O21 -> 24 | AC18: =P22+P21 -> 24 | AD18: =Q22+Q21 -> 15 | AE18: =R22+R21 -> 20 | AF18: =S22+S21 -> 25 | AG18: =T22+T21 -> 25 | ... FS18: =FF22+FF21 -> 25
B19: Move Outs | C19: 0.4 | E19: =E18*$C$19 -> 9.6 | F19: =F18*$C$19 -> 9.6 | G19: =G18*$C$19 -> 9.6 | H19: =H18*$C$19 -> 9.6 | I19: =I18*$C$19 -> 9.6 | J19: =J18*$C$19 -> 9.6 | K19: =K18*$C$19 -> 9.6 | L19: =L18*$C$19 -> 9.6 | ... FS19: =FS18*$C$19 -> 10
B21: Renewals | E21: =E18-E19 -> 14.4 | F21: =F18-F19 -> 14.4 | G21: =G18-G19 -> 14.4 | H21: =H18-H19 -> 14.4 | I21: =I18-I19 -> 14.4 | J21: =J18-J19 -> 14.4 | K21: =K18-K19 -> 14.4 | L21: =L18-L19 -> 14.4 | ... FS21: =FS18-FS19 -> 15
B22: New Move-ins | E22: =E19 -> 9.6 | F22: =F19 -> 9.6 | G22: =G19 -> 9.6 | H22: =H19 -> 9.6 | I22: =I19 -> 9.6 | J22: =J19 -> 9.6 | K22: =K19 -> 9.6 | L22: =L19 -> 9.6 | ... FS22: =FS19 -> 10
B23: Occupied Units | E23: =Detail!C8*Detail!F34 -> 273.6 | F23: =F22+F21-F18+E23 -> 273.6 | G23: =G22+G21-G18+F23 -> 273.6 | H23: =H22+H21-H18+G23 -> 273.6 | I23: =I22+I21-I18+H23 -> 273.6 | J23: =J22+J21-J18+I23 -> 273.6 | K23: =K22+K21-K18+J23 -> 273.6 | L23: =L22+L21-L18+K23 -> 273.6 | M23: =M22+M21-M18+L23 -> 273.6 | ... FS23: =FS22+FS21-FS18+FR23 -> 273.6
B27: Market Rents | E27: =Detail!$H$67*E125 -> 1910.296 | F27: =Detail!$H$67*F125 -> 1910.296 | G27: =Detail!$H$67*G125 -> 1910.296 | H27: =Detail!$H$67*H125 -> 1910.296 | I27: =Detail!$H$67*I125 -> 1910.296 | J27: =Detail!$H$67*J125 -> 1910.296 | K27: =Detail!$H$67*K125 -> 1910.296 | L27: =Detail!$H$67*L125 -> 1915.0718 | ... FS27: =Detail!$H$67*FS125 -> 2876.9957
B28: Market Rents / SF | E28: =E27/Detail!$F$67 -> 1.8713104 | F28: =F27/Detail!$F$67 -> 1.8713104 | G28: =G27/Detail!$F$67 -> 1.8713104 | H28: =H27/Detail!$F$67 -> 1.8713104 | I28: =I27/Detail!$F$67 -> 1.8713104 | J28: =J27/Detail!$F$67 -> 1.8713104 | K28: =K27/Detail!$F$67 -> 1.8713104 | L28: =L27/Detail!$F$67 -> 1.8759887 | ... FS28: =FS27/Detail!$F$67 -> 2.8182815
B29: In-Place Rent | E29: =(E39+E40)/Detail!$C$8 -> 1887.4315 | F29: =(F39+F40)/Detail!$C$8 -> 1888.1936 | G29: =(G39+G40)/Detail!$C$8 -> 1888.9304 | H29: =(H39+H40)/Detail!$C$8 -> 1889.6425 | I29: =(I39+I40)/Detail!$C$8 -> 1890.331 | J29: =(J39+J40)/Detail!$C$8 -> 1890.9965 | K29: =(K39+K40)/Detail!$C$8 -> 1891.6398 | L29: =(L39+L40)/Detail!$C$8 -> 1892.6597 | ... FS29: =(FS39+FS40)/Detail!$C$8 -> 2854.4328
B30: Average In-Place Rent / SF | E30: =E29/Detail!$F$67 -> 1.8489124 | F30: =+F29/Detail!$F$67 -> 1.849659 | G30: =+G29/Detail!$F$67 -> 1.8503808 | H30: =+H29/Detail!$F$67 -> 1.8510784 | I30: =+I29/Detail!$F$67 -> 1.8517528 | J30: =+J29/Detail!$F$67 -> 1.8524047 | K30: =+K29/Detail!$F$67 -> 1.8530349 | L30: =+L29/Detail!$F$67 -> 1.854034 | M30: =+M29/Detail!$F$67 -> 1.8551566 | ... FS30: =+FS29/Detail!$F$67 -> 2.796179
B31: Occupancy | E31: =1+E41/(E39+E40) -> 0.94939429 | F31: =1+F41/(F39+F40) -> 0.94941472 | G31: =1+G41/(G39+G40) -> 0.94943445 | H31: =1+H41/(H39+H40) -> 0.94945351 | I31: =1+I41/(I39+I40) -> 0.94947192 | J31: =1+J41/(J39+J40) -> 0.9494897 | K31: =1+K41/(K39+K40) -> 0.94950688 | L31: =1+L41/(L39+L40) -> 0.94940792 | ... P31: =1+P41/(P39+P40) -> 0.9490429 | Q31: =Q23/Detail!$D$67 -> 0.95 | R31: =R23/Detail!$D$67 -> 0.95 | S31: =S23/Detail!$D$67 -> 0.95 | T31: =T23/Detail!$D$67 -> 0.95 | U31: =U23/Detail!$D$67 -> 0.95 | V31: =V23/Detail!$D$67 -> 0.95 | W31: =W23/Detail!$D$67 -> 0.95 | X31: =X23/Detail!$D$67 -> 0.95 | ... FS31: =FS23/Detail!$D$67 -> 0.95
B33: In-Place Revenue | E33: =Detail!L67*(1-Detail!F33) -> 522657 | F33: =SUM(E39:E41) -> 516072 | G33: =SUM(F39:F41) -> 516291.5 | H33: =SUM(G39:G41) -> 516503.68 | I33: =SUM(H39:H41) -> 516708.79 | J33: =SUM(I39:I41) -> 516907.06 | K33: =SUM(J39:J41) -> 517098.73 | L33: =SUM(K39:K41) -> 517284 | M33: =SUM(L39:L41) -> 517508.95 | ... FS33: =SUM(FR39:FR41) -> 778553.32
B34: New Leases | E34: 0 | F34: =F27*F22 -> 18338.842 | G34: =G27*G22 -> 18338.842 | H34: =H27*H22 -> 18338.842 | I34: =I27*I22 -> 18338.842 | J34: =J27*J22 -> 18338.842 | K34: =K27*K22 -> 18338.842 | L34: =L27*L22 -> 18384.689 | M34: =M27*M22 -> 18430.651 | ... P34: =P27*P22 -> 18569.227 | Q34: =Q27*(Q22+Q21) -> 29086.953 | R34: =R27*(R22+R21) -> 38879.56 | S34: =S27*(S22+S21) -> 48720.949 | T34: =T27*(T22+T21) -> 48842.751 | U34: =U27*(U22+U21) -> 48964.858 | V34: =V27*(V22+V21) -> 49087.27 | W34: =W27*(W22+W21) -> 49289.499 | X34: =X27*(X22+X21) -> 43976.88 | ... FS34: =FS27*(FS22+FS21) -> 71924.892
B35: Old Leases | E35: =-D29*E19 -> 0 | F35: =-E29*F19 -> -18119.342 | G35: =-F29*G19 -> -18126.659 | H35: =-G29*H19 -> -18133.731 | I35: =-H29*I19 -> -18140.568 | J35: =-I29*J19 -> -18147.178 | K35: =-J29*K19 -> -18153.566 | L35: =-K29*L19 -> -18159.742 | ... P35: =-O29*P19 -> -18206.028 | Q35: =-H29*Q18 -> -28344.638 | R35: =-I29*R18 -> -37806.62 | S35: =-J29*S18 -> -47274.912 | T35: =-K29*T18 -> -47290.995 | U35: =-L29*U18 -> -47316.492 | V35: =-M29*V18 -> -47345.143 | W35: =-N29*W18 -> -47453.403 | X35: =-O29*X18 -> -42264.016 | ... FS35: =-FJ29*FS18 -> -69830.314
B36: Total Rent Collected | E36: =SUM(E33:E35) -> 522657 | F36: =SUM(F33:F35) -> 516291.5 | G36: =SUM(G33:G35) -> 516503.68 | H36: =SUM(H33:H35) -> 516708.79 | I36: =SUM(I33:I35) -> 516907.06 | J36: =SUM(J33:J35) -> 517098.73 | K36: =SUM(K33:K35) -> 517284 | L36: =SUM(L33:L35) -> 517508.95 | ... FS36: =SUM(FS33:FS35) -> 780647.9
B38: Income | D38: 0
B39: Gross Potential Rent | E39: =+Detail!$D$67*'Cash Flow'!E27 -> 550165.26 | F39: =+Detail!$D$67*'Cash Flow'!F27 -> 550165.26 | G39: =+Detail!$D$67*'Cash Flow'!G27 -> 550165.26 | H39: =+Detail!$D$67*'Cash Flow'!H27 -> 550165.26 | I39: =+Detail!$D$67*'Cash Flow'!I27 -> 550165.26 | J39: =+Detail!$D$67*'Cash Flow'!J27 -> 550165.26 | K39: =+Detail!$D$67*'Cash Flow'!K27 -> 550165.26 | L39: =+Detail!$D$67*'Cash Flow'!L27 -> 551540.67 | ... FS39: =+Detail!$D$67*'Cash Flow'!FS27 -> 828574.75 | FT39: =SUMIFS($E39:$FS39,$E$8:$FS$8,FT$5) -> 3851156.8 | FU39: =SUMIFS($E39:$FS39,$E$8:$FS$8,FU$5) -> 6710254.9 | FV39: =SUMIFS($E39:$FS39,$E$8:$FS$8,FV$5) -> 6914353.8 | FW39: =SUMIFS($E39:$FS39,$E$8:$FS$8,FW$5) -> 7124660.5 | FX39: =SUMIFS($E39:$FS39,$E$8:$FS$8,FX$5) -> 7341363.8
B40: Loss to Lease | E40: -6585 | F40: =-(F39-F36+F41) -> -6365.5 | G40: =-(G39-G36+G41) -> -6153.3167 | H40: =-(H39-H36+H41) -> -5948.2061 | I40: =-(I39-I36+I41) -> -5749.9326 | J40: =-(J39-J36+J41) -> -5558.2682 | K40: =-(K39-K36+K41) -> -5372.9925 | L40: =-(L39-L36+L41) -> -6454.6882 | M40: =-(M39-M36+M41) -> -7503.4793 | ... FS40: =-(FS39-FS36+FS41) -> -6498.1173
B41: Vacancy | E41: =-(Detail!$D$67-'Cash Flow'!E23)*'Cash Flow'!E27 -> -27508.263 | F41: =-(Detail!$D$67-'Cash Flow'!F23)*'Cash Flow'!F27 -> -27508.263 | G41: =-(Detail!$D$67-'Cash Flow'!G23)*'Cash Flow'!G27 -> -27508.263 | H41: =-(Detail!$D$67-'Cash Flow'!H23)*'Cash Flow'!H27 -> -27508.263 | I41: =-(Detail!$D$67-'Cash Flow'!I23)*'Cash Flow'!I27 -> -27508.263 | J41: =-(Detail!$D$67-'Cash Flow'!J23)*'Cash Flow'!J27 -> -27508.263 | K41: =-(Detail!$D$67-'Cash Flow'!K23)*'Cash Flow'!K27 -> -27508.263 | L41: =-(Detail!$D$67-'Cash Flow'!L23)*'Cash Flow'!L27 -> -27577.034 | ... FS41: =-(Detail!$D$67-'Cash Flow'!FS23)*'Cash Flow'!FS27 -> -41428.738 | FT41: =SUMIFS($E41:$FS41,$E$8:$FS$8,FT$5) -> -192557.84 | FU41: =SUMIFS($E41:$FS41,$E$8:$FS$8,FU$5) -> -335512.75 | FV41: =SUMIFS($E41:$FS41,$E$8:$FS$8,FV$5) -> -345717.69 | FW41: =SUMIFS($E41:$FS41,$E$8:$FS$8,FW$5) -> -356233.02 | FX41: =SUMIFS($E41:$FS41,$E$8:$FS$8,FX$5) -> -367068.19
B42: Gross Schedued Rent | E42: =SUM(E39:E41) -> 516072 | F42: =SUM(F39:F41) -> 516291.5 | G42: =SUM(G39:G41) -> 516503.68 | H42: =SUM(H39:H41) -> 516708.79 | I42: =SUM(I39:I41) -> 516907.06 | J42: =SUM(J39:J41) -> 517098.73 | K42: =SUM(K39:K41) -> 517284 | L42: =SUM(L39:L41) -> 517508.95 | ... FS42: =SUM(FS39:FS41) -> 780647.9 | FT42: =SUMIFS($E42:$FS42,$E$8:$FS$8,FT$5) -> 3616865.8 | FU42: =SUMIFS($E42:$FS42,$E$8:$FS$8,FU$5) -> 6257155.6 | FV42: =SUMIFS($E42:$FS42,$E$8:$FS$8,FV$5) -> 6486654.9 | FW42: =SUMIFS($E42:$FS42,$E$8:$FS$8,FW$5) -> 6727274.4 | FX42: =SUMIFS($E42:$FS42,$E$8:$FS$8,FX$5) -> 6926597.8
B43: Bad Debt / Credit Loss | E43: =-E42*Detail!$F$36 -> -5160.72 | F43: =-F42*Detail!$F$36 -> -5162.915 | G43: =-G42*Detail!$F$36 -> -5165.0368 | H43: =-H42*Detail!$F$36 -> -5167.0879 | I43: =-I42*Detail!$F$36 -> -5169.0706 | J43: =-J42*Detail!$F$36 -> -5170.9873 | K43: =-K42*Detail!$F$36 -> -5172.84 | L43: =-L42*Detail!$F$36 -> -5175.0895 | ... FS43: =-FS42*Detail!$F$36 -> -7806.479 | FT43: =SUMIFS($E43:$FS43,$E$8:$FS$8,FT$5) -> -36168.658 | FU43: =SUMIFS($E43:$FS43,$E$8:$FS$8,FU$5) -> -62571.556 | FV43: =SUMIFS($E43:$FS43,$E$8:$FS$8,FV$5) -> -64866.549 | FW43: =SUMIFS($E43:$FS43,$E$8:$FS$8,FW$5) -> -67272.744 | FX43: =SUMIFS($E43:$FS43,$E$8:$FS$8,FX$5) -> -69265.978
B44: Concessions | E44: =-E22*E27*1.5 -> -27508.263 | F44: =-F22*F27*1.5 -> -27508.263 | G44: =-G22*G27*1.5 -> -27508.263 | H44: =-H22*H27*2 -> -36677.684 | I44: =-I22*I27*2 -> -36677.684 | J44: =-J22*J27*2 -> -36677.684 | K44: =-K22*K27*2 -> -36677.684 | L44: =-L22*L27*2 -> -36769.378 | M44: =-M22*M27*2 -> -36861.302 | N44: =-N22*N27*2 -> -36953.455 | O44: =-O22*O27*2 -> -37045.839 | P44: =-P22*P27*2 -> -37138.453 | Q44: =-Q22*Q27*1.5 -> -17452.172 | R44: =-R22*R27*1.5 -> -23327.736 | S44: =-S22*S27*1.5 -> -29232.569 | T44: =-T22*T27*1.5 -> -29305.651 | U44: =-U22*U27*1 -> -19585.943 | V44: =-V22*V27*1 -> -19634.908 | W44: =-W22*W27*1 -> -19715.8 | X44: 0 | Y44: =IF(Y31>=95%,0,(-Y27*$FZ$44)*Y22) -> 0 | Z44: =IF(Z31>=95%,0,(-Z27*$FZ$44)*Z22) -> 0 | AA44: =IF(AA31>=95%,0,(-AA27*$FZ$44)*AA22) -> 0 | AB44: =IF(AB31>=95%,0,(-AB27*$FZ$44)*AB22) -> 0 | AC44: =IF(AC31>=95%,0,(-AC27*$FZ$44)*AC22) -> 0 | AD44: =IF(AD31>=95%,0,(-AD27*$FZ$44)*AD22) -> 0 | AE44: =IF(AE31>=95%,0,(-AE27*$FZ$44)*AE22) -> 0 | AF44: =IF(AF31>=95%,0,(-AF27*$FZ$44)*AF22) -> 0 | ... FS44: =IF(FS31>=95%,0,(-FS27*$FZ$44)*FS22) -> 0 | FT44: =SUMIFS($E44:$FS44,$E$8:$FS$8,FT$5) -> -229235.53 | FU44: =SUMIFS($E44:$FS44,$E$8:$FS$8,FU$5) -> -343023.2 | FV44: =SUMIFS($E44:$FS44,$E$8:$FS$8,FV$5) -> 0 | FW44: =SUMIFS($E44:$FS44,$E$8:$FS$8,FW$5) -> 0 | FX44: =SUMIFS($E44:$FS44,$E$8:$FS$8,FX$5) -> 0 | FZ44: 2 | GA44: Concessions / month
B45: Total Collected Rent | E45: =SUM(E42:E44) -> 483403.01 | F45: =SUM(F42:F44) -> 483620.32 | G45: =SUM(G42:G44) -> 483830.38 | H45: =SUM(H42:H44) -> 474864.02 | I45: =SUM(I42:I44) -> 475060.31 | J45: =SUM(J42:J44) -> 475250.06 | K45: =SUM(K42:K44) -> 475433.48 | L45: =SUM(L42:L44) -> 475564.48 | ... FS45: =SUM(FS42:FS44) -> 772841.42 | FT45: =SUMIFS($E45:$FS45,$E$8:$FS$8,FT$5) -> 3351461.6 | FU45: =SUMIFS($E45:$FS45,$E$8:$FS$8,FU$5) -> 5851560.8 | FV45: =SUMIFS($E45:$FS45,$E$8:$FS$8,FV$5) -> 6421788.4 | FW45: =SUMIFS($E45:$FS45,$E$8:$FS$8,FW$5) -> 6660001.7 | FX45: =SUMIFS($E45:$FS45,$E$8:$FS$8,FX$5) -> 6857331.8
B46: Commercial Income | E46: 0 | F46: 0 | G46: 0 | H46: 0 | I46: 0 | J46: 0 | K46: 0 | L46: 0 | M46: 0 | N46: 0 | O46: 0 | P46: 0 | Q46: 0 | R46: 0 | S46: 0 | T46: 0 | U46: 0 | V46: 0 | W46: 0 | X46: 0 | Y46: 0 | Z46: 0 | AA46: 0 | AB46: 0 | AC46: 0 | AD46: 0 | AE46: 0 | AF46: 0 | AG46: 0 | AH46: 0 | AI46: 0 | AJ46: 0 | AK46: 0 | AL46: 0 | AM46: 0 | AN46: 0 | AO46: 0 | AP46: 0 | AQ46: 0 | AR46: 0 | AS46: 0 | AT46: 0 | AU46: 0 | AV46: 0 | AW46: 0 | AX46: 0 | AY46: 0 | AZ46: 0 | BA46: 0 | BB46: 0 | BC46: 0 | BD46: 0 | BE46: 0 | BF46: 0 | BG46: 0 | BH46: 0 | BI46: 0 | BJ46: 0 | BK46: 0 | BL46: 0 | BM46: 0 | BN46: 0 | BO46: 0 | BP46: 0 | BQ46: 0 | BR46: 0 | BS46: 0 | BT46: 0 | BU46: 0 | BV46: 0 | BW46: 0 | BX46: 0 | BY46: 0 | BZ46: 0 | CA46: 0 | CB46: 0 | CC46: 0 | CD46: 0 | CE46: 0 | CF46: 0 | CG46: 0 | CH46: 0 | CI46: 0 | CJ46: 0 | CK46: 0 | CL46: 0 | CM46: 0 | CN46: 0 | CO46: 0 | CP46: 0 | CQ46: 0 | CR46: 0 | CS46: 0 | CT46: 0 | CU46: 0 | CV46: 0 | CW46: 0 | CX46: 0 | CY46: 0 | CZ46: 0 | DA46: 0 | DB46: 0 | DC46: 0 | DD46: 0 | DE46: 0 | DF46: 0 | DG46: 0 | DH46: 0 | DI46: 0 | DJ46: 0 | DK46: 0 | DL46: 0 | DM46: 0 | DN46: 0 | DO46: 0 | DP46: 0 | DQ46: 0 | DR46: 0 | DS46: 0 | DT46: 0 | DU46: 0 | DV46: 0 | DW46: 0 | DX46: 0 | DY46: 0 | DZ46: 0 | EA46: 0 | EB46: 0 | EC46: 0 | ED46: 0 | EE46: 0 | EF46: 0 | EG46: 0 | EH46: 0 | EI46: 0 | EJ46: 0 | EK46: 0 | EL46: 0 | EM46: 0 | EN46: 0 | EO46: 0 | EP46: 0 | EQ46: 0 | ER46: 0 | ES46: 0 | ET46: 0 | EU46: 0 | EV46: 0 | EW46: 0 | EX46: 0 | EY46: 0 | EZ46: 0 | FA46: 0 | FB46: 0 | FC46: 0 | FD46: 0 | FE46: 0 | FF46: 0 | FG46: 0 | FH46: 0 | FI46: 0 | FJ46: 0 | FK46: 0 | FL46: 0 | FM46: 0 | FN46: 0 | FO46: 0 | FP46: 0 | FQ46: 0 | FR46: 0 | FS46: 0 | FT46: =SUMIFS($E46:$FS46,$E$8:$FS$8,FT$5) -> 0 | FU46: =SUMIFS($E46:$FS46,$E$8:$FS$8,FU$5) -> 0 | FV46: =SUMIFS($E46:$FS46,$E$8:$FS$8,FV$5) -> 0 | FW46: =SUMIFS($E46:$FS46,$E$8:$FS$8,FW$5) -> 0 | FX46: =SUMIFS($E46:$FS46,$E$8:$FS$8,FX$5) -> 0
FT47: =SUMIFS($E47:$FS47,$E$8:$FS$8,FT$5) -> 0 | FU47: =SUMIFS($E47:$FS47,$E$8:$FS$8,FU$5) -> 0 | FV47: =SUMIFS($E47:$FS47,$E$8:$FS$8,FV$5) -> 0 | FW47: =SUMIFS($E47:$FS47,$E$8:$FS$8,FW$5) -> 0 | FX47: =SUMIFS($E47:$FS47,$E$8:$FS$8,FX$5) -> 0
E48: 0 | F48: 0 | G48: 0 | H48: 0 | I48: 0 | J48: 0 | K48: 0 | L48: 0 | M48: 0 | N48: 0 | O48: 0 | P48: 0 | Q48: 0 | R48: 0 | S48: 0 | T48: 0 | U48: 0 | V48: 0 | W48: 0 | X48: 0 | Y48: 0 | Z48: 0 | AA48: 0 | AB48: 0 | AC48: 0 | AD48: 0 | AE48: 0 | AF48: 0 | AG48: 0 | AH48: 0 | AI48: 0 | AJ48: 0 | AK48: 0 | AL48: 0 | AM48: 0 | AN48: 0 | AO48: 0 | AP48: 0 | AQ48: 0 | AR48: 0 | AS48: 0 | AT48: 0 | AU48: 0 | AV48: 0 | AW48: 0 | AX48: 0 | AY48: 0 | AZ48: 0 | BA48: 0 | BB48: 0 | BC48: 0 | BD48: 0 | BE48: 0 | BF48: 0 | BG48: 0 | BH48: 0 | BI48: 0 | BJ48: 0 | BK48: 0 | BL48: 0 | BM48: 0 | BN48: 0 | BO48: 0 | BP48: 0 | BQ48: 0 | BR48: 0 | BS48: 0 | BT48: 0 | BU48: 0 | BV48: 0 | BW48: 0 | BX48: 0 | BY48: 0 | BZ48: 0 | CA48: 0 | CB48: 0 | CC48: 0 | CD48: 0 | CE48: 0 | CF48: 0 | CG48: 0 | CH48: 0 | CI48: 0 | CJ48: 0 | CK48: 0 | CL48: 0 | CM48: 0 | CN48: 0 | CO48: 0 | CP48: 0 | CQ48: 0 | CR48: 0 | CS48: 0 | CT48: 0 | CU48: 0 | CV48: 0 | CW48: 0 | CX48: 0 | CY48: 0 | CZ48: 0 | DA48: 0 | DB48: 0 | DC48: 0 | DD48: 0 | DE48: 0 | DF48: 0 | DG48: 0 | DH48: 0 | DI48: 0 | DJ48: 0 | DK48: 0 | DL48: 0 | DM48: 0 | DN48: 0 | DO48: 0 | DP48: 0 | DQ48: 0 | DR48: 0 | DS48: 0 | DT48: 0 | DU48: 0 | DV48: 0 | DW48: 0 | DX48: 0 | DY48: 0 | DZ48: 0 | EA48: 0 | EB48: 0 | EC48: 0 | ED48: 0 | EE48: 0 | EF48: 0 | EG48: 0 | EH48: 0 | EI48: 0 | EJ48: 0 | EK48: 0 | EL48: 0 | EM48: 0 | EN48: 0 | EO48: 0 | EP48: 0 | EQ48: 0 | ER48: 0 | ES48: 0 | ET48: 0 | EU48: 0 | EV48: 0 | EW48: 0 | EX48: 0 | EY48: 0 | EZ48: 0 | FA48: 0 | FB48: 0 | FC48: 0 | FD48: 0 | FE48: 0 | FF48: 0 | FG48: 0 | FH48: 0 | FI48: 0 | FJ48: 0 | FK48: 0 | FL48: 0 | FM48: 0 | FN48: 0 | FO48: 0 | FP48: 0 | FQ48: 0 | FR48: 0 | FS48: 0 | FT48: =SUMIFS($E48:$FS48,$E$8:$FS$8,FT$5) -> 0 | FU48: =SUMIFS($E48:$FS48,$E$8:$FS$8,FU$5) -> 0 | FV48: =SUMIFS($E48:$FS48,$E$8:$FS$8,FV$5) -> 0 | FW48: =SUMIFS($E48:$FS48,$E$8:$FS$8,FW$5) -> 0 | FX48: =SUMIFS($E48:$FS48,$E$8:$FS$8,FX$5) -> 0
B49: Garage Income | E49: =IF(E31>=Detail!$F$34,Detail!$L$72*E126,Detail!$L72*'Cash Flow'!E31) -> 4329.238 | F49: =IF(F31>=Detail!$F$34,Detail!$L$72*F126,Detail!$L72*'Cash Flow'!F31) -> 4329.3311 | G49: =IF(G31>=Detail!$F$34,Detail!$L$72*G126,Detail!$L72*'Cash Flow'!G31) -> 4329.4211 | H49: =IF(H31>=Detail!$F$34,Detail!$L$72*H126,Detail!$L72*'Cash Flow'!H31) -> 4329.508 | I49: =IF(I31>=Detail!$F$34,Detail!$L$72*I126,Detail!$L72*'Cash Flow'!I31) -> 4329.5919 | J49: =IF(J31>=Detail!$F$34,Detail!$L$72*J126,Detail!$L72*'Cash Flow'!J31) -> 4329.673 | K49: =IF(K31>=Detail!$F$34,Detail!$L$72*K126,Detail!$L72*'Cash Flow'!K31) -> 4329.7514 | L49: =IF(L31>=Detail!$F$34,Detail!$L$72*L126,Detail!$L72*'Cash Flow'!L31) -> 4329.3001 | ... FS49: =IF(FS31>=Detail!$F$34,Detail!$L$72*FS126,Detail!$L72*'Cash Flow'!FS31) -> 6867.5744 | FT49: =SUMIFS($E49:$FS49,$E$8:$FS$8,FT$5) -> 30306.515 | FU49: =SUMIFS($E49:$FS49,$E$8:$FS$8,FU$5) -> 54288.102 | FV49: =SUMIFS($E49:$FS49,$E$8:$FS$8,FV$5) -> 57309.059 | FW49: =SUMIFS($E49:$FS49,$E$8:$FS$8,FW$5) -> 59052.169 | FX49: =SUMIFS($E49:$FS49,$E$8:$FS$8,FX$5) -> 60848.297
B50: Pet Rent | E50: =Detail!$L$71*E126 -> 2376 | F50: =Detail!$L$71*F126 -> 2376 | G50: =Detail!$L$71*G126 -> 2376 | H50: =Detail!$L$71*H126 -> 2376 | I50: =Detail!$L$71*I126 -> 2376 | J50: =Detail!$L$71*J126 -> 2376 | K50: =Detail!$L$71*K126 -> 2376 | L50: =Detail!$L$71*L126 -> 2381.94 | ... FS50: =Detail!$L$71*FS126 -> 3578.3677 | FT50: =SUMIFS($E50:$FS50,$E$8:$FS$8,FT$5) -> 16632 | FU50: =SUMIFS($E50:$FS50,$E$8:$FS$8,FU$5) -> 28979.594 | FV50: =SUMIFS($E50:$FS50,$E$8:$FS$8,FV$5) -> 29861.036 | FW50: =SUMIFS($E50:$FS50,$E$8:$FS$8,FW$5) -> 30769.288 | FX50: =SUMIFS($E50:$FS50,$E$8:$FS$8,FX$5) -> 31705.165
B51: Storage Rent | E51: =IF(E31>=Detail!$F$34,Detail!$L$73*E126,Detail!$L73*'Cash Flow'!E31) -> 1139.2732 | F51: =IF(F31>=Detail!$F$34,Detail!$L$73*F126,Detail!$L73*'Cash Flow'!F31) -> 1139.2977 | G51: =IF(G31>=Detail!$F$34,Detail!$L$73*G126,Detail!$L73*'Cash Flow'!G31) -> 1139.3213 | H51: =IF(H31>=Detail!$F$34,Detail!$L$73*H126,Detail!$L73*'Cash Flow'!H31) -> 1139.3442 | I51: =IF(I31>=Detail!$F$34,Detail!$L$73*I126,Detail!$L73*'Cash Flow'!I31) -> 1139.3663 | J51: =IF(J31>=Detail!$F$34,Detail!$L$73*J126,Detail!$L73*'Cash Flow'!J31) -> 1139.3876 | K51: =IF(K31>=Detail!$F$34,Detail!$L$73*K126,Detail!$L73*'Cash Flow'!K31) -> 1139.4083 | L51: =IF(L31>=Detail!$F$34,Detail!$L$73*L126,Detail!$L73*'Cash Flow'!L31) -> 1139.2895 | ... FS51: =IF(FS31>=Detail!$F$34,Detail!$L$73*FS126,Detail!$L73*'Cash Flow'!FS31) -> 1807.2564 | FT51: =SUMIFS($E51:$FS51,$E$8:$FS$8,FT$5) -> 7975.3986 | FU51: =SUMIFS($E51:$FS51,$E$8:$FS$8,FU$5) -> 14286.343 | FV51: =SUMIFS($E51:$FS51,$E$8:$FS$8,FV$5) -> 15081.331 | FW51: =SUMIFS($E51:$FS51,$E$8:$FS$8,FW$5) -> 15540.044 | FX51: =SUMIFS($E51:$FS51,$E$8:$FS$8,FX$5) -> 16012.71
B52: Revenue Sharing Contract | E52: =Detail!$F$78*E23*E126 -> 23256 | F52: =Detail!$F$78*F23*F126 -> 23256 | G52: =Detail!$F$78*G23*G126 -> 23256 | H52: =Detail!$F$78*H23*H126 -> 23256 | I52: =Detail!$F$78*I23*I126 -> 23256 | J52: =Detail!$F$78*J23*J126 -> 23256 | K52: =Detail!$F$78*K23*K126 -> 23256 | L52: =Detail!$F$78*L23*L126 -> 23314.14 | ... FS52: =Detail!$F$78*FS23*FS126 -> 35024.63 | FT52: =SUMIFS($E52:$FS52,$E$8:$FS$8,FT$5) -> 162792 | FU52: =SUMIFS($E52:$FS52,$E$8:$FS$8,FU$5) -> 283648.75 | FV52: =SUMIFS($E52:$FS52,$E$8:$FS$8,FV$5) -> 292276.2 | FW52: =SUMIFS($E52:$FS52,$E$8:$FS$8,FW$5) -> 301166.06 | FX52: =SUMIFS($E52:$FS52,$E$8:$FS$8,FX$5) -> 310326.31
B53: Trash Remove Rebill-Door to Door Pickup | E53: =Detail!$F$79*E23*E126 -> 8208 | F53: =Detail!$F$79*F23*F126 -> 8208 | G53: =Detail!$F$79*G23*G126 -> 8208 | H53: =Detail!$F$79*H23*H126 -> 8208 | I53: =Detail!$F$79*I23*I126 -> 8208 | J53: =Detail!$F$79*J23*J126 -> 8208 | K53: =Detail!$F$79*K23*K126 -> 8208 | L53: =Detail!$F$79*L23*L126 -> 8228.52 | ... FS53: =Detail!$F$79*FS23*FS126 -> 12361.634 | FT53: =SUMIFS($E53:$FS53,$E$8:$FS$8,FT$5) -> 57456 | FU53: =SUMIFS($E53:$FS53,$E$8:$FS$8,FU$5) -> 100111.32 | FV53: =SUMIFS($E53:$FS53,$E$8:$FS$8,FV$5) -> 103156.31 | FW53: =SUMIFS($E53:$FS53,$E$8:$FS$8,FW$5) -> 106293.9 | FX53: =SUMIFS($E53:$FS53,$E$8:$FS$8,FX$5) -> 109526.93
B54: Water/Sewer Rebill | E54: =IF(E31>=Detail!$F$34,Detail!$L$77*E126,Detail!$L77*'Cash Flow'!E31) -> 17772.661 | F54: =IF(F31>=Detail!$F$34,Detail!$L$77*F126,Detail!$L77*'Cash Flow'!F31) -> 17773.044 | G54: =IF(G31>=Detail!$F$34,Detail!$L$77*G126,Detail!$L77*'Cash Flow'!G31) -> 17773.413 | H54: =IF(H31>=Detail!$F$34,Detail!$L$77*H126,Detail!$L77*'Cash Flow'!H31) -> 17773.77 | I54: =IF(I31>=Detail!$F$34,Detail!$L$77*I126,Detail!$L77*'Cash Flow'!I31) -> 17774.114 | J54: =IF(J31>=Detail!$F$34,Detail!$L$77*J126,Detail!$L77*'Cash Flow'!J31) -> 17774.447 | K54: =IF(K31>=Detail!$F$34,Detail!$L$77*K126,Detail!$L77*'Cash Flow'!K31) -> 17774.769 | L54: =IF(L31>=Detail!$F$34,Detail!$L$77*L126,Detail!$L77*'Cash Flow'!L31) -> 17772.916 | ... FS54: =IF(FS31>=Detail!$F$34,Detail!$L$77*FS126,Detail!$L77*'Cash Flow'!FS31) -> 28193.2 | FT54: =SUMIFS($E54:$FS54,$E$8:$FS$8,FT$5) -> 124416.22 | FU54: =SUMIFS($E54:$FS54,$E$8:$FS$8,FU$5) -> 222866.95 | FV54: =SUMIFS($E54:$FS54,$E$8:$FS$8,FV$5) -> 235268.77 | FW54: =SUMIFS($E54:$FS54,$E$8:$FS$8,FW$5) -> 242424.69 | FX54: =SUMIFS($E54:$FS54,$E$8:$FS$8,FX$5) -> 249798.27
B55: Miscellaneous | E55: =SUM(Detail!$L$80:$L$82,Detail!$L$85)*E126 -> 9212.4 | F55: =SUM(Detail!$L$80:$L$82,Detail!$L$85)*F126 -> 9212.4 | G55: =SUM(Detail!$L$80:$L$82,Detail!$L$85)*G126 -> 9212.4 | H55: =SUM(Detail!$L$80:$L$82,Detail!$L$85)*H126 -> 9212.4 | I55: =SUM(Detail!$L$80:$L$82,Detail!$L$85)*I126 -> 9212.4 | J55: =SUM(Detail!$L$80:$L$82,Detail!$L$85)*J126 -> 9212.4 | K55: =SUM(Detail!$L$80:$L$82,Detail!$L$85)*K126 -> 9212.4 | L55: =SUM(Detail!$L$80:$L$82,Detail!$L$85)*L126 -> 9235.431 | ... FS55: =SUM(Detail!$L$80:$L$82,Detail!$L$85)*FS126 -> 13874.308 | FT55: =SUMIFS($E55:$FS55,$E$8:$FS$8,FT$5) -> 64486.8 | FU55: =SUMIFS($E55:$FS55,$E$8:$FS$8,FU$5) -> 112361.79 | FV55: =SUMIFS($E55:$FS55,$E$8:$FS$8,FV$5) -> 115779.38 | FW55: =SUMIFS($E55:$FS55,$E$8:$FS$8,FW$5) -> 119300.92 | FX55: =SUMIFS($E55:$FS55,$E$8:$FS$8,FX$5) -> 122929.57
B56: Total Other Income | E56: =+SUM(E49:E55) -> 66293.572 | F56: =+SUM(F49:F55) -> 66294.072 | G56: =+SUM(G49:G55) -> 66294.555 | H56: =+SUM(H49:H55) -> 66295.022 | I56: =+SUM(I49:I55) -> 66295.473 | J56: =+SUM(J49:J55) -> 66295.908 | K56: =+SUM(K49:K55) -> 66296.328 | L56: =+SUM(L49:L55) -> 66401.537 | ... FS56: =+SUM(FS49:FS55) -> 101706.97 | FT56: =SUMIFS($E56:$FS56,$E$8:$FS$8,FT$5) -> 464064.93 | FU56: =SUMIFS($E56:$FS56,$E$8:$FS$8,FU$5) -> 816542.85 | FV56: =SUMIFS($E56:$FS56,$E$8:$FS$8,FV$5) -> 848732.08 | FW56: =SUMIFS($E56:$FS56,$E$8:$FS$8,FW$5) -> 874547.08 | FX56: =SUMIFS($E56:$FS56,$E$8:$FS$8,FX$5) -> 901147.26
B57: Model / Employee Units | E57: =-E27*Detail!$M$34 -> -1910.296 | F57: =-F27*Detail!$M$34 -> -1910.296 | G57: =-G27*Detail!$M$34 -> -1910.296 | H57: =-H27*Detail!$M$34 -> -1910.296 | I57: =-I27*Detail!$M$34 -> -1910.296 | J57: =-J27*Detail!$M$34 -> -1910.296 | K57: =-K27*Detail!$M$34 -> -1910.296 | L57: =-L27*Detail!$M$34 -> -1915.0718 | ... FS57: =-FS27*Detail!$M$34 -> -2876.9957 | FT57: =SUMIFS($E57:$FS57,$E$8:$FS$8,FT$5) -> -13372.072 | FU57: =SUMIFS($E57:$FS57,$E$8:$FS$8,FU$5) -> -23299.496 | FV57: =SUMIFS($E57:$FS57,$E$8:$FS$8,FV$5) -> -24008.173 | FW57: =SUMIFS($E57:$FS57,$E$8:$FS$8,FW$5) -> -24738.404 | FX57: =SUMIFS($E57:$FS57,$E$8:$FS$8,FX$5) -> -25490.847
B58: Effective Gross Income | E58: =SUM(E56:E57,E45:E46) -> 547786.29 | F58: =SUM(F56:F57,F45:F46) -> 548004.1 | G58: =SUM(G56:G57,G45:G46) -> 548214.64 | H58: =SUM(H56:H57,H45:H46) -> 539248.74 | I58: =SUM(I56:I57,I45:I46) -> 539445.49 | J58: =SUM(J56:J57,J45:J46) -> 539635.67 | K58: =SUM(K56:K57,K45:K46) -> 539819.51 | L58: =SUM(L56:L57,L45:L46) -> 540050.95 | ... FS58: =SUM(FS56:FS57,FS45:FS46) -> 871671.39 | FT58: =SUMIFS($E58:$FS58,$E$8:$FS$8,FT$5) -> 3802154.4 | FU58: =SUMIFS($E58:$FS58,$E$8:$FS$8,FU$5) -> 6644804.2 | FV58: =SUMIFS($E58:$FS58,$E$8:$FS$8,FV$5) -> 7246512.3 | FW58: =SUMIFS($E58:$FS58,$E$8:$FS$8,FW$5) -> 7509810.4 | FX58: =SUMIFS($E58:$FS58,$E$8:$FS$8,FX$5) -> 7732988.2
B59: Expenses
B60: Payroll | E60: =Detail!$L$98*E127 -> 40164.917 | F60: =Detail!$L$98*F127 -> 40164.917 | G60: =Detail!$L$98*G127 -> 40164.917 | H60: =Detail!$L$98*H127 -> 40164.917 | I60: =Detail!$L$98*I127 -> 40164.917 | J60: =Detail!$L$98*J127 -> 40164.917 | K60: =Detail!$L$98*K127 -> 40164.917 | L60: =Detail!$L$98*L127 -> 40231.858 | ... FS60: =Detail!$L$98*FS127 -> 52778.278 | FT60: =SUMIFS($E60:$FS60,$E$8:$FS$8,FT$5) -> 281154.42 | FU60: =SUMIFS($E60:$FS60,$E$8:$FS$8,FU$5) -> 487232.48 | FV60: =SUMIFS($E60:$FS60,$E$8:$FS$8,FV$5) -> 497066.96 | FW60: =SUMIFS($E60:$FS60,$E$8:$FS$8,FW$5) -> 507099.93 | FX60: =SUMIFS($E60:$FS60,$E$8:$FS$8,FX$5) -> 517335.42
B61: Administrative | E61: =Detail!$L$102*E127 -> 13689.083 | F61: =Detail!$L$102*F127 -> 13689.083 | G61: =Detail!$L$102*G127 -> 13689.083 | H61: =Detail!$L$102*H127 -> 13689.083 | I61: =Detail!$L$102*I127 -> 13689.083 | J61: =Detail!$L$102*J127 -> 13689.083 | K61: =Detail!$L$102*K127 -> 13689.083 | L61: =Detail!$L$102*L127 -> 13711.898 | ... FS61: =Detail!$L$102*FS127 -> 17987.993 | FT61: =SUMIFS($E61:$FS61,$E$8:$FS$8,FT$5) -> 95823.583 | FU61: =SUMIFS($E61:$FS61,$E$8:$FS$8,FU$5) -> 166059.5 | FV61: =SUMIFS($E61:$FS61,$E$8:$FS$8,FV$5) -> 169411.31 | FW61: =SUMIFS($E61:$FS61,$E$8:$FS$8,FW$5) -> 172830.76 | FX61: =SUMIFS($E61:$FS61,$E$8:$FS$8,FX$5) -> 176319.24
B62: Utilities | E62: =Detail!$L$99*E127 -> 46496.419 | F62: =Detail!$L$99*F127 -> 46496.419 | G62: =Detail!$L$99*G127 -> 46496.419 | H62: =Detail!$L$99*H127 -> 46496.419 | I62: =Detail!$L$99*I127 -> 46496.419 | J62: =Detail!$L$99*J127 -> 46496.419 | K62: =Detail!$L$99*K127 -> 46496.419 | L62: =Detail!$L$99*L127 -> 46573.913 | ... FS62: =Detail!$L$99*FS127 -> 61098.121 | FT62: =SUMIFS($E62:$FS62,$E$8:$FS$8,FT$5) -> 325474.94 | FU62: =SUMIFS($E62:$FS62,$E$8:$FS$8,FU$5) -> 564038.66 | FV62: =SUMIFS($E62:$FS62,$E$8:$FS$8,FV$5) -> 575423.42 | FW62: =SUMIFS($E62:$FS62,$E$8:$FS$8,FW$5) -> 587037.97 | FX62: =SUMIFS($E62:$FS62,$E$8:$FS$8,FX$5) -> 598886.95
B63: Turnover | E63: =Detail!$L$103*E127 -> 4320 | F63: =Detail!$L$103*F127 -> 4320 | G63: =Detail!$L$103*G127 -> 4320 | H63: =Detail!$L$103*H127 -> 4320 | I63: =Detail!$L$103*I127 -> 4320 | J63: =Detail!$L$103*J127 -> 4320 | K63: =Detail!$L$103*K127 -> 4320 | L63: =Detail!$L$103*L127 -> 4327.2 | ... FS63: =Detail!$L$103*FS127 -> 5676.6497 | FT63: =SUMIFS($E63:$FS63,$E$8:$FS$8,FT$5) -> 30240 | FU63: =SUMIFS($E63:$FS63,$E$8:$FS$8,FU$5) -> 52405.046 | FV63: =SUMIFS($E63:$FS63,$E$8:$FS$8,FV$5) -> 53462.808 | FW63: =SUMIFS($E63:$FS63,$E$8:$FS$8,FW$5) -> 54541.921 | FX63: =SUMIFS($E63:$FS63,$E$8:$FS$8,FX$5) -> 55642.814
B64: Repairs and Maintenance | E64: =Detail!$L$101*E127 -> 12648.75 | F64: =Detail!$L$101*F127 -> 12648.75 | G64: =Detail!$L$101*G127 -> 12648.75 | H64: =Detail!$L$101*H127 -> 12648.75 | I64: =Detail!$L$101*I127 -> 12648.75 | J64: =Detail!$L$101*J127 -> 12648.75 | K64: =Detail!$L$101*K127 -> 12648.75 | L64: =Detail!$L$101*L127 -> 12669.831 | ... FS64: =Detail!$L$101*FS127 -> 16620.954 | FT64: =SUMIFS($E64:$FS64,$E$8:$FS$8,FT$5) -> 88541.25 | FU64: =SUMIFS($E64:$FS64,$E$8:$FS$8,FU$5) -> 153439.43 | FV64: =SUMIFS($E64:$FS64,$E$8:$FS$8,FV$5) -> 156536.5 | FW64: =SUMIFS($E64:$FS64,$E$8:$FS$8,FW$5) -> 159696.09 | FX64: =SUMIFS($E64:$FS64,$E$8:$FS$8,FX$5) -> 162919.46
B65: Marketing & Advertising | E65: =Detail!$L$104*E127 -> 11400 | F65: =Detail!$L$104*F127 -> 11400 | G65: =Detail!$L$104*G127 -> 11400 | H65: =Detail!$L$104*H127 -> 11400 | I65: =Detail!$L$104*I127 -> 11400 | J65: =Detail!$L$104*J127 -> 11400 | K65: =Detail!$L$104*K127 -> 11400 | L65: =Detail!$L$104*L127 -> 11419 | ... FS65: =Detail!$L$104*FS127 -> 14980.048 | FT65: =SUMIFS($E65:$FS65,$E$8:$FS$8,FT$5) -> 79800 | FU65: =SUMIFS($E65:$FS65,$E$8:$FS$8,FU$5) -> 138291.09 | FV65: =SUMIFS($E65:$FS65,$E$8:$FS$8,FV$5) -> 141082.41 | FW65: =SUMIFS($E65:$FS65,$E$8:$FS$8,FW$5) -> 143930.07 | FX65: =SUMIFS($E65:$FS65,$E$8:$FS$8,FX$5) -> 146835.2
B66: Contract Services | E66: =Detail!$L$100*E127 -> 2511.6667 | F66: =Detail!$L$100*F127 -> 2511.6667 | G66: =Detail!$L$100*G127 -> 2511.6667 | H66: =Detail!$L$100*H127 -> 2511.6667 | I66: =Detail!$L$100*I127 -> 2511.6667 | J66: =Detail!$L$100*J127 -> 2511.6667 | K66: =Detail!$L$100*K127 -> 2511.6667 | L66: =Detail!$L$100*L127 -> 2515.8528 | ... FS66: =Detail!$L$100*FS127 -> 3300.4286 | FT66: =SUMIFS($E66:$FS66,$E$8:$FS$8,FT$5) -> 17581.667 | FU66: =SUMIFS($E66:$FS66,$E$8:$FS$8,FU$5) -> 30468.52 | FV66: =SUMIFS($E66:$FS66,$E$8:$FS$8,FV$5) -> 31083.508 | FW66: =SUMIFS($E66:$FS66,$E$8:$FS$8,FW$5) -> 31710.908 | FX66: =SUMIFS($E66:$FS66,$E$8:$FS$8,FX$5) -> 32350.973
B67: Variable Expenses | E67: =SUM(E60:E66) -> 131230.84 | F67: =SUM(F60:F66) -> 131230.84 | G67: =SUM(G60:G66) -> 131230.84 | H67: =SUM(H60:H66) -> 131230.84 | I67: =SUM(I60:I66) -> 131230.84 | J67: =SUM(J60:J66) -> 131230.84 | K67: =SUM(K60:K66) -> 131230.84 | L67: =SUM(L60:L66) -> 131449.55 | ... FS67: =SUM(FS60:FS66) -> 172442.47 | FT67: =SUMIFS($E67:$FS67,$E$8:$FS$8,FT$5) -> 918615.85 | FU67: =SUMIFS($E67:$FS67,$E$8:$FS$8,FU$5) -> 1591934.7 | FV67: =SUMIFS($E67:$FS67,$E$8:$FS$8,FV$5) -> 1624066.9 | FW67: =SUMIFS($E67:$FS67,$E$8:$FS$8,FW$5) -> 1656847.7 | FX67: =SUMIFS($E67:$FS67,$E$8:$FS$8,FX$5) -> 1690290.1
B68: Management Fees | E68: =MAX(E58*Detail!$L$128,9000) -> 15064.123 | F68: =MAX(F58*Detail!$L$128,9000) -> 15070.113 | G68: =MAX(G58*Detail!$L$128,9000) -> 15075.903 | H68: =MAX(H58*Detail!$L$128,9000) -> 14829.34 | I68: =MAX(I58*Detail!$L$128,9000) -> 14834.751 | J68: =MAX(J58*Detail!$L$128,9000) -> 14839.981 | K68: =MAX(K58*Detail!$L$128,9000) -> 14845.037 | L68: =MAX(L58*Detail!$L$128,9000) -> 14851.401 | ... FS68: =MAX(FS58*Detail!$L$128,9000) -> 23970.963 | FT68: =SUMIFS($E68:$FS68,$E$8:$FS$8,FT$5) -> 104559.25 | FU68: =SUMIFS($E68:$FS68,$E$8:$FS$8,FU$5) -> 182732.11 | FV68: =SUMIFS($E68:$FS68,$E$8:$FS$8,FV$5) -> 199279.09 | FW68: =SUMIFS($E68:$FS68,$E$8:$FS$8,FW$5) -> 206519.79 | FX68: =SUMIFS($E68:$FS68,$E$8:$FS$8,FX$5) -> 212657.18
B69: RE Taxes | E69: =IF(E17>=Detail!$H$7,Detail!$L$110*E130,Detail!$P$136/12) -> 60266.408 | F69: =IF(F17>=Detail!$H$7,Detail!$L$110*F130,Detail!$P$136/12) -> 60266.408 | G69: =IF(G17>=Detail!$H$7,Detail!$L$110*G130,Detail!$P$136/12) -> 60266.408 | H69: =IF(H17>=Detail!$H$7,Detail!$L$110*H130,Detail!$P$136/12) -> 60266.408 | I69: =IF(I17>=Detail!$H$7,Detail!$L$110*I130,Detail!$P$136/12) -> 60266.408 | J69: =IF(J17>=Detail!$H$7,Detail!$L$110*J130,Detail!$P$136/12) -> 60266.408 | K69: =IF(K17>=Detail!$H$7,Detail!$L$110*K130,Detail!$P$136/12) -> 60266.408 | L69: =IF(L17>=Detail!$H$7,Detail!$L$110*L130,Detail!$P$136/12) -> 60366.852 | ... FS69: =IF(FS17>=Detail!$H$7,Detail!$L$110*FS130,Detail!$P$136/12) -> 79192.426 | FT69: =SUMIFS($E69:$FS69,$E$8:$FS$8,FT$5) -> 421864.85 | FU69: =SUMIFS($E69:$FS69,$E$8:$FS$8,FU$5) -> 731079.6 | FV69: =SUMIFS($E69:$FS69,$E$8:$FS$8,FV$5) -> 745835.97 | FW69: =SUMIFS($E69:$FS69,$E$8:$FS$8,FW$5) -> 760890.19 | FX69: =SUMIFS($E69:$FS69,$E$8:$FS$8,FX$5) -> 776248.27
B70: HOA/CDD | E70: =+Detail!$L$108*'Cash Flow'!E130 -> 1221 | F70: =+Detail!$L$108*'Cash Flow'!F130 -> 1221 | G70: =+Detail!$L$108*'Cash Flow'!G130 -> 1221 | H70: =+Detail!$L$108*'Cash Flow'!H130 -> 1221 | I70: =+Detail!$L$108*'Cash Flow'!I130 -> 1221 | J70: =+Detail!$L$108*'Cash Flow'!J130 -> 1221 | K70: =+Detail!$L$108*'Cash Flow'!K130 -> 1221 | L70: =+Detail!$L$108*'Cash Flow'!L130 -> 1223.035 | ... FS70: =+Detail!$L$108*'Cash Flow'!FS130 -> 1604.442
B71: Insurance - Property | E71: =Detail!$L$109*E127 -> 25200 | F71: =Detail!$L$109*F127 -> 25200 | G71: =Detail!$L$109*G127 -> 25200 | H71: =Detail!$L$109*H127 -> 25200 | I71: =Detail!$L$109*I127 -> 25200 | J71: =Detail!$L$109*J127 -> 25200 | K71: =Detail!$L$109*K127 -> 25200 | L71: =Detail!$L$109*L127 -> 25242 | ... FS71: =Detail!$L$109*FS127 -> 33113.79 | FT71: =SUMIFS($E71:$FS71,$E$8:$FS$8,FT$5) -> 176400 | FU71: =SUMIFS($E71:$FS71,$E$8:$FS$8,FU$5) -> 305696.1 | FV71: =SUMIFS($E71:$FS71,$E$8:$FS$8,FV$5) -> 311866.38 | FW71: =SUMIFS($E71:$FS71,$E$8:$FS$8,FW$5) -> 318161.2 | FX71: =SUMIFS($E71:$FS71,$E$8:$FS$8,FX$5) -> 324583.08
B72: Replacement Reserves | E72: =Detail!$L$112 -> 4800 | F72: =Detail!$L$112 -> 4800 | G72: =Detail!$L$112 -> 4800 | H72: =Detail!$L$112 -> 4800 | I72: =Detail!$L$112 -> 4800 | J72: =Detail!$L$112 -> 4800 | K72: =Detail!$L$112 -> 4800 | L72: =Detail!$L$112 -> 4800 | ... FS72: =Detail!$L$112 -> 4800 | FT72: =SUMIFS($E72:$FS72,$E$8:$FS$8,FT$5) -> 33600 | FU72: =SUMIFS($E72:$FS72,$E$8:$FS$8,FU$5) -> 57600 | FV72: =SUMIFS($E72:$FS72,$E$8:$FS$8,FV$5) -> 57600 | FW72: =SUMIFS($E72:$FS72,$E$8:$FS$8,FW$5) -> 57600 | FX72: =SUMIFS($E72:$FS72,$E$8:$FS$8,FX$5) -> 57600
B73: Fixed Expenses | E73: =SUM(E68:E72) -> 106551.53 | F73: =SUM(F68:F72) -> 106557.52 | G73: =SUM(G68:G72) -> 106563.31 | H73: =SUM(H68:H72) -> 106316.75 | I73: =SUM(I68:I72) -> 106322.16 | J73: =SUM(J68:J72) -> 106327.39 | K73: =SUM(K68:K72) -> 106332.44 | L73: =SUM(L68:L72) -> 106483.29 | ... FS73: =SUM(FS68:FS72) -> 142681.62 | FT73: =SUMIFS($E73:$FS73,$E$8:$FS$8,FT$5) -> 744971.1 | FU73: =SUMIFS($E73:$FS73,$E$8:$FS$8,FU$5) -> 1291919.5 | FV73: =SUMIFS($E73:$FS73,$E$8:$FS$8,FV$5) -> 1329692.1 | FW73: =SUMIFS($E73:$FS73,$E$8:$FS$8,FW$5) -> 1358586.8 | FX73: =SUMIFS($E73:$FS73,$E$8:$FS$8,FX$5) -> 1386815.4
B74: Total Expenses | E74: =SUM(E73, E67) -> 237782.37 | F74: =SUM(F73, F67) -> 237788.36 | G74: =SUM(G73, G67) -> 237794.15 | H74: =SUM(H73, H67) -> 237547.58 | I74: =SUM(I73, I67) -> 237552.99 | J74: =SUM(J73, J67) -> 237558.22 | K74: =SUM(K73, K67) -> 237563.28 | L74: =SUM(L73, L67) -> 237932.84 | ... FS74: =SUM(FS73, FS67) -> 315124.09 | FT74: =SUMIFS($E74:$FS74,$E$8:$FS$8,FT$5) -> 1663587 | FU74: =SUMIFS($E74:$FS74,$E$8:$FS$8,FU$5) -> 2883854.3 | FV74: =SUMIFS($E74:$FS74,$E$8:$FS$8,FV$5) -> 2953759 | FW74: =SUMIFS($E74:$FS74,$E$8:$FS$8,FW$5) -> 3015434.5 | FX74: =SUMIFS($E74:$FS74,$E$8:$FS$8,FX$5) -> 3077105.4
B76: NOI | E76: =E58-E74 -> 310003.92 | F76: =F58-F74 -> 310215.74 | G76: =G58-G74 -> 310420.49 | H76: =H58-H74 -> 301701.16 | I76: =I58-I74 -> 301892.49 | J76: =J58-J74 -> 302077.44 | K76: =K58-K74 -> 302256.23 | L76: =L58-L74 -> 302118.11 | ... FS76: =FS58-FS74 -> 556547.3 | FT76: =SUMIFS($E76:$FS76,$E$8:$FS$8,FT$5) -> 2138567.5 | FU76: =SUMIFS($E76:$FS76,$E$8:$FS$8,FU$5) -> 3760949.9 | FV76: =SUMIFS($E76:$FS76,$E$8:$FS$8,FV$5) -> 4292753.3 | FW76: =SUMIFS($E76:$FS76,$E$8:$FS$8,FW$5) -> 4494375.9 | FX76: =SUMIFS($E76:$FS76,$E$8:$FS$8,FX$5) -> 4655882.8
E77: 342128.92 | F77: 297659.74 | G77: 261774.49 | H77: 243509.16 | I77: 182545.49 | J77: 158088.44 | K77: 110523.23 | L77: 68537.06 | M77: 62800.127 | N77: 36765.625 | O77: 854.73863 | P77: -6545.3513
B78: Lease Up Expense:
B80: Debt Service:
B81: Acquisiton Loan | E81: =SUM(E94:E95) -> 249645.83 | F81: =SUM(F94:F95) -> 257967.36 | G81: =SUM(G94:G95) -> 257967.36 | H81: =SUM(H94:H95) -> 249645.83 | I81: =SUM(I94:I95) -> 257967.36 | J81: =SUM(J94:J95) -> 249645.83 | K81: =SUM(K94:K95) -> 257967.36 | L81: =SUM(L94:L95) -> 257967.36 | ... FS81: =SUM(FS94:FS95) -> 0
B82: Permanent Loan | E82: =SUM(E105:E106) -> 0 | F82: =SUM(F105:F106) -> 0 | G82: =SUM(G105:G106) -> 0 | H82: =SUM(H105:H106) -> 0 | I82: =SUM(I105:I106) -> 0 | J82: =SUM(J105:J106) -> 0 | K82: =SUM(K105:K106) -> 0 | L82: =SUM(L105:L106) -> 0 | ... FS82: =SUM(FS105:FS106) -> 0
B84: Cash Flow after Debt Service | E84: =IF(AND(E17>=Detail!$H$7,E17<=Detail!$H$9),'Cash Flow'!E76-SUM('Cash Flow'!E81:E82),0) -> 60358.09 | F84: =IF(AND(F17>=Detail!$H$7,F17<=Detail!$H$9),'Cash Flow'!F76-SUM('Cash Flow'!F81:F82),0) -> 52248.378 | G84: =IF(AND(G17>=Detail!$H$7,G17<=Detail!$H$9),'Cash Flow'!G76-SUM('Cash Flow'!G81:G82),0) -> 52453.133 | H84: =IF(AND(H17>=Detail!$H$7,H17<=Detail!$H$9),'Cash Flow'!H76-SUM('Cash Flow'!H81:H82),0) -> 52055.327 | I84: =IF(AND(I17>=Detail!$H$7,I17<=Detail!$H$9),'Cash Flow'!I76-SUM('Cash Flow'!I81:I82),0) -> 43925.131 | J84: =IF(AND(J17>=Detail!$H$7,J17<=Detail!$H$9),'Cash Flow'!J76-SUM('Cash Flow'!J81:J82),0) -> 52431.612 | K84: =IF(AND(K17>=Detail!$H$7,K17<=Detail!$H$9),'Cash Flow'!K76-SUM('Cash Flow'!K81:K82),0) -> 44288.871 | L84: =IF(AND(L17>=Detail!$H$7,L17<=Detail!$H$9),'Cash Flow'!L76-SUM('Cash Flow'!L81:L82),0) -> 44150.746 | ... FS84: =IF(AND(FS17>=Detail!$H$7,FS17<=Detail!$H$9),'Cash Flow'!FS76-SUM('Cash Flow'!FS81:FS82),0) -> 0
B89: ACQUISITION LOAN
F90: 1 | G90: =F90+1 -> 2 | H90: =G90+1 -> 3 | I90: =H90+1 -> 4 | J90: =I90+1 -> 5 | K90: =J90+1 -> 6 | L90: =K90+1 -> 7 | M90: =L90+1 -> 8 | N90: =M90+1 -> 9 | ... FS90: =FR90+1 -> 170
B91: Acquisition Loan Infusion | C91: =SUM(E91:FS91) -> 52100000 | E91: =IF(E17=Detail!$H$7,Detail!$D$22,0) -> 52100000 | F91: =IF(F17=Detail!$H$7,Detail!$D$22,0) -> 0 | G91: =IF(G17=Detail!$H$7,Detail!$D$22,0) -> 0 | H91: =IF(H17=Detail!$H$7,Detail!$D$22,0) -> 0 | I91: =IF(I17=Detail!$H$7,Detail!$D$22,0) -> 0 | J91: =IF(J17=Detail!$H$7,Detail!$D$22,0) -> 0 | K91: =IF(K17=Detail!$H$7,Detail!$D$22,0) -> 0 | L91: =IF(L17=Detail!$H$7,Detail!$D$22,0) -> 0 | ... FS91: =IF(FS17=Detail!$H$7,Detail!$D$22,0) -> 0
B92: Acquisiton Loan Beginning Balance | E92: =E91+D96-D97 -> 52100000 | F92: =F91+E96-E97 -> 52100000 | G92: =G91+F96-F97 -> 52100000 | H92: =H91+G96-G97 -> 52100000 | I92: =I91+H96-H97 -> 52100000 | J92: =J91+I96-I97 -> 52100000 | K92: =K91+J96-J97 -> 52100000 | L92: =L91+K96-K97 -> 52100000 | ... FS92: =FS91+FR96-FR97 -> 0
B93: Acquisition Loan Fee | C93: =SUM(E93:FS93) -> 0
B94: Principal | C94: =SUM(E94:FS94) -> 0
B95: Interest | C95: =SUM(E95:FS95) -> 12157752 | E95: =((E5-D5)/360)*E92*Detail!$D$26 -> 249645.83 | F95: =((F5-E5)/360)*F92*Detail!$D$26 -> 257967.36 | G95: =((G5-F5)/360)*G92*Detail!$D$26 -> 257967.36 | H95: =((H5-G5)/360)*H92*Detail!$D$26 -> 249645.83 | I95: =((I5-H5)/360)*I92*Detail!$D$26 -> 257967.36 | J95: =((J5-I5)/360)*J92*Detail!$D$26 -> 249645.83 | K95: =((K5-J5)/360)*K92*Detail!$D$26 -> 257967.36 | L95: =((L5-K5)/360)*L92*Detail!$D$26 -> 257967.36 | ... FS95: =((FS5-FR5)/360)*FS92*Detail!$D$26 -> 0
B96: Acquisition Loan Ending Balance | E96: =E92-E94 -> 52100000 | F96: =F92-F94 -> 52100000 | G96: =G92-G94 -> 52100000 | H96: =H92-H94 -> 52100000 | I96: =I92-I94 -> 52100000 | J96: =J92-J94 -> 52100000 | K96: =K92-K94 -> 52100000 | L96: =L92-L94 -> 52100000 | ... FS96: =FS92-FS94 -> 0
B97: Acquisition Loan Repayment | C97: =SUM(E97:FS97) -> 52100000 | E97: =IF(E17=MIN(IF(Detail!$E$21="NO",Detail!$H$9,Detail!$H$8)),E92-E94,0) -> 0 | F97: =IF(F17=MIN(IF(Detail!$E$21="NO",Detail!$H$9,Detail!$H$8)),F92-F94,0) -> 0 | G97: =IF(G17=MIN(IF(Detail!$E$21="NO",Detail!$H$9,Detail!$H$8)),G92-G94,0) -> 0 | H97: =IF(H17=MIN(IF(Detail!$E$21="NO",Detail!$H$9,Detail!$H$8)),H92-H94,0) -> 0 | I97: =IF(I17=MIN(IF(Detail!$E$21="NO",Detail!$H$9,Detail!$H$8)),I92-I94,0) -> 0 | J97: =IF(J17=MIN(IF(Detail!$E$21="NO",Detail!$H$9,Detail!$H$8)),J92-J94,0) -> 0 | K97: =IF(K17=MIN(IF(Detail!$E$21="NO",Detail!$H$9,Detail!$H$8)),K92-K94,0) -> 0 | L97: =IF(L17=MIN(IF(Detail!$E$21="NO",Detail!$H$9,Detail!$H$8)),L92-L94,0) -> 0 | ... FS97: =IF(FS17=MIN(IF(Detail!$E$21="NO",Detail!$H$9,Detail!$H$8)),FS92-FS94,0) -> 0
B100: PERMANENT LOAN
B102: Permanent Loan Infusion | C102: =SUM(E102:FS102) -> 0 | E102: =IF(AND(E17=Detail!$H$8,Detail!$E$21="YES"),Detail!$E$22+Detail!$E$30,0) -> 0 | F102: =IF(AND(F17=Detail!$H$8,Detail!$E$21="YES"),Detail!$E$22+Detail!$E$30,0) -> 0 | G102: =IF(AND(G17=Detail!$H$8,Detail!$E$21="YES"),Detail!$E$22+Detail!$E$30,0) -> 0 | H102: =IF(AND(H17=Detail!$H$8,Detail!$E$21="YES"),Detail!$E$22+Detail!$E$30,0) -> 0 | I102: =IF(AND(I17=Detail!$H$8,Detail!$E$21="YES"),Detail!$E$22+Detail!$E$30,0) -> 0 | J102: =IF(AND(J17=Detail!$H$8,Detail!$E$21="YES"),Detail!$E$22+Detail!$E$30,0) -> 0 | K102: =IF(AND(K17=Detail!$H$8,Detail!$E$21="YES"),Detail!$E$22+Detail!$E$30,0) -> 0 | L102: =IF(AND(L17=Detail!$H$8,Detail!$E$21="YES"),Detail!$E$22+Detail!$E$30,0) -> 0 | ... FS102: =IF(AND(FS17=Detail!$H$8,Detail!$E$21="YES"),Detail!$E$22+Detail!$E$30,0) -> 0
B103: Permanent Loan Beginning Balane | F103: =+F102+E107-E108 -> 0 | G103: =+G102+F107-F108 -> 0 | H103: =+H102+G107-G108 -> 0 | I103: =+I102+H107-H108 -> 0 | J103: =+J102+I107-I108 -> 0 | K103: =+K102+J107-J108 -> 0 | L103: =+L102+K107-K108 -> 0 | M103: =+M102+L107-L108 -> 0 | ... FS103: =+FS102+FR107-FR108 -> 0
B104: Permanent Loan Fee | C104: =SUM(E104:FS104) -> 0 | F104: =IF(AND(F17=Detail!$H$8,Detail!$E$21="YES"),-Detail!$E$30,0) -> 0 | G104: =IF(AND(G17=Detail!$H$8,Detail!$E$21="YES"),-Detail!$E$30,0) -> 0 | H104: =IF(AND(H17=Detail!$H$8,Detail!$E$21="YES"),-Detail!$E$30,0) -> 0 | I104: =IF(AND(I17=Detail!$H$8,Detail!$E$21="YES"),-Detail!$E$30,0) -> 0 | J104: =IF(AND(J17=Detail!$H$8,Detail!$E$21="YES"),-Detail!$E$30,0) -> 0 | K104: =IF(AND(K17=Detail!$H$8,Detail!$E$21="YES"),-Detail!$E$30,0) -> 0 | L104: =IF(AND(L17=Detail!$H$8,Detail!$E$21="YES"),-Detail!$E$30,0) -> 0 | M104: =IF(AND(M17=Detail!$H$8,Detail!$E$21="YES"),-Detail!$E$30,0) -> 0 | ... FS104: =IF(AND(FS17=Detail!$H$8,Detail!$E$21="YES"),-Detail!$E$30,0) -> 0
B105: Principal | C105: =SUM(E105:FS105) -> 0
B106: Interest | C106: =SUM(E106:FS106) -> 0 | F106: =(F5-E5)/360*F103*Detail!$E$26 -> 0 | G106: =(G5-F5)/360*G103*Detail!$E$26 -> 0 | H106: =(H5-G5)/360*H103*Detail!$E$26 -> 0 | I106: =(I5-H5)/360*I103*Detail!$E$26 -> 0 | J106: =(J5-I5)/360*J103*Detail!$E$26 -> 0 | K106: =(K5-J5)/360*K103*Detail!$E$26 -> 0 | L106: =(L5-K5)/360*L103*Detail!$E$26 -> 0 | M106: =(M5-L5)/360*M103*Detail!$E$26 -> 0 | ... FS106: =(FS5-FR5)/360*FS103*Detail!$E$26 -> 0
B107: Permanent Loan Ending Balance | F107: =+F103-F105+F104 -> 0 | G107: =+G103-G105+G104 -> 0 | H107: =+H103-H105+H104 -> 0 | I107: =+I103-I105+I104 -> 0 | J107: =+J103-J105+J104 -> 0 | K107: =+K103-K105+K104 -> 0 | L107: =+L103-L105+L104 -> 0 | M107: =+M103-M105+M104 -> 0 | ... FS107: =+FS103-FS105+FS104 -> 0
B108: Permanent Loan Repayment | C108: =SUM(E108:FS108) -> 0 | F108: =IF(F17=Detail!$H$9,F103-F105,0) -> 0 | G108: =IF(G17=Detail!$H$9,G103-G105,0) -> 0 | H108: =IF(H17=Detail!$H$9,H103-H105,0) -> 0 | I108: =IF(I17=Detail!$H$9,I103-I105,0) -> 0 | J108: =IF(J17=Detail!$H$9,J103-J105,0) -> 0 | K108: =IF(K17=Detail!$H$9,K103-K105,0) -> 0 | L108: =IF(L17=Detail!$H$9,L103-L105,0) -> 0 | M108: =IF(M17=Detail!$H$9,M103-M105,0) -> 0 | ... FS108: =IF(FS17=Detail!$H$9,FS103-FS105,0) -> 0
B111: EQUITY CASH FLOW SUMMARY
B112: Equity Contribution | C112: =SUM(E112:FS112) -> -18929066 | E112: =IF(E17=Detail!$H$7,-Detail!$C$22,0) -> -18929066 | F112: =IF(F17=Detail!$H$7,-Detail!$C$22,0) -> 0 | G112: =IF(G17=Detail!$H$7,-Detail!$C$22,0) -> 0 | H112: =IF(H17=Detail!$H$7,-Detail!$C$22,0) -> 0 | I112: =IF(I17=Detail!$H$7,-Detail!$C$22,0) -> 0 | J112: =IF(J17=Detail!$H$7,-Detail!$C$22,0) -> 0 | K112: =IF(K17=Detail!$H$7,-Detail!$C$22,0) -> 0 | L112: =IF(L17=Detail!$H$7,-Detail!$C$22,0) -> 0 | ... FS112: =IF(FS17=Detail!$H$7,-Detail!$C$22,0) -> 0
B113: Acquisition Loan Repayment | C113: =SUM(E113:FS113) -> -52100000 | E113: =-E97 -> 0 | F113: =-F97 -> 0 | G113: =-G97 -> 0 | H113: =-H97 -> 0 | I113: =-I97 -> 0 | J113: =-J97 -> 0 | K113: =-K97 -> 0 | L113: =-L97 -> 0 | ... FS113: =-FS97 -> 0
B114: Permanent Loan Infusion | C114: =SUM(E114:FS114) -> 0 | E114: =E102 -> 0 | F114: =F102 -> 0 | G114: =G102 -> 0 | H114: =H102 -> 0 | I114: =I102 -> 0 | J114: =J102 -> 0 | K114: =K102 -> 0 | L114: =L102 -> 0 | ... FS114: =FS102 -> 0
B115: Net Sale Proceeds | C115: =SUM(E115:FS115) -> 91571646 | E115: =IF(E17=Detail!$H$9,Detail!$L$27,0) -> 0 | F115: =IF(F17=Detail!$H$9,Detail!$L$27,0) -> 0 | G115: =IF(G17=Detail!$H$9,Detail!$L$27,0) -> 0 | H115: =IF(H17=Detail!$H$9,Detail!$L$27,0) -> 0 | I115: =IF(I17=Detail!$H$9,Detail!$L$27,0) -> 0 | J115: =IF(J17=Detail!$H$9,Detail!$L$27,0) -> 0 | K115: =IF(K17=Detail!$H$9,Detail!$L$27,0) -> 0 | L115: =IF(L17=Detail!$H$9,Detail!$L$27,0) -> 0 | ... FS115: =IF(FS17=Detail!$H$9,Detail!$L$27,0) -> 0
B116: Permanent Loan Repayment | C116: =SUM(E116:FS116) -> 0 | E116: =-E108 -> 0 | F116: =-F108 -> 0 | G116: =-G108 -> 0 | H116: =-H108 -> 0 | I116: =-I108 -> 0 | J116: =-J108 -> 0 | K116: =-K108 -> 0 | L116: =-L108 -> 0 | ... FS116: =-FS108 -> 0
B117: CF After Debt Service | C117: =SUM(E117:FS117) -> 4450230.3 | E117: =E84 -> 60358.09 | F117: =F84 -> 52248.378 | G117: =G84 -> 52453.133 | H117: =H84 -> 52055.327 | I117: =I84 -> 43925.131 | J117: =J84 -> 52431.612 | K117: =K84 -> 44288.871 | L117: =L84 -> 44150.746 | ... FS117: =FS84 -> 0
B118: Equity Cash Flow Summary | C118: =SUM(E118:FS118) -> 24992810 | E118: =SUM(E112:E117) -> -18868708 | F118: =SUM(F112:F117) -> 52248.378 | G118: =SUM(G112:G117) -> 52453.133 | H118: =SUM(H112:H117) -> 52055.327 | I118: =SUM(I112:I117) -> 43925.131 | J118: =SUM(J112:J117) -> 52431.612 | K118: =SUM(K112:K117) -> 44288.871 | L118: =SUM(L112:L117) -> 44150.746 | ... FS118: =SUM(FS112:FS117) -> 0
E119: =IF(E118<0,IF(AND(E118<0,SUM($E118:E118)<0),SUM($D119:D119)+1,1),0) -> 1 | F119: =IF(F118<0,IF(AND(F118<0,SUM($E118:F118)<0),SUM($D119:E119)+1,1),0) -> 0 | G119: =IF(G118<0,IF(AND(G118<0,SUM($E118:G118)<0),SUM($D119:F119)+1,1),0) -> 0 | H119: =IF(H118<0,IF(AND(H118<0,SUM($E118:H118)<0),SUM($D119:G119)+1,1),0) -> 0 | I119: =IF(I118<0,IF(AND(I118<0,SUM($E118:I118)<0),SUM($D119:H119)+1,1),0) -> 0 | J119: =IF(J118<0,IF(AND(J118<0,SUM($E118:J118)<0),SUM($D119:I119)+1,1),0) -> 0 | K119: =IF(K118<0,IF(AND(K118<0,SUM($E118:K118)<0),SUM($D119:J119)+1,1),0) -> 0 | L119: =IF(L118<0,IF(AND(L118<0,SUM($E118:L118)<0),SUM($D119:K119)+1,1),0) -> 0 | ... FS119: =IF(FS118<0,IF(AND(FS118<0,SUM($E118:FS118)<0),SUM($D119:FR119)+1,1),0) -> 0
...

Sheet Sensitivity
B2: LEVERED PROJECT IRR & MULTIPLE SENSITIVITY
D4: ANNUAL RENT GROWTH
C5: =TEXT('Cash Flow'!C120,"0.0%")&" / "&TEXT('Cash Flow'!C121,"0.00")&"x" -> 25.5% / 2.32x | D5: =E5-0.5% -> 0.015 | E5: =F5-0.5% -> 0.02 | F5: =G5-0.5% -> 0.025 | G5: 0.03 | H5: =G5+0.5% -> 0.035 | I5: =H5+0.5% -> 0.04 | M5: Rent Growth | N5: 0.03
B6: ANNUAL EXPENSE GROWTH | C6: =C7-0.5% -> 0.01 | D6: 21.1% / 2.03x | E6: 23.1% / 2.17x | F6: 25.1% / 2.30x | G6: 27.0% / 2.43x | H6: 28.8% / 2.57x | I6: 30.6% / 2.71x | M6: Expense Growth | N6: 0.02
C7: =C8-0.5% -> 0.015 | D7: 20.3% / 1.98x | E7: 22.3% / 2.11x | F7: 24.3% / 2.24x | G7: 26.2% / 2.38x | H7: 28.1% / 2.51x | I7: 29.9% / 2.65x
C8: 0.02 | D8: 19.4% / 1.93x | E8: 21.5% / 2.06x | F8: 23.5% / 2.19x | G8: 25.5% / 2.32x | H8: 27.4% / 2.46x | I8: 29.2% / 2.60x
C9: =C8+0.5% -> 0.025 | D9: 18.5% / 1.87x | E9: 20.6% / 2.00x | F9: 22.7% / 2.14x | G9: 24.7% / 2.27x | H9: 26.6% / 2.41x | I9: 28.5% / 2.54x
C10: =C9+0.5% -> 0.03 | D10: 17.5% / 1.82x | E10: 19.7% / 1.95x | F10: 21.8% / 2.08x | G10: 23.8% / 2.21x | H10: 25.8% / 2.35x | I10: 27.7% / 2.49x
C11: =C10+0.5% -> 0.035 | D11: 16.5% / 1.76x | E11: 18.7% / 1.89x | F11: 20.9% / 2.02x | G11: 23.0% / 2.16x | H11: 25.0% / 2.29x | I11: 26.9% / 2.43x

Sheet Waterfall (Two Tier)
B2: Sentosa Recap
B3: Waterfall Analysis
B4: Equity Capitalization
B5: LP Equity | C5: =E5/$E$7 -> 0.68265386 | E5: =Summary!C14 -> 12922000
B6: GP Equity | C6: =1-C5 -> 0.31734614 | E6: =E7-E5 -> 6007066.2
B7: Total | C7: =SUM(C5:C6) -> 1 | E7: =Summary!C15 -> 18929066
B9: Promote Structure | E9: Sponsor
C10: Hurdle | E10: Promote
B11: Tier I | C11: -- | E11: 0
B12: Tier II (after) | C12: 0.08 | E12: 0.2
B13: Tier III (after) | C13: 0.11 | E13: 0.25
B14: Tier III (after) | C14: 0.17 | E14: 0.35
B16: Monthly Cash Flow | I16: =YEAR(I17) -> 2026 | J16: =YEAR(J17) -> 2026 | K16: =YEAR(K17) -> 2026 | L16: =YEAR(L17) -> 2026 | M16: =YEAR(M17) -> 2026 | N16: =YEAR(N17) -> 2026 | O16: =YEAR(O17) -> 2026 | P16: =YEAR(P17) -> 2027 | ... FB16: =YEAR(FB17) -> 2038
G17: TOTAL | I17: ='Cash Flow'!E5 -> 46203 | J17: =EDATE(I17, 1) -> 46233 | K17: =EDATE(J17, 1) -> 46264 | L17: =EDATE(K17, 1) -> 46295 | M17: =EDATE(L17, 1) -> 46325 | N17: =EDATE(M17, 1) -> 46356 | O17: =EDATE(N17, 1) -> 46386 | P17: =EDATE(O17, 1) -> 46417 | Q17: =EDATE(P17, 1) -> 46446 | ... FB17: =EDATE(FA17, 1) -> 50737 | FD17: TOTAL
B18: ='Cash Flow'!B112 -> Equity Contribution | I18: ='Cash Flow'!E112 -> -18929066 | J18: ='Cash Flow'!F112 -> 0 | K18: ='Cash Flow'!G112 -> 0 | L18: ='Cash Flow'!H112 -> 0 | M18: ='Cash Flow'!I112 -> 0 | N18: ='Cash Flow'!J112 -> 0 | O18: ='Cash Flow'!K112 -> 0 | P18: ='Cash Flow'!L112 -> 0 | ... FB18: ='Cash Flow'!EX112 -> 0 | FD18: =+SUM(I18:FB18) -> -18929066
B19: ='Cash Flow'!B113 -> Acquisition Loan Repayment | I19: ='Cash Flow'!E113 -> 0 | J19: ='Cash Flow'!F113 -> 0 | K19: ='Cash Flow'!G113 -> 0 | L19: ='Cash Flow'!H113 -> 0 | M19: ='Cash Flow'!I113 -> 0 | N19: ='Cash Flow'!J113 -> 0 | O19: ='Cash Flow'!K113 -> 0 | P19: ='Cash Flow'!L113 -> 0 | ... FB19: ='Cash Flow'!EX113 -> 0 | FD19: =+SUM(I19:FB19) -> -52100000
B20: ='Cash Flow'!B114 -> Permanent Loan Infusion | I20: ='Cash Flow'!E114 -> 0 | J20: ='Cash Flow'!F114 -> 0 | K20: ='Cash Flow'!G114 -> 0 | L20: ='Cash Flow'!H114 -> 0 | M20: ='Cash Flow'!I114 -> 0 | N20: ='Cash Flow'!J114 -> 0 | O20: ='Cash Flow'!K114 -> 0 | P20: ='Cash Flow'!L114 -> 0 | ... FB20: ='Cash Flow'!EX114 -> 0 | FD20: =+SUM(I20:FB20) -> 0
B21: ='Cash Flow'!B115 -> Net Sale Proceeds | I21: ='Cash Flow'!E115 -> 0 | J21: ='Cash Flow'!F115 -> 0 | K21: ='Cash Flow'!G115 -> 0 | L21: ='Cash Flow'!H115 -> 0 | M21: ='Cash Flow'!I115 -> 0 | N21: ='Cash Flow'!J115 -> 0 | O21: ='Cash Flow'!K115 -> 0 | P21: ='Cash Flow'!L115 -> 0 | ... FB21: ='Cash Flow'!EX115 -> 0 | FD21: =+SUM(I21:FB21) -> 91571646
B22: ='Cash Flow'!B116 -> Permanent Loan Repayment | I22: ='Cash Flow'!E116 -> 0 | J22: ='Cash Flow'!F116 -> 0 | K22: ='Cash Flow'!G116 -> 0 | L22: ='Cash Flow'!H116 -> 0 | M22: ='Cash Flow'!I116 -> 0 | N22: ='Cash Flow'!J116 -> 0 | O22: ='Cash Flow'!K116 -> 0 | P22: ='Cash Flow'!L116 -> 0 | ... FB22: ='Cash Flow'!EX116 -> 0 | FD22: =+SUM(I22:FB22) -> 0
B23: ='Cash Flow'!B117 -> CF After Debt Service | I23: ='Cash Flow'!E117 -> 60358.09 | J23: ='Cash Flow'!F117 -> 52248.378 | K23: ='Cash Flow'!G117 -> 52453.133 | L23: ='Cash Flow'!H117 -> 52055.327 | M23: ='Cash Flow'!I117 -> 43925.131 | N23: ='Cash Flow'!J117 -> 52431.612 | O23: ='Cash Flow'!K117 -> 44288.871 | P23: ='Cash Flow'!L117 -> 44150.746 | ... FB23: ='Cash Flow'!EX117 -> 0 | FD23: =+SUM(I23:FB23) -> 4450230.3
I24: 0 | J24: 0 | K24: 0 | L24: 0 | M24: 0 | N24: 0 | O24: 0 | P24: 0 | Q24: 0 | R24: 0 | S24: 0 | T24: 0 | U24: 0 | V24: 0 | W24: 0 | X24: 0 | Y24: 0 | Z24: 0 | AA24: 0 | AB24: 0 | AC24: 0 | AD24: 0 | AE24: 0 | AF24: 0 | AG24: 0 | AH24: 0 | AI24: 0 | AJ24: 0 | AK24: 0 | AL24: 0 | AM24: 0 | AN24: 0 | AO24: 0 | AP24: 0 | AQ24: 0 | AR24: 0 | AS24: 0 | AT24: 0 | AU24: 0 | AV24: 0 | AW24: 0 | AX24: 0 | AY24: 0 | AZ24: 0 | BA24: 0 | BB24: 0 | BC24: 0 | BD24: 0 | BE24: 0 | BF24: 0 | BG24: 0 | BH24: 0 | BI24: 0 | BJ24: 0 | BK24: 0 | BL24: 0 | BM24: 0 | BN24: 0 | BO24: 0 | BP24: 0 | BQ24: 0 | BR24: 0 | BS24: 0 | BT24: 0 | BU24: 0 | BV24: 0 | BW24: 0 | BX24: 0 | BY24: 0 | BZ24: 0 | CA24: 0 | CB24: 0 | CC24: 0 | CD24: 0 | CE24: 0 | CF24: 0 | CG24: 0 | CH24: 0 | CI24: 0 | CJ24: 0 | CK24: 0 | CL24: 0 | CM24: 0 | CN24: 0 | CO24: 0 | CP24: 0 | CQ24: 0 | CR24: 0 | CS24: 0 | CT24: 0 | CU24: 0 | CV24: 0 | CW24: 0 | CX24: 0 | CY24: 0 | CZ24: 0 | DA24: 0 | DB24: 0 | DC24: 0 | DD24: 0 | DE24: 0 | DF24: 0 | DG24: 0 | DH24: 0 | DI24: 0 | DJ24: 0 | DK24: 0 | DL24: 0 | DM24: 0 | DN24: 0 | DO24: 0 | DP24: 0 | DQ24: 0 | DR24: 0 | DS24: 0 | DT24: 0 | DU24: 0 | DV24: 0 | DW24: 0 | DX24: 0 | DY24: 0 | DZ24: 0 | EA24: 0 | EB24: 0 | EC24: 0 | ED24: 0 | EE24: 0 | EF24: 0 | EG24: 0 | EH24: 0 | EI24: 0 | EJ24: 0 | EK24: 0 | EL24: 0 | EM24: 0 | EN24: 0 | EO24: 0 | EP24: 0 | EQ24: 0 | ER24: 0 | ES24: 0 | ET24: 0 | EU24: 0 | EV24: 0 | EW24: 0 | EX24: 0 | EY24: 0 | EZ24: 0 | FA24: 0 | FB24: 0 | FD24: =+SUM(I24:FB24) -> 0
I25: 0 | J25: 0 | K25: 0 | L25: 0 | M25: 0 | N25: 0 | O25: 0 | P25: 0 | Q25: 0 | R25: 0 | S25: 0 | T25: 0 | U25: 0 | V25: 0 | W25: 0 | X25: 0 | Y25: 0 | Z25: 0 | AA25: 0 | AB25: 0 | AC25: 0 | AD25: 0 | AE25: 0 | AF25: 0 | AG25: 0 | AH25: 0 | AI25: 0 | AJ25: 0 | AK25: 0 | AL25: 0 | AM25: 0 | AN25: 0 | AO25: 0 | AP25: 0 | AQ25: 0 | AR25: 0 | AS25: 0 | AT25: 0 | AU25: 0 | AV25: 0 | AW25: 0 | AX25: 0 | AY25: 0 | AZ25: 0 | BA25: 0 | BB25: 0 | BC25: 0 | BD25: 0 | BE25: 0 | BF25: 0 | BG25: 0 | BH25: 0 | BI25: 0 | BJ25: 0 | BK25: 0 | BL25: 0 | BM25: 0 | BN25: 0 | BO25: 0 | BP25: 0 | BQ25: 0 | BR25: 0 | BS25: 0 | BT25: 0 | BU25: 0 | BV25: 0 | BW25: 0 | BX25: 0 | BY25: 0 | BZ25: 0 | CA25: 0 | CB25: 0 | CC25: 0 | CD25: 0 | CE25: 0 | CF25: 0 | CG25: 0 | CH25: 0 | CI25: 0 | CJ25: 0 | CK25: 0 | CL25: 0 | CM25: 0 | CN25: 0 | CO25: 0 | CP25: 0 | CQ25: 0 | CR25: 0 | CS25: 0 | CT25: 0 | CU25: 0 | CV25: 0 | CW25: 0 | CX25: 0 | CY25: 0 | CZ25: 0 | DA25: 0 | DB25: 0 | DC25: 0 | DD25: 0 | DE25: 0 | DF25: 0 | DG25: 0 | DH25: 0 | DI25: 0 | DJ25: 0 | DK25: 0 | DL25: 0 | DM25: 0 | DN25: 0 | DO25: 0 | DP25: 0 | DQ25: 0 | DR25: 0 | DS25: 0 | DT25: 0 | DU25: 0 | DV25: 0 | DW25: 0 | DX25: 0 | DY25: 0 | DZ25: 0 | EA25: 0 | EB25: 0 | EC25: 0 | ED25: 0 | EE25: 0 | EF25: 0 | EG25: 0 | EH25: 0 | EI25: 0 | EJ25: 0 | EK25: 0 | EL25: 0 | EM25: 0 | EN25: 0 | EO25: 0 | EP25: 0 | EQ25: 0 | ER25: 0 | ES25: 0 | ET25: 0 | EU25: 0 | EV25: 0 | EW25: 0 | EX25: 0 | EY25: 0 | EZ25: 0 | FA25: 0 | FB25: 0 | FD25: =+SUM(I25:FB25) -> 0
B26: Net Cash Flow | E26: =IF($C$5>0,TEXT(XIRR($I26:$FB26,$I$17:$FB$17),"#0.0%")&" / "&TEXT(((FD26-SUMIF(I26:FB26,"<0")))/-SUMIF(I26:FB26,"<0"),"#0.00x"),"n/m") -> 25.5% / 2.32x | G26: =SUM(I26:FB26) -> 24992810 | I26: =+SUM(I18:I25) -> -18868708 | J26: =+SUM(J18:J25) -> 52248.378 | K26: =+SUM(K18:K25) -> 52453.133 | L26: =+SUM(L18:L25) -> 52055.327 | M26: =+SUM(M18:M25) -> 43925.131 | N26: =+SUM(N18:N25) -> 52431.612 | O26: =+SUM(O18:O25) -> 44288.871 | P26: =+SUM(P18:P25) -> 44150.746 | ... FB26: =+SUM(FB18:FB25) -> 0 | FD26: =SUM(I26:FB26) -> 24992810
B27: ="Net Cash Flow to the Venture " -> Net Cash Flow to the Venture | E27: =TEXT(XIRR($I27:$FB27,$I$17:$FB$17),"#0.0%")&" / "&TEXT(((FD27-SUMIF(I27:FB27,"<0")))/-SUMIF(I27:FB27,"<0"),"#0.00x") -> 25.5% / 2.32x | G27: =SUM(I27:FB27) -> 24992810 | I27: =SUM(I26:I26) -> -18868708 | J27: =SUM(J26:J26) -> 52248.378 | K27: =SUM(K26:K26) -> 52453.133 | L27: =SUM(L26:L26) -> 52055.327 | M27: =SUM(M26:M26) -> 43925.131 | N27: =SUM(N26:N26) -> 52431.612 | O27: =SUM(O26:O26) -> 44288.871 | P27: =SUM(P26:P26) -> 44150.746 | ... FB27: =SUM(FB26:FB26) -> 0 | FD27: =SUM(I27:FB27) -> 24992810
B29: ="Tier I -- LP IRR below "&TEXT($C$12,"#0%") -> Tier I -- LP IRR below 8%
B30: ="Amount Needed to Achieve "&TEXT($C12,"#0%")&" LP IRR" -> Amount Needed to Achieve 8% LP IRR | J30: =IF(XNPV($C12,$I$68:I$68,$I$17:I$17)>=0,0,FV($C12,(J$17-$I$17)/365,0,(XNPV($C12,$I$68:I$68,$I$17:I$17)))) -> 12962533 | K30: =IF(XNPV($C12,$I$68:J$68,$I$17:J$17)>=0,0,FV($C12,(K$17-$I$17)/365,0,(XNPV($C12,$I$68:J$68,$I$17:J$17)))) -> 13011637 | L30: =IF(XNPV($C12,$I$68:K$68,$I$17:K$17)>=0,0,FV($C12,(L$17-$I$17)/365,0,(XNPV($C12,$I$68:K$68,$I$17:K$17)))) -> 13060923 | M30: =IF(XNPV($C12,$I$68:L$68,$I$17:L$17)>=0,0,FV($C12,(M$17-$I$17)/365,0,(XNPV($C12,$I$68:L$68,$I$17:L$17)))) -> 13108042 | N30: =IF(XNPV($C12,$I$68:M$68,$I$17:M$17)>=0,0,FV($C12,(N$17-$I$17)/365,0,(XNPV($C12,$I$68:M$68,$I$17:M$17)))) -> 13163820 | O30: =IF(XNPV($C12,$I$68:N$68,$I$17:N$17)>=0,0,FV($C12,(O$17-$I$17)/365,0,(XNPV($C12,$I$68:N$68,$I$17:N$17)))) -> 13211332 | P30: =IF(XNPV($C12,$I$68:O$68,$I$17:O$17)>=0,0,FV($C12,(P$17-$I$17)/365,0,(XNPV($C12,$I$68:O$68,$I$17:O$17)))) -> 13267538 | Q30: =IF(XNPV($C12,$I$68:P$68,$I$17:P$17)>=0,0,FV($C12,(Q$17-$I$17)/365,0,(XNPV($C12,$I$68:P$68,$I$17:P$17)))) -> 13318589 | ... CZ30: =IF(XNPV($C12,$I$68:CY$68,$I$17:CY$17)>=0,0,FV($C12,(CZ$17-$I$17)/365,0,(XNPV($C12,$I$68:CY$68,$I$17:CY$17)))) -> 0 | DA30: =IF(XNPV($C12,$I$68:BR$68,$I$17:BR$17)>=0,0,FV($C12,(DA$17-$I$17)/365,0,(XNPV($C12,$I$68:BR$68,$I$17:BR$17)))) -> 0 | DB30: =IF(XNPV($C12,$I$68:BJ$68,$I$17:BJ$17)>=0,0,FV($C12,(DB$17-$I$17)/365,0,(XNPV($C12,$I$68:BJ$68,$I$17:BJ$17)))) -> 0 | DC30: =IF(XNPV($C12,$I$68:DB$68,$I$17:DB$17)>=0,0,FV($C12,(DC$17-$I$17)/365,0,(XNPV($C12,$I$68:DB$68,$I$17:DB$17)))) -> 0 | DD30: =IF(XNPV($C12,$I$68:DC$68,$I$17:DC$17)>=0,0,FV($C12,(DD$17-$I$17)/365,0,(XNPV($C12,$I$68:DC$68,$I$17:DC$17)))) -> 0 | DE30: =IF(XNPV($C12,$I$68:DD$68,$I$17:DD$17)>=0,0,FV($C12,(DE$17-$I$17)/365,0,(XNPV($C12,$I$68:DD$68,$I$17:DD$17)))) -> 0 | DF30: =IF(XNPV($C12,$I$68:DE$68,$I$17:DE$17)>=0,0,FV($C12,(DF$17-$I$17)/365,0,(XNPV($C12,$I$68:DE$68,$I$17:DE$17)))) -> 0 | DG30: =IF(XNPV($C12,$I$68:DF$68,$I$17:DF$17)>=0,0,FV($C12,(DG$17-$I$17)/365,0,(XNPV($C12,$I$68:DF$68,$I$17:DF$17)))) -> 0 | DH30: =IF(XNPV($C12,$I$68:DG$68,$I$17:DG$17)>=0,0,FV($C12,(DH$17-$I$17)/365,0,(XNPV($C12,$I$68:DG$68,$I$17:DG$17)))) -> 0 | DI30: =IF(XNPV($C12,$I$68:DH$68,$I$17:DH$17)>=0,0,FV($C12,(DI$17-$I$17)/365,0,(XNPV($C12,$I$68:DH$68,$I$17:DH$17)))) -> 0 | DJ30: =IF(XNPV($C12,$I$68:DI$68,$I$17:DI$17)>=0,0,FV($C12,(DJ$17-$I$17)/365,0,(XNPV($C12,$I$68:DI$68,$I$17:DI$17)))) -> 0 | DK30: =IF(XNPV($C12,$I$68:DA$68,$I$17:DA$17)>=0,0,FV($C12,(DK$17-$I$17)/365,0,(XNPV($C12,$I$68:DA$68,$I$17:DA$17)))) -> 0 | DL30: =IF(XNPV($C12,$I$68:DK$68,$I$17:DK$17)>=0,0,FV($C12,(DL$17-$I$17)/365,0,(XNPV($C12,$I$68:DK$68,$I$17:DK$17)))) -> 0 | DM30: =IF(XNPV($C12,$I$68:DL$68,$I$17:DL$17)>=0,0,FV($C12,(DM$17-$I$17)/365,0,(XNPV($C12,$I$68:DL$68,$I$17:DL$17)))) -> 0 | DN30: =IF(XNPV($C12,$I$68:DM$68,$I$17:DM$17)>=0,0,FV($C12,(DN$17-$I$17)/365,0,(XNPV($C12,$I$68:DM$68,$I$17:DM$17)))) -> 0 | DO30: =IF(XNPV($C12,$I$68:DN$68,$I$17:DN$17)>=0,0,FV($C12,(DO$17-$I$17)/365,0,(XNPV($C12,$I$68:DN$68,$I$17:DN$17)))) -> 0 | DP30: =IF(XNPV($C12,$I$68:DO$68,$I$17:DO$17)>=0,0,FV($C12,(DP$17-$I$17)/365,0,(XNPV($C12,$I$68:DO$68,$I$17:DO$17)))) -> 0 | DQ30: =IF(XNPV($C12,$I$68:DP$68,$I$17:DP$17)>=0,0,FV($C12,(DQ$17-$I$17)/365,0,(XNPV($C12,$I$68:DP$68,$I$17:DP$17)))) -> 0 | DR30: =IF(XNPV($C12,$I$68:CI$68,$I$17:CI$17)>=0,0,FV($C12,(DR$17-$I$17)/365,0,(XNPV($C12,$I$68:CI$68,$I$17:CI$17)))) -> 0 | DS30: =IF(XNPV($C12,$I$68:CA$68,$I$17:CA$17)>=0,0,FV($C12,(DS$17-$I$17)/365,0,(XNPV($C12,$I$68:CA$68,$I$17:CA$17)))) -> 0 | DT30: =IF(XNPV($C12,$I$68:DS$68,$I$17:DS$17)>=0,0,FV($C12,(DT$17-$I$17)/365,0,(XNPV($C12,$I$68:DS$68,$I$17:DS$17)))) -> 0 | DU30: =IF(XNPV($C12,$I$68:DT$68,$I$17:DT$17)>=0,0,FV($C12,(DU$17-$I$17)/365,0,(XNPV($C12,$I$68:DT$68,$I$17:DT$17)))) -> 0 | DV30: =IF(XNPV($C12,$I$68:DU$68,$I$17:DU$17)>=0,0,FV($C12,(DV$17-$I$17)/365,0,(XNPV($C12,$I$68:DU$68,$I$17:DU$17)))) -> 0 | DW30: =IF(XNPV($C12,$I$68:DV$68,$I$17:DV$17)>=0,0,FV($C12,(DW$17-$I$17)/365,0,(XNPV($C12,$I$68:DV$68,$I$17:DV$17)))) -> 0 | DX30: =IF(XNPV($C12,$I$68:DW$68,$I$17:DW$17)>=0,0,FV($C12,(DX$17-$I$17)/365,0,(XNPV($C12,$I$68:DW$68,$I$17:DW$17)))) -> 0 | DY30: =IF(XNPV($C12,$I$68:DX$68,$I$17:DX$17)>=0,0,FV($C12,(DY$17-$I$17)/365,0,(XNPV($C12,$I$68:DX$68,$I$17:DX$17)))) -> 0 | DZ30: =IF(XNPV($C12,$I$68:DY$68,$I$17:DY$17)>=0,0,FV($C12,(DZ$17-$I$17)/365,0,(XNPV($C12,$I$68:DY$68,$I$17:DY$17)))) -> 0 | EA30: =IF(XNPV($C12,$I$68:DZ$68,$I$17:DZ$17)>=0,0,FV($C12,(EA$17-$I$17)/365,0,(XNPV($C12,$I$68:DZ$68,$I$17:DZ$17)))) -> 0 | EB30: =IF(XNPV($C12,$I$68:DR$68,$I$17:DR$17)>=0,0,FV($C12,(EB$17-$I$17)/365,0,(XNPV($C12,$I$68:DR$68,$I$17:DR$17)))) -> 0 | EC30: =IF(XNPV($C12,$I$68:EB$68,$I$17:EB$17)>=0,0,FV($C12,(EC$17-$I$17)/365,0,(XNPV($C12,$I$68:EB$68,$I$17:EB$17)))) -> 0 | ED30: =IF(XNPV($C12,$I$68:EC$68,$I$17:EC$17)>=0,0,FV($C12,(ED$17-$I$17)/365,0,(XNPV($C12,$I$68:EC$68,$I$17:EC$17)))) -> 0 | EE30: =IF(XNPV($C12,$I$68:ED$68,$I$17:ED$17)>=0,0,FV($C12,(EE$17-$I$17)/365,0,(XNPV($C12,$I$68:ED$68,$I$17:ED$17)))) -> 0 | EF30: =IF(XNPV($C12,$I$68:EE$68,$I$17:EE$17)>=0,0,FV($C12,(EF$17-$I$17)/365,0,(XNPV($C12,$I$68:EE$68,$I$17:EE$17)))) -> 0 | EG30: =IF(XNPV($C12,$I$68:EF$68,$I$17:EF$17)>=0,0,FV($C12,(EG$17-$I$17)/365,0,(XNPV($C12,$I$68:EF$68,$I$17:EF$17)))) -> 0 | EH30: =IF(XNPV($C12,$I$68:EG$68,$I$17:EG$17)>=0,0,FV($C12,(EH$17-$I$17)/365,0,(XNPV($C12,$I$68:EG$68,$I$17:EG$17)))) -> 0 | EI30: =IF(XNPV($C12,$I$68:CZ$68,$I$17:CZ$17)>=0,0,FV($C12,(EI$17-$I$17)/365,0,(XNPV($C12,$I$68:CZ$68,$I$17:CZ$17)))) -> 0 | EJ30: =IF(XNPV($C12,$I$68:CR$68,$I$17:CR$17)>=0,0,FV($C12,(EJ$17-$I$17)/365,0,(XNPV($C12,$I$68:CR$68,$I$17:CR$17)))) -> 0 | EK30: =IF(XNPV($C12,$I$68:EJ$68,$I$17:EJ$17)>=0,0,FV($C12,(EK$17-$I$17)/365,0,(XNPV($C12,$I$68:EJ$68,$I$17:EJ$17)))) -> 0 | EL30: =IF(XNPV($C12,$I$68:EK$68,$I$17:EK$17)>=0,0,FV($C12,(EL$17-$I$17)/365,0,(XNPV($C12,$I$68:EK$68,$I$17:EK$17)))) -> 0 | EM30: =IF(XNPV($C12,$I$68:EL$68,$I$17:EL$17)>=0,0,FV($C12,(EM$17-$I$17)/365,0,(XNPV($C12,$I$68:EL$68,$I$17:EL$17)))) -> 0 | EN30: =IF(XNPV($C12,$I$68:EM$68,$I$17:EM$17)>=0,0,FV($C12,(EN$17-$I$17)/365,0,(XNPV($C12,$I$68:EM$68,$I$17:EM$17)))) -> 0 | EO30: =IF(XNPV($C12,$I$68:EN$68,$I$17:EN$17)>=0,0,FV($C12,(EO$17-$I$17)/365,0,(XNPV($C12,$I$68:EN$68,$I$17:EN$17)))) -> 0 | EP30: =IF(XNPV($C12,$I$68:EO$68,$I$17:EO$17)>=0,0,FV($C12,(EP$17-$I$17)/365,0,(XNPV($C12,$I$68:EO$68,$I$17:EO$17)))) -> 0 | EQ30: =IF(XNPV($C12,$I$68:EP$68,$I$17:EP$17)>=0,0,FV($C12,(EQ$17-$I$17)/365,0,(XNPV($C12,$I$68:EP$68,$I$17:EP$17)))) -> 0 | ER30: =IF(XNPV($C12,$I$68:EQ$68,$I$17:EQ$17)>=0,0,FV($C12,(ER$17-$I$17)/365,0,(XNPV($C12,$I$68:EQ$68,$I$17:EQ$17)))) -> 0 | ES30: =IF(XNPV($C12,$I$68:EI$68,$I$17:EI$17)>=0,0,FV($C12,(ES$17-$I$17)/365,0,(XNPV($C12,$I$68:EI$68,$I$17:EI$17)))) -> 0 | ET30: =IF(XNPV($C12,$I$68:ES$68,$I$17:ES$17)>=0,0,FV($C12,(ET$17-$I$17)/365,0,(XNPV($C12,$I$68:ES$68,$I$17:ES$17)))) -> 0 | EU30: =IF(XNPV($C12,$I$68:ET$68,$I$17:ET$17)>=0,0,FV($C12,(EU$17-$I$17)/365,0,(XNPV($C12,$I$68:ET$68,$I$17:ET$17)))) -> 0 | EV30: =IF(XNPV($C12,$I$68:EU$68,$I$17:EU$17)>=0,0,FV($C12,(EV$17-$I$17)/365,0,(XNPV($C12,$I$68:EU$68,$I$17:EU$17)))) -> 0 | EW30: =IF(XNPV($C12,$I$68:EV$68,$I$17:EV$17)>=0,0,FV($C12,(EW$17-$I$17)/365,0,(XNPV($C12,$I$68:EV$68,$I$17:EV$17)))) -> 0 | EX30: =IF(XNPV($C12,$I$68:EW$68,$I$17:EW$17)>=0,0,FV($C12,(EX$17-$I$17)/365,0,(XNPV($C12,$I$68:EW$68,$I$17:EW$17)))) -> 0 | EY30: =IF(XNPV($C12,$I$68:EX$68,$I$17:EX$17)>=0,0,FV($C12,(EY$17-$I$17)/365,0,(XNPV($C12,$I$68:EX$68,$I$17:EX$17)))) -> 0 | EZ30: =IF(XNPV($C12,$I$68:EY$68,$I$17:EY$17)>=0,0,FV($C12,(EZ$17-$I$17)/365,0,(XNPV($C12,$I$68:EY$68,$I$17:EY$17)))) -> 0 | FA30: =IF(XNPV($C12,$I$68:EZ$68,$I$17:EZ$17)>=0,0,FV($C12,(FA$17-$I$17)/365,0,(XNPV($C12,$I$68:EZ$68,$I$17:EZ$17)))) -> 0 | FB30: =IF(XNPV($C12,$I$68:FA$68,$I$17:FA$17)>=0,0,FV($C12,(FB$17-$I$17)/365,0,(XNPV($C12,$I$68:FA$68,$I$17:FA$17)))) -> 0
B31: Less: Period Payments to LP | I31: 0 | J31: 0 | K31: 0 | L31: 0 | M31: 0 | N31: 0 | O31: 0 | P31: 0 | Q31: 0 | R31: 0 | S31: 0 | T31: 0 | U31: 0 | V31: 0 | W31: 0 | X31: 0 | Y31: 0 | Z31: 0 | AA31: 0 | AB31: 0 | AC31: 0 | AD31: 0 | AE31: 0 | AF31: 0 | AG31: 0 | AH31: 0 | AI31: 0 | AJ31: 0 | AK31: 0 | AL31: 0 | AM31: 0 | AN31: 0 | AO31: 0 | AP31: 0 | AQ31: 0 | AR31: 0 | AS31: 0 | AT31: 0 | AU31: 0 | AV31: 0 | AW31: 0 | AX31: 0 | AY31: 0 | AZ31: 0 | BA31: 0 | BB31: 0 | BC31: 0 | BD31: 0 | BE31: 0 | BF31: 0 | BG31: 0 | BH31: 0 | BI31: 0 | BJ31: 0 | BK31: 0 | BL31: 0 | BM31: 0 | BN31: 0 | BO31: 0 | BP31: 0 | BQ31: 0 | BR31: 0 | BS31: 0 | BT31: 0 | BU31: 0 | BV31: 0 | BW31: 0 | BX31: 0 | BY31: 0 | BZ31: 0 | CA31: 0 | CB31: 0 | CC31: 0 | CD31: 0 | CE31: 0 | CF31: 0 | CG31: 0 | CH31: 0 | CI31: 0 | CJ31: 0 | CK31: 0 | CL31: 0 | CM31: 0 | CN31: 0 | CO31: 0 | CP31: 0 | CQ31: 0 | CR31: 0 | CS31: 0 | CT31: 0 | CU31: 0 | CV31: 0 | CW31: 0 | CX31: 0 | CY31: 0 | CZ31: 0 | DA31: 0 | DB31: 0 | DC31: 0 | DD31: 0 | DE31: 0 | DF31: 0 | DG31: 0 | DH31: 0 | DI31: 0 | DJ31: 0 | DK31: 0 | DL31: 0 | DM31: 0 | DN31: 0 | DO31: 0 | DP31: 0 | DQ31: 0 | DR31: 0 | DS31: 0 | DT31: 0 | DU31: 0 | DV31: 0 | DW31: 0 | DX31: 0 | DY31: 0 | DZ31: 0 | EA31: 0 | EB31: 0 | EC31: 0 | ED31: 0 | EE31: 0 | EF31: 0 | EG31: 0 | EH31: 0 | EI31: 0 | EJ31: 0 | EK31: 0 | EL31: 0 | EM31: 0 | EN31: 0 | EO31: 0 | EP31: 0 | EQ31: 0 | ER31: 0 | ES31: 0 | ET31: 0 | EU31: 0 | EV31: 0 | EW31: 0 | EX31: 0 | EY31: 0 | EZ31: 0 | FA31: 0 | FB31: 0
B32: Effective LP Tier I Threshold | I32: =SUM(I30:I31) -> 0 | J32: =SUM(J30:J31) -> 12962533 | K32: =SUM(K30:K31) -> 13011637 | L32: =SUM(L30:L31) -> 13060923 | M32: =SUM(M30:M31) -> 13108042 | N32: =SUM(N30:N31) -> 13163820 | O32: =SUM(O30:O31) -> 13211332 | P32: =SUM(P30:P31) -> 13267538 | ... FB32: =SUM(FB30:FB31) -> 0
B33: Total Cash Flow Allocated to Tier I | G33: =SUM(I33:FB33) -> 6054747.9 | I33: =MIN(I27,I32/$E34) -> -18868708 | J33: =MIN(J27,J32/$E34) -> 52248.378 | K33: =MIN(K27,K32/$E34) -> 52453.133 | L33: =MIN(L27,L32/$E34) -> 52055.327 | M33: =MIN(M27,M32/$E34) -> 43925.131 | N33: =MIN(N27,N32/$E34) -> 52431.612 | O33: =MIN(O27,O32/$E34) -> 44288.871 | P33: =MIN(P27,P32/$E34) -> 44150.746 | ... FB33: =MIN(FB27,FB32/$E34) -> 0 | FD33: =SUM(I33:FB33) -> 6054747.9
B34: Portion Paid to LP | E34: =1-E35 -> 0.68265386 | G34: =SUM(I34:FB34) -> 4133297 | I34: =$E34*I33 -> -12880796 | J34: =$E34*J33 -> 35667.557 | K34: =$E34*K33 -> 35807.333 | L34: =$E34*L33 -> 35535.77 | M34: =$E34*M33 -> 29985.66 | N34: =$E34*N33 -> 35792.642 | O34: =$E34*O33 -> 30233.969 | P34: =$E34*P33 -> 30139.677 | ... FB34: =$E34*FB33 -> 0 | FD34: =SUM(I34:FB34) -> 4133297
B35: Portion Paid to GP | E35: =$C$6 -> 0.31734614 | G35: =SUM(I35:FB35) -> 1921450.9 | I35: =$E35*I33 -> -5987911.8 | J35: =$E35*J33 -> 16580.821 | K35: =$E35*K33 -> 16645.799 | L35: =$E35*L33 -> 16519.557 | M35: =$E35*M33 -> 13939.471 | N35: =$E35*N33 -> 16638.97 | O35: =$E35*O33 -> 14054.903 | P35: =$E35*P33 -> 14011.069 | ... FB35: =$E35*FB33 -> 0 | FD35: =SUM(I35:FB35) -> 1921450.9
B36: Portion Paid to Sponsor Promote | E36: =E11 -> 0 | G36: =SUM(I36:FB36) -> 0 | I36: =$E36*I33 -> 0 | J36: =$E36*J33 -> 0 | K36: =$E36*K33 -> 0 | L36: =$E36*L33 -> 0 | M36: =$E36*M33 -> 0 | N36: =$E36*N33 -> 0 | O36: =$E36*O33 -> 0 | P36: =$E36*P33 -> 0 | ... FB36: =$E36*FB33 -> 0 | FD36: =SUM(I36:FB36) -> 0
B37: CF Remaining After Tier I | I37: =I27-I33 -> 0 | J37: =J27-J33 -> 0 | K37: =K27-K33 -> 0 | L37: =L27-L33 -> 0 | M37: =M27-M33 -> 0 | N37: =N27-N33 -> 0 | O37: =O27-O33 -> 0 | P37: =P27-P33 -> 0 | ... FB37: =FB27-FB33 -> 0
B39: ="Tier II -- LP IRR between "&TEXT($C$12,"#0%")&" and "&TEXT($C$13,"#0%") -> Tier II -- LP IRR between 8% and 11%
B40: ="Amount Needed to Achieve "&TEXT($C13,"#0%")&" LP IRR" -> Amount Needed to Achieve 11% LP IRR | J40: =IF(XNPV($C13,$I$68:I$68,$I$17:I$17)>=0,0,FV($C13,(J$17-$I$17)/365,0,(XNPV($C13,$I$68:I$68,$I$17:I$17)))) -> 12991757 | K40: =IF(XNPV($C13,$I$68:J$68,$I$17:J$17)>=0,0,FV($C13,(K$17-$I$17)/365,0,(XNPV($C13,$I$68:J$68,$I$17:J$17)))) -> 13071436 | L40: =IF(XNPV($C13,$I$68:K$68,$I$17:K$17)>=0,0,FV($C13,(L$17-$I$17)/365,0,(XNPV($C13,$I$68:K$68,$I$17:K$17)))) -> 13151682 | M40: =IF(XNPV($C13,$I$68:L$68,$I$17:L$17)>=0,0,FV($C13,(M$17-$I$17)/365,0,(XNPV($C13,$I$68:L$68,$I$17:L$17)))) -> 13229135 | N40: =IF(XNPV($C13,$I$68:M$68,$I$17:M$17)>=0,0,FV($C13,(N$17-$I$17)/365,0,(XNPV($C13,$I$68:M$68,$I$17:M$17)))) -> 13316659 | O40: =IF(XNPV($C13,$I$68:N$68,$I$17:N$17)>=0,0,FV($C13,(O$17-$I$17)/365,0,(XNPV($C13,$I$68:N$68,$I$17:N$17)))) -> 13395274 | P40: =IF(XNPV($C13,$I$68:O$68,$I$17:O$17)>=0,0,FV($C13,(P$17-$I$17)/365,0,(XNPV($C13,$I$68:O$68,$I$17:O$17)))) -> 13484027 | Q40: =IF(XNPV($C13,$I$68:P$68,$I$17:P$17)>=0,0,FV($C13,(Q$17-$I$17)/365,0,(XNPV($C13,$I$68:P$68,$I$17:P$17)))) -> 13565905 | ... CZ40: =IF(XNPV($C13,$I$68:CY$68,$I$17:CY$17)>=0,0,FV($C13,(CZ$17-$I$17)/365,0,(XNPV($C13,$I$68:CY$68,$I$17:CY$17)))) -> 0 | DA40: =IF(XNPV($C13,$I$68:BR$68,$I$17:BR$17)>=0,0,FV($C13,(DA$17-$I$17)/365,0,(XNPV($C13,$I$68:BR$68,$I$17:BR$17)))) -> 0 | DB40: =IF(XNPV($C13,$I$68:BJ$68,$I$17:BJ$17)>=0,0,FV($C13,(DB$17-$I$17)/365,0,(XNPV($C13,$I$68:BJ$68,$I$17:BJ$17)))) -> 0 | DC40: =IF(XNPV($C13,$I$68:DB$68,$I$17:DB$17)>=0,0,FV($C13,(DC$17-$I$17)/365,0,(XNPV($C13,$I$68:DB$68,$I$17:DB$17)))) -> 0 | DD40: =IF(XNPV($C13,$I$68:DC$68,$I$17:DC$17)>=0,0,FV($C13,(DD$17-$I$17)/365,0,(XNPV($C13,$I$68:DC$68,$I$17:DC$17)))) -> 0 | DE40: =IF(XNPV($C13,$I$68:DD$68,$I$17:DD$17)>=0,0,FV($C13,(DE$17-$I$17)/365,0,(XNPV($C13,$I$68:DD$68,$I$17:DD$17)))) -> 0 | DF40: =IF(XNPV($C13,$I$68:DE$68,$I$17:DE$17)>=0,0,FV($C13,(DF$17-$I$17)/365,0,(XNPV($C13,$I$68:DE$68,$I$17:DE$17)))) -> 0 | DG40: =IF(XNPV($C13,$I$68:DF$68,$I$17:DF$17)>=0,0,FV($C13,(DG$17-$I$17)/365,0,(XNPV($C13,$I$68:DF$68,$I$17:DF$17)))) -> 0 | DH40: =IF(XNPV($C13,$I$68:DG$68,$I$17:DG$17)>=0,0,FV($C13,(DH$17-$I$17)/365,0,(XNPV($C13,$I$68:DG$68,$I$17:DG$17)))) -> 0 | DI40: =IF(XNPV($C13,$I$68:DH$68,$I$17:DH$17)>=0,0,FV($C13,(DI$17-$I$17)/365,0,(XNPV($C13,$I$68:DH$68,$I$17:DH$17)))) -> 0 | DJ40: =IF(XNPV($C13,$I$68:DI$68,$I$17:DI$17)>=0,0,FV($C13,(DJ$17-$I$17)/365,0,(XNPV($C13,$I$68:DI$68,$I$17:DI$17)))) -> 0 | DK40: =IF(XNPV($C13,$I$68:DA$68,$I$17:DA$17)>=0,0,FV($C13,(DK$17-$I$17)/365,0,(XNPV($C13,$I$68:DA$68,$I$17:DA$17)))) -> 0 | DL40: =IF(XNPV($C13,$I$68:DK$68,$I$17:DK$17)>=0,0,FV($C13,(DL$17-$I$17)/365,0,(XNPV($C13,$I$68:DK$68,$I$17:DK$17)))) -> 0 | DM40: =IF(XNPV($C13,$I$68:DL$68,$I$17:DL$17)>=0,0,FV($C13,(DM$17-$I$17)/365,0,(XNPV($C13,$I$68:DL$68,$I$17:DL$17)))) -> 0 | DN40: =IF(XNPV($C13,$I$68:DM$68,$I$17:DM$17)>=0,0,FV($C13,(DN$17-$I$17)/365,0,(XNPV($C13,$I$68:DM$68,$I$17:DM$17)))) -> 0 | DO40: =IF(XNPV($C13,$I$68:DN$68,$I$17:DN$17)>=0,0,FV($C13,(DO$17-$I$17)/365,0,(XNPV($C13,$I$68:DN$68,$I$17:DN$17)))) -> 0 | DP40: =IF(XNPV($C13,$I$68:DO$68,$I$17:DO$17)>=0,0,FV($C13,(DP$17-$I$17)/365,0,(XNPV($C13,$I$68:DO$68,$I$17:DO$17)))) -> 0 | DQ40: =IF(XNPV($C13,$I$68:DP$68,$I$17:DP$17)>=0,0,FV($C13,(DQ$17-$I$17)/365,0,(XNPV($C13,$I$68:DP$68,$I$17:DP$17)))) -> 0 | DR40: =IF(XNPV($C13,$I$68:CI$68,$I$17:CI$17)>=0,0,FV($C13,(DR$17-$I$17)/365,0,(XNPV($C13,$I$68:CI$68,$I$17:CI$17)))) -> 0 | DS40: =IF(XNPV($C13,$I$68:CA$68,$I$17:CA$17)>=0,0,FV($C13,(DS$17-$I$17)/365,0,(XNPV($C13,$I$68:CA$68,$I$17:CA$17)))) -> 0 | DT40: =IF(XNPV($C13,$I$68:DS$68,$I$17:DS$17)>=0,0,FV($C13,(DT$17-$I$17)/365,0,(XNPV($C13,$I$68:DS$68,$I$17:DS$17)))) -> 0 | DU40: =IF(XNPV($C13,$I$68:DT$68,$I$17:DT$17)>=0,0,FV($C13,(DU$17-$I$17)/365,0,(XNPV($C13,$I$68:DT$68,$I$17:DT$17)))) -> 0 | DV40: =IF(XNPV($C13,$I$68:DU$68,$I$17:DU$17)>=0,0,FV($C13,(DV$17-$I$17)/365,0,(XNPV($C13,$I$68:DU$68,$I$17:DU$17)))) -> 0 | DW40: =IF(XNPV($C13,$I$68:DV$68,$I$17:DV$17)>=0,0,FV($C13,(DW$17-$I$17)/365,0,(XNPV($C13,$I$68:DV$68,$I$17:DV$17)))) -> 0 | DX40: =IF(XNPV($C13,$I$68:DW$68,$I$17:DW$17)>=0,0,FV($C13,(DX$17-$I$17)/365,0,(XNPV($C13,$I$68:DW$68,$I$17:DW$17)))) -> 0 | DY40: =IF(XNPV($C13,$I$68:DX$68,$I$17:DX$17)>=0,0,FV($C13,(DY$17-$I$17)/365,0,(XNPV($C13,$I$68:DX$68,$I$17:DX$17)))) -> 0 | DZ40: =IF(XNPV($C13,$I$68:DY$68,$I$17:DY$17)>=0,0,FV($C13,(DZ$17-$I$17)/365,0,(XNPV($C13,$I$68:DY$68,$I$17:DY$17)))) -> 0 | EA40: =IF(XNPV($C13,$I$68:DZ$68,$I$17:DZ$17)>=0,0,FV($C13,(EA$17-$I$17)/365,0,(XNPV($C13,$I$68:DZ$68,$I$17:DZ$17)))) -> 0 | EB40: =IF(XNPV($C13,$I$68:DR$68,$I$17:DR$17)>=0,0,FV($C13,(EB$17-$I$17)/365,0,(XNPV($C13,$I$68:DR$68,$I$17:DR$17)))) -> 0 | EC40: =IF(XNPV($C13,$I$68:EB$68,$I$17:EB$17)>=0,0,FV($C13,(EC$17-$I$17)/365,0,(XNPV($C13,$I$68:EB$68,$I$17:EB$17)))) -> 0 | ED40: =IF(XNPV($C13,$I$68:EC$68,$I$17:EC$17)>=0,0,FV($C13,(ED$17-$I$17)/365,0,(XNPV($C13,$I$68:EC$68,$I$17:EC$17)))) -> 0 | EE40: =IF(XNPV($C13,$I$68:ED$68,$I$17:ED$17)>=0,0,FV($C13,(EE$17-$I$17)/365,0,(XNPV($C13,$I$68:ED$68,$I$17:ED$17)))) -> 0 | EF40: =IF(XNPV($C13,$I$68:EE$68,$I$17:EE$17)>=0,0,FV($C13,(EF$17-$I$17)/365,0,(XNPV($C13,$I$68:EE$68,$I$17:EE$17)))) -> 0 | EG40: =IF(XNPV($C13,$I$68:EF$68,$I$17:EF$17)>=0,0,FV($C13,(EG$17-$I$17)/365,0,(XNPV($C13,$I$68:EF$68,$I$17:EF$17)))) -> 0 | EH40: =IF(XNPV($C13,$I$68:EG$68,$I$17:EG$17)>=0,0,FV($C13,(EH$17-$I$17)/365,0,(XNPV($C13,$I$68:EG$68,$I$17:EG$17)))) -> 0 | EI40: =IF(XNPV($C13,$I$68:CZ$68,$I$17:CZ$17)>=0,0,FV($C13,(EI$17-$I$17)/365,0,(XNPV($C13,$I$68:CZ$68,$I$17:CZ$17)))) -> 0 | EJ40: =IF(XNPV($C13,$I$68:CR$68,$I$17:CR$17)>=0,0,FV($C13,(EJ$17-$I$17)/365,0,(XNPV($C13,$I$68:CR$68,$I$17:CR$17)))) -> 0 | EK40: =IF(XNPV($C13,$I$68:EJ$68,$I$17:EJ$17)>=0,0,FV($C13,(EK$17-$I$17)/365,0,(XNPV($C13,$I$68:EJ$68,$I$17:EJ$17)))) -> 0 | EL40: =IF(XNPV($C13,$I$68:EK$68,$I$17:EK$17)>=0,0,FV($C13,(EL$17-$I$17)/365,0,(XNPV($C13,$I$68:EK$68,$I$17:EK$17)))) -> 0 | EM40: =IF(XNPV($C13,$I$68:EL$68,$I$17:EL$17)>=0,0,FV($C13,(EM$17-$I$17)/365,0,(XNPV($C13,$I$68:EL$68,$I$17:EL$17)))) -> 0 | EN40: =IF(XNPV($C13,$I$68:EM$68,$I$17:EM$17)>=0,0,FV($C13,(EN$17-$I$17)/365,0,(XNPV($C13,$I$68:EM$68,$I$17:EM$17)))) -> 0 | EO40: =IF(XNPV($C13,$I$68:EN$68,$I$17:EN$17)>=0,0,FV($C13,(EO$17-$I$17)/365,0,(XNPV($C13,$I$68:EN$68,$I$17:EN$17)))) -> 0 | EP40: =IF(XNPV($C13,$I$68:EO$68,$I$17:EO$17)>=0,0,FV($C13,(EP$17-$I$17)/365,0,(XNPV($C13,$I$68:EO$68,$I$17:EO$17)))) -> 0 | EQ40: =IF(XNPV($C13,$I$68:EP$68,$I$17:EP$17)>=0,0,FV($C13,(EQ$17-$I$17)/365,0,(XNPV($C13,$I$68:EP$68,$I$17:EP$17)))) -> 0 | ER40: =IF(XNPV($C13,$I$68:EQ$68,$I$17:EQ$17)>=0,0,FV($C13,(ER$17-$I$17)/365,0,(XNPV($C13,$I$68:EQ$68,$I$17:EQ$17)))) -> 0 | ES40: =IF(XNPV($C13,$I$68:EI$68,$I$17:EI$17)>=0,0,FV($C13,(ES$17-$I$17)/365,0,(XNPV($C13,$I$68:EI$68,$I$17:EI$17)))) -> 0 | ET40: =IF(XNPV($C13,$I$68:ES$68,$I$17:ES$17)>=0,0,FV($C13,(ET$17-$I$17)/365,0,(XNPV($C13,$I$68:ES$68,$I$17:ES$17)))) -> 0 | EU40: =IF(XNPV($C13,$I$68:ET$68,$I$17:ET$17)>=0,0,FV($C13,(EU$17-$I$17)/365,0,(XNPV($C13,$I$68:ET$68,$I$17:ET$17)))) -> 0 | EV40: =IF(XNPV($C13,$I$68:EU$68,$I$17:EU$17)>=0,0,FV($C13,(EV$17-$I$17)/365,0,(XNPV($C13,$I$68:EU$68,$I$17:EU$17)))) -> 0 | EW40: =IF(XNPV($C13,$I$68:EV$68,$I$17:EV$17)>=0,0,FV($C13,(EW$17-$I$17)/365,0,(XNPV($C13,$I$68:EV$68,$I$17:EV$17)))) -> 0 | EX40: =IF(XNPV($C13,$I$68:EW$68,$I$17:EW$17)>=0,0,FV($C13,(EX$17-$I$17)/365,0,(XNPV($C13,$I$68:EW$68,$I$17:EW$17)))) -> 0 | EY40: =IF(XNPV($C13,$I$68:EX$68,$I$17:EX$17)>=0,0,FV($C13,(EY$17-$I$17)/365,0,(XNPV($C13,$I$68:EX$68,$I$17:EX$17)))) -> 0 | EZ40: =IF(XNPV($C13,$I$68:EY$68,$I$17:EY$17)>=0,0,FV($C13,(EZ$17-$I$17)/365,0,(XNPV($C13,$I$68:EY$68,$I$17:EY$17)))) -> 0 | FA40: =IF(XNPV($C13,$I$68:EZ$68,$I$17:EZ$17)>=0,0,FV($C13,(FA$17-$I$17)/365,0,(XNPV($C13,$I$68:EZ$68,$I$17:EZ$17)))) -> 0 | FB40: =IF(XNPV($C13,$I$68:FA$68,$I$17:FA$17)>=0,0,FV($C13,(FB$17-$I$17)/365,0,(XNPV($C13,$I$68:FA$68,$I$17:FA$17)))) -> 0
B41: Less: Period Payments to LP | I41: =-I34 -> 12880796 | J41: =-J34 -> -35667.557 | K41: =-K34 -> -35807.333 | L41: =-L34 -> -35535.77 | M41: =-M34 -> -29985.66 | N41: =-N34 -> -35792.642 | O41: =-O34 -> -30233.969 | P41: =-P34 -> -30139.677 | ... FB41: =-FB34 -> 0
B42: Effective Tier II Threshold | I42: =SUM(I40:I41) -> 12880796 | J42: =SUM(J40:J41) -> 12956089 | K42: =SUM(K40:K41) -> 13035628 | L42: =SUM(L40:L41) -> 13116147 | M42: =SUM(M40:M41) -> 13199149 | N42: =SUM(N40:N41) -> 13280867 | O42: =SUM(O40:O41) -> 13365040 | P42: =SUM(P40:P41) -> 13453887 | ... FB42: =SUM(FB40:FB41) -> 0
B43: Total Cash Flow Allocated to Tier II | G43: =SUM(I43:FB43) -> 3754417 | I43: =MIN(I37,I42/$E44) -> 0 | J43: =MIN(J37,J42/$E44) -> 0 | K43: =MIN(K37,K42/$E44) -> 0 | L43: =MIN(L37,L42/$E44) -> 0 | M43: =MIN(M37,M42/$E44) -> 0 | N43: =MIN(N37,N42/$E44) -> 0 | O43: =MIN(O37,O42/$E44) -> 0 | P43: =MIN(P37,P42/$E44) -> 0 | ... FB43: =MIN(FB37,FB42/$E44) -> 0 | FD43: =SUM(I43:FB43) -> 3754417
B44: Portion Paid to LP | E44: =1-E45-E46 -> 0.48265386 | G44: =SUM(I44:FB44) -> 1812083.8 | I44: =$E44*I43 -> 0 | J44: =$E44*J43 -> 0 | K44: =$E44*K43 -> 0 | L44: =$E44*L43 -> 0 | M44: =$E44*M43 -> 0 | N44: =$E44*N43 -> 0 | O44: =$E44*O43 -> 0 | P44: =$E44*P43 -> 0 | ... FB44: =$E44*FB43 -> 0 | FD44: =SUM(I44:FB44) -> 1812083.8
B45: Portion Paid to GP | E45: =C6 -> 0.31734614 | G45: =SUM(I45:FB45) -> 1191449.8 | I45: =$E45*I43 -> 0 | J45: =$E45*J43 -> 0 | K45: =$E45*K43 -> 0 | L45: =$E45*L43 -> 0 | M45: =$E45*M43 -> 0 | N45: =$E45*N43 -> 0 | O45: =$E45*O43 -> 0 | P45: =$E45*P43 -> 0 | ... FB45: =$E45*FB43 -> 0 | FD45: =SUM(I45:FB45) -> 1191449.8
B46: Portion Paid to Sponsor Promote | E46: =E12 -> 0.2 | G46: =SUM(I46:FB46) -> 750883.4 | I46: =$E46*I43 -> 0 | J46: =$E46*J43 -> 0 | K46: =$E46*K43 -> 0 | L46: =$E46*L43 -> 0 | M46: =$E46*M43 -> 0 | N46: =$E46*N43 -> 0 | O46: =$E46*O43 -> 0 | P46: =$E46*P43 -> 0 | ... FB46: =$E46*FB43 -> 0 | FD46: =SUM(I46:FB46) -> 750883.4
B47: CF Remaining After Tier II | I47: =I37-I43 -> 0 | J47: =J37-J43 -> 0 | K47: =K37-K43 -> 0 | L47: =L37-L43 -> 0 | M47: =M37-M43 -> 0 | N47: =N37-N43 -> 0 | O47: =O37-O43 -> 0 | P47: =P37-P43 -> 0 | ... FB47: =FB37-FB43 -> 0
B49: ="Tier III -- LP IRR between "&TEXT($C$13,"#0%")&" and "&TEXT($C$14,"#0%") -> Tier III -- LP IRR between 11% and 17%
B50: ="Amount Needed to Achieve "&TEXT($C14,"#0%")&" LP IRR" -> Amount Needed to Achieve 17% LP IRR | J50: =IF(XNPV($C14,$I$68:I$68,$I$17:I$17)>=0,0,FV($C14,(J$17-$I$17)/365,0,(XNPV($C14,$I$68:I$68,$I$17:I$17)))) -> 13048093 | K50: =IF(XNPV($C14,$I$68:J$68,$I$17:J$17)>=0,0,FV($C14,(K$17-$I$17)/365,0,(XNPV($C14,$I$68:J$68,$I$17:J$17)))) -> 13187102 | L50: =IF(XNPV($C14,$I$68:K$68,$I$17:K$17)>=0,0,FV($C14,(L$17-$I$17)/365,0,(XNPV($C14,$I$68:K$68,$I$17:K$17)))) -> 13327836 | M50: =IF(XNPV($C14,$I$68:L$68,$I$17:L$17)>=0,0,FV($C14,(M$17-$I$17)/365,0,(XNPV($C14,$I$68:L$68,$I$17:L$17)))) -> 13464941 | N50: =IF(XNPV($C14,$I$68:M$68,$I$17:M$17)>=0,0,FV($C14,(N$17-$I$17)/365,0,(XNPV($C14,$I$68:M$68,$I$17:M$17)))) -> 13615305 | O50: =IF(XNPV($C14,$I$68:N$68,$I$17:N$17)>=0,0,FV($C14,(O$17-$I$17)/365,0,(XNPV($C14,$I$68:N$68,$I$17:N$17)))) -> 13755883 | P50: =IF(XNPV($C14,$I$68:O$68,$I$17:O$17)>=0,0,FV($C14,(P$17-$I$17)/365,0,(XNPV($C14,$I$68:O$68,$I$17:O$17)))) -> 13909900 | Q50: =IF(XNPV($C14,$I$68:P$68,$I$17:P$17)>=0,0,FV($C14,(Q$17-$I$17)/365,0,(XNPV($C14,$I$68:P$68,$I$17:P$17)))) -> 14053985 | ... CZ50: =IF(XNPV($C14,$I$68:CY$68,$I$17:CY$17)>=0,0,FV($C14,(CZ$17-$I$17)/365,0,(XNPV($C14,$I$68:CY$68,$I$17:CY$17)))) -> 0 | DA50: =IF(XNPV($C14,$I$68:BR$68,$I$17:BR$17)>=0,0,FV($C14,(DA$17-$I$17)/365,0,(XNPV($C14,$I$68:BR$68,$I$17:BR$17)))) -> 0 | DB50: =IF(XNPV($C14,$I$68:BJ$68,$I$17:BJ$17)>=0,0,FV($C14,(DB$17-$I$17)/365,0,(XNPV($C14,$I$68:BJ$68,$I$17:BJ$17)))) -> 0 | DC50: =IF(XNPV($C14,$I$68:DB$68,$I$17:DB$17)>=0,0,FV($C14,(DC$17-$I$17)/365,0,(XNPV($C14,$I$68:DB$68,$I$17:DB$17)))) -> 0 | DD50: =IF(XNPV($C14,$I$68:DC$68,$I$17:DC$17)>=0,0,FV($C14,(DD$17-$I$17)/365,0,(XNPV($C14,$I$68:DC$68,$I$17:DC$17)))) -> 0 | DE50: =IF(XNPV($C14,$I$68:DD$68,$I$17:DD$17)>=0,0,FV($C14,(DE$17-$I$17)/365,0,(XNPV($C14,$I$68:DD$68,$I$17:DD$17)))) -> 0 | DF50: =IF(XNPV($C14,$I$68:DE$68,$I$17:DE$17)>=0,0,FV($C14,(DF$17-$I$17)/365,0,(XNPV($C14,$I$68:DE$68,$I$17:DE$17)))) -> 0 | DG50: =IF(XNPV($C14,$I$68:DF$68,$I$17:DF$17)>=0,0,FV($C14,(DG$17-$I$17)/365,0,(XNPV($C14,$I$68:DF$68,$I$17:DF$17)))) -> 0 | DH50: =IF(XNPV($C14,$I$68:DG$68,$I$17:DG$17)>=0,0,FV($C14,(DH$17-$I$17)/365,0,(XNPV($C14,$I$68:DG$68,$I$17:DG$17)))) -> 0 | DI50: =IF(XNPV($C14,$I$68:DH$68,$I$17:DH$17)>=0,0,FV($C14,(DI$17-$I$17)/365,0,(XNPV($C14,$I$68:DH$68,$I$17:DH$17)))) -> 0 | DJ50: =IF(XNPV($C14,$I$68:DI$68,$I$17:DI$17)>=0,0,FV($C14,(DJ$17-$I$17)/365,0,(XNPV($C14,$I$68:DI$68,$I$17:DI$17)))) -> 0 | DK50: =IF(XNPV($C14,$I$68:DA$68,$I$17:DA$17)>=0,0,FV($C14,(DK$17-$I$17)/365,0,(XNPV($C14,$I$68:DA$68,$I$17:DA$17)))) -> 0 | DL50: =IF(XNPV($C14,$I$68:DK$68,$I$17:DK$17)>=0,0,FV($C14,(DL$17-$I$17)/365,0,(XNPV($C14,$I$68:DK$68,$I$17:DK$17)))) -> 0 | DM50: =IF(XNPV($C14,$I$68:DL$68,$I$17:DL$17)>=0,0,FV($C14,(DM$17-$I$17)/365,0,(XNPV($C14,$I$68:DL$68,$I$17:DL$17)))) -> 0 | DN50: =IF(XNPV($C14,$I$68:DM$68,$I$17:DM$17)>=0,0,FV($C14,(DN$17-$I$17)/365,0,(XNPV($C14,$I$68:DM$68,$I$17:DM$17)))) -> 0 | DO50: =IF(XNPV($C14,$I$68:DN$68,$I$17:DN$17)>=0,0,FV($C14,(DO$17-$I$17)/365,0,(XNPV($C14,$I$68:DN$68,$I$17:DN$17)))) -> 0 | DP50: =IF(XNPV($C14,$I$68:DO$68,$I$17:DO$17)>=0,0,FV($C14,(DP$17-$I$17)/365,0,(XNPV($C14,$I$68:DO$68,$I$17:DO$17)))) -> 0 | DQ50: =IF(XNPV($C14,$I$68:DP$68,$I$17:DP$17)>=0,0,FV($C14,(DQ$17-$I$17)/365,0,(XNPV($C14,$I$68:DP$68,$I$17:DP$17)))) -> 0 | DR50: =IF(XNPV($C14,$I$68:CI$68,$I$17:CI$17)>=0,0,FV($C14,(DR$17-$I$17)/365,0,(XNPV($C14,$I$68:CI$68,$I$17:CI$17)))) -> 0 | DS50: =IF(XNPV($C14,$I$68:CA$68,$I$17:CA$17)>=0,0,FV($C14,(DS$17-$I$17)/365,0,(XNPV($C14,$I$68:CA$68,$I$17:CA$17)))) -> 0 | DT50: =IF(XNPV($C14,$I$68:DS$68,$I$17:DS$17)>=0,0,FV($C14,(DT$17-$I$17)/365,0,(XNPV($C14,$I$68:DS$68,$I$17:DS$17)))) -> 0 | DU50: =IF(XNPV($C14,$I$68:DT$68,$I$17:DT$17)>=0,0,FV($C14,(DU$17-$I$17)/365,0,(XNPV($C14,$I$68:DT$68,$I$17:DT$17)))) -> 0 | DV50: =IF(XNPV($C14,$I$68:DU$68,$I$17:DU$17)>=0,0,FV($C14,(DV$17-$I$17)/365,0,(XNPV($C14,$I$68:DU$68,$I$17:DU$17)))) -> 0 | DW50: =IF(XNPV($C14,$I$68:DV$68,$I$17:DV$17)>=0,0,FV($C14,(DW$17-$I$17)/365,0,(XNPV($C14,$I$68:DV$68,$I$17:DV$17)))) -> 0 | DX50: =IF(XNPV($C14,$I$68:DW$68,$I$17:DW$17)>=0,0,FV($C14,(DX$17-$I$17)/365,0,(XNPV($C14,$I$68:DW$68,$I$17:DW$17)))) -> 0 | DY50: =IF(XNPV($C14,$I$68:DX$68,$I$17:DX$17)>=0,0,FV($C14,(DY$17-$I$17)/365,0,(XNPV($C14,$I$68:DX$68,$I$17:DX$17)))) -> 0 | DZ50: =IF(XNPV($C14,$I$68:DY$68,$I$17:DY$17)>=0,0,FV($C14,(DZ$17-$I$17)/365,0,(XNPV($C14,$I$68:DY$68,$I$17:DY$17)))) -> 0 | EA50: =IF(XNPV($C14,$I$68:DZ$68,$I$17:DZ$17)>=0,0,FV($C14,(EA$17-$I$17)/365,0,(XNPV($C14,$I$68:DZ$68,$I$17:DZ$17)))) -> 0 | EB50: =IF(XNPV($C14,$I$68:DR$68,$I$17:DR$17)>=0,0,FV($C14,(EB$17-$I$17)/365,0,(XNPV($C14,$I$68:DR$68,$I$17:DR$17)))) -> 0 | EC50: =IF(XNPV($C14,$I$68:EB$68,$I$17:EB$17)>=0,0,FV($C14,(EC$17-$I$17)/365,0,(XNPV($C14,$I$68:EB$68,$I$17:EB$17)))) -> 0 | ED50: =IF(XNPV($C14,$I$68:EC$68,$I$17:EC$17)>=0,0,FV($C14,(ED$17-$I$17)/365,0,(XNPV($C14,$I$68:EC$68,$I$17:EC$17)))) -> 0 | EE50: =IF(XNPV($C14,$I$68:ED$68,$I$17:ED$17)>=0,0,FV($C14,(EE$17-$I$17)/365,0,(XNPV($C14,$I$68:ED$68,$I$17:ED$17)))) -> 0 | EF50: =IF(XNPV($C14,$I$68:EE$68,$I$17:EE$17)>=0,0,FV($C14,(EF$17-$I$17)/365,0,(XNPV($C14,$I$68:EE$68,$I$17:EE$17)))) -> 0 | EG50: =IF(XNPV($C14,$I$68:EF$68,$I$17:EF$17)>=0,0,FV($C14,(EG$17-$I$17)/365,0,(XNPV($C14,$I$68:EF$68,$I$17:EF$17)))) -> 0 | EH50: =IF(XNPV($C14,$I$68:EG$68,$I$17:EG$17)>=0,0,FV($C14,(EH$17-$I$17)/365,0,(XNPV($C14,$I$68:EG$68,$I$17:EG$17)))) -> 0 | EI50: =IF(XNPV($C14,$I$68:CZ$68,$I$17:CZ$17)>=0,0,FV($C14,(EI$17-$I$17)/365,0,(XNPV($C14,$I$68:CZ$68,$I$17:CZ$17)))) -> 0 | EJ50: =IF(XNPV($C14,$I$68:CR$68,$I$17:CR$17)>=0,0,FV($C14,(EJ$17-$I$17)/365,0,(XNPV($C14,$I$68:CR$68,$I$17:CR$17)))) -> 0 | EK50: =IF(XNPV($C14,$I$68:EJ$68,$I$17:EJ$17)>=0,0,FV($C14,(EK$17-$I$17)/365,0,(XNPV($C14,$I$68:EJ$68,$I$17:EJ$17)))) -> 0 | EL50: =IF(XNPV($C14,$I$68:EK$68,$I$17:EK$17)>=0,0,FV($C14,(EL$17-$I$17)/365,0,(XNPV($C14,$I$68:EK$68,$I$17:EK$17)))) -> 0 | EM50: =IF(XNPV($C14,$I$68:EL$68,$I$17:EL$17)>=0,0,FV($C14,(EM$17-$I$17)/365,0,(XNPV($C14,$I$68:EL$68,$I$17:EL$17)))) -> 0 | EN50: =IF(XNPV($C14,$I$68:EM$68,$I$17:EM$17)>=0,0,FV($C14,(EN$17-$I$17)/365,0,(XNPV($C14,$I$68:EM$68,$I$17:EM$17)))) -> 0 | EO50: =IF(XNPV($C14,$I$68:EN$68,$I$17:EN$17)>=0,0,FV($C14,(EO$17-$I$17)/365,0,(XNPV($C14,$I$68:EN$68,$I$17:EN$17)))) -> 0 | EP50: =IF(XNPV($C14,$I$68:EO$68,$I$17:EO$17)>=0,0,FV($C14,(EP$17-$I$17)/365,0,(XNPV($C14,$I$68:EO$68,$I$17:EO$17)))) -> 0 | EQ50: =IF(XNPV($C14,$I$68:EP$68,$I$17:EP$17)>=0,0,FV($C14,(EQ$17-$I$17)/365,0,(XNPV($C14,$I$68:EP$68,$I$17:EP$17)))) -> 0 | ER50: =IF(XNPV($C14,$I$68:EQ$68,$I$17:EQ$17)>=0,0,FV($C14,(ER$17-$I$17)/365,0,(XNPV($C14,$I$68:EQ$68,$I$17:EQ$17)))) -> 0 | ES50: =IF(XNPV($C14,$I$68:EI$68,$I$17:EI$17)>=0,0,FV($C14,(ES$17-$I$17)/365,0,(XNPV($C14,$I$68:EI$68,$I$17:EI$17)))) -> 0 | ET50: =IF(XNPV($C14,$I$68:ES$68,$I$17:ES$17)>=0,0,FV($C14,(ET$17-$I$17)/365,0,(XNPV($C14,$I$68:ES$68,$I$17:ES$17)))) -> 0 | EU50: =IF(XNPV($C14,$I$68:ET$68,$I$17:ET$17)>=0,0,FV($C14,(EU$17-$I$17)/365,0,(XNPV($C14,$I$68:ET$68,$I$17:ET$17)))) -> 0 | EV50: =IF(XNPV($C14,$I$68:EU$68,$I$17:EU$17)>=0,0,FV($C14,(EV$17-$I$17)/365,0,(XNPV($C14,$I$68:EU$68,$I$17:EU$17)))) -> 0 | EW50: =IF(XNPV($C14,$I$68:EV$68,$I$17:EV$17)>=0,0,FV($C14,(EW$17-$I$17)/365,0,(XNPV($C14,$I$68:EV$68,$I$17:EV$17)))) -> 0 | EX50: =IF(XNPV($C14,$I$68:EW$68,$I$17:EW$17)>=0,0,FV($C14,(EX$17-$I$17)/365,0,(XNPV($C14,$I$68:EW$68,$I$17:EW$17)))) -> 0 | EY50: =IF(XNPV($C14,$I$68:EX$68,$I$17:EX$17)>=0,0,FV($C14,(EY$17-$I$17)/365,0,(XNPV($C14,$I$68:EX$68,$I$17:EX$17)))) -> 0 | EZ50: =IF(XNPV($C14,$I$68:EY$68,$I$17:EY$17)>=0,0,FV($C14,(EZ$17-$I$17)/365,0,(XNPV($C14,$I$68:EY$68,$I$17:EY$17)))) -> 0 | FA50: =IF(XNPV($C14,$I$68:EZ$68,$I$17:EZ$17)>=0,0,FV($C14,(FA$17-$I$17)/365,0,(XNPV($C14,$I$68:EZ$68,$I$17:EZ$17)))) -> 0 | FB50: =IF(XNPV($C14,$I$68:FA$68,$I$17:FA$17)>=0,0,FV($C14,(FB$17-$I$17)/365,0,(XNPV($C14,$I$68:FA$68,$I$17:FA$17)))) -> 0
B51: ="Amount Needed to Achieve "&TEXT($C14,"#0%")&"" -> Amount Needed to Achieve 17% | J51: =MAX(J50:J50) -> 13048093 | K51: =MAX(K50:K50) -> 13187102 | L51: =MAX(L50:L50) -> 13327836 | M51: =MAX(M50:M50) -> 13464941 | N51: =MAX(N50:N50) -> 13615305 | O51: =MAX(O50:O50) -> 13755883 | P51: =MAX(P50:P50) -> 13909900 | Q51: =MAX(Q50:Q50) -> 14053985 | ... FB51: =MAX(FB50:FB50) -> 0
B52: Less: Period Payments to LP | I52: =-(I34+I44) -> 12880796 | J52: =-(J34+J44) -> -35667.557 | K52: =-(K34+K44) -> -35807.333 | L52: =-(L34+L44) -> -35535.77 | M52: =-(M34+M44) -> -29985.66 | N52: =-(N34+N44) -> -35792.642 | O52: =-(O34+O44) -> -30233.969 | P52: =-(P34+P44) -> -30139.677 | ... FB52: =-(FB34+FB44) -> 0
B53: Effective Tier III Threshold | I53: =SUM(I51:I52) -> 12880796 | J53: =SUM(J51:J52) -> 13012425 | K53: =SUM(K51:K52) -> 13151295 | L53: =SUM(L51:L52) -> 13292300 | M53: =SUM(M51:M52) -> 13434955 | N53: =SUM(N51:N52) -> 13579512 | O53: =SUM(O51:O52) -> 13725649 | P53: =SUM(P51:P52) -> 13879761 | ... FB53: =SUM(FB51:FB52) -> 0
B54: Total Cash Flow Allocated to Tier III | G54: =SUM(I54:FB54) -> 9473167.1 | I54: =MIN(I47,I53/$E55) -> 0 | J54: =MIN(J47,J53/$E55) -> 0 | K54: =MIN(K47,K53/$E55) -> 0 | L54: =MIN(L47,L53/$E55) -> 0 | M54: =MIN(M47,M53/$E55) -> 0 | N54: =MIN(N47,N53/$E55) -> 0 | O54: =MIN(O47,O53/$E55) -> 0 | P54: =MIN(P47,P53/$E55) -> 0 | ... FB54: =MIN(FB47,FB53/$E55) -> 0 | FD54: =SUM(I54:FB54) -> 9473167.1
B55: Portion Paid to LP | E55: =1-E56-E57 -> 0.43265386 | G55: =SUM(I55:FB55) -> 4098602.3 | I55: =$E55*I54 -> 0 | J55: =$E55*J54 -> 0 | K55: =$E55*K54 -> 0 | L55: =$E55*L54 -> 0 | M55: =$E55*M54 -> 0 | N55: =$E55*N54 -> 0 | O55: =$E55*O54 -> 0 | P55: =$E55*P54 -> 0 | ... FB55: =$E55*FB54 -> 0 | FD55: =SUM(I55:FB55) -> 4098602.3
B56: Portion Paid to GP | E56: =C6 -> 0.31734614 | G56: =SUM(I56:FB56) -> 3006273.1 | I56: =$E56*I54 -> 0 | J56: =$E56*J54 -> 0 | K56: =$E56*K54 -> 0 | L56: =$E56*L54 -> 0 | M56: =$E56*M54 -> 0 | N56: =$E56*N54 -> 0 | O56: =$E56*O54 -> 0 | P56: =$E56*P54 -> 0 | ... FB56: =$E56*FB54 -> 0 | FD56: =SUM(I56:FB56) -> 3006273.1
B57: Portion Paid to Sponsor Promote | E57: =E13 -> 0.25 | G57: =SUM(I57:FB57) -> 2368291.8 | I57: =$E57*I54 -> 0 | J57: =$E57*J54 -> 0 | K57: =$E57*K54 -> 0 | L57: =$E57*L54 -> 0 | M57: =$E57*M54 -> 0 | N57: =$E57*N54 -> 0 | O57: =$E57*O54 -> 0 | P57: =$E57*P54 -> 0 | ... FB57: =$E57*FB54 -> 0 | FD57: =SUM(I57:FB57) -> 2368291.8
B58: CF Remaining After Tier III | I58: =I47-I54 -> 0 | J58: =J47-J54 -> 0 | K58: =K47-K54 -> 0 | L58: =L47-L54 -> 0 | M58: =M47-M54 -> 0 | N58: =N47-N54 -> 0 | O58: =O47-O54 -> 0 | P58: =P47-P54 -> 0 | ... FB58: =FB47-FB54 -> 0
B60: ="Tier IV -- LP IRR above "&TEXT(C14,"#0%")&"" -> Tier IV -- LP IRR above 17%
B61: Total Cash Flow Allocated to Tier IV | G61: =SUM(I61:FB61) -> 5710478.4 | I61: =I58 -> 0 | J61: =J58 -> 0 | K61: =K58 -> 0 | L61: =L58 -> 0 | M61: =M58 -> 0 | N61: =N58 -> 0 | O61: =O58 -> 0 | P61: =P58 -> 0 | ... FB61: =FB58 -> 0 | FD61: =SUM(I61:FB61) -> 5710478.4
B62: Portion Paid to LP | E62: =1-E63-E64 -> 0.33265386 | G62: =SUM(I62:FB62) -> 1899612.7 | I62: =$E62*I61 -> 0 | J62: =$E62*J61 -> 0 | K62: =$E62*K61 -> 0 | L62: =$E62*L61 -> 0 | M62: =$E62*M61 -> 0 | N62: =$E62*N61 -> 0 | O62: =$E62*O61 -> 0 | P62: =$E62*P61 -> 0 | ... FB62: =$E62*FB61 -> 0 | FD62: =SUM(I62:FB62) -> 1899612.7
B63: Portion Paid to GP | E63: =C6 -> 0.31734614 | G63: =SUM(I63:FB63) -> 1812198.3 | I63: =$E63*I61 -> 0 | J63: =$E63*J61 -> 0 | K63: =$E63*K61 -> 0 | L63: =$E63*L61 -> 0 | M63: =$E63*M61 -> 0 | N63: =$E63*N61 -> 0 | O63: =$E63*O61 -> 0 | P63: =$E63*P61 -> 0 | ... FB63: =$E63*FB61 -> 0 | FD63: =SUM(I63:FB63) -> 1812198.3
B64: Portion Paid to Sponsor Promote | E64: =E14 -> 0.35 | G64: =SUM(I64:FB64) -> 1998667.5 | I64: =$E64*I61 -> 0 | J64: =$E64*J61 -> 0 | K64: =$E64*K61 -> 0 | L64: =$E64*L61 -> 0 | M64: =$E64*M61 -> 0 | N64: =$E64*N61 -> 0 | O64: =$E64*O61 -> 0 | P64: =$E64*P61 -> 0 | ... FB64: =$E64*FB61 -> 0 | FD64: =SUM(I64:FB64) -> 1998667.5
B65: CF Remaining After Tier IV | I65: =I58-I61 -> 0 | J65: =J58-J61 -> 0 | K65: =K58-K61 -> 0 | L65: =L58-L61 -> 0 | M65: =M58-M61 -> 0 | N65: =N58-N61 -> 0 | O65: =O58-O61 -> 0 | P65: =P58-P61 -> 0 | ... FB65: =FB58-FB61 -> 0
C67: % of Profit | E67: Return Metrics
B68: LP TOTAL (IRR / MOIC) | C68: =G68/$G$71 -> 0.47788126 | E68: =IF($C$5>0,TEXT(XIRR($I68:$FB68,$I$17:$FB$17),"#0.0%")&" / "&TEXT(((FD68-SUMIF(I68:FB68,"<0")))/-SUMIF(I68:FB68,"<0"),"#0.00x"),"n/m") -> 19.5% / 1.93x | G68: =SUM(I68:FB68) -> 11943596 | I68: =I34+I44+I55+I62 -> -12880796 | J68: =J34+J44+J55+J62 -> 35667.557 | K68: =K34+K44+K55+K62 -> 35807.333 | L68: =L34+L44+L55+L62 -> 35535.77 | M68: =M34+M44+M55+M62 -> 29985.66 | N68: =N34+N44+N55+N62 -> 35792.642 | O68: =O34+O44+O55+O62 -> 30233.969 | P68: =P34+P44+P55+P62 -> 30139.677 | ... FB68: =FB34+FB44+FB55+FB62 -> 0 | FD68: =SUM(I68:FB68) -> 11943596
B69: GP TOTAL (IRR / MOIC) | C69: =G69/$G$71 -> 0.31734614 | E69: =IF($C$6>0,TEXT(XIRR($I69:$FB69,$I$17:$FB$17),"#0.0%")&" / "&TEXT(((FD69-SUMIF(I69:FB69,"<0")))/-SUMIF(I69:FB69,"<0"),"#0.00x"),"n/m") -> 25.5% / 2.32x | G69: =SUM(I69:FB69) -> 7931372 | I69: =I35+I45+I56+I63 -> -5987911.8 | J69: =J35+J45+J56+J63 -> 16580.821 | K69: =K35+K45+K56+K63 -> 16645.799 | L69: =L35+L45+L56+L63 -> 16519.557 | M69: =M35+M45+M56+M63 -> 13939.471 | N69: =N35+N45+N56+N63 -> 16638.97 | O69: =O35+O45+O56+O63 -> 14054.903 | P69: =P35+P45+P56+P63 -> 14011.069 | ... FB69: =FB35+FB45+FB56+FB63 -> 0 | FD69: =SUM(I69:FB69) -> 7931372
B70: SPONSOR PROMOTE | C70: =G70/$G$71 -> 0.20477259 | E70: =IF($C$8>0,TEXT(XIRR($I70:$FB70,$I$17:$FB$17),"#0.0%")&" / "&TEXT(((FD70-SUMIF(I70:FB70,"<0")))/-SUMIF(I70:FB70,"<0"),"#0.00x"),"n/m") -> n/m | G70: =SUM(I70:FB70) -> 5117842.6 | I70: =I36+I46+I57+I64 -> 0 | J70: =J36+J46+J57+J64 -> 0 | K70: =K36+K46+K57+K64 -> 0 | L70: =L36+L46+L57+L64 -> 0 | M70: =M36+M46+M57+M64 -> 0 | N70: =N36+N46+N57+N64 -> 0 | O70: =O36+O46+O57+O64 -> 0 | P70: =P36+P46+P57+P64 -> 0 | ... FB70: =FB36+FB46+FB57+FB64 -> 0 | FD70: =SUM(I70:FB70) -> 5117842.6
B71: COMBINED TOTAL (IRR / MOIC) | E71: =TEXT(XIRR($I71:$FB71,$I$17:$FB$17),"#0.0%")&" / "&TEXT(((FD71-SUMIF(I71:FB71,"<0")))/-SUMIF(I71:FB71,"<0"),"#0.00x") -> 25.5% / 2.32x | G71: =SUM(G68:G70) -> 24992810 | I71: =SUM(I68:I70) -> -18868708 | J71: =SUM(J68:J70) -> 52248.378 | K71: =SUM(K68:K70) -> 52453.133 | L71: =SUM(L68:L70) -> 52055.327 | M71: =SUM(M68:M70) -> 43925.131 | N71: =SUM(N68:N70) -> 52431.612 | O71: =SUM(O68:O70) -> 44288.871 | P71: =SUM(P68:P70) -> 44150.746 | ... FB71: =SUM(FB68:FB70) -> 0 | FD71: =SUM(FD68:FD70) -> 24992810
B73: Total GP | C73: =SUM(C69:C70) -> 0.52211874 | E73: =IF($C$5>0,TEXT(XIRR($I73:$FB73,$I$17:$FB$17),"#0.0%")&" / "&TEXT(((FD73-SUMIF(I73:FB73,"<0")))/-SUMIF(I73:FB73,"<0"),"#0.00x"),"n/m") -> 36.1% / 3.18x | G73: =SUM(I73:FB73) -> 13049215 | I73: =SUM(I69:I70) -> -5987911.8 | J73: =SUM(J69:J70) -> 16580.821 | K73: =SUM(K69:K70) -> 16645.799 | L73: =SUM(L69:L70) -> 16519.557 | M73: =SUM(M69:M70) -> 13939.471 | N73: =SUM(N69:N70) -> 16638.97 | O73: =SUM(O69:O70) -> 14054.903 | P73: =SUM(P69:P70) -> 14011.069 | ... FD73: =SUM(FD69:FD70) -> 13049215
B75: Sanity Check | G75: =G27-G71 -> 0 | I75: =I27-I71 -> 0 | J75: =J27-J71 -> 0 | K75: =K27-K71 -> 0 | L75: =L27-L71 -> 0 | M75: =M27-M71 -> 0 | N75: =N27-N71 -> 0 | O75: =O27-O71 -> 0 | P75: =P27-P71 -> 0 | ... FB75: =FB27-FB71 -> 0 | FD75: =FD27-FD71 -> 0

Sheet Annual Waterfall (Two Tier)
B2: Sentosa Recap
B4: Equity Capitalization
B5: LP Equity | C5: =+'Waterfall (Two Tier)'!C5 -> 0.68265386 | E5: =C5*$E$7 -> 12922000
B6: GP Equity | C6: =+'Waterfall (Two Tier)'!C6 -> 0.31734614 | E6: =C6*$E$7 -> 6007066.2
B7: Total | C7: =SUM(C5:C6) -> 1 | E7: ='Waterfall (Two Tier)'!E7 -> 18929066
B9: Promote Structure | E9: Sponsor
C10: Hurdle | E10: Promote
B11: Tier I | C11: =+'Waterfall (Two Tier)'!C11 -> -- | E11: =+'Waterfall (Two Tier)'!E11 -> 0
B12: Tier II (after) | C12: =+'Waterfall (Two Tier)'!C12 -> 0.08 | E12: =+'Waterfall (Two Tier)'!E12 -> 0.2
B13: Tier III (after) | C13: =+'Waterfall (Two Tier)'!C13 -> 0.11 | E13: =+'Waterfall (Two Tier)'!E13 -> 0.25
B14: Tier IV (after) | C14: =+'Waterfall (Two Tier)'!C14 -> 0.17 | E14: =+'Waterfall (Two Tier)'!E14 -> 0.35
B16: Monthly Cash Flow
G17: TOTAL | I17: 2025 | J17: =I17+1 -> 2026 | K17: =J17+1 -> 2027 | L17: =K17+1 -> 2028 | M17: =L17+1 -> 2029 | N17: =M17+1 -> 2030 | O17: =N17+1 -> 2031 | P17: =O17+1 -> 2032 | R17: TOTAL
B18: Net Cash Flow | E18: =+'Waterfall (Two Tier)'!E26 -> 25.5% / 2.32x | G18: =SUM(I18:P18) -> 24992810 | I18: =SUMIF('Waterfall (Two Tier)'!$I$16:$FB$16,I$17,'Waterfall (Two Tier)'!$I26:$FB26) -> 0 | J18: =SUMIF('Waterfall (Two Tier)'!$I$16:$FB$16,J$17,'Waterfall (Two Tier)'!$I26:$FB26) -> -18571306 | K18: =SUMIF('Waterfall (Two Tier)'!$I$16:$FB$16,K$17,'Waterfall (Two Tier)'!$I26:$FB26) -> 723592.28 | L18: =SUMIF('Waterfall (Two Tier)'!$I$16:$FB$16,L$17,'Waterfall (Two Tier)'!$I26:$FB26) -> 1247074.1 | M18: =SUMIF('Waterfall (Two Tier)'!$I$16:$FB$16,M$17,'Waterfall (Two Tier)'!$I26:$FB26) -> 1457018.2 | N18: =SUMIF('Waterfall (Two Tier)'!$I$16:$FB$16,N$17,'Waterfall (Two Tier)'!$I26:$FB26) -> 40136431 | O18: =SUMIF('Waterfall (Two Tier)'!$I$16:$FB$16,O$17,'Waterfall (Two Tier)'!$I26:$FB26) -> 0 | P18: =SUMIF('Waterfall (Two Tier)'!$I$16:$FB$16,P$17,'Waterfall (Two Tier)'!$I26:$FB26) -> 0 | R18: =SUM(I18:L18) -> -16600639
B19: ="Net Cash Flow to the Venture " -> Net Cash Flow to the Venture | E19: =+'Waterfall (Two Tier)'!E27 -> 25.5% / 2.32x | G19: =SUM(I19:P19) -> 24992810 | I19: =SUM(I18:I18) -> 0 | J19: =SUM(J18:J18) -> -18571306 | K19: =SUM(K18:K18) -> 723592.28 | L19: =SUM(L18:L18) -> 1247074.1 | M19: =SUM(M18:M18) -> 1457018.2 | N19: =SUM(N18:N18) -> 40136431 | O19: =SUM(O18:O18) -> 0 | P19: =SUM(P18:P18) -> 0 | R19: =SUM(I19:L19) -> -16600639
B21: ="Tier I -- LP IRR below "&TEXT($C$12,"#0%") -> Tier I -- LP IRR below 8%
B22: Total Cash Flow Allocated to Tier I | G22: =SUM(I22:P22) -> 6054747.9 | I22: =SUMIF('Waterfall (Two Tier)'!$I$16:$FB$16,I$17,'Waterfall (Two Tier)'!$I33:$FB33) -> 0 | J22: =SUMIF('Waterfall (Two Tier)'!$I$16:$FB$16,J$17,'Waterfall (Two Tier)'!$I33:$FB33) -> -18571306 | K22: =SUMIF('Waterfall (Two Tier)'!$I$16:$FB$16,K$17,'Waterfall (Two Tier)'!$I33:$FB33) -> 723592.28 | L22: =SUMIF('Waterfall (Two Tier)'!$I$16:$FB$16,L$17,'Waterfall (Two Tier)'!$I33:$FB33) -> 1247074.1 | M22: =SUMIF('Waterfall (Two Tier)'!$I$16:$FB$16,M$17,'Waterfall (Two Tier)'!$I33:$FB33) -> 1457018.2 | N22: =SUMIF('Waterfall (Two Tier)'!$I$16:$FB$16,N$17,'Waterfall (Two Tier)'!$I33:$FB33) -> 21198369 | O22: =SUMIF('Waterfall (Two Tier)'!$I$16:$FB$16,O$17,'Waterfall (Two Tier)'!$I33:$FB33) -> 0 | P22: =SUMIF('Waterfall (Two Tier)'!$I$16:$FB$16,P$17,'Waterfall (Two Tier)'!$I33:$FB33) -> 0 | R22: =SUM(I22:L22) -> -16600639
B23: Portion Paid to LP | E23: =1-E24 -> 0.68265386 | G23: =SUM(I23:P23) -> 4133297 | I23: =SUMIF('Waterfall (Two Tier)'!$I$16:$FB$16,I$17,'Waterfall (Two Tier)'!$I34:$FB34) -> 0 | J23: =SUMIF('Waterfall (Two Tier)'!$I$16:$FB$16,J$17,'Waterfall (Two Tier)'!$I34:$FB34) -> -12677773 | K23: =SUMIF('Waterfall (Two Tier)'!$I$16:$FB$16,K$17,'Waterfall (Two Tier)'!$I34:$FB34) -> 493963.06 | L23: =SUMIF('Waterfall (Two Tier)'!$I$16:$FB$16,L$17,'Waterfall (Two Tier)'!$I34:$FB34) -> 851319.95 | M23: =SUMIF('Waterfall (Two Tier)'!$I$16:$FB$16,M$17,'Waterfall (Two Tier)'!$I34:$FB34) -> 994639.12 | N23: =SUMIF('Waterfall (Two Tier)'!$I$16:$FB$16,N$17,'Waterfall (Two Tier)'!$I34:$FB34) -> 14471148 | O23: =SUMIF('Waterfall (Two Tier)'!$I$16:$FB$16,O$17,'Waterfall (Two Tier)'!$I34:$FB34) -> 0 | P23: =SUMIF('Waterfall (Two Tier)'!$I$16:$FB$16,P$17,'Waterfall (Two Tier)'!$I34:$FB34) -> 0 | R23: =SUM(I23:L23) -> -11332490
B24: Portion Paid to GP | E24: =$C$6 -> 0.31734614 | G24: =SUM(I24:P24) -> 1921450.9 | I24: =SUMIF('Waterfall (Two Tier)'!$I$16:$FB$16,I$17,'Waterfall (Two Tier)'!$I35:$FB35) -> 0 | J24: =SUMIF('Waterfall (Two Tier)'!$I$16:$FB$16,J$17,'Waterfall (Two Tier)'!$I35:$FB35) -> -5893532.2 | K24: =SUMIF('Waterfall (Two Tier)'!$I$16:$FB$16,K$17,'Waterfall (Two Tier)'!$I35:$FB35) -> 229629.22 | L24: =SUMIF('Waterfall (Two Tier)'!$I$16:$FB$16,L$17,'Waterfall (Two Tier)'!$I35:$FB35) -> 395754.16 | M24: =SUMIF('Waterfall (Two Tier)'!$I$16:$FB$16,M$17,'Waterfall (Two Tier)'!$I35:$FB35) -> 462379.12 | N24: =SUMIF('Waterfall (Two Tier)'!$I$16:$FB$16,N$17,'Waterfall (Two Tier)'!$I35:$FB35) -> 6727220.6 | O24: =SUMIF('Waterfall (Two Tier)'!$I$16:$FB$16,O$17,'Waterfall (Two Tier)'!$I35:$FB35) -> 0 | P24: =SUMIF('Waterfall (Two Tier)'!$I$16:$FB$16,P$17,'Waterfall (Two Tier)'!$I35:$FB35) -> 0 | R24: =SUM(I24:L24) -> -5268148.9
B25: Portion Paid to Sponsor Promote | E25: =E11 -> 0 | G25: =SUM(I25:P25) -> 0 | I25: =SUMIF('Waterfall (Two Tier)'!$I$16:$FB$16,I$17,'Waterfall (Two Tier)'!$I36:$FB36) -> 0 | J25: =SUMIF('Waterfall (Two Tier)'!$I$16:$FB$16,J$17,'Waterfall (Two Tier)'!$I36:$FB36) -> 0 | K25: =SUMIF('Waterfall (Two Tier)'!$I$16:$FB$16,K$17,'Waterfall (Two Tier)'!$I36:$FB36) -> 0 | L25: =SUMIF('Waterfall (Two Tier)'!$I$16:$FB$16,L$17,'Waterfall (Two Tier)'!$I36:$FB36) -> 0 | M25: =SUMIF('Waterfall (Two Tier)'!$I$16:$FB$16,M$17,'Waterfall (Two Tier)'!$I36:$FB36) -> 0 | N25: =SUMIF('Waterfall (Two Tier)'!$I$16:$FB$16,N$17,'Waterfall (Two Tier)'!$I36:$FB36) -> 0 | O25: =SUMIF('Waterfall (Two Tier)'!$I$16:$FB$16,O$17,'Waterfall (Two Tier)'!$I36:$FB36) -> 0 | P25: =SUMIF('Waterfall (Two Tier)'!$I$16:$FB$16,P$17,'Waterfall (Two Tier)'!$I36:$FB36) -> 0 | R25: =SUM(I25:L25) -> 0
B26: CF Remaining After Tier I | I26: =I19-I22 -> 0 | J26: =J19-J22 -> 0 | K26: =K19-K22 -> 0 | L26: =L19-L22 -> 0 | M26: =M19-M22 -> 0 | N26: =N19-N22 -> 18938063 | O26: =O19-O22 -> 0 | P26: =P19-P22 -> 0
B28: ="Tier II -- LP IRR between "&TEXT($C$12,"#0%")&" and "&TEXT($C$13,"#0%") -> Tier II -- LP IRR between 8% and 11%
B29: Total Cash Flow Allocated to Tier II | G29: =SUM(I29:P29) -> 3754417 | I29: =SUMIF('Waterfall (Two Tier)'!$I$16:$FB$16,I$17,'Waterfall (Two Tier)'!$I43:$FB43) -> 0 | J29: =SUMIF('Waterfall (Two Tier)'!$I$16:$FB$16,J$17,'Waterfall (Two Tier)'!$I43:$FB43) -> 0 | K29: =SUMIF('Waterfall (Two Tier)'!$I$16:$FB$16,K$17,'Waterfall (Two Tier)'!$I43:$FB43) -> 0 | L29: =SUMIF('Waterfall (Two Tier)'!$I$16:$FB$16,L$17,'Waterfall (Two Tier)'!$I43:$FB43) -> 0 | M29: =SUMIF('Waterfall (Two Tier)'!$I$16:$FB$16,M$17,'Waterfall (Two Tier)'!$I43:$FB43) -> 0 | N29: =SUMIF('Waterfall (Two Tier)'!$I$16:$FB$16,N$17,'Waterfall (Two Tier)'!$I43:$FB43) -> 3754417 | O29: =SUMIF('Waterfall (Two Tier)'!$I$16:$FB$16,O$17,'Waterfall (Two Tier)'!$I43:$FB43) -> 0 | P29: =SUMIF('Waterfall (Two Tier)'!$I$16:$FB$16,P$17,'Waterfall (Two Tier)'!$I43:$FB43) -> 0 | R29: =SUM(I29:L29) -> 0
B30: Portion Paid to LP | E30: =1-E31-E32 -> 0.48265386 | G30: =SUM(I30:P30) -> 1812083.8 | I30: =SUMIF('Waterfall (Two Tier)'!$I$16:$FB$16,I$17,'Waterfall (Two Tier)'!$I44:$FB44) -> 0 | J30: =SUMIF('Waterfall (Two Tier)'!$I$16:$FB$16,J$17,'Waterfall (Two Tier)'!$I44:$FB44) -> 0 | K30: =SUMIF('Waterfall (Two Tier)'!$I$16:$FB$16,K$17,'Waterfall (Two Tier)'!$I44:$FB44) -> 0 | L30: =SUMIF('Waterfall (Two Tier)'!$I$16:$FB$16,L$17,'Waterfall (Two Tier)'!$I44:$FB44) -> 0 | M30: =SUMIF('Waterfall (Two Tier)'!$I$16:$FB$16,M$17,'Waterfall (Two Tier)'!$I44:$FB44) -> 0 | N30: =SUMIF('Waterfall (Two Tier)'!$I$16:$FB$16,N$17,'Waterfall (Two Tier)'!$I44:$FB44) -> 1812083.8 | O30: =SUMIF('Waterfall (Two Tier)'!$I$16:$FB$16,O$17,'Waterfall (Two Tier)'!$I44:$FB44) -> 0 | P30: =SUMIF('Waterfall (Two Tier)'!$I$16:$FB$16,P$17,'Waterfall (Two Tier)'!$I44:$FB44) -> 0 | R30: =SUM(I30:L30) -> 0
B31: Portion Paid to GP | E31: =C6 -> 0.31734614 | G31: =SUM(I31:P31) -> 1191449.8 | I31: =SUMIF('Waterfall (Two Tier)'!$I$16:$FB$16,I$17,'Waterfall (Two Tier)'!$I45:$FB45) -> 0 | J31: =SUMIF('Waterfall (Two Tier)'!$I$16:$FB$16,J$17,'Waterfall (Two Tier)'!$I45:$FB45) -> 0 | K31: =SUMIF('Waterfall (Two Tier)'!$I$16:$FB$16,K$17,'Waterfall (Two Tier)'!$I45:$FB45) -> 0 | L31: =SUMIF('Waterfall (Two Tier)'!$I$16:$FB$16,L$17,'Waterfall (Two Tier)'!$I45:$FB45) -> 0 | M31: =SUMIF('Waterfall (Two Tier)'!$I$16:$FB$16,M$17,'Waterfall (Two Tier)'!$I45:$FB45) -> 0 | N31: =SUMIF('Waterfall (Two Tier)'!$I$16:$FB$16,N$17,'Waterfall (Two Tier)'!$I45:$FB45) -> 1191449.8 | O31: =SUMIF('Waterfall (Two Tier)'!$I$16:$FB$16,O$17,'Waterfall (Two Tier)'!$I45:$FB45) -> 0 | P31: =SUMIF('Waterfall (Two Tier)'!$I$16:$FB$16,P$17,'Waterfall (Two Tier)'!$I45:$FB45) -> 0 | R31: =SUM(I31:L31) -> 0
B32: Portion Paid to Sponsor Promote | E32: =E12 -> 0.2 | G32: =SUM(I32:P32) -> 750883.4 | I32: =SUMIF('Waterfall (Two Tier)'!$I$16:$FB$16,I$17,'Waterfall (Two Tier)'!$I46:$FB46) -> 0 | J32: =SUMIF('Waterfall (Two Tier)'!$I$16:$FB$16,J$17,'Waterfall (Two Tier)'!$I46:$FB46) -> 0 | K32: =SUMIF('Waterfall (Two Tier)'!$I$16:$FB$16,K$17,'Waterfall (Two Tier)'!$I46:$FB46) -> 0 | L32: =SUMIF('Waterfall (Two Tier)'!$I$16:$FB$16,L$17,'Waterfall (Two Tier)'!$I46:$FB46) -> 0 | M32: =SUMIF('Waterfall (Two Tier)'!$I$16:$FB$16,M$17,'Waterfall (Two Tier)'!$I46:$FB46) -> 0 | N32: =SUMIF('Waterfall (Two Tier)'!$I$16:$FB$16,N$17,'Waterfall (Two Tier)'!$I46:$FB46) -> 750883.4 | O32: =SUMIF('Waterfall (Two Tier)'!$I$16:$FB$16,O$17,'Waterfall (Two Tier)'!$I46:$FB46) -> 0 | P32: =SUMIF('Waterfall (Two Tier)'!$I$16:$FB$16,P$17,'Waterfall (Two Tier)'!$I46:$FB46) -> 0 | R32: =SUM(I32:L32) -> 0
B33: CF Remaining After Tier II | I33: =I26-I29 -> 0 | J33: =J26-J29 -> 0 | K33: =K26-K29 -> 0 | L33: =L26-L29 -> 0 | M33: =M26-M29 -> 0 | N33: =N26-N29 -> 15183646 | O33: =O26-O29 -> 0 | P33: =P26-P29 -> 0
B35: ="Tier III -- LP IRR between "&TEXT($C$13,"#0%")&" and "&TEXT($C$14,"#0%") -> Tier III -- LP IRR between 11% and 17%
B36: Total Cash Flow Allocated to Tier III | G36: =SUM(I36:P36) -> 9473167.1 | I36: =SUMIF('Waterfall (Two Tier)'!$I$16:$FB$16,I$17,'Waterfall (Two Tier)'!$I54:$FB54) -> 0 | J36: =SUMIF('Waterfall (Two Tier)'!$I$16:$FB$16,J$17,'Waterfall (Two Tier)'!$I54:$FB54) -> 0 | K36: =SUMIF('Waterfall (Two Tier)'!$I$16:$FB$16,K$17,'Waterfall (Two Tier)'!$I54:$FB54) -> 0 | L36: =SUMIF('Waterfall (Two Tier)'!$I$16:$FB$16,L$17,'Waterfall (Two Tier)'!$I54:$FB54) -> 0 | M36: =SUMIF('Waterfall (Two Tier)'!$I$16:$FB$16,M$17,'Waterfall (Two Tier)'!$I54:$FB54) -> 0 | N36: =SUMIF('Waterfall (Two Tier)'!$I$16:$FB$16,N$17,'Waterfall (Two Tier)'!$I54:$FB54) -> 9473167.1 | O36: =SUMIF('Waterfall (Two Tier)'!$I$16:$FB$16,O$17,'Waterfall (Two Tier)'!$I54:$FB54) -> 0 | P36: =SUMIF('Waterfall (Two Tier)'!$I$16:$FB$16,P$17,'Waterfall (Two Tier)'!$I54:$FB54) -> 0 | R36: =SUM(I36:L36) -> 0
B37: Portion Paid to LP | E37: =1-E38-E39 -> 0.43265386 | G37: =SUM(I37:P37) -> 4098602.3 | I37: =SUMIF('Waterfall (Two Tier)'!$I$16:$FB$16,I$17,'Waterfall (Two Tier)'!$I55:$FB55) -> 0 | J37: =SUMIF('Waterfall (Two Tier)'!$I$16:$FB$16,J$17,'Waterfall (Two Tier)'!$I55:$FB55) -> 0 | K37: =SUMIF('Waterfall (Two Tier)'!$I$16:$FB$16,K$17,'Waterfall (Two Tier)'!$I55:$FB55) -> 0 | L37: =SUMIF('Waterfall (Two Tier)'!$I$16:$FB$16,L$17,'Waterfall (Two Tier)'!$I55:$FB55) -> 0 | M37: =SUMIF('Waterfall (Two Tier)'!$I$16:$FB$16,M$17,'Waterfall (Two Tier)'!$I55:$FB55) -> 0 | N37: =SUMIF('Waterfall (Two Tier)'!$I$16:$FB$16,N$17,'Waterfall (Two Tier)'!$I55:$FB55) -> 4098602.3 | O37: =SUMIF('Waterfall (Two Tier)'!$I$16:$FB$16,O$17,'Waterfall (Two Tier)'!$I55:$FB55) -> 0 | P37: =SUMIF('Waterfall (Two Tier)'!$I$16:$FB$16,P$17,'Waterfall (Two Tier)'!$I55:$FB55) -> 0 | R37: =SUM(I37:L37) -> 0
B38: Portion Paid to GP | E38: =C6 -> 0.31734614 | G38: =SUM(I38:P38) -> 3006273.1 | I38: =SUMIF('Waterfall (Two Tier)'!$I$16:$FB$16,I$17,'Waterfall (Two Tier)'!$I56:$FB56) -> 0 | J38: =SUMIF('Waterfall (Two Tier)'!$I$16:$FB$16,J$17,'Waterfall (Two Tier)'!$I56:$FB56) -> 0 | K38: =SUMIF('Waterfall (Two Tier)'!$I$16:$FB$16,K$17,'Waterfall (Two Tier)'!$I56:$FB56) -> 0 | L38: =SUMIF('Waterfall (Two Tier)'!$I$16:$FB$16,L$17,'Waterfall (Two Tier)'!$I56:$FB56) -> 0 | M38: =SUMIF('Waterfall (Two Tier)'!$I$16:$FB$16,M$17,'Waterfall (Two Tier)'!$I56:$FB56) -> 0 | N38: =SUMIF('Waterfall (Two Tier)'!$I$16:$FB$16,N$17,'Waterfall (Two Tier)'!$I56:$FB56) -> 3006273.1 | O38: =SUMIF('Waterfall (Two Tier)'!$I$16:$FB$16,O$17,'Waterfall (Two Tier)'!$I56:$FB56) -> 0 | P38: =SUMIF('Waterfall (Two Tier)'!$I$16:$FB$16,P$17,'Waterfall (Two Tier)'!$I56:$FB56) -> 0 | R38: =SUM(I38:L38) -> 0
B39: Portion Paid to Sponsor Promote | E39: =E13 -> 0.25 | G39: =SUM(I39:P39) -> 2368291.8 | I39: =SUMIF('Waterfall (Two Tier)'!$I$16:$FB$16,I$17,'Waterfall (Two Tier)'!$I57:$FB57) -> 0 | J39: =SUMIF('Waterfall (Two Tier)'!$I$16:$FB$16,J$17,'Waterfall (Two Tier)'!$I57:$FB57) -> 0 | K39: =SUMIF('Waterfall (Two Tier)'!$I$16:$FB$16,K$17,'Waterfall (Two Tier)'!$I57:$FB57) -> 0 | L39: =SUMIF('Waterfall (Two Tier)'!$I$16:$FB$16,L$17,'Waterfall (Two Tier)'!$I57:$FB57) -> 0 | M39: =SUMIF('Waterfall (Two Tier)'!$I$16:$FB$16,M$17,'Waterfall (Two Tier)'!$I57:$FB57) -> 0 | N39: =SUMIF('Waterfall (Two Tier)'!$I$16:$FB$16,N$17,'Waterfall (Two Tier)'!$I57:$FB57) -> 2368291.8 | O39: =SUMIF('Waterfall (Two Tier)'!$I$16:$FB$16,O$17,'Waterfall (Two Tier)'!$I57:$FB57) -> 0 | P39: =SUMIF('Waterfall (Two Tier)'!$I$16:$FB$16,P$17,'Waterfall (Two Tier)'!$I57:$FB57) -> 0 | R39: =SUM(I39:L39) -> 0
B40: CF Remaining After Tier III | I40: =I33-I36 -> 0 | J40: =J33-J36 -> 0 | K40: =K33-K36 -> 0 | L40: =L33-L36 -> 0 | M40: =M33-M36 -> 0 | N40: =N33-N36 -> 5710478.4 | O40: =O33-O36 -> 0 | P40: =P33-P36 -> 0
B42: ="Tier IV -- LP IRR above "&TEXT(C14,"#0%")&"" -> Tier IV -- LP IRR above 17%
B43: Total Cash Flow Allocated to Tier IV | G43: =SUM(I43:P43) -> 5710478.4 | I43: =SUMIF('Waterfall (Two Tier)'!$I$16:$FB$16,I$17,'Waterfall (Two Tier)'!$I61:$FB61) -> 0 | J43: =SUMIF('Waterfall (Two Tier)'!$I$16:$FB$16,J$17,'Waterfall (Two Tier)'!$I61:$FB61) -> 0 | K43: =SUMIF('Waterfall (Two Tier)'!$I$16:$FB$16,K$17,'Waterfall (Two Tier)'!$I61:$FB61) -> 0 | L43: =SUMIF('Waterfall (Two Tier)'!$I$16:$FB$16,L$17,'Waterfall (Two Tier)'!$I61:$FB61) -> 0 | M43: =SUMIF('Waterfall (Two Tier)'!$I$16:$FB$16,M$17,'Waterfall (Two Tier)'!$I61:$FB61) -> 0 | N43: =SUMIF('Waterfall (Two Tier)'!$I$16:$FB$16,N$17,'Waterfall (Two Tier)'!$I61:$FB61) -> 5710478.4 | O43: =SUMIF('Waterfall (Two Tier)'!$I$16:$FB$16,O$17,'Waterfall (Two Tier)'!$I61:$FB61) -> 0 | P43: =SUMIF('Waterfall (Two Tier)'!$I$16:$FB$16,P$17,'Waterfall (Two Tier)'!$I61:$FB61) -> 0 | R43: =SUM(I43:L43) -> 0
B44: Portion Paid to LP | E44: =1-E45-E46 -> 0.33265386 | G44: =SUM(I44:P44) -> 1899612.7 | I44: =SUMIF('Waterfall (Two Tier)'!$I$16:$FB$16,I$17,'Waterfall (Two Tier)'!$I62:$FB62) -> 0 | J44: =SUMIF('Waterfall (Two Tier)'!$I$16:$FB$16,J$17,'Waterfall (Two Tier)'!$I62:$FB62) -> 0 | K44: =SUMIF('Waterfall (Two Tier)'!$I$16:$FB$16,K$17,'Waterfall (Two Tier)'!$I62:$FB62) -> 0 | L44: =SUMIF('Waterfall (Two Tier)'!$I$16:$FB$16,L$17,'Waterfall (Two Tier)'!$I62:$FB62) -> 0 | M44: =SUMIF('Waterfall (Two Tier)'!$I$16:$FB$16,M$17,'Waterfall (Two Tier)'!$I62:$FB62) -> 0 | N44: =SUMIF('Waterfall (Two Tier)'!$I$16:$FB$16,N$17,'Waterfall (Two Tier)'!$I62:$FB62) -> 1899612.7 | O44: =SUMIF('Waterfall (Two Tier)'!$I$16:$FB$16,O$17,'Waterfall (Two Tier)'!$I62:$FB62) -> 0 | P44: =SUMIF('Waterfall (Two Tier)'!$I$16:$FB$16,P$17,'Waterfall (Two Tier)'!$I62:$FB62) -> 0 | R44: =SUM(I44:L44) -> 0
B45: Portion Paid to GP | E45: =C6 -> 0.31734614 | G45: =SUM(I45:P45) -> 1812198.3 | I45: =SUMIF('Waterfall (Two Tier)'!$I$16:$FB$16,I$17,'Waterfall (Two Tier)'!$I63:$FB63) -> 0 | J45: =SUMIF('Waterfall (Two Tier)'!$I$16:$FB$16,J$17,'Waterfall (Two Tier)'!$I63:$FB63) -> 0 | K45: =SUMIF('Waterfall (Two Tier)'!$I$16:$FB$16,K$17,'Waterfall (Two Tier)'!$I63:$FB63) -> 0 | L45: =SUMIF('Waterfall (Two Tier)'!$I$16:$FB$16,L$17,'Waterfall (Two Tier)'!$I63:$FB63) -> 0 | M45: =SUMIF('Waterfall (Two Tier)'!$I$16:$FB$16,M$17,'Waterfall (Two Tier)'!$I63:$FB63) -> 0 | N45: =SUMIF('Waterfall (Two Tier)'!$I$16:$FB$16,N$17,'Waterfall (Two Tier)'!$I63:$FB63) -> 1812198.3 | O45: =SUMIF('Waterfall (Two Tier)'!$I$16:$FB$16,O$17,'Waterfall (Two Tier)'!$I63:$FB63) -> 0 | P45: =SUMIF('Waterfall (Two Tier)'!$I$16:$FB$16,P$17,'Waterfall (Two Tier)'!$I63:$FB63) -> 0 | R45: =SUM(I45:L45) -> 0
B46: Portion Paid to Sponsor Promote | E46: =E14 -> 0.35 | G46: =SUM(I46:P46) -> 1998667.5 | I46: =SUMIF('Waterfall (Two Tier)'!$I$16:$FB$16,I$17,'Waterfall (Two Tier)'!$I64:$FB64) -> 0 | J46: =SUMIF('Waterfall (Two Tier)'!$I$16:$FB$16,J$17,'Waterfall (Two Tier)'!$I64:$FB64) -> 0 | K46: =SUMIF('Waterfall (Two Tier)'!$I$16:$FB$16,K$17,'Waterfall (Two Tier)'!$I64:$FB64) -> 0 | L46: =SUMIF('Waterfall (Two Tier)'!$I$16:$FB$16,L$17,'Waterfall (Two Tier)'!$I64:$FB64) -> 0 | M46: =SUMIF('Waterfall (Two Tier)'!$I$16:$FB$16,M$17,'Waterfall (Two Tier)'!$I64:$FB64) -> 0 | N46: =SUMIF('Waterfall (Two Tier)'!$I$16:$FB$16,N$17,'Waterfall (Two Tier)'!$I64:$FB64) -> 1998667.5 | O46: =SUMIF('Waterfall (Two Tier)'!$I$16:$FB$16,O$17,'Waterfall (Two Tier)'!$I64:$FB64) -> 0 | P46: =SUMIF('Waterfall (Two Tier)'!$I$16:$FB$16,P$17,'Waterfall (Two Tier)'!$I64:$FB64) -> 0 | R46: =SUM(I46:L46) -> 0
B47: CF Remaining After Tier IV | I47: =I40-I43 -> 0 | J47: =J40-J43 -> 0 | K47: =K40-K43 -> 0 | L47: =L40-L43 -> 0 | M47: =M40-M43 -> 0 | N47: =N40-N43 -> 0 | O47: =O40-O43 -> 0 | P47: =P40-P43 -> 0
C49: % of Profit | E49: Return Metrics
B50: LP TOTAL (IRR / MOIC) | C50: =G50/$G$53 -> 0.47788126 | E50: =+'Waterfall (Two Tier)'!E68 -> 19.5% / 1.93x | G50: =SUM(I50:P50) -> 11943596 | I50: =SUMIF('Waterfall (Two Tier)'!$I$16:$FB$16,I$17,'Waterfall (Two Tier)'!$I68:$FB68) -> 0 | J50: =SUMIF('Waterfall (Two Tier)'!$I$16:$FB$16,J$17,'Waterfall (Two Tier)'!$I68:$FB68) -> -12677773 | K50: =SUMIF('Waterfall (Two Tier)'!$I$16:$FB$16,K$17,'Waterfall (Two Tier)'!$I68:$FB68) -> 493963.06 | L50: =SUMIF('Waterfall (Two Tier)'!$I$16:$FB$16,L$17,'Waterfall (Two Tier)'!$I68:$FB68) -> 851319.95 | M50: =SUMIF('Waterfall (Two Tier)'!$I$16:$FB$16,M$17,'Waterfall (Two Tier)'!$I68:$FB68) -> 994639.12 | N50: =SUMIF('Waterfall (Two Tier)'!$I$16:$FB$16,N$17,'Waterfall (Two Tier)'!$I68:$FB68) -> 22281447 | O50: =SUMIF('Waterfall (Two Tier)'!$I$16:$FB$16,O$17,'Waterfall (Two Tier)'!$I68:$FB68) -> 0 | P50: =SUMIF('Waterfall (Two Tier)'!$I$16:$FB$16,P$17,'Waterfall (Two Tier)'!$I68:$FB68) -> 0 | R50: =SUM(I50:L50) -> -11332490
B51: GP TOTAL (IRR / MOIC) | C51: =G51/$G$53 -> 0.31734614 | E51: =+'Waterfall (Two Tier)'!E69 -> 25.5% / 2.32x | G51: =SUM(I51:P51) -> 7931372 | I51: =SUMIF('Waterfall (Two Tier)'!$I$16:$FB$16,I$17,'Waterfall (Two Tier)'!$I69:$FB69) -> 0 | J51: =SUMIF('Waterfall (Two Tier)'!$I$16:$FB$16,J$17,'Waterfall (Two Tier)'!$I69:$FB69) -> -5893532.2 | K51: =SUMIF('Waterfall (Two Tier)'!$I$16:$FB$16,K$17,'Waterfall (Two Tier)'!$I69:$FB69) -> 229629.22 | L51: =SUMIF('Waterfall (Two Tier)'!$I$16:$FB$16,L$17,'Waterfall (Two Tier)'!$I69:$FB69) -> 395754.16 | M51: =SUMIF('Waterfall (Two Tier)'!$I$16:$FB$16,M$17,'Waterfall (Two Tier)'!$I69:$FB69) -> 462379.12 | N51: =SUMIF('Waterfall (Two Tier)'!$I$16:$FB$16,N$17,'Waterfall (Two Tier)'!$I69:$FB69) -> 12737142 | O51: =SUMIF('Waterfall (Two Tier)'!$I$16:$FB$16,O$17,'Waterfall (Two Tier)'!$I69:$FB69) -> 0 | P51: =SUMIF('Waterfall (Two Tier)'!$I$16:$FB$16,P$17,'Waterfall (Two Tier)'!$I69:$FB69) -> 0 | R51: =SUM(I51:L51) -> -5268148.9
B52: SPONSOR PROMOTE | C52: =G52/$G$53 -> 0.20477259 | E52: =+'Waterfall (Two Tier)'!E70 -> n/m | G52: =SUM(I52:P52) -> 5117842.6 | I52: =SUMIF('Waterfall (Two Tier)'!$I$16:$FB$16,I$17,'Waterfall (Two Tier)'!$I70:$FB70) -> 0 | J52: =SUMIF('Waterfall (Two Tier)'!$I$16:$FB$16,J$17,'Waterfall (Two Tier)'!$I70:$FB70) -> 0 | K52: =SUMIF('Waterfall (Two Tier)'!$I$16:$FB$16,K$17,'Waterfall (Two Tier)'!$I70:$FB70) -> 0 | L52: =SUMIF('Waterfall (Two Tier)'!$I$16:$FB$16,L$17,'Waterfall (Two Tier)'!$I70:$FB70) -> 0 | M52: =SUMIF('Waterfall (Two Tier)'!$I$16:$FB$16,M$17,'Waterfall (Two Tier)'!$I70:$FB70) -> 0 | N52: =SUMIF('Waterfall (Two Tier)'!$I$16:$FB$16,N$17,'Waterfall (Two Tier)'!$I70:$FB70) -> 5117842.6 | O52: =SUMIF('Waterfall (Two Tier)'!$I$16:$FB$16,O$17,'Waterfall (Two Tier)'!$I70:$FB70) -> 0 | P52: =SUMIF('Waterfall (Two Tier)'!$I$16:$FB$16,P$17,'Waterfall (Two Tier)'!$I70:$FB70) -> 0 | R52: =SUM(I52:L52) -> 0
B53: COMBINED TOTAL (IRR / MOIC) | E53: =+'Waterfall (Two Tier)'!E71 -> 25.5% / 2.32x | G53: =SUM(I53:P53) -> 24992810 | I53: =SUMIF('Waterfall (Two Tier)'!$I$16:$FB$16,I$17,'Waterfall (Two Tier)'!$I71:$FB71) -> 0 | J53: =SUMIF('Waterfall (Two Tier)'!$I$16:$FB$16,J$17,'Waterfall (Two Tier)'!$I71:$FB71) -> -18571306 | K53: =SUMIF('Waterfall (Two Tier)'!$I$16:$FB$16,K$17,'Waterfall (Two Tier)'!$I71:$FB71) -> 723592.28 | L53: =SUMIF('Waterfall (Two Tier)'!$I$16:$FB$16,L$17,'Waterfall (Two Tier)'!$I71:$FB71) -> 1247074.1 | M53: =SUMIF('Waterfall (Two Tier)'!$I$16:$FB$16,M$17,'Waterfall (Two Tier)'!$I71:$FB71) -> 1457018.2 | N53: =SUMIF('Waterfall (Two Tier)'!$I$16:$FB$16,N$17,'Waterfall (Two Tier)'!$I71:$FB71) -> 40136431 | O53: =SUMIF('Waterfall (Two Tier)'!$I$16:$FB$16,O$17,'Waterfall (Two Tier)'!$I71:$FB71) -> 0 | P53: =SUMIF('Waterfall (Two Tier)'!$I$16:$FB$16,P$17,'Waterfall (Two Tier)'!$I71:$FB71) -> 0 | R53: =SUM(R50:R52) -> -16600639
B55: Total GP | C55: =G55/$G$53 -> 0.52211874 | E55: =+'Waterfall (Two Tier)'!E73 -> 36.1% / 3.18x | G55: =SUM(I55:P55) -> 13049215 | I55: =SUMIF('Waterfall (Two Tier)'!$I$16:$FB$16,I$17,'Waterfall (Two Tier)'!$I73:$FB73) -> 0 | J55: =SUMIF('Waterfall (Two Tier)'!$I$16:$FB$16,J$17,'Waterfall (Two Tier)'!$I73:$FB73) -> -5893532.2 | K55: =SUMIF('Waterfall (Two Tier)'!$I$16:$FB$16,K$17,'Waterfall (Two Tier)'!$I73:$FB73) -> 229629.22 | L55: =SUMIF('Waterfall (Two Tier)'!$I$16:$FB$16,L$17,'Waterfall (Two Tier)'!$I73:$FB73) -> 395754.16 | M55: =SUMIF('Waterfall (Two Tier)'!$I$16:$FB$16,M$17,'Waterfall (Two Tier)'!$I73:$FB73) -> 462379.12 | N55: =SUMIF('Waterfall (Two Tier)'!$I$16:$FB$16,N$17,'Waterfall (Two Tier)'!$I73:$FB73) -> 17854984 | O55: =SUMIF('Waterfall (Two Tier)'!$I$16:$FB$16,O$17,'Waterfall (Two Tier)'!$I73:$FB73) -> 0 | P55: =SUMIF('Waterfall (Two Tier)'!$I$16:$FB$16,P$17,'Waterfall (Two Tier)'!$I73:$FB73) -> 0 | R55: =SUM(I55:L55) -> -5268148.9
B57: Sanity Check | G57: =G19-G53 -> 0 | I57: =I19-I53 -> 0 | J57: =J19-J53 -> 0 | K57: =K19-K53 -> 0 | L57: =L19-L53 -> 0 | M57: =M19-M53 -> 0 | N57: =N19-N53 -> 0 | O57: =O19-O53 -> 0 | P57: =P19-P53 -> 0 | R57: =R19-R53 -> 0
B59: Falcone Total Proceeds | G59: =SUMIF('Waterfall (Two Tier)'!I73:FB73,">0") -> 19037126
